Workbook
Name allowed149726: 'Valid Values'!$T$2:$T$221
Name allowed149756: 'Valid Values'!$AQ$2:$AQ$5
Name allowed149964: 'Valid Values'!$AH$2:$AH$9
Name allowed149965: 'Valid Values'!$AF$2:$AF$9
Name allowed184838: 'Valid Values'!$GI$2:$GI$16
Name allowed185252: 'Valid Values'!$U$2:$U$70
Name allowed185254: 'Valid Values'!$BJ$2:$BJ$70
Name allowed185256: 'Valid Values'!$GT$2:$GT$70
Name allowed185257: 'Valid Values'!$FK$2:$FK$71
Name allowed192864: 'Valid Values'!$AJ$2:$AJ$4
Name allowed192875: 'Valid Values'!$AP$2:$AP$5
Name allowed194726: 'Valid Values'!$ED$2:$ED$4
Name allowed194739: 'Valid Values'!$EM$2:$EM$5
Name allowed19928: 'Valid Values'!$CW$2:$CW$9
Name allowed200855: 'Valid Values'!$CY$2:$CY$11
Name allowed200866: 'Valid Values'!$CX$2:$CX$56
Name allowed200874: 'Valid Values'!$DA$2:$DA$43
Name allowed200875: 'Valid Values'!$DV$2:$DV$12
Name allowed201479: 'Valid Values'!$BF$2:$BF$3
Name allowed202222: 'Valid Values'!$DG$2:$DG$9
Name allowed20251: 'Valid Values'!$DH$2:$DH$22
Name allowed20252: 'Valid Values'!$DY$2:$DY$17
Name allowed20254: 'Valid Values'!$DU$2:$DU$21
Name allowed202653: 'Valid Values'!$HO$2:$HO$6
Name allowed204373: 'Valid Values'!$EI$2:$EI$6
Name allowed214542: 'Valid Values'!$FD$2:$FD$3
Name allowed217965: 'Valid Values'!$CQ$2:$CQ$20
Name allowed220265: 'Valid Values'!$BW$2:$BW$16
Name allowed220267: 'Valid Values'!$BV$2:$BV$9
Name allowed222414: 'Valid Values'!$DI$2:$DI$3
Name allowed222775: 'Valid Values'!$CR$2:$CR$5
Name allowed222778: 'Valid Values'!$CS$2:$CS$61
Name allowed222782: 'Valid Values'!$IG$2:$IG$5
Name allowed222785: 'Valid Values'!$IH$2:$IH$61
Name allowed222789: 'Valid Values'!$GC$2:$GC$5
Name allowed222792: 'Valid Values'!$GD$2:$GD$61
Name allowed222860: 'Valid Values'!$BD$2:$BD$12
Name allowed222861: 'Valid Values'!$BE$2:$BE$7
Name allowed222862: 'Valid Values'!$DE$2:$DE$12
Name allowed222863: 'Valid Values'!$DF$2:$DF$7
Name allowed222864: 'Valid Values'!$GO$2:$GO$7
Name allowed222865: 'Valid Values'!$GP$2:$GP$12
Name allowed222867: 'Valid Values'!$FE$2:$FE$12
Name allowed222868: 'Valid Values'!$FF$2:$FF$7
Name allowed223412: 'Valid Values'!$EA$2:$EA$10
Name allowed223513: 'Valid Values'!$GQ$2:$GQ$3
Name allowed223515: 'Valid Values'!$FG$2:$FG$3
Name allowed224155: 'Valid Values'!$HD$2:$HD$13
Name allowed224158: 'Valid Values'!$HE$2:$HE$9
Name allowed224163: 'Valid Values'!$GL$2:$GL$12
Name allowed224311: 'Valid Values'!$HM$2:$HM$5
Name allowed224759: 'Valid Values'!$CB$2:$CB$4
Name allowed224768: 'Valid Values'!$HJ$2:$HJ$5
Name allowed224770: 'Valid Values'!$FT$2:$FT$4
Name allowed224843: 'Valid Values'!$AK$2:$AK$5
Name allowed224856: 'Valid Values'!$EE$2:$EE$5
Name allowed224980: 'Valid Values'!$CC$2:$CC$4
Name allowed224989: 'Valid Values'!$HK$2:$HK$5
Name allowed224991: 'Valid Values'!$FU$2:$FU$4
Name allowed225064: 'Valid Values'!$AL$2:$AL$5

Sheet Instructions
A1: New Features | D1: For Mandarin translations of product questions, please click here. All answer inputs should still be provided in English. 点击此处查看所有产品相关问题的中文翻译。
A2: Variant Grouping
A3: If you have indicated that you will provide variant grouping data via template settings, additional columns for variant grouping information have been added to the class | C3: Legends
A4: sheet. Enter a common identifier to indicate which part numbers should be grouped together, select attribute(s) to group variants by (or enter custom category if | C4: Cell Fill Colors
A5: desired category is not included in the dropdown), and provide corresponding variant attribute. Groupings that violate Wayfair's Do Not Join rules will be excluded. | C5: Light Red | D5: Missing required data
A6: If Wayfair detects additional variants, products will be grouped further after submission. | C6: Gray | D6: Not required/will be autofilled*
C7: Red | D7: Error/incorrect answer
A8: Class Sheet Instructions | C8: Blue | D8: Autofill suggested by Wayfair (review needed)
A9: Conditional Formatting | C9: Yellow | D9: Warning
A10: Some answers to questions on the spec sheet are dependent on upstream responses, whether they are related to attributes like material type, existence of features | C10: No fill | D10: Validated/no action required
A11: or compliance. Real-time cell coloring per the legend indicates whether an input is required, has an error or has a conditional rule applied. | D11: * For products that have already been submitted, the entire row will be filled gray and cannot be edited further
A12: Error Guidance
A13: Errors are highlighted on the Error Summary Tab which shows a summary of all errors across all sheets with high level details and hyperlinks to the corresponding | C13: Data Priority
A14: cell where the error occurred. Additionally, a new Error Status Column at the beginning of each class sheet will show the status of each row and will display the first error | C14: Required | D14: Data required for product to be live on site
A15: error message in that row, and will update as errors are resolved from left to right. | C15: Recommended | D15: Not required but recommended to improve search and browse
C16: Additional | D16: Optional but enhances listings for customers
A17: All data provided in the class sheet feeds directly to the customer-facing Product Details Page (PDP), optimizes search and enables order fulfillment. Please ensure the | C17: Conditional | D17: Data may be required based on prior responses
A18: data provided is accurate and as detailed as possible.
A19: Notes: | C19: Data Type
A20: • Column headers provide additional information on the data required for each column. | C20: Text | D20: Enter a text-based response
A21: • Completing Recommended and Additional fields further enhances the customer experience and improves the quality of listings for better product discovery. | C21: Single-Select | D21: Select one option from a list of provided options (listed in a dropdown on the cell)
A22: • Marketing Copy should provide a compelling, informative overview of the product, ensuring it effectively highlights key features, benefits, and use cases. | C22: Multi-Select | D22: Enter one or more options from a list of provided options, separated using a semi-colon (;)
A23: Incorporating comprehensive, descriptive language will enable future enhancements for capturing and improving product tagging. | C23: Number* | D23: Enter a decimal numeric response with up to 2 decimal points
A24: ◦ Provide key selling point(s)/feature(s) that differentiate your product and inform customers about your product and encourage purchase. | C24: Whole Number* | D24: Enter an integer (whole number) numeric response
A25: ◦ Either Marketing Copy OR at least 3 Feature Bullets are required. Feature bullets will be displayed on Wayfair PDP in bulleted form. | C25: Yes or No | D25: Enter a Yes, No or Does Not Apply response (listed in a dropdown on the cell)
A26: • The order in which media is input may not be reflected in order of imagery on the product page. | D26: * Does Not Apply is a valid response when applicable
A27: • If all products in a class have the same answer to a question, a default value can be set. An answer entered in the Default Answer row will be applied to all products
A28: in that class automatically. Additional products added to this class in the future will have the same default value applied as well. For any products that have a
A29: different answer than others in the class, enter the answer manually to the applicable row to bypass the default just for that question and product.
A31: Additional Tabs Instructions
A32: Additional Cartons
A33: If a product ships in more than 5 cartons, use the Additional Cartons tab to submit data for cartons 6 and beyond. To add additional cartons, provide the Supplier Part
A34: Number followed by corresponding data for each carton.
A35: Additional Chemicals
A36: If your product contains more than 5 chemicals that need to be reported for Proposition 65, use the Additional Chemicals tab to add additional data.
A37: Additional Media
A38: If a product has more media files than there are columns for in the class sheet, use the Additional Images, Videos or Documents tabs to add additional data.
A39: Notes:
... A45: The Failed Products tab will only show if products in your template failed to upload. These products will need to be added to a new template and uploaded again.

Sheet Error Summary
A1: This Error Summary tab lists all errors and warnings in the spec sheet. Each entry includes a link to the specific cell and detailed information about the issue.
A2: Status | B2: Location | C2: Sheet Name | D2: Supplier Part Number | E2: Product Name | F2: Field | G2: Provided Answer | H2: Error Message
A3: {=_xlfn.LET(_xlpm.class3Data, GetSheetStatusData(Class3Tracker, Class3Errors), _xlpm.class6Data, GetSheetStatusData(Class6Tracker, Class6Errors), _xlpm.class10Data, GetSheetStatusData(Class10Tracker, Class10Errors), _xlpm.class13Data, GetSheetStatusData(Class13Tracker, Class13Errors), _xlpm.class12Data, GetSheetStatusData(Class12Tracker, Class12Errors), _xlpm.shippingAndFulfillment__cartonsData, GetSheetStatusData(shippingAndFulfillment__cartonsTracker, shippingAndFulfillment__cartonsErrors), _xlpm.propSixtyFive__chemicalsData, GetSheetStatusData(propSixtyFive__chemicalsTracker, propSixtyFive__chemicalsErrors), _xlpm.media__imagesData, GetSheetStatusData(media__imagesTracker, media__imagesErrors), _xlpm.media__videosData, GetSheetStatusData(media__videosTracker, media__videosErrors), _xlpm.media__documentsData, GetSheetStatusData(media__documentsTracker, media__documentsErrors), _xlpm.stackedData, _xlfn.VSTACK(_xlpm.class3Data, _xlpm.class6Data, _xlpm.class10Data, _xlpm.class13Data, _xlpm.class12Data, _xlpm.shippingAndFulfillment__cartonsData, _xlpm.propSixtyFive__chemicalsData, _xlpm.media__imagesData, _xlpm.media__videosData, _xlpm.media__documentsData), _xlfn._xlws.FILTER(_xlpm.stackedData, _xlpm.stackedData<>"", ""))} | B3: =IF(AND(C3<>"", J3<>""), HYPERLINK("#'" & C3 & "'!" & J3, J3), "") | C3: {=_xlfn.LET(_xlpm.class3Data, GetSheetNameData(Class3Tracker, Class3Errors, "3 - Carts & Stands"), _xlpm.class6Data, GetSheetNameData(Class6Tracker, Class6Errors, "6 - TV Stands & Enterta"), _xlpm.class10Data, GetSheetNameData(Class10Tracker, Class10Errors, "10 - Office Chairs"), _xlpm.class13Data, GetSheetNameData(Class13Tracker, Class13Errors, "13 - Dressers & Chests"), _xlpm.class12Data, GetSheetNameData(Class12Tracker, Class12Errors, "12 - Beds"), _xlpm.shippingAndFulfillment__cartonsData, GetSheetNameData(shippingAndFulfillment__cartonsTracker, shippingAndFulfillment__cartonsErrors, "Additional Cartons"), _xlpm.propSixtyFive__chemicalsData, GetSheetNameData(propSixtyFive__chemicalsTracker, propSixtyFive__chemicalsErrors, "Additional Chemicals"), _xlpm.media__imagesData, GetSheetNameData(media__imagesTracker, media__imagesErrors, "Additional Images"), _xlpm.media__videosData, GetSheetNameData(media__videosTracker, media__videosErrors, "Additional Videos"), _xlpm.media__documentsData, GetSheetNameData(media__documentsTracker, media__documentsErrors, "Additional Documents"), _xlpm.stackedData, _xlfn.VSTACK(_xlpm.class3Data, _xlpm.class6Data, _xlpm.class10Data, _xlpm.class13Data, _xlpm.class12Data, _xlpm.shippingAndFulfillment__cartonsData, _xlpm.propSixtyFive__chemicalsData, _xlpm.media__imagesData, _xlpm.media__videosData, _xlpm.media__documentsData), _xlfn._xlws.FILTER(_xlpm.stackedData, _xlpm.stackedData<>"", ""))} | D3: {=_xlfn.LET(_xlpm.class3PartNumbers, GetSheetSupplierPartNumbers(Class3Tracker, Class3Errors, '3 - Carts & Stands'!B:B), _xlpm.class6PartNumbers, GetSheetSupplierPartNumbers(Class6Tracker, Class6Errors, '6 - TV Stands & Enterta'!B:B), _xlpm.class10PartNumbers, GetSheetSupplierPartNumbers(Class10Tracker, Class10Errors, '10 - Office Chairs'!B:B), _xlpm.class13PartNumbers, GetSheetSupplierPartNumbers(Class13Tracker, Class13Errors, '13 - Dressers & Chests'!B:B), _xlpm.class12PartNumbers, GetSheetSupplierPartNumbers(Class12Tracker, Class12Errors, '12 - Beds'!B:B), _xlpm.shippingAndFulfillment__cartonsPartNumbers, GetSheetSupplierPartNumbers(shippingAndFulfillment__cartonsTracker, shippingAndFulfillment__cartonsErrors, 'Additional Cartons'!B:B), _xlpm.propSixtyFive__chemicalsPartNumbers, GetSheetSupplierPartNumbers(propSixtyFive__chemicalsTracker, propSixtyFive__chemicalsErrors, 'Additional Chemicals'!B:B), _xlpm.media__imagesPartNumbers, GetSheetSupplierPartNumbers(media__imagesTracker, media__imagesErrors, 'Additional Images'!B:B), _xlpm.media__videosPartNumbers, GetSheetSupplierPartNumbers(media__videosTracker, media__videosErrors, 'Additional Videos'!B:B), _xlpm.media__documentsPartNumbers, GetSheetSupplierPartNumbers(media__documentsTracker, media__documentsErrors, 'Additional Documents'!B:B), _xlpm.stackedPartNumbers, _xlfn.VSTACK(_xlpm.class3PartNumbers, _xlpm.class6PartNumbers, _xlpm.class10PartNumbers, _xlpm.class13PartNumbers, _xlpm.class12PartNumbers, _xlpm.shippingAndFulfillment__cartonsPartNumbers, _xlpm.propSixtyFive__chemicalsPartNumbers, _xlpm.media__imagesPartNumbers, _xlpm.media__videosPartNumbers, _xlpm.media__documentsPartNumbers), _xlfn._xlws.FILTER(_xlpm.stackedPartNumbers, _xlpm.stackedPartNumbers<>"", ""))} | E3: {=_xlfn.LET(_xlpm.class3ProductNames, GetSheetProductNames(Class3Tracker, Class3Errors, '3 - Carts & Stands'!G:G), _xlpm.class6ProductNames, GetSheetProductNames(Class6Tracker, Class6Errors, '6 - TV Stands & Enterta'!G:G), _xlpm.class10ProductNames, GetSheetProductNames(Class10Tracker, Class10Errors, '10 - Office Chairs'!G:G), _xlpm.class13ProductNames, GetSheetProductNames(Class13Tracker, Class13Errors, '13 - Dressers & Chests'!G:G), _xlpm.class12ProductNames, GetSheetProductNames(Class12Tracker, Class12Errors, '12 - Beds'!G:G), _xlpm.shippingAndFulfillment__cartonsProductNames, GetSheetProductNames(shippingAndFulfillment__cartonsTracker, shippingAndFulfillment__cartonsErrors, 'Additional Cartons'!Z:Z), _xlpm.propSixtyFive__chemicalsProductNames, GetSheetProductNames(propSixtyFive__chemicalsTracker, propSixtyFive__chemicalsErrors, 'Additional Chemicals'!Z:Z), _xlpm.media__imagesProductNames, GetSheetProductNames(media__imagesTracker, media__imagesErrors, 'Additional Images'!Z:Z), _xlpm.media__videosProductNames, GetSheetProductNames(media__videosTracker, media__videosErrors, 'Additional Videos'!Z:Z), _xlpm.media__documentsProductNames, GetSheetProductNames(media__documentsTracker, media__documentsErrors, 'Additional Documents'!Z:Z), _xlpm.stackedProductNames, _xlfn.VSTACK(_xlpm.class3ProductNames, _xlpm.class6ProductNames, _xlpm.class10ProductNames, _xlpm.class13ProductNames, _xlpm.class12ProductNames, _xlpm.shippingAndFulfillment__cartonsProductNames, _xlpm.propSixtyFive__chemicalsProductNames, _xlpm.media__imagesProductNames, _xlpm.media__videosProductNames, _xlpm.media__documentsProductNames), _xlfn._xlws.FILTER(_xlpm.stackedProductNames, _xlpm.stackedProductNames<>"EMPTY_ERROR", ""))} | F3: {=_xlfn.LET( _xlpm.class3QuestionDisplayNames, GetErrorQuestionDisplayNames(Class3Headers, Class3Tracker, Class3Errors) , _xlpm.class6QuestionDisplayNames, GetErrorQuestionDisplayNames(Class6Headers, Class6Tracker, Class6Errors) , _xlpm.class10QuestionDisplayNames, GetErrorQuestionDisplayNames(Class10Headers, Class10Tracker, Class10Errors) , _xlpm.class13QuestionDisplayNames, GetErrorQuestionDisplayNames(Class13Headers, Class13Tracker, Class13Errors) , _xlpm.class12QuestionDisplayNames, GetErrorQuestionDisplayNames(Class12Headers, Class12Tracker, Class12Errors) , _xlpm.shippingAndFulfillment__cartonsQuestionDisplayNames, GetErrorQuestionDisplayNames(shippingAndFulfillment__cartonsHeaders, shippingAndFulfillment__cartonsTracker, shippingAndFulfillment__cartonsErrors) , _xlpm.propSixtyFive__chemicalsQuestionDisplayNames, GetErrorQuestionDisplayNames(propSixtyFive__chemicalsHeaders, propSixtyFive__chemicalsTracker, propSixtyFive__chemicalsErrors) , _xlpm.media__imagesQuestionDisplayNames, GetErrorQuestionDisplayNames(media__imagesHeaders, media__imagesTracker, media__imagesErrors) , _xlpm.media__videosQuestionDisplayNames, GetErrorQuestionDisplayNames(media__videosHeaders, media__videosTracker, media__videosErrors) , _xlpm.media__documentsQuestionDisplayNames, GetErrorQuestionDisplayNames(media__documentsHeaders, media__documentsTracker, media__documentsErrors) , _xlpm.stackedQuestionDisplayNames, _xlfn.VSTACK(_xlpm.class3QuestionDisplayNames, _xlpm.class6QuestionDisplayNames, _xlpm.class10QuestionDisplayNames, _xlpm.class13QuestionDisplayNames, _xlpm.class12QuestionDisplayNames, _xlpm.shippingAndFulfillment__cartonsQuestionDisplayNames, _xlpm.propSixtyFive__chemicalsQuestionDisplayNames, _xlpm.media__imagesQuestionDisplayNames, _xlpm.media__videosQuestionDisplayNames, _xlpm.media__documentsQuestionDisplayNames), _xlfn._xlws.FILTER(_xlpm.stackedQuestionDisplayNames, _xlpm.stackedQuestionDisplayNames<>"", ""))} | G3: {=_xlfn.LET( _xlpm.class3ProvidedAnswers, GetFilteredProvidedAnswers(Class3Answers, Class3Errors, Class3Tracker) , _xlpm.class6ProvidedAnswers, GetFilteredProvidedAnswers(Class6Answers, Class6Errors, Class6Tracker) , _xlpm.class10ProvidedAnswers, GetFilteredProvidedAnswers(Class10Answers, Class10Errors, Class10Tracker) , _xlpm.class13ProvidedAnswers, GetFilteredProvidedAnswers(Class13Answers, Class13Errors, Class13Tracker) , _xlpm.class12ProvidedAnswers, GetFilteredProvidedAnswers(Class12Answers, Class12Errors, Class12Tracker) , _xlpm.shippingAndFulfillment__cartonsProvidedAnswers, GetFilteredProvidedAnswers(shippingAndFulfillment__cartonsAnswers, shippingAndFulfillment__cartonsErrors, shippingAndFulfillment__cartonsTracker) , _xlpm.propSixtyFive__chemicalsProvidedAnswers, GetFilteredProvidedAnswers(propSixtyFive__chemicalsAnswers, propSixtyFive__chemicalsErrors, propSixtyFive__chemicalsTracker) , _xlpm.media__imagesProvidedAnswers, GetFilteredProvidedAnswers(media__imagesAnswers, media__imagesErrors, media__imagesTracker) , _xlpm.media__videosProvidedAnswers, GetFilteredProvidedAnswers(media__videosAnswers, media__videosErrors, media__videosTracker) , _xlpm.media__documentsProvidedAnswers, GetFilteredProvidedAnswers(media__documentsAnswers, media__documentsErrors, media__documentsTracker) , _xlpm.stackedProvidedAnswers, _xlfn.VSTACK(_xlpm.class3ProvidedAnswers, _xlpm.class6ProvidedAnswers, _xlpm.class10ProvidedAnswers, _xlpm.class13ProvidedAnswers, _xlpm.class12ProvidedAnswers, _xlpm.shippingAndFulfillment__cartonsProvidedAnswers, _xlpm.propSixtyFive__chemicalsProvidedAnswers, _xlpm.media__imagesProvidedAnswers, _xlpm.media__videosProvidedAnswers, _xlpm.media__documentsProvidedAnswers), _xlfn._xlws.FILTER(_xlpm.stackedProvidedAnswers, _xlpm.stackedProvidedAnswers<>"EMPTY_ERROR", ""))} | H3: {=_xlfn.LET(_xlpm.class3ErrorMessages, _xlfn.FILTER( _xlfn.TOCOL(Class3Errors), _xlfn.TOCOL((Class3Errors <> "") * (Class3Tracker <> "Valid") * (Class3Tracker <> "Disabled")), "" ), _xlpm.class6ErrorMessages, _xlfn.FILTER( _xlfn.TOCOL(Class6Errors), _xlfn.TOCOL((Class6Errors <> "") * (Class6Tracker <> "Valid") * (Class6Tracker <> "Disabled")), "" ), _xlpm.class10ErrorMessages, _xlfn.FILTER( _xlfn.TOCOL(Class10Errors), _xlfn.TOCOL((Class10Errors <> "") * (Class10Tracker <> "Valid") * (Class10Tracker <> "Disabled")), "" ), _xlpm.class13ErrorMessages, _xlfn.FILTER( _xlfn.TOCOL(Class13Errors), _xlfn.TOCOL((Class13Errors <> "") * (Class13Tracker <> "Valid") * (Class13Tracker <> "Disabled")), "" ), _xlpm.class12ErrorMessages, _xlfn.FILTER( _xlfn.TOCOL(Class12Errors), _xlfn.TOCOL((Class12Errors <> "") * (Class12Tracker <> "Valid") * (Class12Tracker <> "Disabled")), "" ), _xlpm.shippingAndFulfillment__cartonsErrorMessages, _xlfn.FILTER( _xlfn.TOCOL(shippingAndFulfillment__cartonsErrors), _xlfn.TOCOL((shippingAndFulfillment__cartonsErrors <> "") * (shippingAndFulfillment__cartonsTracker <> "Valid") * (shippingAndFulfillment__cartonsTracker <> "Disabled")), "" ), _xlpm.propSixtyFive__chemicalsErrorMessages, _xlfn.FILTER( _xlfn.TOCOL(propSixtyFive__chemicalsErrors), _xlfn.TOCOL((propSixtyFive__chemicalsErrors <> "") * (propSixtyFive__chemicalsTracker <> "Valid") * (propSixtyFive__chemicalsTracker <> "Disabled")), "" ), _xlpm.media__imagesErrorMessages, _xlfn.FILTER( _xlfn.TOCOL(media__imagesErrors), _xlfn.TOCOL((media__imagesErrors <> "") * (media__imagesTracker <> "Valid") * (media__imagesTracker <> "Disabled")), "" ), _xlpm.media__videosErrorMessages, _xlfn.FILTER( _xlfn.TOCOL(media__videosErrors), _xlfn.TOCOL((media__videosErrors <> "") * (media__videosTracker <> "Valid") * (media__videosTracker <> "Disabled")), "" ), _xlpm.media__documentsErrorMessages, _xlfn.FILTER( _xlfn.TOCOL(media__documentsErrors), _xlfn.TOCOL((media__documentsErrors <> "") * (media__documentsTracker <> "Valid") * (media__documentsTracker <> "Disabled")), "" ), _xlpm.stackedErrorMessages, _xlfn.VSTACK(_xlpm.class3ErrorMessages, _xlpm.class6ErrorMessages, _xlpm.class10ErrorMessages, _xlpm.class13ErrorMessages, _xlpm.class12ErrorMessages, _xlpm.shippingAndFulfillment__cartonsErrorMessages, _xlpm.propSixtyFive__chemicalsErrorMessages, _xlpm.media__imagesErrorMessages, _xlpm.media__videosErrorMessages, _xlpm.media__documentsErrorMessages), _xlpm.filteredMessages, _xlfn._xlws.FILTER(_xlpm.stackedErrorMessages, _xlpm.stackedErrorMessages<>"", ""), IFERROR(_xlfn.TEXTAFTER(_xlpm.filteredMessages, ":"), _xlpm.filteredMessages))} | J3: {=_xlfn.LET(_xlpm.class3Addresses, GetSheetLocationAddresses(Class3Tracker, Class3Errors), _xlpm.class6Addresses, GetSheetLocationAddresses(Class6Tracker, Class6Errors), _xlpm.class10Addresses, GetSheetLocationAddresses(Class10Tracker, Class10Errors), _xlpm.class13Addresses, GetSheetLocationAddresses(Class13Tracker, Class13Errors), _xlpm.class12Addresses, GetSheetLocationAddresses(Class12Tracker, Class12Errors), _xlpm.shippingAndFulfillment__cartonsAddresses, GetSheetLocationAddresses(shippingAndFulfillment__cartonsTracker, shippingAndFulfillment__cartonsErrors), _xlpm.propSixtyFive__chemicalsAddresses, GetSheetLocationAddresses(propSixtyFive__chemicalsTracker, propSixtyFive__chemicalsErrors), _xlpm.media__imagesAddresses, GetSheetLocationAddresses(media__imagesTracker, media__imagesErrors), _xlpm.media__videosAddresses, GetSheetLocationAddresses(media__videosTracker, media__videosErrors), _xlpm.media__documentsAddresses, GetSheetLocationAddresses(media__documentsTracker, media__documentsErrors), _xlpm.stackedAddresses, _xlfn.VSTACK(_xlpm.class3Addresses, _xlpm.class6Addresses, _xlpm.class10Addresses, _xlpm.class13Addresses, _xlpm.class12Addresses, _xlpm.shippingAndFulfillment__cartonsAddresses, _xlpm.propSixtyFive__chemicalsAddresses, _xlpm.media__imagesAddresses, _xlpm.media__videosAddresses, _xlpm.media__documentsAddresses), _xlfn._xlws.FILTER(_xlpm.stackedAddresses, _xlpm.stackedAddresses<>"", ""))}
B4: =IF(AND(C4<>"", J4<>""), HYPERLINK("#'" & C4 & "'!" & J4, J4), "")
B5: =IF(AND(C5<>"", J5<>""), HYPERLINK("#'" & C5 & "'!" & J5, J5), "")
B6: =IF(AND(C6<>"", J6<>""), HYPERLINK("#'" & C6 & "'!" & J6, J6), "")
B7: =IF(AND(C7<>"", J7<>""), HYPERLINK("#'" & C7 & "'!" & J7, J7), "")
B8: =IF(AND(C8<>"", J8<>""), HYPERLINK("#'" & C8 & "'!" & J8, J8), "")
B9: =IF(AND(C9<>"", J9<>""), HYPERLINK("#'" & C9 & "'!" & J9, J9), "")
B10: =IF(AND(C10<>"", J10<>""), HYPERLINK("#'" & C10 & "'!" & J10, J10), "")
B11: =IF(AND(C11<>"", J11<>""), HYPERLINK("#'" & C11 & "'!" & J11, J11), "")
B12: =IF(AND(C12<>"", J12<>""), HYPERLINK("#'" & C12 & "'!" & J12, J12), "")
B13: =IF(AND(C13<>"", J13<>""), HYPERLINK("#'" & C13 & "'!" & J13, J13), "")
B14: =IF(AND(C14<>"", J14<>""), HYPERLINK("#'" & C14 & "'!" & J14, J14), "")
B15: =IF(AND(C15<>"", J15<>""), HYPERLINK("#'" & C15 & "'!" & J15, J15), "")
... B6002: =IF(AND(C6002<>"", J6002<>""), HYPERLINK("#'" & C6002 & "'!" & J6002, J6002), "")

Sheet WAYFAIR_USE_ONLY
A1: {"brand_catalog_id": 1, "previous_upload_id": null, "template_type": "DEFAULT_QUESTIONS", "supplier_id": 455634, "template_context": "STANDARD", "app_version": "v2", "product_count": 0, "default_answers_included": true, "default_answers_supported": true, "use_legacy_excel_format": false, "include_variant_grouping": true, "download_template_request_id": "60a3a202-b692-44e4-ba02-96f72434bb32", "sheet_metadata": null} | C1: =_xlfn.INFO("release")
C2: =_xlfn.INFO("system")
C3: {=IF(ISERROR(_xlfn.MAP(A8:A8,_xlfn.LAMBDA(_xlpm.class,_xlpm.class<>""))), "Not Available", "Supported")}
A8: Carts & Stands | B8: AV Cart | C8: No | D8: No | E8: No | F8: Yes | G8: Yes | H8: No | I8: Lithium Metal | J8: Cell | K8: 1 | L8: Stand alone | M8: Cells exceeding 5 grams | N8: Cells of between 20w/h and 60w/h | O8: 2.5kg or less | P8: Yes | Q8: Yes | R8: Yes | S8: Free Standing | T8: Yes | U8: Yes | V8: Yes | W8: Yes | X8: Yes | Y8: Yes | Z8: Yes | AA8: Yes | AB8: Yes | AC8: Yes | AD8: Yes | AE8: 1 | AF8: I | AG8: >0 - ≤25ml | AH8: Yes | AI8: No | AJ8: 1A | AK8: Yes | AL8: Yes | AM8: 30 Days | AN8: Yes | AO8: Yes | AQ8: US | AR8: Arabic | AS8: Yes | AT8: A-alpha-C (2-Amino-9H-pyrido[2,3-b]indole) | AU8: United States | AV8: Small Parcel | AW8: 50 | AX8: 0 | AY8: 0 | AZ8: Yes | BA8: Yes | BB8: Primary Variant | BC8: Color | BD8: Entertainment Center | BE8: Yes | BF8: Yes | BG8: No | BH8: Yes | BI8: Yes | BJ8: Yes | BK8: No | BL8: Yes | BM8: Yes | BN8: Yes | BO8: Yes | BP8: No | BQ8: Yes | BR8: No | BS8: No | BT8: No | BU8: Yes | BV8: No | BW8: No | BX8: Dovetail | BY8: Yes | BZ8: Lithium Metal | CA8: Cell | CB8: 1 | CC8: Stand alone | CD8: Cells exceeding 5 grams | CE8: Cells of between 20w/h and 60w/h | CF8: 2.5kg or less | CG8: Yes | CH8: No | CI8: Yes | CJ8: Yes | CK8: Direct Vent | CL8: Yes | CM8: Yes | CN8: Yes | CO8: Yes | CP8: Yes | CQ8: Yes | CR8: Yes | CS8: Yes | CT8: Yes | CU8: Yes | CV8: Yes | CW8: 1 | CX8: I | CY8: >0 - ≤25ml | CZ8: Yes | DA8: No | DB8: No | DC8: 1A | DD8: Yes | DE8: BIFMA Accredited | DF8: 28" | DG8: Yes | DH8: No Assembly Needed | DI8: 30 Days | DJ8: Yes | DK8: Yes | DL8: Full | DM8: Color | DN8: Bankers Chair | DO8: Metal | DP8: Yes | DQ8: Yes | DR8: Yes | DS8: No | DT8: No | DU8: No | DV8: Yes | DW8: No | DX8: Yes | DY8: No | DZ8: No | EA8: No | EB8: Yes | EC8: No | ED8: No | EE8: No | EF8: No | EG8: Yes | EH8: No | EI8: Dovetail | EJ8: Yes | EK8: No | EL8: Lithium Metal | EM8: Cell | EN8: 1 | EO8: Stand alone | EP8: Cells exceeding 5 grams | EQ8: Cells of between 20w/h and 60w/h | ER8: 2.5kg or less | ES8: Yes | ET8: Yes | EU8: Yes | EV8: No | EW8: No | EX8: Yes | EY8: Yes | EZ8: Less than 3,000 | FA8: Yes | FB8: Yes | FC8: Yes | FD8: Yes | FE8: Yes | FF8: Yes | FG8: Yes | FH8: Yes | FI8: Yes | FJ8: Yes | FK8: Yes | FL8: Yes | FM8: Yes | FN8: Yes | FO8: 1 | FP8: I | FQ8: >0 - ≤25ml | FR8: Yes | FS8: No | FT8: Yes | FU8: 1A | FV8: Yes | FW8: Yes | FX8: BIFMA Accredited | FY8: Yes | FZ8: No Assembly Needed | GA8: 30 Days | GB8: Yes | GC8: Yes | GD8: Full | GE8: Frame Color | GF8: Combo Dresser | GG8: Yes | GH8: No | GI8: No | GJ8: Yes | GK8: Yes | GL8: No | GM8: No | GN8: Metal | GO8: No | GP8: Dovetail | GQ8: Yes | GR8: Yes | GS8: Yes | GT8: Yes | GU8: Particle Board / Chipboard | GV8: Yes | GW8: Yes | GX8: Yes | GY8: Yes | GZ8: Yes | HA8: No | HB8: Yes | HC8: Yes | HD8: Yes | HE8: Yes | HF8: Yes | HG8: Yes | HH8: Yes | HI8: Yes | HJ8: Yes | HK8: Yes | HL8: No | HM8: 1A | HN8: Yes | HO8: Yes | HP8: BIFMA Accredited | HQ8: Yes | HR8: No Assembly Needed | HS8: 30 Days | HT8: Yes | HU8: Yes | HV8: Full | HW8: Color | HX8: Twin | HY8: Standard | HZ8: Yes | IA8: Yes | IB8: Bonded Leather | IC8: Yes | ID8: No | IE8: Yes | IF8: Yes | IG8: Yes | IH8: No | II8: Dovetail | IJ8: Yes | IK8: Cell | IL8: Lithium Metal | IM8: 1 | IN8: Stand alone | IO8: Cells exceeding 5 grams | IP8: Cells of between 20w/h and 60w/h | IQ8: 2.5kg or less | IR8: Yes | IS8: Yes | IT8: No | IU8: Yes | IV8: Yes | IW8: Particle Board / Chipboard | IX8: No | IY8: Suede | IZ8: Chenille | JA8: Beveled | JB8: Yes | JC8: Yes | JD8: Yes | JE8: Yes | JF8: Yes | JG8: Yes | JH8: Yes | JI8: Yes | JJ8: Yes | JK8: Yes | JL8: Yes | JM8: Yes | JN8: Yes | JO8: Yes | JP8: Yes | JQ8: Yes | JR8: Yes | JS8: 1 | JT8: I | JU8: >0 - ≤25ml | JV8: Yes | JW8: No | JX8: 1A | JY8: Yes | JZ8: Yes | KA8: No | KB8: Yes | KC8: Yes | KD8: Yes | KE8: Yes | KF8: No Assembly Needed | KG8: 30 Days | KH8: Yes | KI8: Yes | KJ8: Full | KK8: Size
A9: Multimedia Storage | B9: Book Cart | C9: Yes | D9: Yes | E9: Yes | F9: No | G9: No | H9: Yes | I9: Lithium Ion / Lithium Polymer | J9: Battery | K9: 2 | L9: Contained in product | M9: Batteries of 2 grams or less | N9: Cells exceeding 60w/h | O9: 2.5kg to 5kg | P9: No | Q9: No | R9: No | S9: Fixed | T9: No | U9: No | V9: No | W9: No | X9: No | Y9: No | Z9: No | AA9: No | AB9: No | AC9: No | AD9: No | AE9: 2.2 | AF9: III | AG9: >1L - ≤5L | AH9: No | AI9: Yes | AJ9: 3A or 6A | AK9: No | AL9: No | AM9: 60 Days | AN9: No | AO9: No | AQ9: UK | AR9: Bulgarian | AS9: No | AT9: Abiraterone acetate | AU9: Canada | AV9: LTL | AW9: 55 | AX9: 24 | AY9: 24 | AZ9: No | BA9: No | BB9: Non-Primary Variant | BC9: Finish | BD9: TV Stand | BE9: No | BF9: No | BG9: Yes | BH9: No | BI9: No | BJ9: No | BK9: Yes | BL9: No | BM9: No | BN9: No | BO9: No | BP9: Yes | BQ9: No | BR9: Yes | BS9: Yes | BT9: Yes | BU9: No | BV9: Yes | BW9: Yes | BX9: Mortise and Tenon | BY9: No | BZ9: Lithium Ion / Lithium Polymer | CA9: Battery | CB9: 2 | CC9: Contained in product | CD9: Batteries of 2 grams or less | CE9: Cells exceeding 60w/h | CF9: 2.5kg to 5kg | CG9: No | CH9: Yes | CI9: No | CJ9: No | CK9: Natural Vent | CL9: No | CM9: No | CN9: No | CO9: No | CP9: No | CQ9: No | CR9: No | CS9: No | CT9: No | CU9: No | CV9: No | CW9: 2.2 | CX9: III | CY9: >1L - ≤5L | CZ9: No | DA9: Yes | DB9: Yes | DC9: 3A or 6A | DD9: No | DE9: BIFMA Equivalent | DF9: 24" | DG9: No | DH9: Minimal Assembly Needed | DI9: 60 Days | DJ9: No | DK9: No | DL9: Limited | DM9: Material | DN9: Conference Chair | DO9: Aluminum | DP9: No | DQ9: No | DR9: No | DS9: Yes | DT9: Yes | DU9: Yes | DV9: No | DW9: Yes | DX9: No | DY9: Yes | DZ9: Yes | EA9: Yes | EB9: No | EC9: Yes | ED9: Yes | EE9: Yes | EF9: Yes | EG9: No | EH9: Yes | EI9: Mortise and Tenon | EJ9: No | EK9: Yes | EL9: Lithium Ion / Lithium Polymer | EM9: Battery | EN9: 2 | EO9: Contained in product | EP9: Batteries of 2 grams or less | EQ9: Cells exceeding 60w/h | ER9: 2.5kg to 5kg | ES9: No | ET9: No | EU9: No | EV9: Yes | EW9: Yes | EX9: No | EY9: No | EZ9: 3,000-9,000 | FA9: No | FB9: No | FC9: No | FD9: No | FE9: No | FF9: No | FG9: No | FH9: No | FI9: No | FJ9: No | FK9: No | FL9: No | FM9: No | FN9: No | FO9: 2.2 | FP9: III | FQ9: >1L - ≤5L | FR9: No | FS9: Yes | FT9: No | FU9: 3A or 6A | FV9: No | FW9: No | FX9: BIFMA Equivalent | FY9: No | FZ9: Minimal Assembly Needed | GA9: 60 Days | GB9: No | GC9: No | GD9: Limited | GE9: Upholstery Color | GF9: Double Dresser | GG9: No | GH9: Yes | GI9: Yes | GJ9: No | GK9: No | GL9: Yes | GM9: Yes | GN9: Ceramic | GO9: Yes | GP9: Mortise and Tenon | GQ9: No | GR9: No | GS9: No | GT9: No | GU9: MDF | GV9: No | GW9: No | GX9: No | GY9: No | GZ9: No | HA9: Yes | HB9: No | HC9: No | HD9: No | HE9: No | HF9: No | HG9: No | HH9: No | HI9: No | HJ9: No | HK9: No | HL9: Yes | HM9: 3A or 6A | HN9: No | HO9: No | HP9: BIFMA Equivalent | HQ9: No | HR9: Minimal Assembly Needed | HS9: 60 Days | HT9: No | HU9: No | HV9: Limited | HX9: Extra-long Twin | HY9: Canopy | HZ9: No | IA9: No | IB9: PU | IC9: No | ID9: Yes | IE9: No | IF9: No | IG9: No | IH9: Yes | II9: Mortise and Tenon | IJ9: No | IK9: Battery | IL9: Lithium Ion / Lithium Polymer | IM9: 2 | IN9: Contained in product | IO9: Batteries of 2 grams or less | IP9: Cells exceeding 60w/h | IQ9: 2.5kg to 5kg | IR9: No | IS9: No | IT9: Yes | IU9: No | IV9: No | IW9: MDF | IX9: Yes | IY9: Leather Match | IZ9: Velvet | JA9: Arched | JB9: No | JC9: No | JD9: No | JE9: No | JF9: No | JG9: No | JH9: No | JI9: No | JJ9: No | JK9: No | JL9: No | JM9: No | JN9: No | JO9: No | JP9: No | JQ9: No | JR9: No | JS9: 2.2 | JT9: III | JU9: >1L - ≤5L | JV9: No | JW9: Yes | JX9: 3A or 6A | JY9: No | JZ9: No | KA9: Yes | KB9: No | KC9: No | KD9: No | KE9: No | KF9: Minimal Assembly Needed | KG9: 60 Days | KH9: No | KI9: No | KJ9: Limited | KK9: Color
A10: Speaker Stands | B10: CPU Holder | C10: Does Not Apply | D10: Unavailable | G10: Unavailable | I10: Nickel Cadmium | J10: Button Cell | K10: 3 | L10: Packed with product | M10: Batteries of between 2 and 25 grams | N10: Cells of 20w/h or less | O10: More than 10kg | P10: Unavailable | Q10: Unavailable | R10: Does Not Apply | S10: Wall Mounted | T10: Unavailable | U10: Yes, Compliance Verified Program Member | V10: Does Not Apply | W10: Yes, Compliance Verified Program Member | X10: Yes, Compliance Verified Program Member | Y10: Yes, Compliance Verified Program Member | Z10: Does Not Apply | AA10: Yes, Compliance Verified Program Member | AC10: Yes, Compliance Verified Program Member | AD10: Yes, Compliance Verified Program Member | AE10: 2.1 | AF10: No Packing Group | AG10: >0.5L - ≤1L | AI10: Yes, Compliance Verified Program Member | AJ10: Does Not Apply | AK10: Does Not Apply | AM10: 90 Days | AN10: Does Not Apply | AQ10: EU | AR10: Czech (Czech Republic) | AT10: Acetaldehyde | AU10: Afghanistan | AW10: 60 | AX10: 48 | AY10: 48 | BB10: Not Variant | BC10: Assembly | BE10: Unavailable | BH10: Does Not Apply | BJ10: Unavailable | BK10: Unavailable | BL10: Unavailable | BM10: Does Not Apply | BN10: Unavailable | BO10: Unavailable | BP10: Unavailable | BQ10: Unavailable | BV10: Unavailable | BW10: Does Not Apply | BX10: Rabbet Joint | BY10: Unavailable | BZ10: Nickel Cadmium | CA10: Button Cell | CB10: 3 | CC10: Packed with product | CD10: Batteries of between 2 and 25 grams | CE10: Cells of 20w/h or less | CF10: More than 10kg | CG10: Unavailable | CH10: Unavailable | CI10: Does Not Apply | CJ10: Unavailable | CK10: Vent Free | CL10: Unavailable | CM10: Unavailable | CN10: Unavailable | CO10: Does Not Apply | CP10: Does Not Apply | CQ10: Does Not Apply | CR10: Yes, Compliance Verified Program Member | CS10: Does Not Apply | CV10: Yes, Compliance Verified Program Member | CW10: 2.1 | CX10: No Packing Group | CY10: >0.5L - ≤1L | DA10: Yes, Compliance Verified Program Member | DB10: Yes, Compliance Verified Program Member | DC10: Does Not Apply | DD10: Does Not Apply | DE10: Contract Grade Accredited | DF10: 40" | DH10: Full Assembly Needed | DI10: 90 Days | DJ10: Does Not Apply | DL10: Does Not Apply | DM10: Size | DN10: Drafting Chair | DO10: Solid Wood | DQ10: Unavailable | DR10: Unavailable | DS10: Unavailable | DV10: Unavailable | DW10: Unavailable | DX10: Unavailable | DY10: Unavailable | DZ10: Does Not Apply | EA10: Unavailable | EB10: Unavailable | EC10: Unavailable | ED10: Does Not Apply | EE10: Unavailable | EF10: Unavailable | EG10: Unavailable | EH10: Unavailable | EI10: Rabbet Joint | EJ10: Unavailable | EK10: Unavailable | EL10: Nickel Cadmium | EM10: Button Cell | EN10: 3 | EO10: Packed with product | EP10: Batteries of between 2 and 25 grams | EQ10: Cells of 20w/h or less | ER10: More than 10kg | ES10: Unavailable | ET10: Unavailable | EU10: Does Not Apply | EW10: Unavailable | EX10: Unavailable | EY10: Unavailable | EZ10: 9,000-15,000 | FA10: Yes, Compliance Verified Program Member | FB10: Yes, Compliance Verified Program Member | FC10: Yes, Compliance Verified Program Member | FD10: Yes, Compliance Verified Program Member | FE10: Does Not Apply | FF10: Does Not Apply | FH10: Yes, Compliance Verified Program Member | FI10: Yes, Compliance Verified Program Member | FJ10: Yes, Compliance Verified Program Member | FK10: Yes, Compliance Verified Program Member | FM10: Yes, Compliance Verified Program Member | FN10: Does Not Apply | FO10: 2.1 | FP10: No Packing Group | FQ10: >0.5L - ≤1L | FS10: Yes, Compliance Verified Program Member | FT10: Yes, Compliance Verified Program Member | FU10: Does Not Apply | FV10: Yes, Compliance Verified Program Member | FW10: Does Not Apply | FX10: Contract Grade Accredited | FZ10: Full Assembly Needed | GA10: 90 Days | GB10: Does Not Apply | GD10: Does Not Apply | GE10: Upholstery Material | GF10: Gentlemens Chest | GG10: Unavailable | GI10: Unavailable | GJ10: Unavailable | GN10: Plastic | GO10: Unavailable | GP10: Rabbet Joint | GQ10: Unavailable | GR10: Unavailable | GS10: Unavailable | GT10: Unavailable | GU10: Plywood / Laminate Board | GV10: Unavailable | GW10: Unavailable | GX10: Unavailable | GY10: Unavailable | HA10: Does Not Apply | HC10: Does Not Apply | HD10: Does Not Apply | HE10: Does Not Apply | HF10: Does Not Apply | HG10: Yes, Compliance Verified Program Member | HH10: Does Not Apply | HI10: Does Not Apply | HL10: Yes, Compliance Verified Program Member | HM10: Does Not Apply | HN10: Yes, Compliance Verified Program Member | HO10: Does Not Apply | HP10: Contract Grade Accredited | HR10: Full Assembly Needed | HS10: 90 Days | HT10: Does Not Apply | HV10: Unavailable | HX10: Full / Double | HY10: Four Poster | HZ10: Unavailable | IB10: PVC | ID10: Unavailable | IE10: Unavailable | IG10: Unavailable | II10: Rabbet Joint | IJ10: Unavailable | IK10: Button Cell | IL10: Nickel Cadmium | IM10: 3 | IN10: Packed with product | IO10: Batteries of between 2 and 25 grams | IP10: Cells of 20w/h or less | IQ10: More than 10kg | IR10: Unavailable | IS10: Unavailable | IU10: Unavailable | IV10: Unavailable | IW10: Plywood / Laminate Board | IX10: Unavailable | IY10: Top Grain Leather | IZ10: Cord | JA10: Portman | JB10: Unavailable | JC10: Unavailable | JE10: Yes, Compliance Verified Program Member | JF10: Yes, Compliance Verified Program Member | JG10: Yes, Compliance Verified Program Member | JH10: Does Not Apply | JI10: Yes, Compliance Verified Program Member | JJ10: Yes, Compliance Verified Program Member | JK10: Yes, Compliance Verified Program Member | JL10: Yes, Compliance Verified Program Member | JN10: Yes, Compliance Verified Program Member | JO10: Yes, Compliance Verified Program Member | JP10: Does Not Apply | JQ10: Yes, Compliance Verified Program Member | JR10: Yes, Compliance Verified Program Member | JS10: 2.1 | JT10: No Packing Group | JU10: >0.5L - ≤1L | JW10: Yes, Compliance Verified Program Member | JX10: Does Not Apply | JY10: Yes, Compliance Verified Program Member | JZ10: Yes, Compliance Verified Program Member | KA10: Yes, Compliance Verified Program Member | KB10: Yes, Compliance Verified Program Member | KC10: Does Not Apply | KD10: Yes, Compliance Verified Program Member | KF10: Full Assembly Needed | KG10: 90 Days | KH10: Does Not Apply | KJ10: Does Not Apply | KK10: Frame Material
A11: TV Stands & Entertainment Centers | B11: File Cart | I11: Nickel Metal Hydride | J11: Does Not Apply | K11: 6 | L11: Does Not Apply | M11: Cells of 1gram or less | N11: Batteries exceeding 300w/h | O11: 5kg to 10kg | Q11: Does Not Apply | S11: Tilt | W11: Does Not Apply | X11: Does Not Apply | Y11: Does Not Apply | AC11: Does Not Apply | AD11: Does Not Apply | AE11: 7 | AF11: II | AG11: >0 - ≤100g | AI11: Unavailable | AM11: 6 Months | AQ11: CA | AR11: Danish | AT11: Acetamide | AU11: Åland Islands | AW11: 65 | AX11: 72 | AY11: 72 | BX11: Basic Butt | BY11: Does Not Apply | BZ11: Nickel Metal Hydride | CA11: Does Not Apply | CB11: 6 | CC11: Does Not Apply | CD11: Cells of 1gram or less | CE11: Batteries exceeding 300w/h | CF11: 5kg to 10kg | CH11: Does Not Apply | CK11: External | CL11: Does Not Apply | CM11: Does Not Apply | CN11: Does Not Apply | CR11: Does Not Apply | CV11: Does Not Apply | CW11: 7 | CX11: II | CY11: >0 - ≤100g | DA11: Unavailable | DB11: Does Not Apply | DE11: Unavailable | DF11: 32" | DH11: Does Not Apply | DI11: 6 Months | DM11: Fireplace Included | DN11: Executive Chair | DO11: Composite | DV11: Does Not Apply | DX11: Does Not Apply | EH11: Does Not Apply | EI11: Basic Butt | EJ11: Does Not Apply | EK11: Does Not Apply | EL11: Nickel Metal Hydride | EM11: Does Not Apply | EN11: 6 | EO11: Does Not Apply | EP11: Cells of 1gram or less | EQ11: Batteries exceeding 300w/h | ER11: 5kg to 10kg | EW11: Does Not Apply | EX11: Does Not Apply | EY11: Does Not Apply | EZ11: Not Tested | FB11: Does Not Apply | FC11: Does Not Apply | FD11: Does Not Apply | FH11: Unavailable | FI11: Unavailable | FJ11: Does Not Apply | FM11: Does Not Apply | FO11: 7 | FP11: II | FQ11: >0 - ≤100g | FS11: Unavailable | FT11: Does Not Apply | FV11: Does Not Apply | FX11: Unavailable | FZ11: Does Not Apply | GA11: 6 Months | GE11: Leather Type | GF11: Lingerie Chest / Semainier | GI11: Does Not Apply | GN11: Wood | GO11: Does Not Apply | GP11: Basic Butt | GQ11: Does Not Apply | GR11: Does Not Apply | GT11: Does Not Apply | GU11: Unavailable | GW11: Does Not Apply | GX11: Does Not Apply | GY11: Does Not Apply | HG11: Does Not Apply | HN11: Does Not Apply | HP11: Unavailable | HR11: Does Not Apply | HS11: 6 Months | HV11: Does Not Apply | HX11: Queen | HY11: Sleigh | HZ11: Does Not Apply | IB11: Vinyl | II11: Basic Butt | IJ11: Does Not Apply | IK11: Does Not Apply | IL11: Nickel Metal Hydride | IM11: 6 | IN11: Does Not Apply | IO11: Cells of 1gram or less | IP11: Batteries exceeding 300w/h | IQ11: 5kg to 10kg | IW11: Unavailable | IY11: Split Grain Leather | IZ11: Denim | JA11: Rectangular | JB11: Does Not Apply | JC11: Does Not Apply | JE11: Does Not Apply | JF11: Does Not Apply | JG11: Does Not Apply | JI11: Does Not Apply | JJ11: Unavailable | JK11: Unavailable | JN11: Does Not Apply | JO11: Does Not Apply | JQ11: Does Not Apply | JR11: Does Not Apply | JS11: 7 | JT11: II | JU11: >0 - ≤100g | JW11: Does Not Apply | JY11: Does Not Apply | JZ11: Does Not Apply | KA11: Does Not Apply | KD11: Yes, Compliance Verified Program or Baby Safety Alliance (fka JPMA) | KF11: Does Not Apply | KG11: 6 Months | KK11: Print/Pattern
A12: Audio Towers | B12: Laptop Cart | I12: Alkaline | K12: 7 | M12: Cells of between 1 and 5 grams | N12: Batteries of between 100w/h and 300 w/h | O12: Does Not Apply | S12: Articulating | AE12: 5.2 | AF12: Does Not Apply | AG12: >100 - ≤500g | AI12: Does Not Apply | AM12: 1 Year | AR12: German | AT12: Acetazolamide | AU12: Albania | AW12: 70 | AX12: 96 | AY12: 96 | BX12: Biscuit Joint | BZ12: Alkaline | CB12: 7 | CD12: Cells of between 1 and 5 grams | CE12: Batteries of between 100w/h and 300 w/h | CF12: Does Not Apply | CK12: Convertible | CW12: 5.2 | CX12: Does Not Apply | CY12: >100 - ≤500g | DA12: Does Not Apply | DE12: Does Not Apply | DF12: 42" | DI12: 1 Year | DN12: Gaming Chair | DO12: Plastic | EI12: Biscuit Joint | EL12: Alkaline | EN12: 7 | EP12: Cells of between 1 and 5 grams | EQ12: Batteries of between 100w/h and 300 w/h | ER12: Does Not Apply | EZ12: 30,000-50,000 | FH12: Does Not Apply | FI12: Does Not Apply | FO12: 5.2 | FP12: Does Not Apply | FQ12: >100 - ≤500g | FS12: Does Not Apply | FX12: Does Not Apply | GA12: 1 Year | GE12: Casters/Glides | GF12: Mini Chest | GN12: Aluminum | GP12: Biscuit Joint | GU12: Does Not Apply | HP12: Does Not Apply | HS12: 1 Year | HX12: King | HY12: TV Bed | IB12: Shagreen Embossed | II12: Biscuit Joint | IL12: Alkaline | IM12: 7 | IO12: Cells of between 1 and 5 grams | IP12: Batteries of between 100w/h and 300 w/h | IQ12: Does Not Apply | IW12: Does Not Apply | IY12: Nubuck | IZ12: Microfiber / Microsuede | JA12: Camelback | JJ12: Does Not Apply | JK12: Does Not Apply | JS12: 5.2 | JT12: Does Not Apply | JU12: >100 - ≤500g | KD12: Does Not Apply | KG12: 1 Year | KK12: Storage
A13: Office Chairs | B13: Printer Stand | I13: Carbon Zinc | K13: 5 | M13: Batteries exceeding 25 grams | N13: Batteries of 100w/h or less | S13: Tank mount | AE13: 6.1 | AG13: >500g - ≤1kg | AM13: 2 Years | AR13: Greek | AT13: Acetochlor | AU13: Algeria | AW13: 77.5 | AX13: 120 | AY13: 120 | BX13: Tongue and Groove | BZ13: Carbon Zinc | CB13: 5 | CD13: Batteries exceeding 25 grams | CE13: Batteries of 100w/h or less | CK13: Recirculating | CW13: 6.1 | CY13: >500g - ≤1kg | DF13: 49" | DI13: 2 Years | DN13: Side Chair | DO13: Acrylic | EI13: Tongue and Groove | EL13: Carbon Zinc | EN13: 5 | EP13: Batteries exceeding 25 grams | EQ13: Batteries of 100w/h or less | EZ13: 15,000-30,000 | FO13: 6.1 | FQ13: >500g - ≤1kg | GA13: 2 Years | GE13: Arm Type | GF13: Standard Dresser / Chest | GN13: Melamine | GP13: Tongue and Groove | HS13: 2 Years | HX13: California King | HY13: Scalloped | IB13: Bicast Leather | II13: Tongue and Groove | IL13: Carbon Zinc | IM13: 5 | IO13: Batteries exceeding 25 grams | IP13: Batteries of 100w/h or less | IY13: Full Grain Leather | IZ13: Twill | JA13: Scooped | JS13: 6.1 | JU13: >500g - ≤1kg | KG13: 2 Years
A14: Beds | B14: Utility Cart | I14: Lead Acid (Spillable) | K14: 8 | M14: Does Not Apply | N14: Does Not Apply | S14: Recessed | AE14: 3 | AG14: >125ml - ≤500ml | AM14: 3 Years | AR14: English (United Kingdom) | AT14: Acetohydroxamic acid | AU14: American Samoa | AW14: 85 | AX14: 144 | BX14: Pocket Joint | BZ14: Lead Acid (Spillable) | CB14: 8 | CD14: Does Not Apply | CE14: Does Not Apply | CK14: B-Vent | CW14: 3 | CY14: >125ml - ≤500ml | DF14: 55" | DI14: 3 Years | DN14: Task Chair | DO14: Manufactured Wood | EI14: Pocket Joint | EL14: Lead Acid (Spillable) | EN14: 8 | EP14: Does Not Apply | EQ14: Does Not Apply | EZ14: 50,000+ | FO14: 3 | FQ14: >125ml - ≤500ml | GA14: 3 Years | GE14: Customization | GF14: Unavailable | GN14: Silicone | GP14: Pocket Joint | HS14: 3 Years | HX14: Full XL | HY14: Panel Headboard Design | IB14: Faux Cowhide | II14: Pocket Joint | IL14: Lead Acid (Spillable) | IM14: 8 | IO14: Does Not Apply | IP14: Does Not Apply | IY14: Sheepskin | IZ14: Unavailable | JA14: Stepped | JS14: 3 | JU14: >125ml - ≤500ml | KG14: 3 Years
A15: Dressers & Chests | B15: Laptop/Tablet Storage Cart | I15: Lead Acid (Non-Spillable) | K15: 10 | S15: Unavailable | AE15: 4.1 | AG15: >25 - ≤125ml | AM15: 5 Years | AR15: English (United States) | AT15: 2-Acetylaminofluorene | AU15: Andorra | AW15: 92.5 | AX15: 168 | BX15: Cam Bolt | BZ15: Lead Acid (Non-Spillable) | CB15: 10 | CK15: Does Not Apply | CW15: 4.1 | CY15: >25 - ≤125ml | DF15: 50" | DI15: 5 Years | DN15: Criss Cross Chair | DO15: Solid + Manufactured Wood | EI15: Cam Bolt | EL15: Lead Acid (Non-Spillable) | EN15: 10 | EZ15: Unavailable | FO15: 4.1 | FQ15: >25 - ≤125ml | GA15: 5 Years | GE15: Back Height | GN15: Brass | GP15: Cam Bolt | HS15: 5 Years | HX15: Super Single | HY15: Bookcase | IB15: Faux Sheepskin | II15: Cam Bolt | IL15: Lead Acid (Non-Spillable) | IM15: 10 | IY15: Cowhide | IZ15: Does Not Apply | JA15: Other | JS15: 4.1 | JU15: >25 - ≤125ml | KG15: 5 Years
A16: Nightstands | I16: Silver Oxide | K16: 4 | AE16: 4.3 | AG16: >1kg - ≤5kg | AM16: 10 Years | AR16: Spanish | AT16: Acifluorfen sodium | AU16: Angola | AW16: 100 | AX16: 192 | BX16: Dowel Joint | BZ16: Silver Oxide | CB16: 4 | CW16: 4.3 | CY16: >1kg - ≤5kg | DF16: 58" | DI16: 10 Years | DO16: Steel | EI16: Dowel Joint | EL16: Silver Oxide | EN16: 4 | EZ16: Does Not Apply | FO16: 4.3 | FQ16: >1kg - ≤5kg | GA16: 10 Years | GE16: Team Logo | GN16: Fabric | GP16: Dowel Joint | HS16: 10 Years | HX16: RV King | HY16: Spindle | IB16: Faux Shearing | II16: Dowel Joint | IL16: Silver Oxide | IM16: 4 | IY16: Corrected Grain Leather | JA16: Rounded | JS16: 4.3 | JU16: >1kg - ≤5kg | KG16: 10 Years
A17: Armoires & Wardrobes | I17: Does Not Apply | K17: 9 | AE17: 4.2 | AG17: >5L | AM17: 20 Years | AR17: Finnish | AT17: Acrylamide | AU17: Anguilla | AW17: 110 | AX17: 216 | BX17: Half-Lap | BZ17: Does Not Apply | CB17: 9 | CW17: 4.2 | CY17: >5L | DF17: 65" | DI17: 20 Years | DO17: Iron | EI17: Half-Lap | EL17: Does Not Apply | EN17: 9 | FO17: 4.2 | FQ17: >5L | GA17: 20 Years | GE17: Pattern | GN17: Bamboo | GP17: Half-Lap | HS17: 20 Years | HX17: Short Queen | HY17: Murphy | IB17: Unavailable | II17: Half-Lap | IL17: Does Not Apply | IM17: 9 | IY17: Shearling | JA17: Unavailable | JS17: 4.2 | JU17: >5L | KG17: 20 Years
A18: Daybeds & Guest Beds | K18: Unavailable | AE18: 5.1 | AG18: >5kg | AM18: 25 Years | AR18: French (Canada) | AT18: Acrylonitrile | AU18: Antarctica | AW18: 125 | AX18: 240 | BX18: Box | CB18: Unavailable | CW18: 5.1 | CY18: >5kg | DF18: 75" | DI18: 25 Years | DO18: Cane | EI18: Box | EN18: Unavailable | FO18: 5.1 | FQ18: >5kg | GA18: 25 Years | GN18: Bakelite | GP18: Box | HS18: 25 Years | HX18: Antique / Three Quarter | HY18: Wingback | IB18: Does Not Apply | II18: Box | IM18: Unavailable | IY18: Unavailable | JA18: Does Not Apply | JS18: 5.1 | JU18: >5kg | KG18: 25 Years
A19: Headboards | K19: Does Not Apply | AE19: 2.3 | AG19: Does Not Apply | AM19: Lifetime | AR19: Hungarian | AT19: Actinomycin D | AU19: Antigua and Barbuda | AW19: 150 | AX19: 360 | BX19: Lap | CB19: Does Not Apply | CW19: 2.3 | CY19: Does Not Apply | DF19: 70" | DI19: Lifetime | DO19: Raffia | EI19: Lap | EN19: Does Not Apply | FO19: 2.3 | FQ19: Does Not Apply | GA19: Lifetime | GN19: Nylon | GP19: Lap | HS19: Lifetime | HX19: Split California King | HY19: Open-Frame | II19: Lap | IM19: Does Not Apply | IY19: Does Not Apply | JS19: 2.3 | JU19: Does Not Apply | KG19: Lifetime
A20: Bedroom Sets | AE20: 6.2 | AM20: 15 Years | AR20: Indonesian | AT20: AF-2;[2-(2-furyl)-3-(5-nitro-2-furyl)]acrylamide | AU20: Argentina | AW20: 175 | AX20: 480 | BX20: Double Dowelled | CW20: 6.2 | DF20: 48" | DI20: 15 Years | DO20: Nickel | EI20: Double Dowelled | FO20: 6.2 | GA20: 15 Years | GN20: Enameled Cast Iron | GP20: Double Dowelled | HS20: 15 Years | HX20: Short Full | HY20: Slat Headboard Design | II20: Double Dowelled | JS20: 6.2 | KG20: 15 Years
A21: Easels | AE21: 9 | AM21: 4 Years | AR21: Icelandic | AT21: Aflatoxins | AU21: Armenia | AW21: 200 | AX21: 600 | BX21: Bridle | CW21: 9 | DF21: 43" | DI21: 4 Years | DO21: Glass | EI21: Bridle | FO21: 9 | GA21: 4 Years | GN21: Cast Iron | GP21: Bridle | HS21: 4 Years | HX21: Split King | HY21: Daybed | II21: Bridle | JS21: 9 | KG21: 4 Years
A22: Display Cases | AE22: 8 | AM22: 18 Months | AR22: Italian | AT22: Alachlor | AU22: Aruba | AW22: 250 | AX22: 720 | BX22: Halved | CW22: 8 | DF22: 88" | DI22: 18 Months | DO22: Laminate | EI22: Halved | FO22: 8 | GA22: 18 Months | GN22: Gold Plated | GP22: Halved | HS22: 18 Months | HX22: California Queen | HY22: Unavailable | II22: Halved | JS22: 8 | KG22: 18 Months
A23: Lockers | AE23: Does Not Apply | AM23: 6 Years | AR23: Japanese | AT23: Alcoholic beverages, when associated with alcohol abuse | AU23: Australia | AW23: 300 | AX23: 840 | BX23: Corner Block Reinforced | CW23: Does Not Apply | DF23: 60" | DI23: 6 Years | DO23: Wicker | EI23: Corner Block Reinforced | FO23: Does Not Apply | GA23: 6 Years | GN23: Sterling Silver | GP23: Corner Block Reinforced | HS23: 6 Years | HX23: Split Queen | II23: Corner Block Reinforced | JS23: Does Not Apply | KG23: 6 Years
A24: Lecterns & Podiums | AM24: 7 Years | AR24: Korean | AT24: Aldrin | AU24: Austria | AW24: 400 | AX24: 960 | BX24: Miter | DF24: 78" | DI24: 7 Years | DO24: Leather | EI24: Miter | GA24: 7 Years | GN24: Resin | GP24: Miter | HS24: 7 Years | HX24: Split Top King | II24: Miter | KG24: 7 Years
A25: Desks | AM25: 8 Years | AR25: Norwegian (Bokmål) | AT25: All-trans retinoic acid | AU25: Azerbaijan | AW25: 500 | BX25: Unavailable | DF25: 85" | DI25: 8 Years | DO25: Vinyl | EI25: Unavailable | GA25: 8 Years | GN25: Silver Plated | GP25: Unavailable | HS25: 8 Years | HX25: Split Top Queen | II25: Unavailable | KG25: 8 Years
A26: Literature Racks | AM26: 9 Years | AR26: Dutch | AT26: Aloe Vera, non-decolorized whole leaf extract | AU26: Bahamas | BX26: Does Not Apply | DF26: 77" | DI26: 9 Years | DO26: Foam | EI26: Does Not Apply | GA26: 9 Years | GN26: Rubber | GP26: Does Not Apply | HS26: 9 Years | II26: Does Not Apply | KG26: 9 Years
A27: Filing Cabinets | AM27: 12 Years | AR27: Polish | AT27: Alprazolam | AU27: Bahrain | DI27: 12 Years | DO27: Kiln Dried Hardwood | GA27: 12 Years | GN27: Stainless Steel | HS27: 12 Years | KG27: 12 Years
A28: Bookcases | AM28: 11 Years | AR28: Portuguese | AT28: Amantadine hydrochloride | AU28: Bangladesh | DI28: 11 Years | DO28: Stainless Steel | GA28: 11 Years | GN28: Pewter | HS28: 11 Years | KG28: 11 Years
A29: Classroom Chairs | AM29: 13 Years | AR29: Romanian | AT29: Amikacin sulfate | AU29: Barbados | DI29: 13 Years | DO29: Rubber | GA29: 13 Years | GN29: No Handles | HS29: 13 Years | KG29: 13 Years
A30: Wall & Accent Mirrors | AM30: 14 Years | AR30: Russian | AT30: 2-Aminoanthraquinone | AU30: Belarus | DI30: 14 Years | DO30: Plywood | GA30: 14 Years | GN30: Steel | HS30: 14 Years | KG30: 14 Years
A31: Office Stools | AM31: No Commercial Warranty | AR31: Slovak | AT31: p-Aminoazobenzene | AU31: Belgium | DI31: No Commercial Warranty | DO31: Ceramic | GA31: No Commercial Warranty | GN31: Unavailable | HS31: No Commercial Warranty | KG31: No Commercial Warranty
A32: Office Sets | AM32: Does Not Apply | AR32: Swedish | AT32: o-Aminoazotoluene | AU32: Belize | DI32: Does Not Apply | DO32: Brass | GA32: Does Not Apply | GN32: Does Not Apply | HS32: Does Not Apply | KG32: Does Not Apply
A33: Stackable & Nesting Chairs | AR33: Ukrainian | AT33: 4-Aminobiphenyl (4-aminodiphenyl) | AU33: Benin | DO33: Fabric
A34: Futon Mattresses | AR34: Vietnamese | AT34: 1-Amino-2,4-dibromoanthraquinone | AU34: Bermuda | DO34: Concrete
A35: Pot Racks | AR35: Chinese (S) | AT35: 3-Amino-9-ethylcarbazole hydrochloride | AU35: Bhutan | DO35: Particle Board
A36: Plant Stands & Tables | AR36: Chinese (T) | AT36: 2-Aminofluorene | AU36: Bolivia | DO36: Fiberglass
A37: Accent Chairs | AT37: Aminoglutethimide | AU37: Bosnia and Herzegovina | DO37: Resin
A38: Kitchen Islands | AT38: Aminoglycosides | AU38: Botswana | DO38: Faux Leather
A39: Baker's Racks | AT39: 1-Amino-2-methylanthraquinone | AU39: Bouvet Island | DO39: Cardboard
A40: Wine Racks | AT40: 2-Amino-5-(5-nitro-2-furyl)-1,3,4-thiadiazole | AU40: Brazil | DO40: Genuine Marble
A41: Bar Stools | AT41: 4-Amino-2-nitrophenol | AU41: British Indian Ocean Territory | DO41: High-Density Polyethylene (HDPE)
A42: Mantel & Tabletop Clocks | AT42: Aminopterin | AU42: Brunei Darussalam | DO42: Stone
A43: Grandfather Clocks / Floor Clocks | AT43: Amiodarone hydrochloride | AU43: Bulgaria | DO43: Rope
A44: Conference Tables | AT44: Amitraz | AU44: Burkina Faso | DO44: Bamboo / Rattan
A45: Folding Tables | AT45: Amitrole | AU45: Burundi | DO45: Woven Palm
A46: Coat Racks and Hooks | AT46: Amoxapine | AU46: Cambodia | DO46: Zinc
A47: Cafeteria Tables | AT47: Amsacrine | AU47: Cameroon | DO47: Wrought Iron
A48: Bars & Bar Sets | AT48: Analgesic mixtures containing Phenacetin | AU48: Cape Verde | DO48: Powder Coated Steel
... A62: Tool Cabinets | AT62: Arsenic (inorganic oxides) | AU62: Côte D'Ivoire | DO62: Does Not Apply
A63: Dining Table Sets | AT63: Asbestos | AU63: Croatia
A64: Dining Tables | AT64: Aspirin (NOTE: It is especially important not to use aspirin during the last three months of pregnancy, unless specifically directed to do so by a physician because it may cause problems in the unborn child or complications during delivery.) | AU64: Cuba
A65: Vanities | AT65: Atenolol | AU65: Cyprus
A66: Bean Bags | AT66: Atrazine | AU66: Czech Republic
A67: Accent Chests / Cabinets | AT67: Auramine | AU67: Denmark
A68: Classic Game Tables & Puzzle Tables | AT68: Auranofin | AU68: Djibouti
A69: Sideboards & Buffets | AT69: Avermectin B1 (Abamectin) | AU69: Dominica
A70: Hammocks | AT70: Azacitidine | AU70: Dominican Republic
A71: Area Rugs | AT71: Azaserine | AU71: Ecuador
A72: Dining Chairs | AT72: Azathioprine | AU72: Egypt
A73: China Cabinets | AT73: Azobenzene | AU73: El Salvador
A74: Hall Trees | AT74: Barbiturates | AU74: Equatorial Guinea
... A254: Swing Sets & Playgrounds | AT254: Dibromoacetic acid | AU254: United States - APO/FPO/DPO
A255: Swing Set Accessories | AT255: Dibromoacetonitrile
A256: Toaster Ovens | AT256: 2,3-Dibromo-1-propanol
A257: Slides | AT257: Dichloroacetic acid
A258: Coffee Makers | AT258: p-Dichlorobenzene
A259: Indoor Gardening | AT259: 3,3'-Dichlorobenzidine
A260: Wine Refrigerators | AT260: 3,3'-Dichlorobenzidine dihydrochloride
A261: Microwaves | AT261: 1,1-Dichloro-2,2-bis(p-chloropheny)ethylene (DDE)
A262: Cabinet Organization | AT262: 1,4-Dichloro-2-butene
A263: Teeter-Totters & Seesaws | AT263: 3,3'-Dichloro-4,4'-diamino-diphenyl ether
A264: Sandboxes & Sand Toys | AT264: 1,1-Dichloroethane
A265: Commercial Playground Equipment | AT265: Dichloromethane (Methylene chloride)
A266: Indoor Chaise Lounges | AT266: Dichlorophene
... A850: Cold Plunges | AT850: Nickel hydroxide
AT851: Norethisterone (Norethindrone) /Mestranol
AT852: Anabolic steroids
AT853: Altretamine
AT854: Beryllium
AT855: Beryllium Oxide
AT856: Beryllium Sulfate
AT857: Hexachlorocyclohexane (alpha isomer)
AT858: Hexachlorocyclohexane (beta isomer)
AT859: Hexachlorocyclohexane (gamma isomer)
AT860: Cyanide salts that readily dissociate in solution (expressed as cyanide)
AT861: Hydrogen cyanide
AT862: Potassium cyanide
... AT908: Vismodegib

Sheet 3 - Carts & Stands
B1: core::supplierPartNumber | C1: core::amazonStandardIdentificationNumber | D1: core::manufacturerId | E1: core::manufacturerPartNumber | F1: core::universalProductCode | G1: core::productName | H1: core::collectionName | I1: core::manufacturerProductUrl | J1: variantGrouping::variantType | K1: variantGrouping::groupReferenceId | L1: variantGrouping::variantGrouping | M1: variantGrouping::variantAttributeNameOnSite | N1: variantGrouping::variantGrouping | O1: variantGrouping::variantAttributeNameOnSite | P1: variantGrouping::variantGrouping | Q1: variantGrouping::variantAttributeNameOnSite | R1: price::wholesalePrice | S1: price::minimumAdvertizedPrice | T1: price::manufacturerSuggestedRetailPrice | U1: featureDescription::romanceCopy | V1: featureDescription::genericFeatures | W1: featureDescription::genericFeatures | X1: featureDescription::genericFeatures | Y1: featureDescription::genericFeatures | Z1: featureDescription::genericFeatures | AA1: shippingAndFulfillment::minimumOrderQuantity | AB1: shippingAndFulfillment::forceQuantityMultiplier | AC1: shippingAndFulfillment::displaySetQuantity | AD1: shippingAndFulfillment::productWeight | AE1: shippingAndFulfillment::shipType | AF1: shippingAndFulfillment::freightClass | AG1: shippingAndFulfillment::leadTime | AH1: shippingAndFulfillment::replacementLeadTime | AI1: shippingAndFulfillment::nationalMotorFreightClass | AJ1: shippingAndFulfillment::flatPack | AK1: shippingAndFulfillment::shipPalletized | AL1: shippingAndFulfillment::weight | AM1: shippingAndFulfillment::height | AN1: shippingAndFulfillment::width | AO1: shippingAndFulfillment::depth | AP1: propSixtyFive::warningRequired | AQ1: propSixtyFive::chemicalId | AR1: propSixtyFive::toxicity | AS1: propSixtyFive::countryOfManufacturer | AT1: media::imageValue | AU1: media::imageValue | AV1: media::imageValue | AW1: media::imageValue | AX1: media::imageValue | AY1: media::videoValue | AZ1: media::documentValue | BA1: media::documentType | BB1: media::legalDocumentType | BC1: media::regionType | BD1: media::language | BE1: media::documentValue | BF1: media::documentType | BG1: media::legalDocumentType | BH1: media::regionType | BI1: media::language | BJ1: media::documentValue | BK1: media::documentType | BL1: media::legalDocumentType | BM1: media::regionType | BN1: media::language | BO1: 70212 | BP1: 149726 | BQ1: 149770 | BR1: 185252 | BS1: 149785 | BT1: 182057 | BU1: 164399 | BV1: 149748 | BW1: 149749 | BX1: 149750 | BY1: 149753 | BZ1: 229333 | CA1: 245268 | CB1: 344983 | CC1: 351568 | CD1: 346774 | CE1: 367308 | CF1: 351573 | CG1: 352308 | CH1: 352295 | CI1: 351604 | CJ1: 363032 | CK1: 149782 | CL1: 382561 | CM1: 149965 | CN1: 383797 | CO1: 149784 | CP1: 384383 | CQ1: 149964 | CR1: 419944 | CS1: 149794 | CT1: 149810 | CU1: 192864 | CV1: 149754 | CW1: 201408 | CX1: 224843 | CY1: 225064 | CZ1: 364709 | DA1: 236080 | DB1: 249312 | DC1: 251061 | DD1: 192875 | DE1: 149756 | DF1: 339306 | DG1: 373554 | DH1: 340804 | DI1: 341056 | DJ1: 369616 | DK1: 368261 | DL1: 375301 | DM1: 376200 | DN1: 385918 | DO1: 415201 | DP1: 149771 | DQ1: 70234 | DR1: 70239 | DS1: 70240 | DT1: 70241 | DU1: 229332 | DV1: 334763 | DW1: 254003 | DX1: 255912
B2: Basic Information | J2: Variants | R2: Pricing | U2: Marketing Information | AA2: Fulfillment Information | AL2: Carton Details | AP2: Compliance | AT2: Media | BO2: Attributes
B3: Required | C3: Additional | D3: Required | E3: Required | F3: Recommended | G3: Required | H3: Additional | I3: Additional | J3: Required | K3: Conditional | L3: Recommended | M3: Conditional | N3: Recommended | O3: Conditional | P3: Recommended | Q3: Conditional | R3: Required | S3: Additional | T3: Additional | U3: Conditional | V3: Conditional | W3: Conditional | X3: Conditional | Y3: Conditional | Z3: Conditional | AA3: Required | AB3: Required | AC3: Required | AD3: Required | AE3: Required | AF3: Conditional | AG3: Required | AH3: Required | AI3: Additional | AJ3: Additional | AK3: Additional | AL3: Required | AM3: Required | AN3: Required | AO3: Required | AP3: Required | AQ3: Conditional | AR3: Conditional | AS3: Required | AT3: Required | AU3: Additional | AV3: Additional | AW3: Additional | AX3: Additional | AY3: Additional | AZ3: Conditional | BA3: Conditional | BB3: Conditional | BC3: Conditional | BD3: Conditional | BE3: Conditional | BF3: Conditional | BG3: Conditional | BH3: Conditional | BI3: Conditional | BJ3: Conditional | BK3: Conditional | BL3: Conditional | BM3: Conditional | BN3: Conditional | BO3: Required | BP3: Required | BQ3: Recommended | BR3: Recommended | BS3: Recommended | BT3: Recommended | BU3: Recommended | BV3: Recommended | BW3: Recommended | BX3: Recommended | BY3: Recommended | BZ3: Required | CA3: Additional | CB3: Additional | CC3: Additional | CD3: Additional | CE3: Additional | CF3: Additional | CG3: Additional | CH3: Additional | CI3: Additional | CJ3: Recommended | CK3: Recommended | CL3: Recommended | CM3: Recommended | CN3: Required | CO3: Recommended | CP3: Recommended | CQ3: Recommended | CR3: Recommended | CS3: Recommended | CT3: Recommended | CU3: Required | CV3: Additional | CW3: Required | CX3: Required | CY3: Required | CZ3: Required | DA3: Required | DB3: Required | DC3: Required | DD3: Required | DE3: Required | DF3: Additional | DG3: Additional | DH3: Additional | DI3: Additional | DJ3: Additional | DK3: Required | DL3: Required | DM3: Additional | DN3: Recommended | DO3: Recommended | DP3: Required | DQ3: Required | DR3: Required | DS3: Recommended | DT3: Required | DU3: Required | DV3: Recommended | DW3: Recommended | DX3: Recommended
A4: Errors | B4: Supplier Part Number | C4: ASIN or Amazon Seller SKU | D4: Brand | E4: Manufacturer Part Number | F4: Universal Product Code | G4: Product Name | H4: Collection Name | I4: Manufacturer Product URL | J4: Variant Type | K4: Group Reference ID | L4: Variant Grouping 1 | M4: Variant Attribute Name On Site 1 | N4: Variant Grouping 2 | O4: Variant Attribute Name On Site 2 | P4: Variant Grouping 3 | Q4: Variant Attribute Name On Site 3 | R4: Base Cost | S4: Minimum Advertised Price | T4: Manufacturer Suggested Retail Price | U4: Marketing Copy | V4: Feature Bullet 1 | W4: Feature Bullet 2 | X4: Feature Bullet 3 | Y4: Feature Bullet 4 | Z4: Feature Bullet 5 | AA4: Minimum Order Quantity | AB4: Force Quantity Multiplier | AC4: Display Set Quantity | AD4: Product Weight | AE4: Ship Type | AF4: Freight Class | AG4: Lead Time | AH4: Replacement Lead Time | AI4: National Motor Freight Class | AJ4: Flat Pack | AK4: Ship Palletized | AL4: Carton Weight 1 | AM4: Carton Height 1 | AN4: Carton Width 1 | AO4: Carton Depth 1 | AP4: Warning Required | AQ4: Chemical 1 | AR4: Toxicity 1 | AS4: Country Of Manufacturer | AT4: Image File Name or URL 1 | AU4: Image File Name or URL 2 | AV4: Image File Name or URL 3 | AW4: Image File Name or URL 4 | AX4: Image File Name or URL 5 | AY4: Video File Name or URL 1 | AZ4: Document File Name or URL 1 | BA4: Document Type 1 | BB4: Legal Document Type 1 | BC4: Document Region 1 | BD4: Document Language 1 | BE4: Document File Name or URL 2 | BF4: Document Type 2 | BG4: Legal Document Type 2 | BH4: Document Region 2 | BI4: Document Language 2 | BJ4: Document File Name or URL 3 | BK4: Document Type 3 | BL4: Legal Document Type 3 | BM4: Document Region 3 | BN4: Document Language 3 | BO4: Product Type | BP4: Material | BQ4: Adjustable Height | BR4: Wood Species | BS4: Shelf Weight Capacity | BT4: Tilting | BU4: Cabinets Included | BV4: Drawers Included | BW4: Legs Included | BX4: Wheels / Casters Included | BY4: Overall Weight Capacity | BZ4: Supplier Intended and Approved Use | CA4: Country of Origin - Additional Details | CB4: Battery or Batteries Included | CC4: Battery Type | CD4: Battery Composition | CE4: Number of Batteries | CF4: Battery Shipment | CG4: Lithium Content | CH4: Watt Rating of Cells / Battery | CI4: Weight of Cells / Battery | CJ4: Removable Components | CK4: Adjustable Shelves | CL4: Locking Wheels | CM4: Mount Type | CN4: Color / Finish | CO4: Number of Shelves | CP4: Storage Included | CQ4: Shelf Type | CR4: Pieces Included | CS4: Number of Cabinets | CT4: Number of Wheels / Casters Included | CU4: CPSC - 16 CFR 1303 Compliant | CV4: ADA Compliant | CW4: Composite Wood Product (CWP) | CX4: CARB Phase II Compliant (formaldehyde emissions) | CY4: TSCA Title VI Compliant (formaldehyde emissions) | CZ4: CANFER Compliant | DA4: Uniform Packaging and Labeling Regulations (UPLR) Compliant | DB4: Canada Product Restriction | DC4: Reason for Restriction | DD4: Lacey Act Compliant | DE4: General Certificate of Conformity (GCC) | DF4: Hazardous Material / Dangerous Goods | DG4: UN or ID number | DH4: Hazard Class(es) | DI4: Packing Group | DJ4: Hazardous Material Weight | DK4: Energy Efficiency Regulations Compliant | DL4: Safety Listing(s) | DM4: Safety Listing(s) Registration Number | DN4: ISTA Certified | DO4: Sustainability & Social Responsibility Certifications (North America Only) | DP4: Overall Height - Top to Bottom | DQ4: Overall Width - Side to Side | DR4: Overall Depth - Front to Back | DS4: Overall Product Weight | DT4: Assembly Required | DU4: Commercial Warranty | DV4: Commercial Warranty Length | DW4: Product Warranty | DX4: Warranty Length
A5: Displays the error status and message for the first error in the row, with a link to the corresponding cell. | B5: Must be less than 64 characters and must be a unique value (products cannot be added if they have the same part number as something you already have in your catalog). This is the supplier-specific value for the product as it appears on your Inventory Feed and Purchased Orders. | C5: The Amazon Standard Identification Number (ASIN) is a 10-character alphanumeric unique identifier assigned by Amazon.com and its partners for product identification within the Amazon organization. The Amazon Seller SKU is Amazon's identifier for your product that allows you to fulfill the product through Amazon shipping even when selling the product on other sites like Wayfair. | D5: Enter your product's brand (may be the same as the product's manufacturer). New brands must be created in the brand management tool in Partner Home before they can be selected here. | E5: Must be less than 64 characters and must be a unique value (products cannot be added if they have the same part number as something you already have in your catalog). This is the part number provided by the manufacturer. | F5: Must follow the standard UPC format and must be a unique value (products cannot be added if they have the same UPC as something you already have in your catalog). | G5: Please do not use abbreviations or exceed the 255 character limit. Wayfair may adjust the provided name based on marketing standards per class. | H5: If the product belongs to a collection of associated products that are not just product variances/options, enter the collection here. This can match with collections of products you already sell on site. For example, a collection may be a bed and nightstand that both follow a modern theme, but would not be a bed that comes in two separate colors. Products in a collection do not share the same listing on site. | I5: Enter the URL for the specific manufacturer product page of your product. | J5: Indicate whether this part number is a standalone product, primary variant (all required fields must be provided), or non-primary variant (data can be autofilled from primary variant). | K5: Provide an identifier to group your variants. This information will be used to create a listing. | L5: Common attribute to group products by. Select from dropdown or enter a custom value. | M5: Display name for variant attribute, if differs from corresponding Attribute answer. | N5: Common attribute to group products by. Select from dropdown or enter a custom value. | O5: Display name for variant attribute, if differs from corresponding Attribute answer. | P5: Common attribute to group products by. Select from dropdown or enter a custom value. | Q5: Display name for variant attribute, if differs from corresponding Attribute answer. | R5: Your supplier profile preference for currency is used to determine the currency of the base (wholesale) cost provided. | S5: The region selected for this sheet is used to determine the currency of the MAP provided. This may differ from the currency of your base cost. | T5: The region selected for this sheet is used to determine the currency of the MSRP provided. This may differ from the currency of your base cost. | U5: Please do not use special symbols (trademark, copyright, etc.) or extra lines/spacing. This should be a short, single paragraph product description in complete sentences highlighting details about key product information. | V5: 15 words or less, describing one aspect of the product, eg., Unique aspects, benefits, use cases, technology. These provide customers with key facts at first glance and help them to decide whether they want to make the purchase. If no marketing copy is provided, then at least 3 feature bullets must be provided. | W5: 15 words or less, describing one aspect of the product, eg., Unique aspects, benefits, use cases, technology. These provide customers with key facts at first glance and help them to decide whether they want to make the purchase. If no marketing copy is provided, then at least 3 feature bullets must be provided. | X5: 15 words or less, describing one aspect of the product, eg., Unique aspects, benefits, use cases, technology. These provide customers with key facts at first glance and help them to decide whether they want to make the purchase. If no marketing copy is provided, then at least 3 feature bullets must be provided. | Y5: 15 words or less, describing one aspect of the product, eg., Unique aspects, benefits, use cases, technology. These provide customers with key facts at first glance and help them to decide whether they want to make the purchase. If no marketing copy is provided, then at least 3 feature bullets must be provided. | Z5: 15 words or less, describing one aspect of the product, eg., Unique aspects, benefits, use cases, technology. These provide customers with key facts at first glance and help them to decide whether they want to make the purchase. If no marketing copy is provided, then at least 3 feature bullets must be provided. | AA5: The minimum count of items a customer must choose to purchase the product. | AB5: This represents how many items the customer must buy in increments of, or in addition to. For example, a multiplier of 2 would mean a custom must buy 1 quantity, 3 quantity, 5 quantity, or some other multiple of 2. | AC5: Number of items represented by the part number and wholesale price. For example, if you want to sell a bundle of pillows, and the part number and wholesale cost you provided represents that full bundle of pillows, then you would answer the Display Set Quantity question with how many pillows are in the bundle. | AD5: [Pounds] What is the total weight of this product once assembled? Please enter just the number (i.e. 45.5) without a unit of measurement. | AE5: Enter small parcel or LTL to indicate how the product can ship based on size and weight. | AF5: Each product falls into 1 of 18 classes determined by a product's 'transportability' and are crucial for calculating shipping cost. The field is required when ship type is LTL. | AG5: [Hours] This is the length of time from receipt of PO to shipment from the warehouse. | AH5: [Hours] This is length of time from receipt of a replacement PO to shipment from the warehouse | AI5: 5 to 7 digit number in length (depending on any sub classification) that will identify what is shipping in the box | AJ5: Also known as 'knocked down'. Select 'Yes' if this product ships disassembled in a flat pack box. | AK5: Select 'Yes' if this product ships on a pallet. | AL5: [Pounds] Enter in the shipping weight (i.e. 45.5) of the packaging used for the product. If the product ships in more than one box, this measurement is per box. | AM5: [Inches] Enter in the shipping height (i.e. 45.5) of the packaging used for the product. If the product ships in more than one box, this measurement is per box. | AN5: [Inches] Enter in the shipping width (i.e. 45.5) of the packaging used for the product. If the product ships in more than one box, this measurement is per box. | AO5: [Inches] Enter in the shipping depth (i.e. 45.5) of the packaging used for the product. If the product ships in more than one box, this measurement is per box. | AP5: If the product requires a warning for Proposition 65 compliance in California, answer 'Yes' and indicate which chemicals and toxicities are applicable. | AQ5: Select the chemical that requires the Prop65 warning. | AR5: Select the toxicity that can result from the selected chemical. | AS5: Provide only a single country of manufacture for each product. | AT5: Your first image will be set as the lead image for this listing, however, is subject to change upon Wayfair review. For each image uploaded, provide the file name with extension (e.g. PART_1.jpeg) or a direct public URL which leads to a single image (tip: to isolate the image, right click + select Open Image in New Tab). Elements like logos, buttons, etc will interfere with our ability to download the image. Do not exceed 20 images per product. | AU5: Your first image will be set as the lead image for this listing, however, is subject to change upon Wayfair review. For each image uploaded, provide the file name with extension (e.g. PART_1.jpeg) or a direct public URL which leads to a single image (tip: to isolate the image, right click + select Open Image in New Tab). Elements like logos, buttons, etc will interfere with our ability to download the image. Do not exceed 20 images per product. | AV5: Your first image will be set as the lead image for this listing, however, is subject to change upon Wayfair review. For each image uploaded, provide the file name with extension (e.g. PART_1.jpeg) or a direct public URL which leads to a single image (tip: to isolate the image, right click + select Open Image in New Tab). Elements like logos, buttons, etc will interfere with our ability to download the image. Do not exceed 20 images per product. | AW5: Your first image will be set as the lead image for this listing, however, is subject to change upon Wayfair review. For each image uploaded, provide the file name with extension (e.g. PART_1.jpeg) or a direct public URL which leads to a single image (tip: to isolate the image, right click + select Open Image in New Tab). Elements like logos, buttons, etc will interfere with our ability to download the image. Do not exceed 20 images per product. | AX5: Your first image will be set as the lead image for this listing, however, is subject to change upon Wayfair review. For each image uploaded, provide the file name with extension (e.g. PART_1.jpeg) or a direct public URL which leads to a single image (tip: to isolate the image, right click + select Open Image in New Tab). Elements like logos, buttons, etc will interfere with our ability to download the image. Do not exceed 20 images per product. | AY5: Provide the video’s file name with extension for separate uploads or a direct public URL. Do not exceed 10 videos per product. | AZ5: Provide the document’s file name with extension for separate uploads or a direct public URL. Do not exceed 10 documents per product. | BA5: Select one or more values from the provided list that best describe the document’s purpose. This classification helps customers easily find information like “Installation & Assembly” guides, “Warranty Information,” or “Specifications. | BB5: If the document serves as a legal notice or certification (e.g., “ASTM F2057 - 19,” “ANSI A117.1 Compliant”), select the specific type(s) from the provided list. This is used for compliance and to display certifications to customers. | BC5: Select the country or region where this document is legally applicable. This is crucial for compliance-related documents that may differ across locations. | BD5: Select the language in which the document is written. | BE5: Provide the document’s file name with extension for separate uploads or a direct public URL. Do not exceed 10 documents per product. | BF5: Select one or more values from the provided list that best describe the document’s purpose. This classification helps customers easily find information like “Installation & Assembly” guides, “Warranty Information,” or “Specifications. | BG5: If the document serves as a legal notice or certification (e.g., “ASTM F2057 - 19,” “ANSI A117.1 Compliant”), select the specific type(s) from the provided list. This is used for compliance and to display certifications to customers. | BH5: Select the country or region where this document is legally applicable. This is crucial for compliance-related documents that may differ across locations. | BI5: Select the language in which the document is written. | BJ5: Provide the document’s file name with extension for separate uploads or a direct public URL. Do not exceed 10 documents per product. | BK5: Select one or more values from the provided list that best describe the document’s purpose. This classification helps customers easily find information like “Installation & Assembly” guides, “Warranty Information,” or “Specifications. | BL5: If the document serves as a legal notice or certification (e.g., “ASTM F2057 - 19,” “ANSI A117.1 Compliant”), select the specific type(s) from the provided list. This is used for compliance and to display certifications to customers. | BM5: Select the country or region where this document is legally applicable. This is crucial for compliance-related documents that may differ across locations. | BN5: Select the language in which the document is written. | BO5: What type of product is this? | BP5: What material is the product made of? | BQ5: Is the height of this product adjustable? | BR5: What type of wood was used to construct this product? This describes the actual materials used, not the product's appearance. | BS5: [Pounds] What is the weight capacity of the shelf/shelves? | BT5: Does this product tilt? | BU5: Does this product include cabinets? | BV5: Does this product have any drawers? | BW5: Does this product have legs? | BX5: Does this product have wheels or casters? | BY5: [Pounds] What is the weight capacity of the overall product? | BZ5: What type of environmental setting was this product designed and manufactured to be used in? Note: your answer indicates that Wayfair is able to market this product as being intended for use in the selected setting(s). Please select both, if both options apply. | CA5: Does this product and/or packaging have additional advertising or labeling details regarding claims about the product’s origin? Please use this field to provide a qualified or unqualified claim regarding the product origin in accordance with US Federal Trade Commission (FTC) and Canada Competition Bureau regulations. Additionally, if applicable, please use this field to communicate any appropriate qualified, comparative, or descriptive claims regarding the origin of the product. Examples include, but are not limited to, communicating relevant percentage of domestic and non-domestic content (ex: 60% U.S. Content), communicating the origin of certain components of the product (ex: "Hand carved in U.S. — Wood from Philippines"), or communicating where the product was assembled (Ex : “Assembled In Mexico”). See https://www.ftc.gov/tips-advice/business-center/guidance/complying-made-usa-standard#qualified and https://www.competitionbureau.gc.ca/eic/site/cb-bc.nsf/eng/03169.html | CB5: Is the product a battery or does the product include batteries? | CC5: What type is the battery? Button Cell, Cell, Battery? | CD5: What is the composition of the batteries included with product? | CE5: Confirm number of batteries in this product | CF5: Do the cells/batteries ship stand alone/packed with the equipment/ contained (installed) in the equipment? | CG5: What is the aggregate lithium content of the cell/battery? Aggregate lithium content means the sum of the grams of lithium content contained by the cells comprising a battery. Please note, this is the weight weight of the lithium in the cell or battery, and not the weight of the entire cell or battery. | CH5: What is the Watt-hour(Wh) rating of the cell/battery? The Watt-hour rating of a lithium cell or battery is calculated by multiplying the rated capacity in ampere-hours by the nominal voltage. If only the milliampere-hours (mAh) are marked on the battery then divide that number by 1000 to get ampere-hours (Ah) (i.e. 4400 mAh / 1000 = 4.4. Ah). | CI5: What is the net weight of the cells or batteries that ship with the product in grams or kilograms. | CJ5: Select all product components that can be removed from the base product | CK5: Does this product have adjustable shelves? | CL5: Can the wheels be locked to keep the product from moving? | CM5: Does this product have to be mounted to the wall or is it free standing? | CN5: What is the color or finish of the product? If your color/finish name is not listed, please type in the value. | CO5: How many shelves are included in this product? | CP5: Does this product include any storage elements such as shelves, drawers, cabinets or a hidden storage compartment? | CQ5: What type of product is the shelf designed for? If this product does not fit any of the listed options, please enter the correct information/value. | CR5: What pieces are included with this product? | CS5: How many cabinets does this product have? | CT5: How many wheels or casters does this product have? | CU5: Does your product comply with 16 CFR Part 1303, the federal regulation banning paint and similar surface-coating materials for consumer use that contain lead or lead compounds and in which the lead content (calculated as lead metal) is in excess of 0.009 percent? Please note: A no answer to this question will prevent this item from being listed for sale. | CV5: Is this product ADA (Americans with Disabilities Act) compliant? | CW5: FOR COMPLIANCE PURPOSES. Not customer facing information. Does this product include any pieces made of manufactured or composite wood products (CWP) This includes any of the following 1) HWPW-CC [Hardwood Plywood with Composite Core] 2) HWPW-VC [Hardwood Plywood with Veneer Core] 3) PB [Particleboard] 4) MDF or thin-MDF [Medium Density Fiberboard] | CX5: Is this product certified compliant for CARB ATCM Phase II formaldehyde emission standards from Composite Wood Products [California Air Resources Board (CARB)- Airborne Toxic Control Measures (ATCM) Phase II] | CY5: Is this product certified TSCA Title VI compliant regarding formaldehyde emissions from Composite Wood Products [Environmental Protection Agency (EPA)-Toxic Substance Control Act (TSCA)-Title VI] | CZ5: Is this product CANFER compliant regarding formaldehyde emissions from composite wood products? [Canada Formaldehyde Emissions Regulation] NOTE: Please provide proof of certification to applicable formaldehyde emissions standards and a Declaration of Certification. More information on the Declaration of Certification and on other requirements for CANFER compliance can be found in Health Canada's Guidance Document (https://bit.ly/3FvYK2B) or by contacting any of our Product Compliance Resources (https://bit.ly/3h8EIlw). | DA5: Does your product comply with the Uniform Packaging and Labeling Regulations, which requires product packaging to be accurate and provide adequate information as to the identity and quantity of its contents, as well as the name and address of the manufacturer and/or distributor? | DB5: Is this product legally or operationally restricted from being offered for sale to Canadian customers on Wayfair.ca or delivered to Canadian addresses? Select “Yes” only if the product cannot legally be sold or shipped to Canada. For example, if it requires a license or certification you do not hold, or if you operate through a separate Canadian entity that cannot support the listing. | DC5: Please select the reason this product can not ship to Canada? Please select from the options or write in a reason if not selectable | DD5: Is this product compliant with the Lacey Act (a set of conservation laws also known as the Lacey Act of 1900)? | DE5: Does this product have a General Certificate of Conformity (GCC), as required by the U.S. CPSC for certain product classes? | DF5: Is the product regulated as Hazardous Material / Dangerous Goods? Hazardous Materials/Dangerous Goods are substances that when transported pose a risk to health, safety, property or the environment. These materials may include explosives, compressed gases (aerosols), flammable liquids, oxidizers, toxic/poisonous, radioactive, corrosive, batteries, etc. An SDS is is a document that lists information relating to occupational safety and health for the use of various substances and products. The SDS includes information such as the properties of each chemical; the physical, health, and environmental health hazards; protective measures; and safety precautions for handling, storing, and transporting the chemical or product. | DG5: Please provide the UN or ID number. The UN or ID number is a 4 digit numeric code that identifies hazardous materials/dangerous goods, and articles in the framework of international and domestic transport. This can be found in section 14 of the Safety Data Sheet (SDS). Example - "UN3480" - Lithium Ion Batteries. If your UN number is not one of the options in the dropdown, please write this in manually. | DH5: Please provide the Hazard Class(es). This is the category of hazard assigned to a hazardous material/dangerous goods under the definitional criteria of the transportation regulations. A material may meet the defining criteria for more than one hazard class but is assigned to only one hazard class. Hazard classes vary from 1-9.This can be found in section 14 of the Safety Data Sheet (SDS). | DI5: Please provide the packing group (if applicable). Packing Groups I, II and III indicate the degree of danger presented by the material is great, medium or minor, respectively. Some hazardous materials/dangerous goods do not have a packing group assigned. This can be found in section 14 of the Safety Data Sheet (SDS). | DJ5: Please provide the net weight or, for liquids, the net volume of hazardous material per unit of product. Provide the net weight of the hazardous materials/dangerous goods in your product in grams or kilograms. For example -if your product is a vacuum containing a lithium ion battery, you would enter the net weight of the battery. | DK5: Is this product compliant with U.S. Energy Efficiency requirements, including those set forth in the Energy Policy and Conservation Act of 1975 (ECPA), the National Appliance Energy Conservation Act (NAECA), the Energy Policy Act of 1992 and 2005, and the Energy Independence and Security Act of 2007, as applicable? | DL5: Which of the following certification or verification marks does your product have? If the item is not certified/verified with any safety listing, please select Does Not Apply. | DM5: In a comma separated list, please outline the registration numbers associated to the safety listings you claimed this product has, in the following structure: Safety Listing - Registration Number. Example: UL Listed - ABC1234567, TÜV Rheinland Certified - DEFGH8910. This number may be referred to as a "Certification Number", "File Number", "Model Number", "Listing Number" or "Certification ID Number" depending on where the certification is from | DN5: Is the packaging for this SKU ISTA Certified (1A, 3A, 6A)? | DO5: Do you have any certifications or credentials related to environmental sustainability, social responsibility, or ethical sourcing (e.g.,OEKO-TEX®, GREENGUARD, GoodWeave, Fair Trade, FSC, etc.)? To see examples of certificates currently part of our Shop Sustainably program, please visit: https://www.aboutwayfair.com/shop-sustainably. Please upload all related certificates so your products can be merchandised as part of the Shop Sustainably program. | DP5: [Inches] What is the overall height of the product from top to bottom? Please enter just the number (e.g. 45.5). | DQ5: [Inches] What is overall width of the product from side to side? Please enter just the number (e.g. 45.5). | DR5: [Inches] What is the overall depth of the product from front to back? Please enter just the number (e.g. 45.5). | DS5: [Pounds] What is the total weight of this product once assembled? If this product includes multiples of the same item, add weight of one individual unit (e.g. 1 Dining Chair in a set of 2). Please enter just the number (i.e. 45.5). | DT5: Does the product require any form of assembly prior to use as intended? | DU5: Does the manufacturer warranty cover the use of this product in a commercial environment? | DV5: How long does the manufacturer warranty apply for the product used in a commercial (non-residential) environment? If the correct value is not found, please select the closest available answer that is shorter than the warranty length. If warranty length varies by part, please select the answer that matches the part of the product with the shortest warranty. Please use the “Warranty Details” tag for any additional details. | DW5: Please indicate if there is a warranty on this product if it were to be used in a residential setting. | DX5: Please indicate the length of the warranty offered from our list if this product were to be used in a residential setting. If the correct value is not found, please indicate both the number and unit (Days, Months, Years) that is appropriate.
A6: Read-Only | B6: Text | C6: Text | D6: Select | E6: Text | F6: Text | G6: Text | H6: Text | I6: Text | J6: Select | K6: Text | L6: Select | M6: Text | N6: Select | O6: Text | P6: Select | Q6: Text | R6: Number | S6: Number | T6: Number | U6: Text | V6: Text | W6: Text | X6: Text | Y6: Text | Z6: Text | AA6: Whole Number | AB6: Whole Number | AC6: Whole Number | AD6: Number | AE6: Select | AF6: Select | AG6: Select | AH6: Select | AI6: Text | AJ6: Yes or No | AK6: Yes or No | AL6: Number | AM6: Number | AN6: Number | AO6: Number | AP6: Yes or No | AQ6: Select | AR6: Please choose one or more from the following, using a semicolon (;) to separate each value: Cancer; Developmental | AS6: Select | AT6: Text | AU6: Text | AV6: Text | AW6: Text | AX6: Text | AY6: Text | AZ6: Text | BA6: Please choose one or more from the following, using a semicolon (;) to separate each value: Specifications; Installation & Assembly; Owner Manual; Delivery Information; Warranty Information; Certifications; Disclaimers; Buying Guides; Promotions; Dimensions; Marketing Materials; Energy Guide; Other; Product Information Sheet; Digital Law Label | BB6: Please choose one or more from the following, using a semicolon (;) to separate each value: AAFA Certified; AATCC 116 Grade; AATCC 16.1-2014 Grade; AATCC 16.3-2014 Grade; AATCC 8 Grade; AC Rated; ACT Flammability Guidelines Compliant; AHAM CADR Dust rating; AHAM CADR Pollen rating; AHAM CADR Smoke rating; AHMA Certified; AHMA Compliant; AHRI Certified; ANSI A117.1 Compliant; ANSI A137.1 Compliant; ANSI IT9.2 Compliant; ANSI Z1.5A/CGA 9.1M Certified; ANSI Z124.1.2 Compliant; ANSI Z124.3 Compliant; ANSI Z124.6-97 Compliant; ANSI Z21.11.2-2016 - Gas-Fired Unvented Room Heaters and Gas-Fired Unvented Decorative Room Heaters; ANSI Z21.50-2016/CSA 2.22-2016 - Standard for Vented Decorative Gas Appliances; ANSI Z21.60-2017/CSA 2.26-2017- Standard for Decorative Gas Appliances; ANSI Z21.84-2017 - Standard for Manually Lighted/ Natural Gas/ Decorative Gas Appliances; ANSI Z21.88-2017/CSA 2.33-2017- Standard for Vented Gas Fireplace Heaters; ANSI Z358 Compliant; ANSI/BHMA A156 Certified; ANSI/BIFMA M7.1 Standard Test Method for Determining VOC Emissions; ANSI/BIFMA X5.1 Office Seating; ANSI/BIFMA X5.11 Large Occupant Office Seating; ANSI/BIFMA X5.3 Vertical Files; ANSI/BIFMA X5.4 Lounge & Public Seating; ANSI/BIFMA X5.5 Desk Products; ANSI/BIFMA X5.6 Panel Systems; ANSI/BIFMA X5.9 Storage; ANSI/BIFMA X6.1 Educational Seating; ANSI/BIFMA X7.1 Standard for Formaldehyde & TVOC Emissions; ANSI/ESD S20.20 Certified; ANSI/NISO Z39.48 Compliant; ANSI/SOHO S6.5 Small Office/Home Office; APMA Certified; ASHRAE 62.2 Standard Compliant; ASME A112.18.1 Compliant; ASME A112.18.2 Compliant; ASME A112.19.1 Compliant; ASME A112.19.2 Compliant; ASME A112.19.3 Compliant; ASP:02:01 Certification; ASSE 1001 Certified; ASSE 1006 Certified; ASSE 1016 Certified; ASTM 1821-19; ASTM E1590-07 Compliant; ASTM F1004-19 Certified; ASTM F1148-17 Compliant; ASTM F1148-18 Compliant; ASTM F1148-18 Certified; ASTM F1169 - 13 Compliant; ASTM F1487-17 Compliant; ASTM F1821 - 16 Compliant; ASTM F1912-17 Compliant; ASTM F1917 - 12 Compliant; ASTM F2057 - 14; ASTM F2057 - 17; ASTM F2057 - 19 | BC6: Select | BD6: Select | BE6: Text | BF6: Please choose one or more from the following, using a semicolon (;) to separate each value: Specifications; Installation & Assembly; Owner Manual; Delivery Information; Warranty Information; Certifications; Disclaimers; Buying Guides; Promotions; Dimensions; Marketing Materials; Energy Guide; Other; Product Information Sheet; Digital Law Label | BG6: Please choose one or more from the following, using a semicolon (;) to separate each value: AAFA Certified; AATCC 116 Grade; AATCC 16.1-2014 Grade; AATCC 16.3-2014 Grade; AATCC 8 Grade; AC Rated; ACT Flammability Guidelines Compliant; AHAM CADR Dust rating; AHAM CADR Pollen rating; AHAM CADR Smoke rating; AHMA Certified; AHMA Compliant; AHRI Certified; ANSI A117.1 Compliant; ANSI A137.1 Compliant; ANSI IT9.2 Compliant; ANSI Z1.5A/CGA 9.1M Certified; ANSI Z124.1.2 Compliant; ANSI Z124.3 Compliant; ANSI Z124.6-97 Compliant; ANSI Z21.11.2-2016 - Gas-Fired Unvented Room Heaters and Gas-Fired Unvented Decorative Room Heaters; ANSI Z21.50-2016/CSA 2.22-2016 - Standard for Vented Decorative Gas Appliances; ANSI Z21.60-2017/CSA 2.26-2017- Standard for Decorative Gas Appliances; ANSI Z21.84-2017 - Standard for Manually Lighted/ Natural Gas/ Decorative Gas Appliances; ANSI Z21.88-2017/CSA 2.33-2017- Standard for Vented Gas Fireplace Heaters; ANSI Z358 Compliant; ANSI/BHMA A156 Certified; ANSI/BIFMA M7.1 Standard Test Method for Determining VOC Emissions; ANSI/BIFMA X5.1 Office Seating; ANSI/BIFMA X5.11 Large Occupant Office Seating; ANSI/BIFMA X5.3 Vertical Files; ANSI/BIFMA X5.4 Lounge & Public Seating; ANSI/BIFMA X5.5 Desk Products; ANSI/BIFMA X5.6 Panel Systems; ANSI/BIFMA X5.9 Storage; ANSI/BIFMA X6.1 Educational Seating; ANSI/BIFMA X7.1 Standard for Formaldehyde & TVOC Emissions; ANSI/ESD S20.20 Certified; ANSI/NISO Z39.48 Compliant; ANSI/SOHO S6.5 Small Office/Home Office; APMA Certified; ASHRAE 62.2 Standard Compliant; ASME A112.18.1 Compliant; ASME A112.18.2 Compliant; ASME A112.19.1 Compliant; ASME A112.19.2 Compliant; ASME A112.19.3 Compliant; ASP:02:01 Certification; ASSE 1001 Certified; ASSE 1006 Certified; ASSE 1016 Certified; ASTM 1821-19; ASTM E1590-07 Compliant; ASTM F1004-19 Certified; ASTM F1148-17 Compliant; ASTM F1148-18 Compliant; ASTM F1148-18 Certified; ASTM F1169 - 13 Compliant; ASTM F1487-17 Compliant; ASTM F1821 - 16 Compliant; ASTM F1912-17 Compliant; ASTM F1917 - 12 Compliant; ASTM F2057 - 14; ASTM F2057 - 17; ASTM F2057 - 19 | BH6: Select | BI6: Select | BJ6: Text | BK6: Please choose one or more from the following, using a semicolon (;) to separate each value: Specifications; Installation & Assembly; Owner Manual; Delivery Information; Warranty Information; Certifications; Disclaimers; Buying Guides; Promotions; Dimensions; Marketing Materials; Energy Guide; Other; Product Information Sheet; Digital Law Label | BL6: Please choose one or more from the following, using a semicolon (;) to separate each value: AAFA Certified; AATCC 116 Grade; AATCC 16.1-2014 Grade; AATCC 16.3-2014 Grade; AATCC 8 Grade; AC Rated; ACT Flammability Guidelines Compliant; AHAM CADR Dust rating; AHAM CADR Pollen rating; AHAM CADR Smoke rating; AHMA Certified; AHMA Compliant; AHRI Certified; ANSI A117.1 Compliant; ANSI A137.1 Compliant; ANSI IT9.2 Compliant; ANSI Z1.5A/CGA 9.1M Certified; ANSI Z124.1.2 Compliant; ANSI Z124.3 Compliant; ANSI Z124.6-97 Compliant; ANSI Z21.11.2-2016 - Gas-Fired Unvented Room Heaters and Gas-Fired Unvented Decorative Room Heaters; ANSI Z21.50-2016/CSA 2.22-2016 - Standard for Vented Decorative Gas Appliances; ANSI Z21.60-2017/CSA 2.26-2017- Standard for Decorative Gas Appliances; ANSI Z21.84-2017 - Standard for Manually Lighted/ Natural Gas/ Decorative Gas Appliances; ANSI Z21.88-2017/CSA 2.33-2017- Standard for Vented Gas Fireplace Heaters; ANSI Z358 Compliant; ANSI/BHMA A156 Certified; ANSI/BIFMA M7.1 Standard Test Method for Determining VOC Emissions; ANSI/BIFMA X5.1 Office Seating; ANSI/BIFMA X5.11 Large Occupant Office Seating; ANSI/BIFMA X5.3 Vertical Files; ANSI/BIFMA X5.4 Lounge & Public Seating; ANSI/BIFMA X5.5 Desk Products; ANSI/BIFMA X5.6 Panel Systems; ANSI/BIFMA X5.9 Storage; ANSI/BIFMA X6.1 Educational Seating; ANSI/BIFMA X7.1 Standard for Formaldehyde & TVOC Emissions; ANSI/ESD S20.20 Certified; ANSI/NISO Z39.48 Compliant; ANSI/SOHO S6.5 Small Office/Home Office; APMA Certified; ASHRAE 62.2 Standard Compliant; ASME A112.18.1 Compliant; ASME A112.18.2 Compliant; ASME A112.19.1 Compliant; ASME A112.19.2 Compliant; ASME A112.19.3 Compliant; ASP:02:01 Certification; ASSE 1001 Certified; ASSE 1006 Certified; ASSE 1016 Certified; ASTM 1821-19; ASTM E1590-07 Compliant; ASTM F1004-19 Certified; ASTM F1148-17 Compliant; ASTM F1148-18 Compliant; ASTM F1148-18 Certified; ASTM F1169 - 13 Compliant; ASTM F1487-17 Compliant; ASTM F1821 - 16 Compliant; ASTM F1912-17 Compliant; ASTM F1917 - 12 Compliant; ASTM F2057 - 14; ASTM F2057 - 17; ASTM F2057 - 19 | BM6: Select | BN6: Select | BO6: Select | BP6: Please choose one or more from the following, using a semicolon (;) to separate each value: Polycarbonate (PC); Polyethylene Plastic; Glass; Silicone; Stainless Steel; Melamine; Polypropylene; Cane; Raffia; Mango Wood; Aluminum; Linen Blend; Acrylic; Manufactured Wood; Limestone; Artificial Grass; Antler; HDPE; Jersey; Linen; Foam; Cowhide; Copper / Copper Plated; Engineered Wood; Cast Aluminum; Flat Wire; Crystal; Fleece / Microfiber; Cardboard / Paper; Chenille; Cherry Wood; Handblown Glass; Cement; Flannel; Chrome; Enamelware; Enameled Cast Iron; Agate / Geode; Fiberglass; Bronze; Cast Iron; Bamboo Slat / Seagrass; Beaded; Alpaca; Felt; Denim; Clay; Gel; Coir; Cardboard; Leather; Cashmere; Galvanized Steel; Hemp; Fireclay; Anodized Aluminum; Blended Fabric; Bamboo; Brass; Burlap; Ceramic; Canvas; Composite; Carbon Steel; Compressed Polyester; Ceramic / Porcelain; Bone China; Cedar; Concrete; Cotton; Earthenware; Engineered Stone; Concrete / Cement; Corrugated; Enamel / Lacquer; Cotton Blend; Compressed Stone; Copper; Faux Leather; Fabric; Faux Sheepskin; Fiberstone; Fine Silver; Hard-Anodized Aluminum; Granite; Heavy Gauge Wire; Faux Fur; Faux Mohair; Faux Cowhide; Iron; High Leaded Crystal; Marble; Lead Crystal; Ironstone; Leather / Faux Leather; Latex; Jute; Lead Free Crystal; Lace; Jute / Sisal; Laminate; Marble / Granite; Mercury Glass; Medium Density Fiberboard (MDF); Mesh; Merino Wool; Memory Foam; Natural Stone; Microfiber / Polyester; Natural Fiber; Microfiber; Natural Fibers; Magnet; Muslin; Metal; Microfiber / Microsuede; Paper; Olefin; Nickel; PEVA; Nylon; Oak; Oxford Fabric; Polyamide; Plywood; Pinecones; Plastic / Acrylic; Pewter; Polycarbonate Plastic; Nickel Plated; Plastic; Polyester; Polymer; Polyester Fill; Polystyrene; Polyvinyl Chloride (PVC); Polyurethane; Porcelain China; Powder Coated Steel; Polypropylene Plastic; Porcelain Enameled Steel; Porcelain; Powder Coated Aluminum; Polyester Blend; Polyresin; Polymarble; Polyurethane (PU); Sandstone; Silver; Sheepskin; Sateen; Rayon / Viscose; Rayon from Bamboo; Silver Plated | BQ6: Yes or No | BR6: Please choose one or more from the following, using a semicolon (;) to separate each value: Acacia; Alder; Ash; Bamboo; Beech; Birch; Camphor; Cedar; Cherry; Elm; Eucalyptus; Fir; Hickory; Mahogany; Mango; Maple; Oak; Pine; Poplar; Rosewood; Rubberwood; Sheesham; Spruce; Teak; Walnut; Wenge; Pecan; Shorea; Paulownia; Chestnut; Hemlock; Aspen; Mindi; Ipe; Olive; Ajo; Agarwood; Afzelia; Afrormosia; Bubinga; Brazilwood; Cumaru; Cedar, Mulanje; Cedar, Spanish; Aloewood; Lignum vitae; Mahogany, African; Mahogany, Mexican; Padauk, African; Macacauba; Ebony, Madagascar; Lignum vitae, Argentine; Gavilan; Mahogany, Honduran; Mahogany, Cuban; Stinkwood, red; Yew, Chinese; Pau rosa, Brazilian; Sandalwood, East African; Ramin; Zitan; Yew, Himalayan; Yew, Japanese; Rosewood, Siamese; Yew, Taiwan; Burlwood; Platane Wood; Sungkai; Does Not Apply | BS6: Number | BT6: Yes or No | BU6: Yes or No | BV6: Yes or No | BW6: Yes or No | BX6: Yes or No | BY6: Number | BZ6: Please choose one or more from the following, using a semicolon (;) to separate each value: Non Residential Use; Residential Use | CA6: Please choose one or more from the following, using a semicolon (;) to separate each value: Made in USA; Made in USA of Imported Materials; Product of Canada; Made In Canada; Does Not Apply | CB6: Yes or No | CC6: Select | CD6: Select | CE6: Select | CF6: Select | CG6: Select | CH6: Select | CI6: Select | CJ6: Please choose one or more from the following, using a semicolon (;) to separate each value: Wheels / Casters; Seat Cushion; Legs; Cover; Lid; Headboard; Back Cushion; Footboard; Tray; Pillow Top; Cushion Cover; Canopy; Shelves; Drawers; Mirror; Unavailable; Does Not Apply | CK6: Yes or No | CL6: Yes or No | CM6: Select | CN6: Please choose one or more from the following, using a semicolon (;) to separate each value: Clear; Cream; Purple; Gold; Silver; Polished Chrome; Polished Nickel; Stainless Steel; Bronze; Chrome; Oil Rubbed Bronze; Matte Black; Satin Nickel; Brushed Nickel; Antique Brass; Antique Bronze; Copper; Antique Copper; Brushed Brass; Polished Brass; Brass; Satin Brass; Brushed Gold; Nickel; Ivory; Green; Orange; Beige; Teal; Red; Satin; Yellow; Pink; White; Brown; Blue; Satin Black; Rose Gold; Navy; Black; Tan; Gray; Brown Wood; Dark Brown Wood; Medium Yellow Wood; Espresso Wood; Medium Wood; Red Wood; Beige Wood; Natural Wood; Gray Wood; Light Yellow Wood; White Wood; Oak Wood | CO6: Whole Number | CP6: Yes or No | CQ6: Please choose one or more from the following, using a semicolon (;) to separate each value: Laptop; Projector; CPU; Printer; Keyboard; TV/Monitor; Unavailable; Does Not Apply | CR6: Please choose one or more from the following, using a semicolon (;) to separate each value: Drawers; Legs; Storage; TV Mount; Wheels / Casters; Cabinets; Unavailable; Does Not Apply | CS6: Whole Number | CT6: Whole Number | CU6: Select | CV6: Yes or No | CW6: Yes or No | CX6: Select | CY6: Select | CZ6: Select | DA6: Select | DB6: Yes or No | DC6: Please choose one or more from the following, using a semicolon (;) to separate each value: Dual Language; Distribution Conflict; Logistics; Does Not Apply | DD6: Select | DE6: Select | DF6: Yes or No | DG6: Please choose one or more from the following, using a semicolon (;) to separate each value: UN3091; UN3481; UN2800; UN1950; UN3496; ID8000; UN1013; UN3082; UN3077; UN3480; UN2857; UN3358; UN3090; UN1266; UN1993; UN1944; UN1070; UN1044; UN3163; UN1268; UN1760; UN1011; UN2794; UN1759; UN3171; UN1987; UN1263; UN1170; UN3265; UN3260; UN3215; UN1006; UN3175; Does Not Apply | DH6: Select | DI6: Select | DJ6: Select | DK6: Select | DL6: Please choose one or more from the following, using a semicolon (;) to separate each value: TÜV Rheinland Certified; MET Listed; AFNOR UK Ltd; BSI Assurance UK Ltd; cUL Listed; ETL Listed; DBI Certification Ltd; UL Listed; cETL Listed; CSA Certified; SGS North America Listed; Does Not Apply | DM6: Text | DN6: Select | DO6: Yes or No | DP6: Number | DQ6: Number | DR6: Number | DS6: Number | DT6: Yes or No | DU6: Yes or No | DV6: Select | DW6: Yes or No | DX6: Please choose one or more from the following, using a semicolon (;) to separate each value: 30 Days; 60 Days; 90 Days; 6 Months; 1 Year; 2 Years; 3 Years; 5 Years; 10 Years; 20 Years; 25 Years; Lifetime; Warranty length varies by part; 15 Years; 18 Months; 12 Years; 6 Years; 4 Years; 8 Years; 7 Years; Does Not Apply
B7: Default Row: | C7: N/A | E7: N/A | F7: N/A | G7: N/A | I7: N/A | J7: N/A | K7: N/A | L7: N/A | M7: N/A | N7: N/A | O7: N/A | P7: N/A | Q7: N/A | R7: N/A | AT7: N/A | AU7: N/A | AV7: N/A | AW7: N/A | AX7: N/A | AY7: N/A
A8: =IF('3 - Carts & Stands'!B8 = "", "", IF('3 - Carts & Stands-WUO_ERR'!A8 = "", "Validated", HYPERLINK("#" & ADDRESS(8, '3 - Carts & Stands-WUO_TRK'!A8),_xlfn.TEXTAFTER('3 - Carts & Stands-WUO_ERR'!A8, ":"))))
A9: =IF('3 - Carts & Stands'!B9 = "", "", IF('3 - Carts & Stands-WUO_ERR'!A9 = "", "Validated", HYPERLINK("#" & ADDRESS(9, '3 - Carts & Stands-WUO_TRK'!A9),_xlfn.TEXTAFTER('3 - Carts & Stands-WUO_ERR'!A9, ":"))))
A10: =IF('3 - Carts & Stands'!B10 = "", "", IF('3 - Carts & Stands-WUO_ERR'!A10 = "", "Validated", HYPERLINK("#" & ADDRESS(10, '3 - Carts & Stands-WUO_TRK'!A10),_xlfn.TEXTAFTER('3 - Carts & Stands-WUO_ERR'!A10, ":"))))
A11: =IF('3 - Carts & Stands'!B11 = "", "", IF('3 - Carts & Stands-WUO_ERR'!A11 = "", "Validated", HYPERLINK("#" & ADDRESS(11, '3 - Carts & Stands-WUO_TRK'!A11),_xlfn.TEXTAFTER('3 - Carts & Stands-WUO_ERR'!A11, ":"))))
A12: =IF('3 - Carts & Stands'!B12 = "", "", IF('3 - Carts & Stands-WUO_ERR'!A12 = "", "Validated", HYPERLINK("#" & ADDRESS(12, '3 - Carts & Stands-WUO_TRK'!A12),_xlfn.TEXTAFTER('3 - Carts & Stands-WUO_ERR'!A12, ":"))))
A13: =IF('3 - Carts & Stands'!B13 = "", "", IF('3 - Carts & Stands-WUO_ERR'!A13 = "", "Validated", HYPERLINK("#" & ADDRESS(13, '3 - Carts & Stands-WUO_TRK'!A13),_xlfn.TEXTAFTER('3 - Carts & Stands-WUO_ERR'!A13, ":"))))
A14: =IF('3 - Carts & Stands'!B14 = "", "", IF('3 - Carts & Stands-WUO_ERR'!A14 = "", "Validated", HYPERLINK("#" & ADDRESS(14, '3 - Carts & Stands-WUO_TRK'!A14),_xlfn.TEXTAFTER('3 - Carts & Stands-WUO_ERR'!A14, ":"))))
A15: =IF('3 - Carts & Stands'!B15 = "", "", IF('3 - Carts & Stands-WUO_ERR'!A15 = "", "Validated", HYPERLINK("#" & ADDRESS(15, '3 - Carts & Stands-WUO_TRK'!A15),_xlfn.TEXTAFTER('3 - Carts & Stands-WUO_ERR'!A15, ":"))))
A16: =IF('3 - Carts & Stands'!B16 = "", "", IF('3 - Carts & Stands-WUO_ERR'!A16 = "", "Validated", HYPERLINK("#" & ADDRESS(16, '3 - Carts & Stands-WUO_TRK'!A16),_xlfn.TEXTAFTER('3 - Carts & Stands-WUO_ERR'!A16, ":"))))
A17: =IF('3 - Carts & Stands'!B17 = "", "", IF('3 - Carts & Stands-WUO_ERR'!A17 = "", "Validated", HYPERLINK("#" & ADDRESS(17, '3 - Carts & Stands-WUO_TRK'!A17),_xlfn.TEXTAFTER('3 - Carts & Stands-WUO_ERR'!A17, ":"))))
A18: =IF('3 - Carts & Stands'!B18 = "", "", IF('3 - Carts & Stands-WUO_ERR'!A18 = "", "Validated", HYPERLINK("#" & ADDRESS(18, '3 - Carts & Stands-WUO_TRK'!A18),_xlfn.TEXTAFTER('3 - Carts & Stands-WUO_ERR'!A18, ":"))))
A19: =IF('3 - Carts & Stands'!B19 = "", "", IF('3 - Carts & Stands-WUO_ERR'!A19 = "", "Validated", HYPERLINK("#" & ADDRESS(19, '3 - Carts & Stands-WUO_TRK'!A19),_xlfn.TEXTAFTER('3 - Carts & Stands-WUO_ERR'!A19, ":"))))
A20: =IF('3 - Carts & Stands'!B20 = "", "", IF('3 - Carts & Stands-WUO_ERR'!A20 = "", "Validated", HYPERLINK("#" & ADDRESS(20, '3 - Carts & Stands-WUO_TRK'!A20),_xlfn.TEXTAFTER('3 - Carts & Stands-WUO_ERR'!A20, ":"))))
A21: =IF('3 - Carts & Stands'!B21 = "", "", IF('3 - Carts & Stands-WUO_ERR'!A21 = "", "Validated", HYPERLINK("#" & ADDRESS(21, '3 - Carts & Stands-WUO_TRK'!A21),_xlfn.TEXTAFTER('3 - Carts & Stands-WUO_ERR'!A21, ":"))))
A22: =IF('3 - Carts & Stands'!B22 = "", "", IF('3 - Carts & Stands-WUO_ERR'!A22 = "", "Validated", HYPERLINK("#" & ADDRESS(22, '3 - Carts & Stands-WUO_TRK'!A22),_xlfn.TEXTAFTER('3 - Carts & Stands-WUO_ERR'!A22, ":"))))
A23: =IF('3 - Carts & Stands'!B23 = "", "", IF('3 - Carts & Stands-WUO_ERR'!A23 = "", "Validated", HYPERLINK("#" & ADDRESS(23, '3 - Carts & Stands-WUO_TRK'!A23),_xlfn.TEXTAFTER('3 - Carts & Stands-WUO_ERR'!A23, ":"))))
A24: =IF('3 - Carts & Stands'!B24 = "", "", IF('3 - Carts & Stands-WUO_ERR'!A24 = "", "Validated", HYPERLINK("#" & ADDRESS(24, '3 - Carts & Stands-WUO_TRK'!A24),_xlfn.TEXTAFTER('3 - Carts & Stands-WUO_ERR'!A24, ":"))))
A25: =IF('3 - Carts & Stands'!B25 = "", "", IF('3 - Carts & Stands-WUO_ERR'!A25 = "", "Validated", HYPERLINK("#" & ADDRESS(25, '3 - Carts & Stands-WUO_TRK'!A25),_xlfn.TEXTAFTER('3 - Carts & Stands-WUO_ERR'!A25, ":"))))
A26: =IF('3 - Carts & Stands'!B26 = "", "", IF('3 - Carts & Stands-WUO_ERR'!A26 = "", "Validated", HYPERLINK("#" & ADDRESS(26, '3 - Carts & Stands-WUO_TRK'!A26),_xlfn.TEXTAFTER('3 - Carts & Stands-WUO_ERR'!A26, ":"))))
A27: =IF('3 - Carts & Stands'!B27 = "", "", IF('3 - Carts & Stands-WUO_ERR'!A27 = "", "Validated", HYPERLINK("#" & ADDRESS(27, '3 - Carts & Stands-WUO_TRK'!A27),_xlfn.TEXTAFTER('3 - Carts & Stands-WUO_ERR'!A27, ":"))))
A28: =IF('3 - Carts & Stands'!B28 = "", "", IF('3 - Carts & Stands-WUO_ERR'!A28 = "", "Validated", HYPERLINK("#" & ADDRESS(28, '3 - Carts & Stands-WUO_TRK'!A28),_xlfn.TEXTAFTER('3 - Carts & Stands-WUO_ERR'!A28, ":"))))
A29: =IF('3 - Carts & Stands'!B29 = "", "", IF('3 - Carts & Stands-WUO_ERR'!A29 = "", "Validated", HYPERLINK("#" & ADDRESS(29, '3 - Carts & Stands-WUO_TRK'!A29),_xlfn.TEXTAFTER('3 - Carts & Stands-WUO_ERR'!A29, ":"))))
A30: =IF('3 - Carts & Stands'!B30 = "", "", IF('3 - Carts & Stands-WUO_ERR'!A30 = "", "Validated", HYPERLINK("#" & ADDRESS(30, '3 - Carts & Stands-WUO_TRK'!A30),_xlfn.TEXTAFTER('3 - Carts & Stands-WUO_ERR'!A30, ":"))))
A31: =IF('3 - Carts & Stands'!B31 = "", "", IF('3 - Carts & Stands-WUO_ERR'!A31 = "", "Validated", HYPERLINK("#" & ADDRESS(31, '3 - Carts & Stands-WUO_TRK'!A31),_xlfn.TEXTAFTER('3 - Carts & Stands-WUO_ERR'!A31, ":"))))
A32: =IF('3 - Carts & Stands'!B32 = "", "", IF('3 - Carts & Stands-WUO_ERR'!A32 = "", "Validated", HYPERLINK("#" & ADDRESS(32, '3 - Carts & Stands-WUO_TRK'!A32),_xlfn.TEXTAFTER('3 - Carts & Stands-WUO_ERR'!A32, ":"))))
A33: =IF('3 - Carts & Stands'!B33 = "", "", IF('3 - Carts & Stands-WUO_ERR'!A33 = "", "Validated", HYPERLINK("#" & ADDRESS(33, '3 - Carts & Stands-WUO_TRK'!A33),_xlfn.TEXTAFTER('3 - Carts & Stands-WUO_ERR'!A33, ":"))))
A34: =IF('3 - Carts & Stands'!B34 = "", "", IF('3 - Carts & Stands-WUO_ERR'!A34 = "", "Validated", HYPERLINK("#" & ADDRESS(34, '3 - Carts & Stands-WUO_TRK'!A34),_xlfn.TEXTAFTER('3 - Carts & Stands-WUO_ERR'!A34, ":"))))
A35: =IF('3 - Carts & Stands'!B35 = "", "", IF('3 - Carts & Stands-WUO_ERR'!A35 = "", "Validated", HYPERLINK("#" & ADDRESS(35, '3 - Carts & Stands-WUO_TRK'!A35),_xlfn.TEXTAFTER('3 - Carts & Stands-WUO_ERR'!A35, ":"))))
A36: =IF('3 - Carts & Stands'!B36 = "", "", IF('3 - Carts & Stands-WUO_ERR'!A36 = "", "Validated", HYPERLINK("#" & ADDRESS(36, '3 - Carts & Stands-WUO_TRK'!A36),_xlfn.TEXTAFTER('3 - Carts & Stands-WUO_ERR'!A36, ":"))))
A37: =IF('3 - Carts & Stands'!B37 = "", "", IF('3 - Carts & Stands-WUO_ERR'!A37 = "", "Validated", HYPERLINK("#" & ADDRESS(37, '3 - Carts & Stands-WUO_TRK'!A37),_xlfn.TEXTAFTER('3 - Carts & Stands-WUO_ERR'!A37, ":"))))
A38: =IF('3 - Carts & Stands'!B38 = "", "", IF('3 - Carts & Stands-WUO_ERR'!A38 = "", "Validated", HYPERLINK("#" & ADDRESS(38, '3 - Carts & Stands-WUO_TRK'!A38),_xlfn.TEXTAFTER('3 - Carts & Stands-WUO_ERR'!A38, ":"))))
A39: =IF('3 - Carts & Stands'!B39 = "", "", IF('3 - Carts & Stands-WUO_ERR'!A39 = "", "Validated", HYPERLINK("#" & ADDRESS(39, '3 - Carts & Stands-WUO_TRK'!A39),_xlfn.TEXTAFTER('3 - Carts & Stands-WUO_ERR'!A39, ":"))))
A40: =IF('3 - Carts & Stands'!B40 = "", "", IF('3 - Carts & Stands-WUO_ERR'!A40 = "", "Validated", HYPERLINK("#" & ADDRESS(40, '3 - Carts & Stands-WUO_TRK'!A40),_xlfn.TEXTAFTER('3 - Carts & Stands-WUO_ERR'!A40, ":"))))
A41: =IF('3 - Carts & Stands'!B41 = "", "", IF('3 - Carts & Stands-WUO_ERR'!A41 = "", "Validated", HYPERLINK("#" & ADDRESS(41, '3 - Carts & Stands-WUO_TRK'!A41),_xlfn.TEXTAFTER('3 - Carts & Stands-WUO_ERR'!A41, ":"))))
A42: =IF('3 - Carts & Stands'!B42 = "", "", IF('3 - Carts & Stands-WUO_ERR'!A42 = "", "Validated", HYPERLINK("#" & ADDRESS(42, '3 - Carts & Stands-WUO_TRK'!A42),_xlfn.TEXTAFTER('3 - Carts & Stands-WUO_ERR'!A42, ":"))))
A43: =IF('3 - Carts & Stands'!B43 = "", "", IF('3 - Carts & Stands-WUO_ERR'!A43 = "", "Validated", HYPERLINK("#" & ADDRESS(43, '3 - Carts & Stands-WUO_TRK'!A43),_xlfn.TEXTAFTER('3 - Carts & Stands-WUO_ERR'!A43, ":"))))
A44: =IF('3 - Carts & Stands'!B44 = "", "", IF('3 - Carts & Stands-WUO_ERR'!A44 = "", "Validated", HYPERLINK("#" & ADDRESS(44, '3 - Carts & Stands-WUO_TRK'!A44),_xlfn.TEXTAFTER('3 - Carts & Stands-WUO_ERR'!A44, ":"))))
A45: =IF('3 - Carts & Stands'!B45 = "", "", IF('3 - Carts & Stands-WUO_ERR'!A45 = "", "Validated", HYPERLINK("#" & ADDRESS(45, '3 - Carts & Stands-WUO_TRK'!A45),_xlfn.TEXTAFTER('3 - Carts & Stands-WUO_ERR'!A45, ":"))))
A46: =IF('3 - Carts & Stands'!B46 = "", "", IF('3 - Carts & Stands-WUO_ERR'!A46 = "", "Validated", HYPERLINK("#" & ADDRESS(46, '3 - Carts & Stands-WUO_TRK'!A46),_xlfn.TEXTAFTER('3 - Carts & Stands-WUO_ERR'!A46, ":"))))
A47: =IF('3 - Carts & Stands'!B47 = "", "", IF('3 - Carts & Stands-WUO_ERR'!A47 = "", "Validated", HYPERLINK("#" & ADDRESS(47, '3 - Carts & Stands-WUO_TRK'!A47),_xlfn.TEXTAFTER('3 - Carts & Stands-WUO_ERR'!A47, ":"))))
A48: =IF('3 - Carts & Stands'!B48 = "", "", IF('3 - Carts & Stands-WUO_ERR'!A48 = "", "Validated", HYPERLINK("#" & ADDRESS(48, '3 - Carts & Stands-WUO_TRK'!A48),_xlfn.TEXTAFTER('3 - Carts & Stands-WUO_ERR'!A48, ":"))))
A49: =IF('3 - Carts & Stands'!B49 = "", "", IF('3 - Carts & Stands-WUO_ERR'!A49 = "", "Validated", HYPERLINK("#" & ADDRESS(49, '3 - Carts & Stands-WUO_TRK'!A49),_xlfn.TEXTAFTER('3 - Carts & Stands-WUO_ERR'!A49, ":"))))
A50: =IF('3 - Carts & Stands'!B50 = "", "", IF('3 - Carts & Stands-WUO_ERR'!A50 = "", "Validated", HYPERLINK("#" & ADDRESS(50, '3 - Carts & Stands-WUO_TRK'!A50),_xlfn.TEXTAFTER('3 - Carts & Stands-WUO_ERR'!A50, ":"))))
A51: =IF('3 - Carts & Stands'!B51 = "", "", IF('3 - Carts & Stands-WUO_ERR'!A51 = "", "Validated", HYPERLINK("#" & ADDRESS(51, '3 - Carts & Stands-WUO_TRK'!A51),_xlfn.TEXTAFTER('3 - Carts & Stands-WUO_ERR'!A51, ":"))))
A52: =IF('3 - Carts & Stands'!B52 = "", "", IF('3 - Carts & Stands-WUO_ERR'!A52 = "", "Validated", HYPERLINK("#" & ADDRESS(52, '3 - Carts & Stands-WUO_TRK'!A52),_xlfn.TEXTAFTER('3 - Carts & Stands-WUO_ERR'!A52, ":"))))
A53: =IF('3 - Carts & Stands'!B53 = "", "", IF('3 - Carts & Stands-WUO_ERR'!A53 = "", "Validated", HYPERLINK("#" & ADDRESS(53, '3 - Carts & Stands-WUO_TRK'!A53),_xlfn.TEXTAFTER('3 - Carts & Stands-WUO_ERR'!A53, ":"))))
A54: =IF('3 - Carts & Stands'!B54 = "", "", IF('3 - Carts & Stands-WUO_ERR'!A54 = "", "Validated", HYPERLINK("#" & ADDRESS(54, '3 - Carts & Stands-WUO_TRK'!A54),_xlfn.TEXTAFTER('3 - Carts & Stands-WUO_ERR'!A54, ":"))))
A55: =IF('3 - Carts & Stands'!B55 = "", "", IF('3 - Carts & Stands-WUO_ERR'!A55 = "", "Validated", HYPERLINK("#" & ADDRESS(55, '3 - Carts & Stands-WUO_TRK'!A55),_xlfn.TEXTAFTER('3 - Carts & Stands-WUO_ERR'!A55, ":"))))
A56: =IF('3 - Carts & Stands'!B56 = "", "", IF('3 - Carts & Stands-WUO_ERR'!A56 = "", "Validated", HYPERLINK("#" & ADDRESS(56, '3 - Carts & Stands-WUO_TRK'!A56),_xlfn.TEXTAFTER('3 - Carts & Stands-WUO_ERR'!A56, ":"))))
A57: =IF('3 - Carts & Stands'!B57 = "", "", IF('3 - Carts & Stands-WUO_ERR'!A57 = "", "Validated", HYPERLINK("#" & ADDRESS(57, '3 - Carts & Stands-WUO_TRK'!A57),_xlfn.TEXTAFTER('3 - Carts & Stands-WUO_ERR'!A57, ":"))))
A58: =IF('3 - Carts & Stands'!B58 = "", "", IF('3 - Carts & Stands-WUO_ERR'!A58 = "", "Validated", HYPERLINK("#" & ADDRESS(58, '3 - Carts & Stands-WUO_TRK'!A58),_xlfn.TEXTAFTER('3 - Carts & Stands-WUO_ERR'!A58, ":"))))
A59: =IF('3 - Carts & Stands'!B59 = "", "", IF('3 - Carts & Stands-WUO_ERR'!A59 = "", "Validated", HYPERLINK("#" & ADDRESS(59, '3 - Carts & Stands-WUO_TRK'!A59),_xlfn.TEXTAFTER('3 - Carts & Stands-WUO_ERR'!A59, ":"))))
A60: =IF('3 - Carts & Stands'!B60 = "", "", IF('3 - Carts & Stands-WUO_ERR'!A60 = "", "Validated", HYPERLINK("#" & ADDRESS(60, '3 - Carts & Stands-WUO_TRK'!A60),_xlfn.TEXTAFTER('3 - Carts & Stands-WUO_ERR'!A60, ":"))))
A61: =IF('3 - Carts & Stands'!B61 = "", "", IF('3 - Carts & Stands-WUO_ERR'!A61 = "", "Validated", HYPERLINK("#" & ADDRESS(61, '3 - Carts & Stands-WUO_TRK'!A61),_xlfn.TEXTAFTER('3 - Carts & Stands-WUO_ERR'!A61, ":"))))
A62: =IF('3 - Carts & Stands'!B62 = "", "", IF('3 - Carts & Stands-WUO_ERR'!A62 = "", "Validated", HYPERLINK("#" & ADDRESS(62, '3 - Carts & Stands-WUO_TRK'!A62),_xlfn.TEXTAFTER('3 - Carts & Stands-WUO_ERR'!A62, ":"))))
A63: =IF('3 - Carts & Stands'!B63 = "", "", IF('3 - Carts & Stands-WUO_ERR'!A63 = "", "Validated", HYPERLINK("#" & ADDRESS(63, '3 - Carts & Stands-WUO_TRK'!A63),_xlfn.TEXTAFTER('3 - Carts & Stands-WUO_ERR'!A63, ":"))))
A64: =IF('3 - Carts & Stands'!B64 = "", "", IF('3 - Carts & Stands-WUO_ERR'!A64 = "", "Validated", HYPERLINK("#" & ADDRESS(64, '3 - Carts & Stands-WUO_TRK'!A64),_xlfn.TEXTAFTER('3 - Carts & Stands-WUO_ERR'!A64, ":"))))
A65: =IF('3 - Carts & Stands'!B65 = "", "", IF('3 - Carts & Stands-WUO_ERR'!A65 = "", "Validated", HYPERLINK("#" & ADDRESS(65, '3 - Carts & Stands-WUO_TRK'!A65),_xlfn.TEXTAFTER('3 - Carts & Stands-WUO_ERR'!A65, ":"))))
A66: =IF('3 - Carts & Stands'!B66 = "", "", IF('3 - Carts & Stands-WUO_ERR'!A66 = "", "Validated", HYPERLINK("#" & ADDRESS(66, '3 - Carts & Stands-WUO_TRK'!A66),_xlfn.TEXTAFTER('3 - Carts & Stands-WUO_ERR'!A66, ":"))))
A67: =IF('3 - Carts & Stands'!B67 = "", "", IF('3 - Carts & Stands-WUO_ERR'!A67 = "", "Validated", HYPERLINK("#" & ADDRESS(67, '3 - Carts & Stands-WUO_TRK'!A67),_xlfn.TEXTAFTER('3 - Carts & Stands-WUO_ERR'!A67, ":"))))
A68: =IF('3 - Carts & Stands'!B68 = "", "", IF('3 - Carts & Stands-WUO_ERR'!A68 = "", "Validated", HYPERLINK("#" & ADDRESS(68, '3 - Carts & Stands-WUO_TRK'!A68),_xlfn.TEXTAFTER('3 - Carts & Stands-WUO_ERR'!A68, ":"))))
A69: =IF('3 - Carts & Stands'!B69 = "", "", IF('3 - Carts & Stands-WUO_ERR'!A69 = "", "Validated", HYPERLINK("#" & ADDRESS(69, '3 - Carts & Stands-WUO_TRK'!A69),_xlfn.TEXTAFTER('3 - Carts & Stands-WUO_ERR'!A69, ":"))))
A70: =IF('3 - Carts & Stands'!B70 = "", "", IF('3 - Carts & Stands-WUO_ERR'!A70 = "", "Validated", HYPERLINK("#" & ADDRESS(70, '3 - Carts & Stands-WUO_TRK'!A70),_xlfn.TEXTAFTER('3 - Carts & Stands-WUO_ERR'!A70, ":"))))
A71: =IF('3 - Carts & Stands'!B71 = "", "", IF('3 - Carts & Stands-WUO_ERR'!A71 = "", "Validated", HYPERLINK("#" & ADDRESS(71, '3 - Carts & Stands-WUO_TRK'!A71),_xlfn.TEXTAFTER('3 - Carts & Stands-WUO_ERR'!A71, ":"))))
A72: =IF('3 - Carts & Stands'!B72 = "", "", IF('3 - Carts & Stands-WUO_ERR'!A72 = "", "Validated", HYPERLINK("#" & ADDRESS(72, '3 - Carts & Stands-WUO_TRK'!A72),_xlfn.TEXTAFTER('3 - Carts & Stands-WUO_ERR'!A72, ":"))))
A73: =IF('3 - Carts & Stands'!B73 = "", "", IF('3 - Carts & Stands-WUO_ERR'!A73 = "", "Validated", HYPERLINK("#" & ADDRESS(73, '3 - Carts & Stands-WUO_TRK'!A73),_xlfn.TEXTAFTER('3 - Carts & Stands-WUO_ERR'!A73, ":"))))
A74: =IF('3 - Carts & Stands'!B74 = "", "", IF('3 - Carts & Stands-WUO_ERR'!A74 = "", "Validated", HYPERLINK("#" & ADDRESS(74, '3 - Carts & Stands-WUO_TRK'!A74),_xlfn.TEXTAFTER('3 - Carts & Stands-WUO_ERR'!A74, ":"))))
A75: =IF('3 - Carts & Stands'!B75 = "", "", IF('3 - Carts & Stands-WUO_ERR'!A75 = "", "Validated", HYPERLINK("#" & ADDRESS(75, '3 - Carts & Stands-WUO_TRK'!A75),_xlfn.TEXTAFTER('3 - Carts & Stands-WUO_ERR'!A75, ":"))))
A76: =IF('3 - Carts & Stands'!B76 = "", "", IF('3 - Carts & Stands-WUO_ERR'!A76 = "", "Validated", HYPERLINK("#" & ADDRESS(76, '3 - Carts & Stands-WUO_TRK'!A76),_xlfn.TEXTAFTER('3 - Carts & Stands-WUO_ERR'!A76, ":"))))
A77: =IF('3 - Carts & Stands'!B77 = "", "", IF('3 - Carts & Stands-WUO_ERR'!A77 = "", "Validated", HYPERLINK("#" & ADDRESS(77, '3 - Carts & Stands-WUO_TRK'!A77),_xlfn.TEXTAFTER('3 - Carts & Stands-WUO_ERR'!A77, ":"))))
A78: =IF('3 - Carts & Stands'!B78 = "", "", IF('3 - Carts & Stands-WUO_ERR'!A78 = "", "Validated", HYPERLINK("#" & ADDRESS(78, '3 - Carts & Stands-WUO_TRK'!A78),_xlfn.TEXTAFTER('3 - Carts & Stands-WUO_ERR'!A78, ":"))))
A79: =IF('3 - Carts & Stands'!B79 = "", "", IF('3 - Carts & Stands-WUO_ERR'!A79 = "", "Validated", HYPERLINK("#" & ADDRESS(79, '3 - Carts & Stands-WUO_TRK'!A79),_xlfn.TEXTAFTER('3 - Carts & Stands-WUO_ERR'!A79, ":"))))
A80: =IF('3 - Carts & Stands'!B80 = "", "", IF('3 - Carts & Stands-WUO_ERR'!A80 = "", "Validated", HYPERLINK("#" & ADDRESS(80, '3 - Carts & Stands-WUO_TRK'!A80),_xlfn.TEXTAFTER('3 - Carts & Stands-WUO_ERR'!A80, ":"))))
A81: =IF('3 - Carts & Stands'!B81 = "", "", IF('3 - Carts & Stands-WUO_ERR'!A81 = "", "Validated", HYPERLINK("#" & ADDRESS(81, '3 - Carts & Stands-WUO_TRK'!A81),_xlfn.TEXTAFTER('3 - Carts & Stands-WUO_ERR'!A81, ":"))))
A82: =IF('3 - Carts & Stands'!B82 = "", "", IF('3 - Carts & Stands-WUO_ERR'!A82 = "", "Validated", HYPERLINK("#" & ADDRESS(82, '3 - Carts & Stands-WUO_TRK'!A82),_xlfn.TEXTAFTER('3 - Carts & Stands-WUO_ERR'!A82, ":"))))
A83: =IF('3 - Carts & Stands'!B83 = "", "", IF('3 - Carts & Stands-WUO_ERR'!A83 = "", "Validated", HYPERLINK("#" & ADDRESS(83, '3 - Carts & Stands-WUO_TRK'!A83),_xlfn.TEXTAFTER('3 - Carts & Stands-WUO_ERR'!A83, ":"))))
A84: =IF('3 - Carts & Stands'!B84 = "", "", IF('3 - Carts & Stands-WUO_ERR'!A84 = "", "Validated", HYPERLINK("#" & ADDRESS(84, '3 - Carts & Stands-WUO_TRK'!A84),_xlfn.TEXTAFTER('3 - Carts & Stands-WUO_ERR'!A84, ":"))))
A85: =IF('3 - Carts & Stands'!B85 = "", "", IF('3 - Carts & Stands-WUO_ERR'!A85 = "", "Validated", HYPERLINK("#" & ADDRESS(85, '3 - Carts & Stands-WUO_TRK'!A85),_xlfn.TEXTAFTER('3 - Carts & Stands-WUO_ERR'!A85, ":"))))
A86: =IF('3 - Carts & Stands'!B86 = "", "", IF('3 - Carts & Stands-WUO_ERR'!A86 = "", "Validated", HYPERLINK("#" & ADDRESS(86, '3 - Carts & Stands-WUO_TRK'!A86),_xlfn.TEXTAFTER('3 - Carts & Stands-WUO_ERR'!A86, ":"))))
A87: =IF('3 - Carts & Stands'!B87 = "", "", IF('3 - Carts & Stands-WUO_ERR'!A87 = "", "Validated", HYPERLINK("#" & ADDRESS(87, '3 - Carts & Stands-WUO_TRK'!A87),_xlfn.TEXTAFTER('3 - Carts & Stands-WUO_ERR'!A87, ":"))))
A88: =IF('3 - Carts & Stands'!B88 = "", "", IF('3 - Carts & Stands-WUO_ERR'!A88 = "", "Validated", HYPERLINK("#" & ADDRESS(88, '3 - Carts & Stands-WUO_TRK'!A88),_xlfn.TEXTAFTER('3 - Carts & Stands-WUO_ERR'!A88, ":"))))
A89: =IF('3 - Carts & Stands'!B89 = "", "", IF('3 - Carts & Stands-WUO_ERR'!A89 = "", "Validated", HYPERLINK("#" & ADDRESS(89, '3 - Carts & Stands-WUO_TRK'!A89),_xlfn.TEXTAFTER('3 - Carts & Stands-WUO_ERR'!A89, ":"))))
A90: =IF('3 - Carts & Stands'!B90 = "", "", IF('3 - Carts & Stands-WUO_ERR'!A90 = "", "Validated", HYPERLINK("#" & ADDRESS(90, '3 - Carts & Stands-WUO_TRK'!A90),_xlfn.TEXTAFTER('3 - Carts & Stands-WUO_ERR'!A90, ":"))))
A91: =IF('3 - Carts & Stands'!B91 = "", "", IF('3 - Carts & Stands-WUO_ERR'!A91 = "", "Validated", HYPERLINK("#" & ADDRESS(91, '3 - Carts & Stands-WUO_TRK'!A91),_xlfn.TEXTAFTER('3 - Carts & Stands-WUO_ERR'!A91, ":"))))
A92: =IF('3 - Carts & Stands'!B92 = "", "", IF('3 - Carts & Stands-WUO_ERR'!A92 = "", "Validated", HYPERLINK("#" & ADDRESS(92, '3 - Carts & Stands-WUO_TRK'!A92),_xlfn.TEXTAFTER('3 - Carts & Stands-WUO_ERR'!A92, ":"))))
A93: =IF('3 - Carts & Stands'!B93 = "", "", IF('3 - Carts & Stands-WUO_ERR'!A93 = "", "Validated", HYPERLINK("#" & ADDRESS(93, '3 - Carts & Stands-WUO_TRK'!A93),_xlfn.TEXTAFTER('3 - Carts & Stands-WUO_ERR'!A93, ":"))))
A94: =IF('3 - Carts & Stands'!B94 = "", "", IF('3 - Carts & Stands-WUO_ERR'!A94 = "", "Validated", HYPERLINK("#" & ADDRESS(94, '3 - Carts & Stands-WUO_TRK'!A94),_xlfn.TEXTAFTER('3 - Carts & Stands-WUO_ERR'!A94, ":"))))
A95: =IF('3 - Carts & Stands'!B95 = "", "", IF('3 - Carts & Stands-WUO_ERR'!A95 = "", "Validated", HYPERLINK("#" & ADDRESS(95, '3 - Carts & Stands-WUO_TRK'!A95),_xlfn.TEXTAFTER('3 - Carts & Stands-WUO_ERR'!A95, ":"))))
A96: =IF('3 - Carts & Stands'!B96 = "", "", IF('3 - Carts & Stands-WUO_ERR'!A96 = "", "Validated", HYPERLINK("#" & ADDRESS(96, '3 - Carts & Stands-WUO_TRK'!A96),_xlfn.TEXTAFTER('3 - Carts & Stands-WUO_ERR'!A96, ":"))))
A97: =IF('3 - Carts & Stands'!B97 = "", "", IF('3 - Carts & Stands-WUO_ERR'!A97 = "", "Validated", HYPERLINK("#" & ADDRESS(97, '3 - Carts & Stands-WUO_TRK'!A97),_xlfn.TEXTAFTER('3 - Carts & Stands-WUO_ERR'!A97, ":"))))
A98: =IF('3 - Carts & Stands'!B98 = "", "", IF('3 - Carts & Stands-WUO_ERR'!A98 = "", "Validated", HYPERLINK("#" & ADDRESS(98, '3 - Carts & Stands-WUO_TRK'!A98),_xlfn.TEXTAFTER('3 - Carts & Stands-WUO_ERR'!A98, ":"))))
A99: =IF('3 - Carts & Stands'!B99 = "", "", IF('3 - Carts & Stands-WUO_ERR'!A99 = "", "Validated", HYPERLINK("#" & ADDRESS(99, '3 - Carts & Stands-WUO_TRK'!A99),_xlfn.TEXTAFTER('3 - Carts & Stands-WUO_ERR'!A99, ":"))))
A100: =IF('3 - Carts & Stands'!B100 = "", "", IF('3 - Carts & Stands-WUO_ERR'!A100 = "", "Validated", HYPERLINK("#" & ADDRESS(100, '3 - Carts & Stands-WUO_TRK'!A100),_xlfn.TEXTAFTER('3 - Carts & Stands-WUO_ERR'!A100, ":"))))
...

Sheet 3 - Carts & Stands-WUO_ERR
B1: core::supplierPartNumber | C1: core::amazonStandardIdentificationNumber | D1: core::manufacturerId | E1: core::manufacturerPartNumber | F1: core::universalProductCode | G1: core::productName | H1: core::collectionName | I1: core::manufacturerProductUrl | J1: variantGrouping::variantType | K1: variantGrouping::groupReferenceId | L1: variantGrouping::variantGrouping | M1: variantGrouping::variantAttributeNameOnSite | N1: variantGrouping::variantGrouping | O1: variantGrouping::variantAttributeNameOnSite | P1: variantGrouping::variantGrouping | Q1: variantGrouping::variantAttributeNameOnSite | R1: price::wholesalePrice | S1: price::minimumAdvertizedPrice | T1: price::manufacturerSuggestedRetailPrice | U1: featureDescription::romanceCopy | V1: featureDescription::genericFeatures | W1: featureDescription::genericFeatures | X1: featureDescription::genericFeatures | Y1: featureDescription::genericFeatures | Z1: featureDescription::genericFeatures | AA1: shippingAndFulfillment::minimumOrderQuantity | AB1: shippingAndFulfillment::forceQuantityMultiplier | AC1: shippingAndFulfillment::displaySetQuantity | AD1: shippingAndFulfillment::productWeight | AE1: shippingAndFulfillment::shipType | AF1: shippingAndFulfillment::freightClass | AG1: shippingAndFulfillment::leadTime | AH1: shippingAndFulfillment::replacementLeadTime | AI1: shippingAndFulfillment::nationalMotorFreightClass | AJ1: shippingAndFulfillment::flatPack | AK1: shippingAndFulfillment::shipPalletized | AL1: shippingAndFulfillment::weight | AM1: shippingAndFulfillment::height | AN1: shippingAndFulfillment::width | AO1: shippingAndFulfillment::depth | AP1: propSixtyFive::warningRequired | AQ1: propSixtyFive::chemicalId | AR1: propSixtyFive::toxicity | AS1: propSixtyFive::countryOfManufacturer | AT1: media::imageValue | AU1: media::imageValue | AV1: media::imageValue | AW1: media::imageValue | AX1: media::imageValue | AY1: media::videoValue | AZ1: media::documentValue | BA1: media::documentType | BB1: media::legalDocumentType | BC1: media::regionType | BD1: media::language | BE1: media::documentValue | BF1: media::documentType | BG1: media::legalDocumentType | BH1: media::regionType | BI1: media::language | BJ1: media::documentValue | BK1: media::documentType | BL1: media::legalDocumentType | BM1: media::regionType | BN1: media::language | BO1: 70212 | BP1: 149726 | BQ1: 149770 | BR1: 185252 | BS1: 149785 | BT1: 182057 | BU1: 164399 | BV1: 149748 | BW1: 149749 | BX1: 149750 | BY1: 149753 | BZ1: 229333 | CA1: 245268 | CB1: 344983 | CC1: 351568 | CD1: 346774 | CE1: 367308 | CF1: 351573 | CG1: 352308 | CH1: 352295 | CI1: 351604 | CJ1: 363032 | CK1: 149782 | CL1: 382561 | CM1: 149965 | CN1: 383797 | CO1: 149784 | CP1: 384383 | CQ1: 149964 | CR1: 419944 | CS1: 149794 | CT1: 149810 | CU1: 192864 | CV1: 149754 | CW1: 201408 | CX1: 224843 | CY1: 225064 | CZ1: 364709 | DA1: 236080 | DB1: 249312 | DC1: 251061 | DD1: 192875 | DE1: 149756 | DF1: 339306 | DG1: 373554 | DH1: 340804 | DI1: 341056 | DJ1: 369616 | DK1: 368261 | DL1: 375301 | DM1: 376200 | DN1: 385918 | DO1: 415201 | DP1: 149771 | DQ1: 70234 | DR1: 70239 | DS1: 70240 | DT1: 70241 | DU1: 229332 | DV1: 334763 | DW1: 254003 | DX1: 255912
B2: Basic Information | J2: Variants | R2: Pricing | U2: Marketing Information | AA2: Fulfillment Information | AL2: Carton Details | AP2: Compliance | AT2: Media | BO2: Attributes
B3: Required | C3: Additional | D3: Required | E3: Required | F3: Recommended | G3: Required | H3: Additional | I3: Additional | J3: Required | K3: Conditional | L3: Recommended | M3: Conditional | N3: Recommended | O3: Conditional | P3: Recommended | Q3: Conditional | R3: Required | S3: Additional | T3: Additional | U3: Conditional | V3: Conditional | W3: Conditional | X3: Conditional | Y3: Conditional | Z3: Conditional | AA3: Required | AB3: Required | AC3: Required | AD3: Required | AE3: Required | AF3: Conditional | AG3: Required | AH3: Required | AI3: Additional | AJ3: Additional | AK3: Additional | AL3: Required | AM3: Required | AN3: Required | AO3: Required | AP3: Required | AQ3: Conditional | AR3: Conditional | AS3: Required | AT3: Required | AU3: Additional | AV3: Additional | AW3: Additional | AX3: Additional | AY3: Additional | AZ3: Conditional | BA3: Conditional | BB3: Conditional | BC3: Conditional | BD3: Conditional | BE3: Conditional | BF3: Conditional | BG3: Conditional | BH3: Conditional | BI3: Conditional | BJ3: Conditional | BK3: Conditional | BL3: Conditional | BM3: Conditional | BN3: Conditional | BO3: Required | BP3: Required | BQ3: Recommended | BR3: Recommended | BS3: Recommended | BT3: Recommended | BU3: Recommended | BV3: Recommended | BW3: Recommended | BX3: Recommended | BY3: Recommended | BZ3: Required | CA3: Additional | CB3: Additional | CC3: Additional | CD3: Additional | CE3: Additional | CF3: Additional | CG3: Additional | CH3: Additional | CI3: Additional | CJ3: Recommended | CK3: Recommended | CL3: Recommended | CM3: Recommended | CN3: Required | CO3: Recommended | CP3: Recommended | CQ3: Recommended | CR3: Recommended | CS3: Recommended | CT3: Recommended | CU3: Required | CV3: Additional | CW3: Required | CX3: Required | CY3: Required | CZ3: Required | DA3: Required | DB3: Required | DC3: Required | DD3: Required | DE3: Required | DF3: Additional | DG3: Additional | DH3: Additional | DI3: Additional | DJ3: Additional | DK3: Required | DL3: Required | DM3: Additional | DN3: Recommended | DO3: Recommended | DP3: Required | DQ3: Required | DR3: Required | DS3: Recommended | DT3: Required | DU3: Required | DV3: Recommended | DW3: Recommended | DX3: Recommended
B4: Supplier Part Number | C4: ASIN or Amazon Seller SKU | D4: Brand | E4: Manufacturer Part Number | F4: Universal Product Code | G4: Product Name | H4: Collection Name | I4: Manufacturer Product URL | J4: Variant Type | K4: Group Reference ID | L4: Variant Grouping 1 | M4: Variant Attribute Name On Site 1 | N4: Variant Grouping 2 | O4: Variant Attribute Name On Site 2 | P4: Variant Grouping 3 | Q4: Variant Attribute Name On Site 3 | R4: Base Cost | S4: Minimum Advertised Price | T4: Manufacturer Suggested Retail Price | U4: Marketing Copy | V4: Feature Bullet 1 | W4: Feature Bullet 2 | X4: Feature Bullet 3 | Y4: Feature Bullet 4 | Z4: Feature Bullet 5 | AA4: Minimum Order Quantity | AB4: Force Quantity Multiplier | AC4: Display Set Quantity | AD4: Product Weight | AE4: Ship Type | AF4: Freight Class | AG4: Lead Time | AH4: Replacement Lead Time | AI4: National Motor Freight Class | AJ4: Flat Pack | AK4: Ship Palletized | AL4: Carton Weight 1 | AM4: Carton Height 1 | AN4: Carton Width 1 | AO4: Carton Depth 1 | AP4: Warning Required | AQ4: Chemical 1 | AR4: Toxicity 1 | AS4: Country Of Manufacturer | AT4: Image File Name or URL 1 | AU4: Image File Name or URL 2 | AV4: Image File Name or URL 3 | AW4: Image File Name or URL 4 | AX4: Image File Name or URL 5 | AY4: Video File Name or URL 1 | AZ4: Document File Name or URL 1 | BA4: Document Type 1 | BB4: Legal Document Type 1 | BC4: Document Region 1 | BD4: Document Language 1 | BE4: Document File Name or URL 2 | BF4: Document Type 2 | BG4: Legal Document Type 2 | BH4: Document Region 2 | BI4: Document Language 2 | BJ4: Document File Name or URL 3 | BK4: Document Type 3 | BL4: Legal Document Type 3 | BM4: Document Region 3 | BN4: Document Language 3 | BO4: Product Type | BP4: Material | BQ4: Adjustable Height | BR4: Wood Species | BS4: Shelf Weight Capacity | BT4: Tilting | BU4: Cabinets Included | BV4: Drawers Included | BW4: Legs Included | BX4: Wheels / Casters Included | BY4: Overall Weight Capacity | BZ4: Supplier Intended and Approved Use | CA4: Country of Origin - Additional Details | CB4: Battery or Batteries Included | CC4: Battery Type | CD4: Battery Composition | CE4: Number of Batteries | CF4: Battery Shipment | CG4: Lithium Content | CH4: Watt Rating of Cells / Battery | CI4: Weight of Cells / Battery | CJ4: Removable Components | CK4: Adjustable Shelves | CL4: Locking Wheels | CM4: Mount Type | CN4: Color / Finish | CO4: Number of Shelves | CP4: Storage Included | CQ4: Shelf Type | CR4: Pieces Included | CS4: Number of Cabinets | CT4: Number of Wheels / Casters Included | CU4: CPSC - 16 CFR 1303 Compliant | CV4: ADA Compliant | CW4: Composite Wood Product (CWP) | CX4: CARB Phase II Compliant (formaldehyde emissions) | CY4: TSCA Title VI Compliant (formaldehyde emissions) | CZ4: CANFER Compliant | DA4: Uniform Packaging and Labeling Regulations (UPLR) Compliant | DB4: Canada Product Restriction | DC4: Reason for Restriction | DD4: Lacey Act Compliant | DE4: General Certificate of Conformity (GCC) | DF4: Hazardous Material / Dangerous Goods | DG4: UN or ID number | DH4: Hazard Class(es) | DI4: Packing Group | DJ4: Hazardous Material Weight | DK4: Energy Efficiency Regulations Compliant | DL4: Safety Listing(s) | DM4: Safety Listing(s) Registration Number | DN4: ISTA Certified | DO4: Sustainability & Social Responsibility Certifications (North America Only) | DP4: Overall Height - Top to Bottom | DQ4: Overall Width - Side to Side | DR4: Overall Depth - Front to Back | DS4: Overall Product Weight | DT4: Assembly Required | DU4: Commercial Warranty | DV4: Commercial Warranty Length | DW4: Product Warranty | DX4: Warranty Length
B5: Must be less than 64 characters and must be a unique value (products cannot be added if they have the same part number as something you already have in your catalog). This is the supplier-specific value for the product as it appears on your Inventory Feed and Purchased Orders. | C5: The Amazon Standard Identification Number (ASIN) is a 10-character alphanumeric unique identifier assigned by Amazon.com and its partners for product identification within the Amazon organization. The Amazon Seller SKU is Amazon's identifier for your product that allows you to fulfill the product through Amazon shipping even when selling the product on other sites like Wayfair. | D5: Enter your product's brand (may be the same as the product's manufacturer). New brands must be created in the brand management tool in Partner Home before they can be selected here. | E5: Must be less than 64 characters and must be a unique value (products cannot be added if they have the same part number as something you already have in your catalog). This is the part number provided by the manufacturer. | F5: Must follow the standard UPC format and must be a unique value (products cannot be added if they have the same UPC as something you already have in your catalog). | G5: Please do not use abbreviations or exceed the 255 character limit. Wayfair may adjust the provided name based on marketing standards per class. | H5: If the product belongs to a collection of associated products that are not just product variances/options, enter the collection here. This can match with collections of products you already sell on site. For example, a collection may be a bed and nightstand that both follow a modern theme, but would not be a bed that comes in two separate colors. Products in a collection do not share the same listing on site. | I5: Enter the URL for the specific manufacturer product page of your product. | J5: Indicate whether this part number is a standalone product, primary variant (all required fields must be provided), or non-primary variant (data can be autofilled from primary variant). | K5: Provide an identifier to group your variants. This information will be used to create a listing. | L5: Common attribute to group products by. Select from dropdown or enter a custom value. | M5: Display name for variant attribute, if differs from corresponding Attribute answer. | N5: Common attribute to group products by. Select from dropdown or enter a custom value. | O5: Display name for variant attribute, if differs from corresponding Attribute answer. | P5: Common attribute to group products by. Select from dropdown or enter a custom value. | Q5: Display name for variant attribute, if differs from corresponding Attribute answer. | R5: Your supplier profile preference for currency is used to determine the currency of the base (wholesale) cost provided. | S5: The region selected for this sheet is used to determine the currency of the MAP provided. This may differ from the currency of your base cost. | T5: The region selected for this sheet is used to determine the currency of the MSRP provided. This may differ from the currency of your base cost. | U5: Please do not use special symbols (trademark, copyright, etc.) or extra lines/spacing. This should be a short, single paragraph product description in complete sentences highlighting details about key product information. | V5: 15 words or less, describing one aspect of the product, eg., Unique aspects, benefits, use cases, technology. These provide customers with key facts at first glance and help them to decide whether they want to make the purchase. If no marketing copy is provided, then at least 3 feature bullets must be provided. | W5: 15 words or less, describing one aspect of the product, eg., Unique aspects, benefits, use cases, technology. These provide customers with key facts at first glance and help them to decide whether they want to make the purchase. If no marketing copy is provided, then at least 3 feature bullets must be provided. | X5: 15 words or less, describing one aspect of the product, eg., Unique aspects, benefits, use cases, technology. These provide customers with key facts at first glance and help them to decide whether they want to make the purchase. If no marketing copy is provided, then at least 3 feature bullets must be provided. | Y5: 15 words or less, describing one aspect of the product, eg., Unique aspects, benefits, use cases, technology. These provide customers with key facts at first glance and help them to decide whether they want to make the purchase. If no marketing copy is provided, then at least 3 feature bullets must be provided. | Z5: 15 words or less, describing one aspect of the product, eg., Unique aspects, benefits, use cases, technology. These provide customers with key facts at first glance and help them to decide whether they want to make the purchase. If no marketing copy is provided, then at least 3 feature bullets must be provided. | AA5: The minimum count of items a customer must choose to purchase the product. | AB5: This represents how many items the customer must buy in increments of, or in addition to. For example, a multiplier of 2 would mean a custom must buy 1 quantity, 3 quantity, 5 quantity, or some other multiple of 2. | AC5: Number of items represented by the part number and wholesale price. For example, if you want to sell a bundle of pillows, and the part number and wholesale cost you provided represents that full bundle of pillows, then you would answer the Display Set Quantity question with how many pillows are in the bundle. | AD5: [Pounds] What is the total weight of this product once assembled? Please enter just the number (i.e. 45.5) without a unit of measurement. | AE5: Enter small parcel or LTL to indicate how the product can ship based on size and weight. | AF5: Each product falls into 1 of 18 classes determined by a product's 'transportability' and are crucial for calculating shipping cost. The field is required when ship type is LTL. | AG5: [Hours] This is the length of time from receipt of PO to shipment from the warehouse. | AH5: [Hours] This is length of time from receipt of a replacement PO to shipment from the warehouse | AI5: 5 to 7 digit number in length (depending on any sub classification) that will identify what is shipping in the box | AJ5: Also known as 'knocked down'. Select 'Yes' if this product ships disassembled in a flat pack box. | AK5: Select 'Yes' if this product ships on a pallet. | AL5: [Pounds] Enter in the shipping weight (i.e. 45.5) of the packaging used for the product. If the product ships in more than one box, this measurement is per box. | AM5: [Inches] Enter in the shipping height (i.e. 45.5) of the packaging used for the product. If the product ships in more than one box, this measurement is per box. | AN5: [Inches] Enter in the shipping width (i.e. 45.5) of the packaging used for the product. If the product ships in more than one box, this measurement is per box. | AO5: [Inches] Enter in the shipping depth (i.e. 45.5) of the packaging used for the product. If the product ships in more than one box, this measurement is per box. | AP5: If the product requires a warning for Proposition 65 compliance in California, answer 'Yes' and indicate which chemicals and toxicities are applicable. | AQ5: Select the chemical that requires the Prop65 warning. | AR5: Select the toxicity that can result from the selected chemical. | AS5: Provide only a single country of manufacture for each product. | AT5: Your first image will be set as the lead image for this listing, however, is subject to change upon Wayfair review. For each image uploaded, provide the file name with extension (e.g. PART_1.jpeg) or a direct public URL which leads to a single image (tip: to isolate the image, right click + select Open Image in New Tab). Elements like logos, buttons, etc will interfere with our ability to download the image. Do not exceed 20 images per product. | AU5: Your first image will be set as the lead image for this listing, however, is subject to change upon Wayfair review. For each image uploaded, provide the file name with extension (e.g. PART_1.jpeg) or a direct public URL which leads to a single image (tip: to isolate the image, right click + select Open Image in New Tab). Elements like logos, buttons, etc will interfere with our ability to download the image. Do not exceed 20 images per product. | AV5: Your first image will be set as the lead image for this listing, however, is subject to change upon Wayfair review. For each image uploaded, provide the file name with extension (e.g. PART_1.jpeg) or a direct public URL which leads to a single image (tip: to isolate the image, right click + select Open Image in New Tab). Elements like logos, buttons, etc will interfere with our ability to download the image. Do not exceed 20 images per product. | AW5: Your first image will be set as the lead image for this listing, however, is subject to change upon Wayfair review. For each image uploaded, provide the file name with extension (e.g. PART_1.jpeg) or a direct public URL which leads to a single image (tip: to isolate the image, right click + select Open Image in New Tab). Elements like logos, buttons, etc will interfere with our ability to download the image. Do not exceed 20 images per product. | AX5: Your first image will be set as the lead image for this listing, however, is subject to change upon Wayfair review. For each image uploaded, provide the file name with extension (e.g. PART_1.jpeg) or a direct public URL which leads to a single image (tip: to isolate the image, right click + select Open Image in New Tab). Elements like logos, buttons, etc will interfere with our ability to download the image. Do not exceed 20 images per product. | AY5: Provide the video’s file name with extension for separate uploads or a direct public URL. Do not exceed 10 videos per product. | AZ5: Provide the document’s file name with extension for separate uploads or a direct public URL. Do not exceed 10 documents per product. | BA5: Select one or more values from the provided list that best describe the document’s purpose. This classification helps customers easily find information like “Installation & Assembly” guides, “Warranty Information,” or “Specifications. | BB5: If the document serves as a legal notice or certification (e.g., “ASTM F2057 - 19,” “ANSI A117.1 Compliant”), select the specific type(s) from the provided list. This is used for compliance and to display certifications to customers. | BC5: Select the country or region where this document is legally applicable. This is crucial for compliance-related documents that may differ across locations. | BD5: Select the language in which the document is written. | BE5: Provide the document’s file name with extension for separate uploads or a direct public URL. Do not exceed 10 documents per product. | BF5: Select one or more values from the provided list that best describe the document’s purpose. This classification helps customers easily find information like “Installation & Assembly” guides, “Warranty Information,” or “Specifications. | BG5: If the document serves as a legal notice or certification (e.g., “ASTM F2057 - 19,” “ANSI A117.1 Compliant”), select the specific type(s) from the provided list. This is used for compliance and to display certifications to customers. | BH5: Select the country or region where this document is legally applicable. This is crucial for compliance-related documents that may differ across locations. | BI5: Select the language in which the document is written. | BJ5: Provide the document’s file name with extension for separate uploads or a direct public URL. Do not exceed 10 documents per product. | BK5: Select one or more values from the provided list that best describe the document’s purpose. This classification helps customers easily find information like “Installation & Assembly” guides, “Warranty Information,” or “Specifications. | BL5: If the document serves as a legal notice or certification (e.g., “ASTM F2057 - 19,” “ANSI A117.1 Compliant”), select the specific type(s) from the provided list. This is used for compliance and to display certifications to customers. | BM5: Select the country or region where this document is legally applicable. This is crucial for compliance-related documents that may differ across locations. | BN5: Select the language in which the document is written. | BO5: What type of product is this? | BP5: What material is the product made of? | BQ5: Is the height of this product adjustable? | BR5: What type of wood was used to construct this product? This describes the actual materials used, not the product's appearance. | BS5: [Pounds] What is the weight capacity of the shelf/shelves? | BT5: Does this product tilt? | BU5: Does this product include cabinets? | BV5: Does this product have any drawers? | BW5: Does this product have legs? | BX5: Does this product have wheels or casters? | BY5: [Pounds] What is the weight capacity of the overall product? | BZ5: What type of environmental setting was this product designed and manufactured to be used in? Note: your answer indicates that Wayfair is able to market this product as being intended for use in the selected setting(s). Please select both, if both options apply. | CA5: Does this product and/or packaging have additional advertising or labeling details regarding claims about the product’s origin? Please use this field to provide a qualified or unqualified claim regarding the product origin in accordance with US Federal Trade Commission (FTC) and Canada Competition Bureau regulations. Additionally, if applicable, please use this field to communicate any appropriate qualified, comparative, or descriptive claims regarding the origin of the product. Examples include, but are not limited to, communicating relevant percentage of domestic and non-domestic content (ex: 60% U.S. Content), communicating the origin of certain components of the product (ex: "Hand carved in U.S. — Wood from Philippines"), or communicating where the product was assembled (Ex : “Assembled In Mexico”). See https://www.ftc.gov/tips-advice/business-center/guidance/complying-made-usa-standard#qualified and https://www.competitionbureau.gc.ca/eic/site/cb-bc.nsf/eng/03169.html | CB5: Is the product a battery or does the product include batteries? | CC5: What type is the battery? Button Cell, Cell, Battery? | CD5: What is the composition of the batteries included with product? | CE5: Confirm number of batteries in this product | CF5: Do the cells/batteries ship stand alone/packed with the equipment/ contained (installed) in the equipment? | CG5: What is the aggregate lithium content of the cell/battery? Aggregate lithium content means the sum of the grams of lithium content contained by the cells comprising a battery. Please note, this is the weight weight of the lithium in the cell or battery, and not the weight of the entire cell or battery. | CH5: What is the Watt-hour(Wh) rating of the cell/battery? The Watt-hour rating of a lithium cell or battery is calculated by multiplying the rated capacity in ampere-hours by the nominal voltage. If only the milliampere-hours (mAh) are marked on the battery then divide that number by 1000 to get ampere-hours (Ah) (i.e. 4400 mAh / 1000 = 4.4. Ah). | CI5: What is the net weight of the cells or batteries that ship with the product in grams or kilograms. | CJ5: Select all product components that can be removed from the base product | CK5: Does this product have adjustable shelves? | CL5: Can the wheels be locked to keep the product from moving? | CM5: Does this product have to be mounted to the wall or is it free standing? | CN5: What is the color or finish of the product? If your color/finish name is not listed, please type in the value. | CO5: How many shelves are included in this product? | CP5: Does this product include any storage elements such as shelves, drawers, cabinets or a hidden storage compartment? | CQ5: What type of product is the shelf designed for? If this product does not fit any of the listed options, please enter the correct information/value. | CR5: What pieces are included with this product? | CS5: How many cabinets does this product have? | CT5: How many wheels or casters does this product have? | CU5: Does your product comply with 16 CFR Part 1303, the federal regulation banning paint and similar surface-coating materials for consumer use that contain lead or lead compounds and in which the lead content (calculated as lead metal) is in excess of 0.009 percent? Please note: A no answer to this question will prevent this item from being listed for sale. | CV5: Is this product ADA (Americans with Disabilities Act) compliant? | CW5: FOR COMPLIANCE PURPOSES. Not customer facing information. Does this product include any pieces made of manufactured or composite wood products (CWP) This includes any of the following 1) HWPW-CC [Hardwood Plywood with Composite Core] 2) HWPW-VC [Hardwood Plywood with Veneer Core] 3) PB [Particleboard] 4) MDF or thin-MDF [Medium Density Fiberboard] | CX5: Is this product certified compliant for CARB ATCM Phase II formaldehyde emission standards from Composite Wood Products [California Air Resources Board (CARB)- Airborne Toxic Control Measures (ATCM) Phase II] | CY5: Is this product certified TSCA Title VI compliant regarding formaldehyde emissions from Composite Wood Products [Environmental Protection Agency (EPA)-Toxic Substance Control Act (TSCA)-Title VI] | CZ5: Is this product CANFER compliant regarding formaldehyde emissions from composite wood products? [Canada Formaldehyde Emissions Regulation] NOTE: Please provide proof of certification to applicable formaldehyde emissions standards and a Declaration of Certification. More information on the Declaration of Certification and on other requirements for CANFER compliance can be found in Health Canada's Guidance Document (https://bit.ly/3FvYK2B) or by contacting any of our Product Compliance Resources (https://bit.ly/3h8EIlw). | DA5: Does your product comply with the Uniform Packaging and Labeling Regulations, which requires product packaging to be accurate and provide adequate information as to the identity and quantity of its contents, as well as the name and address of the manufacturer and/or distributor? | DB5: Is this product legally or operationally restricted from being offered for sale to Canadian customers on Wayfair.ca or delivered to Canadian addresses? Select “Yes” only if the product cannot legally be sold or shipped to Canada. For example, if it requires a license or certification you do not hold, or if you operate through a separate Canadian entity that cannot support the listing. | DC5: Please select the reason this product can not ship to Canada? Please select from the options or write in a reason if not selectable | DD5: Is this product compliant with the Lacey Act (a set of conservation laws also known as the Lacey Act of 1900)? | DE5: Does this product have a General Certificate of Conformity (GCC), as required by the U.S. CPSC for certain product classes? | DF5: Is the product regulated as Hazardous Material / Dangerous Goods? Hazardous Materials/Dangerous Goods are substances that when transported pose a risk to health, safety, property or the environment. These materials may include explosives, compressed gases (aerosols), flammable liquids, oxidizers, toxic/poisonous, radioactive, corrosive, batteries, etc. An SDS is is a document that lists information relating to occupational safety and health for the use of various substances and products. The SDS includes information such as the properties of each chemical; the physical, health, and environmental health hazards; protective measures; and safety precautions for handling, storing, and transporting the chemical or product. | DG5: Please provide the UN or ID number. The UN or ID number is a 4 digit numeric code that identifies hazardous materials/dangerous goods, and articles in the framework of international and domestic transport. This can be found in section 14 of the Safety Data Sheet (SDS). Example - "UN3480" - Lithium Ion Batteries. If your UN number is not one of the options in the dropdown, please write this in manually. | DH5: Please provide the Hazard Class(es). This is the category of hazard assigned to a hazardous material/dangerous goods under the definitional criteria of the transportation regulations. A material may meet the defining criteria for more than one hazard class but is assigned to only one hazard class. Hazard classes vary from 1-9.This can be found in section 14 of the Safety Data Sheet (SDS). | DI5: Please provide the packing group (if applicable). Packing Groups I, II and III indicate the degree of danger presented by the material is great, medium or minor, respectively. Some hazardous materials/dangerous goods do not have a packing group assigned. This can be found in section 14 of the Safety Data Sheet (SDS). | DJ5: Please provide the net weight or, for liquids, the net volume of hazardous material per unit of product. Provide the net weight of the hazardous materials/dangerous goods in your product in grams or kilograms. For example -if your product is a vacuum containing a lithium ion battery, you would enter the net weight of the battery. | DK5: Is this product compliant with U.S. Energy Efficiency requirements, including those set forth in the Energy Policy and Conservation Act of 1975 (ECPA), the National Appliance Energy Conservation Act (NAECA), the Energy Policy Act of 1992 and 2005, and the Energy Independence and Security Act of 2007, as applicable? | DL5: Which of the following certification or verification marks does your product have? If the item is not certified/verified with any safety listing, please select Does Not Apply. | DM5: In a comma separated list, please outline the registration numbers associated to the safety listings you claimed this product has, in the following structure: Safety Listing - Registration Number. Example: UL Listed - ABC1234567, TÜV Rheinland Certified - DEFGH8910. This number may be referred to as a "Certification Number", "File Number", "Model Number", "Listing Number" or "Certification ID Number" depending on where the certification is from | DN5: Is the packaging for this SKU ISTA Certified (1A, 3A, 6A)? | DO5: Do you have any certifications or credentials related to environmental sustainability, social responsibility, or ethical sourcing (e.g.,OEKO-TEX®, GREENGUARD, GoodWeave, Fair Trade, FSC, etc.)? To see examples of certificates currently part of our Shop Sustainably program, please visit: https://www.aboutwayfair.com/shop-sustainably. Please upload all related certificates so your products can be merchandised as part of the Shop Sustainably program. | DP5: [Inches] What is the overall height of the product from top to bottom? Please enter just the number (e.g. 45.5). | DQ5: [Inches] What is overall width of the product from side to side? Please enter just the number (e.g. 45.5). | DR5: [Inches] What is the overall depth of the product from front to back? Please enter just the number (e.g. 45.5). | DS5: [Pounds] What is the total weight of this product once assembled? If this product includes multiples of the same item, add weight of one individual unit (e.g. 1 Dining Chair in a set of 2). Please enter just the number (i.e. 45.5). | DT5: Does the product require any form of assembly prior to use as intended? | DU5: Does the manufacturer warranty cover the use of this product in a commercial environment? | DV5: How long does the manufacturer warranty apply for the product used in a commercial (non-residential) environment? If the correct value is not found, please select the closest available answer that is shorter than the warranty length. If warranty length varies by part, please select the answer that matches the part of the product with the shortest warranty. Please use the “Warranty Details” tag for any additional details. | DW5: Please indicate if there is a warranty on this product if it were to be used in a residential setting. | DX5: Please indicate the length of the warranty offered from our list if this product were to be used in a residential setting. If the correct value is not found, please indicate both the number and unit (Days, Months, Years) that is appropriate.
B6: Text | C6: Text | D6: Select | E6: Text | F6: Text | G6: Text | H6: Text | I6: Text | J6: Select | K6: Text | L6: Select | M6: Text | N6: Select | O6: Text | P6: Select | Q6: Text | R6: Number | S6: Number | T6: Number | U6: Text | V6: Text | W6: Text | X6: Text | Y6: Text | Z6: Text | AA6: Whole Number | AB6: Whole Number | AC6: Whole Number | AD6: Number | AE6: Select | AF6: Select | AG6: Select | AH6: Select | AI6: Text | AJ6: Yes or No | AK6: Yes or No | AL6: Number | AM6: Number | AN6: Number | AO6: Number | AP6: Yes or No | AQ6: Select | AR6: Please choose one or more from the following, using a semicolon (;) to separate each value: Cancer; Developmental | AS6: Select | AT6: Text | AU6: Text | AV6: Text | AW6: Text | AX6: Text | AY6: Text | AZ6: Text | BA6: Please choose one or more from the following, using a semicolon (;) to separate each value: Specifications; Installation & Assembly; Owner Manual; Delivery Information; Warranty Information; Certifications; Disclaimers; Buying Guides; Promotions; Dimensions; Marketing Materials; Energy Guide; Other; Product Information Sheet; Digital Law Label | BB6: Please choose one or more from the following, using a semicolon (;) to separate each value: AAFA Certified; AATCC 116 Grade; AATCC 16.1-2014 Grade; AATCC 16.3-2014 Grade; AATCC 8 Grade; AC Rated; ACT Flammability Guidelines Compliant; AHAM CADR Dust rating; AHAM CADR Pollen rating; AHAM CADR Smoke rating; AHMA Certified; AHMA Compliant; AHRI Certified; ANSI A117.1 Compliant; ANSI A137.1 Compliant; ANSI IT9.2 Compliant; ANSI Z1.5A/CGA 9.1M Certified; ANSI Z124.1.2 Compliant; ANSI Z124.3 Compliant; ANSI Z124.6-97 Compliant; ANSI Z21.11.2-2016 - Gas-Fired Unvented Room Heaters and Gas-Fired Unvented Decorative Room Heaters; ANSI Z21.50-2016/CSA 2.22-2016 - Standard for Vented Decorative Gas Appliances; ANSI Z21.60-2017/CSA 2.26-2017- Standard for Decorative Gas Appliances; ANSI Z21.84-2017 - Standard for Manually Lighted/ Natural Gas/ Decorative Gas Appliances; ANSI Z21.88-2017/CSA 2.33-2017- Standard for Vented Gas Fireplace Heaters; ANSI Z358 Compliant; ANSI/BHMA A156 Certified; ANSI/BIFMA M7.1 Standard Test Method for Determining VOC Emissions; ANSI/BIFMA X5.1 Office Seating; ANSI/BIFMA X5.11 Large Occupant Office Seating; ANSI/BIFMA X5.3 Vertical Files; ANSI/BIFMA X5.4 Lounge & Public Seating; ANSI/BIFMA X5.5 Desk Products; ANSI/BIFMA X5.6 Panel Systems; ANSI/BIFMA X5.9 Storage; ANSI/BIFMA X6.1 Educational Seating; ANSI/BIFMA X7.1 Standard for Formaldehyde & TVOC Emissions; ANSI/ESD S20.20 Certified; ANSI/NISO Z39.48 Compliant; ANSI/SOHO S6.5 Small Office/Home Office; APMA Certified; ASHRAE 62.2 Standard Compliant; ASME A112.18.1 Compliant; ASME A112.18.2 Compliant; ASME A112.19.1 Compliant; ASME A112.19.2 Compliant; ASME A112.19.3 Compliant; ASP:02:01 Certification; ASSE 1001 Certified; ASSE 1006 Certified; ASSE 1016 Certified; ASTM 1821-19; ASTM E1590-07 Compliant; ASTM F1004-19 Certified; ASTM F1148-17 Compliant; ASTM F1148-18 Compliant; ASTM F1148-18 Certified; ASTM F1169 - 13 Compliant; ASTM F1487-17 Compliant; ASTM F1821 - 16 Compliant; ASTM F1912-17 Compliant; ASTM F1917 - 12 Compliant; ASTM F2057 - 14; ASTM F2057 - 17; ASTM F2057 - 19 | BC6: Select | BD6: Select | BE6: Text | BF6: Please choose one or more from the following, using a semicolon (;) to separate each value: Specifications; Installation & Assembly; Owner Manual; Delivery Information; Warranty Information; Certifications; Disclaimers; Buying Guides; Promotions; Dimensions; Marketing Materials; Energy Guide; Other; Product Information Sheet; Digital Law Label | BG6: Please choose one or more from the following, using a semicolon (;) to separate each value: AAFA Certified; AATCC 116 Grade; AATCC 16.1-2014 Grade; AATCC 16.3-2014 Grade; AATCC 8 Grade; AC Rated; ACT Flammability Guidelines Compliant; AHAM CADR Dust rating; AHAM CADR Pollen rating; AHAM CADR Smoke rating; AHMA Certified; AHMA Compliant; AHRI Certified; ANSI A117.1 Compliant; ANSI A137.1 Compliant; ANSI IT9.2 Compliant; ANSI Z1.5A/CGA 9.1M Certified; ANSI Z124.1.2 Compliant; ANSI Z124.3 Compliant; ANSI Z124.6-97 Compliant; ANSI Z21.11.2-2016 - Gas-Fired Unvented Room Heaters and Gas-Fired Unvented Decorative Room Heaters; ANSI Z21.50-2016/CSA 2.22-2016 - Standard for Vented Decorative Gas Appliances; ANSI Z21.60-2017/CSA 2.26-2017- Standard for Decorative Gas Appliances; ANSI Z21.84-2017 - Standard for Manually Lighted/ Natural Gas/ Decorative Gas Appliances; ANSI Z21.88-2017/CSA 2.33-2017- Standard for Vented Gas Fireplace Heaters; ANSI Z358 Compliant; ANSI/BHMA A156 Certified; ANSI/BIFMA M7.1 Standard Test Method for Determining VOC Emissions; ANSI/BIFMA X5.1 Office Seating; ANSI/BIFMA X5.11 Large Occupant Office Seating; ANSI/BIFMA X5.3 Vertical Files; ANSI/BIFMA X5.4 Lounge & Public Seating; ANSI/BIFMA X5.5 Desk Products; ANSI/BIFMA X5.6 Panel Systems; ANSI/BIFMA X5.9 Storage; ANSI/BIFMA X6.1 Educational Seating; ANSI/BIFMA X7.1 Standard for Formaldehyde & TVOC Emissions; ANSI/ESD S20.20 Certified; ANSI/NISO Z39.48 Compliant; ANSI/SOHO S6.5 Small Office/Home Office; APMA Certified; ASHRAE 62.2 Standard Compliant; ASME A112.18.1 Compliant; ASME A112.18.2 Compliant; ASME A112.19.1 Compliant; ASME A112.19.2 Compliant; ASME A112.19.3 Compliant; ASP:02:01 Certification; ASSE 1001 Certified; ASSE 1006 Certified; ASSE 1016 Certified; ASTM 1821-19; ASTM E1590-07 Compliant; ASTM F1004-19 Certified; ASTM F1148-17 Compliant; ASTM F1148-18 Compliant; ASTM F1148-18 Certified; ASTM F1169 - 13 Compliant; ASTM F1487-17 Compliant; ASTM F1821 - 16 Compliant; ASTM F1912-17 Compliant; ASTM F1917 - 12 Compliant; ASTM F2057 - 14; ASTM F2057 - 17; ASTM F2057 - 19 | BH6: Select | BI6: Select | BJ6: Text | BK6: Please choose one or more from the following, using a semicolon (;) to separate each value: Specifications; Installation & Assembly; Owner Manual; Delivery Information; Warranty Information; Certifications; Disclaimers; Buying Guides; Promotions; Dimensions; Marketing Materials; Energy Guide; Other; Product Information Sheet; Digital Law Label | BL6: Please choose one or more from the following, using a semicolon (;) to separate each value: AAFA Certified; AATCC 116 Grade; AATCC 16.1-2014 Grade; AATCC 16.3-2014 Grade; AATCC 8 Grade; AC Rated; ACT Flammability Guidelines Compliant; AHAM CADR Dust rating; AHAM CADR Pollen rating; AHAM CADR Smoke rating; AHMA Certified; AHMA Compliant; AHRI Certified; ANSI A117.1 Compliant; ANSI A137.1 Compliant; ANSI IT9.2 Compliant; ANSI Z1.5A/CGA 9.1M Certified; ANSI Z124.1.2 Compliant; ANSI Z124.3 Compliant; ANSI Z124.6-97 Compliant; ANSI Z21.11.2-2016 - Gas-Fired Unvented Room Heaters and Gas-Fired Unvented Decorative Room Heaters; ANSI Z21.50-2016/CSA 2.22-2016 - Standard for Vented Decorative Gas Appliances; ANSI Z21.60-2017/CSA 2.26-2017- Standard for Decorative Gas Appliances; ANSI Z21.84-2017 - Standard for Manually Lighted/ Natural Gas/ Decorative Gas Appliances; ANSI Z21.88-2017/CSA 2.33-2017- Standard for Vented Gas Fireplace Heaters; ANSI Z358 Compliant; ANSI/BHMA A156 Certified; ANSI/BIFMA M7.1 Standard Test Method for Determining VOC Emissions; ANSI/BIFMA X5.1 Office Seating; ANSI/BIFMA X5.11 Large Occupant Office Seating; ANSI/BIFMA X5.3 Vertical Files; ANSI/BIFMA X5.4 Lounge & Public Seating; ANSI/BIFMA X5.5 Desk Products; ANSI/BIFMA X5.6 Panel Systems; ANSI/BIFMA X5.9 Storage; ANSI/BIFMA X6.1 Educational Seating; ANSI/BIFMA X7.1 Standard for Formaldehyde & TVOC Emissions; ANSI/ESD S20.20 Certified; ANSI/NISO Z39.48 Compliant; ANSI/SOHO S6.5 Small Office/Home Office; APMA Certified; ASHRAE 62.2 Standard Compliant; ASME A112.18.1 Compliant; ASME A112.18.2 Compliant; ASME A112.19.1 Compliant; ASME A112.19.2 Compliant; ASME A112.19.3 Compliant; ASP:02:01 Certification; ASSE 1001 Certified; ASSE 1006 Certified; ASSE 1016 Certified; ASTM 1821-19; ASTM E1590-07 Compliant; ASTM F1004-19 Certified; ASTM F1148-17 Compliant; ASTM F1148-18 Compliant; ASTM F1148-18 Certified; ASTM F1169 - 13 Compliant; ASTM F1487-17 Compliant; ASTM F1821 - 16 Compliant; ASTM F1912-17 Compliant; ASTM F1917 - 12 Compliant; ASTM F2057 - 14; ASTM F2057 - 17; ASTM F2057 - 19 | BM6: Select | BN6: Select | BO6: Select | BP6: Please choose one or more from the following, using a semicolon (;) to separate each value: Polycarbonate (PC); Polyethylene Plastic; Glass; Silicone; Stainless Steel; Melamine; Polypropylene; Cane; Raffia; Mango Wood; Aluminum; Linen Blend; Acrylic; Manufactured Wood; Limestone; Artificial Grass; Antler; HDPE; Jersey; Linen; Foam; Cowhide; Copper / Copper Plated; Engineered Wood; Cast Aluminum; Flat Wire; Crystal; Fleece / Microfiber; Cardboard / Paper; Chenille; Cherry Wood; Handblown Glass; Cement; Flannel; Chrome; Enamelware; Enameled Cast Iron; Agate / Geode; Fiberglass; Bronze; Cast Iron; Bamboo Slat / Seagrass; Beaded; Alpaca; Felt; Denim; Clay; Gel; Coir; Cardboard; Leather; Cashmere; Galvanized Steel; Hemp; Fireclay; Anodized Aluminum; Blended Fabric; Bamboo; Brass; Burlap; Ceramic; Canvas; Composite; Carbon Steel; Compressed Polyester; Ceramic / Porcelain; Bone China; Cedar; Concrete; Cotton; Earthenware; Engineered Stone; Concrete / Cement; Corrugated; Enamel / Lacquer; Cotton Blend; Compressed Stone; Copper; Faux Leather; Fabric; Faux Sheepskin; Fiberstone; Fine Silver; Hard-Anodized Aluminum; Granite; Heavy Gauge Wire; Faux Fur; Faux Mohair; Faux Cowhide; Iron; High Leaded Crystal; Marble; Lead Crystal; Ironstone; Leather / Faux Leather; Latex; Jute; Lead Free Crystal; Lace; Jute / Sisal; Laminate; Marble / Granite; Mercury Glass; Medium Density Fiberboard (MDF); Mesh; Merino Wool; Memory Foam; Natural Stone; Microfiber / Polyester; Natural Fiber; Microfiber; Natural Fibers; Magnet; Muslin; Metal; Microfiber / Microsuede; Paper; Olefin; Nickel; PEVA; Nylon; Oak; Oxford Fabric; Polyamide; Plywood; Pinecones; Plastic / Acrylic; Pewter; Polycarbonate Plastic; Nickel Plated; Plastic; Polyester; Polymer; Polyester Fill; Polystyrene; Polyvinyl Chloride (PVC); Polyurethane; Porcelain China; Powder Coated Steel; Polypropylene Plastic; Porcelain Enameled Steel; Porcelain; Powder Coated Aluminum; Polyester Blend; Polyresin; Polymarble; Polyurethane (PU); Sandstone; Silver; Sheepskin; Sateen; Rayon / Viscose; Rayon from Bamboo; Silver Plated | BQ6: Yes or No | BR6: Please choose one or more from the following, using a semicolon (;) to separate each value: Acacia; Alder; Ash; Bamboo; Beech; Birch; Camphor; Cedar; Cherry; Elm; Eucalyptus; Fir; Hickory; Mahogany; Mango; Maple; Oak; Pine; Poplar; Rosewood; Rubberwood; Sheesham; Spruce; Teak; Walnut; Wenge; Pecan; Shorea; Paulownia; Chestnut; Hemlock; Aspen; Mindi; Ipe; Olive; Ajo; Agarwood; Afzelia; Afrormosia; Bubinga; Brazilwood; Cumaru; Cedar, Mulanje; Cedar, Spanish; Aloewood; Lignum vitae; Mahogany, African; Mahogany, Mexican; Padauk, African; Macacauba; Ebony, Madagascar; Lignum vitae, Argentine; Gavilan; Mahogany, Honduran; Mahogany, Cuban; Stinkwood, red; Yew, Chinese; Pau rosa, Brazilian; Sandalwood, East African; Ramin; Zitan; Yew, Himalayan; Yew, Japanese; Rosewood, Siamese; Yew, Taiwan; Burlwood; Platane Wood; Sungkai; Does Not Apply | BS6: Number | BT6: Yes or No | BU6: Yes or No | BV6: Yes or No | BW6: Yes or No | BX6: Yes or No | BY6: Number | BZ6: Please choose one or more from the following, using a semicolon (;) to separate each value: Non Residential Use; Residential Use | CA6: Please choose one or more from the following, using a semicolon (;) to separate each value: Made in USA; Made in USA of Imported Materials; Product of Canada; Made In Canada; Does Not Apply | CB6: Yes or No | CC6: Select | CD6: Select | CE6: Select | CF6: Select | CG6: Select | CH6: Select | CI6: Select | CJ6: Please choose one or more from the following, using a semicolon (;) to separate each value: Wheels / Casters; Seat Cushion; Legs; Cover; Lid; Headboard; Back Cushion; Footboard; Tray; Pillow Top; Cushion Cover; Canopy; Shelves; Drawers; Mirror; Unavailable; Does Not Apply | CK6: Yes or No | CL6: Yes or No | CM6: Select | CN6: Please choose one or more from the following, using a semicolon (;) to separate each value: Clear; Cream; Purple; Gold; Silver; Polished Chrome; Polished Nickel; Stainless Steel; Bronze; Chrome; Oil Rubbed Bronze; Matte Black; Satin Nickel; Brushed Nickel; Antique Brass; Antique Bronze; Copper; Antique Copper; Brushed Brass; Polished Brass; Brass; Satin Brass; Brushed Gold; Nickel; Ivory; Green; Orange; Beige; Teal; Red; Satin; Yellow; Pink; White; Brown; Blue; Satin Black; Rose Gold; Navy; Black; Tan; Gray; Brown Wood; Dark Brown Wood; Medium Yellow Wood; Espresso Wood; Medium Wood; Red Wood; Beige Wood; Natural Wood; Gray Wood; Light Yellow Wood; White Wood; Oak Wood | CO6: Whole Number | CP6: Yes or No | CQ6: Please choose one or more from the following, using a semicolon (;) to separate each value: Laptop; Projector; CPU; Printer; Keyboard; TV/Monitor; Unavailable; Does Not Apply | CR6: Please choose one or more from the following, using a semicolon (;) to separate each value: Drawers; Legs; Storage; TV Mount; Wheels / Casters; Cabinets; Unavailable; Does Not Apply | CS6: Whole Number | CT6: Whole Number | CU6: Select | CV6: Yes or No | CW6: Yes or No | CX6: Select | CY6: Select | CZ6: Select | DA6: Select | DB6: Yes or No | DC6: Please choose one or more from the following, using a semicolon (;) to separate each value: Dual Language; Distribution Conflict; Logistics; Does Not Apply | DD6: Select | DE6: Select | DF6: Yes or No | DG6: Please choose one or more from the following, using a semicolon (;) to separate each value: UN3091; UN3481; UN2800; UN1950; UN3496; ID8000; UN1013; UN3082; UN3077; UN3480; UN2857; UN3358; UN3090; UN1266; UN1993; UN1944; UN1070; UN1044; UN3163; UN1268; UN1760; UN1011; UN2794; UN1759; UN3171; UN1987; UN1263; UN1170; UN3265; UN3260; UN3215; UN1006; UN3175; Does Not Apply | DH6: Select | DI6: Select | DJ6: Select | DK6: Select | DL6: Please choose one or more from the following, using a semicolon (;) to separate each value: TÜV Rheinland Certified; MET Listed; AFNOR UK Ltd; BSI Assurance UK Ltd; cUL Listed; ETL Listed; DBI Certification Ltd; UL Listed; cETL Listed; CSA Certified; SGS North America Listed; Does Not Apply | DM6: Text | DN6: Select | DO6: Yes or No | DP6: Number | DQ6: Number | DR6: Number | DS6: Number | DT6: Yes or No | DU6: Yes or No | DV6: Select | DW6: Yes or No | DX6: Please choose one or more from the following, using a semicolon (;) to separate each value: 30 Days; 60 Days; 90 Days; 6 Months; 1 Year; 2 Years; 3 Years; 5 Years; 10 Years; 20 Years; 25 Years; Lifetime; Warranty length varies by part; 15 Years; 18 Months; 12 Years; 6 Years; 4 Years; 8 Years; 7 Years; Does Not Apply
B7: Default Row: | C7: N/A | E7: N/A | F7: N/A | G7: N/A | I7: N/A | J7: N/A | K7: N/A | L7: N/A | M7: N/A | N7: N/A | O7: N/A | P7: N/A | Q7: N/A | R7: N/A | AT7: N/A | AU7: N/A | AV7: N/A | AW7: N/A | AX7: N/A | AY7: N/A
