Workbook
Name allowed185254: 'Valid Values'!$V$2:$V$70
Name allowed201479: 'Valid Values'!$R$2:$R$3
Name allowed217965: 'Valid Values'!$BC$2:$BC$20
Name allowed220265: 'Valid Values'!$AI$2:$AI$16
Name allowed220267: 'Valid Values'!$AH$2:$AH$9
Name allowed222775: 'Valid Values'!$BD$2:$BD$5
Name allowed222778: 'Valid Values'!$BE$2:$BE$61
Name allowed222860: 'Valid Values'!$P$2:$P$12
Name allowed222861: 'Valid Values'!$Q$2:$Q$7
Name allowed224759: 'Valid Values'!$AN$2:$AN$4
Name allowed224980: 'Valid Values'!$AO$2:$AO$4
Name allowed227966: 'Valid Values'!$S$2:$S$3
Name allowed236083: 'Valid Values'!$AQ$2:$AQ$3
Name allowed244566: 'Valid Values'!$T$2:$T$6
Name allowed251110: 'Valid Values'!$AR$2:$AR$5
Name allowed255305: 'Valid Values'!$BG$2:$BG$4
Name allowed256090: 'Valid Values'!$BH$2:$BH$22
Name allowed292794: 'Valid Values'!$AG$2:$AG$17
Name allowed293480: 'Valid Values'!$U$2:$U$20
Name allowed310560: 'Valid Values'!$AS$2:$AS$5
Name allowed333812: 'Valid Values'!$BF$2:$BF$26
Name allowed340810: 'Valid Values'!$AU$2:$AU$17
Name allowed341070: 'Valid Values'!$AV$2:$AV$6
Name allowed346869: 'Valid Values'!$W$2:$W$11
Name allowed351619: 'Valid Values'!$X$2:$X$5
Name allowed351641: 'Valid Values'!$Z$2:$Z$5
Name allowed351649: 'Valid Values'!$AC$2:$AC$6
Name allowed352342: 'Valid Values'!$AB$2:$AB$8
Name allowed352351: 'Valid Values'!$AA$2:$AA$8
Name allowed364708: 'Valid Values'!$AP$2:$AP$5
Name allowed367149: 'Valid Values'!$Y$2:$Y$13
Name allowed368262: 'Valid Values'!$AX$2:$AX$6
Name allowed368645: 'Valid Values'!$AD$2:$AD$100
Name allowed369614: 'Valid Values'!$AW$2:$AW$13
Name allowed373560: 'Valid Values'!$AT$2:$AT$35
Name allowed375302: 'Valid Values'!$AY$2:$AY$13
Name allowed379875: 'Valid Values'!$AF$2:$AF$55
Name allowed382060: 'Valid Values'!$AZ$2:$AZ$5
Name allowed384286: 'Valid Values'!$AJ$2:$AJ$14
Name allowed385921: 'Valid Values'!$BA$2:$BA$4
Name allowed420139: 'Valid Values'!$AK$2:$AK$18
Name allowed421601: 'Valid Values'!$BB$2:$BB$6
Name allowed5620: 'Valid Values'!$M$2:$M$3
Name allowed5621: 'Valid Values'!$N$2:$N$26
Name allowed5625: 'Valid Values'!$O$2:$O$22
Name allowed5671: 'Valid Values'!$AM$2:$AM$4
Name allowed5910: 'Valid Values'!$AE$2:$AE$31
Name allowed5938: 'Valid Values'!$AL$2:$AL$7
Name allowedcore__manufacturerId: 'Valid Values'!$A$2:$A$1
Name allowedmedia__documentType: 'Valid Values'!$I$2:$I$16
Name allowedmedia__language: 'Valid Values'!$L$2:$L$30
Name allowedmedia__legalDocumentType: 'Valid Values'!$J$2:$J$506
Name allowedmedia__regionType: 'Valid Values'!$K$2:$K$5
Name allowedpropSixtyFive__chemicalId: 'Valid Values'!$F$2:$F$902
Name allowedpropSixtyFive__countryOfManufacturer: 'Valid Values'!$H$2:$H$248
Name allowedpropSixtyFive__toxicity: 'Valid Values'!$G$2:$G$3
Name allowedshippingAndFulfillment__freightClass: 'Valid Values'!$C$2:$C$19
Name allowedshippingAndFulfillment__leadTime: 'Valid Values'!$D$2:$D$18
Name allowedshippingAndFulfillment__replacementLeadTime: 'Valid Values'!$E$2:$E$7
Name allowedshippingAndFulfillment__shipType: 'Valid Values'!$B$2:$B$3

Sheet Instructions
A1: New Features | D1: For Mandarin translations of product questions, please click here. All answer inputs should still be provided in English. 点击此处查看所有产品相关问题的中文翻译。
A2: Conditional Formatting
A3: Some answers to questions on the spec sheet are dependent on upstream responses, whether they are related to attributes like material type, existence of features | C3: Legends
A4: or compliance. Real-time cell coloring per the legend indicates whether an input is required, has an error or has a conditional rule applied. | C4: Cell Fill Colors
A5: Error Guidance | C5: Light Red | D5: Missing required data
A6: Errors are highlighted on the Error Summary Tab which shows a summary of all errors across all sheets with high level details and hyperlinks to the corresponding | C6: Gray | D6: Not required/will be autofilled*
A7: cell where the error occurred. Additionally, a new Error Status Column at the beginning of each class sheet will show the status of each row and will display the first error | C7: Red | D7: Error/incorrect answer
A8: error message in that row, and will update as errors are resolved from left to right. | C8: Blue | D8: Autofill suggested by Wayfair (review needed)
C9: Yellow | D9: Warning
A10: Class Sheet Instructions | C10: No fill | D10: Validated/no action required
D11: * For products that have already been submitted, the entire row will be filled gray and cannot be edited further
A12: All data provided in the class sheet feeds directly to the customer-facing Product Details Page (PDP), optimizes search and enables order fulfillment. Please ensure the
A13: data provided is accurate and as detailed as possible. | C13: Data Priority
A14: Notes: | C14: Required | D14: Data required for product to be live on site
A15: • Column headers provide additional information on the data required for each column. | C15: Recommended | D15: Not required but recommended to improve search and browse
A16: • Completing Recommended and Additional fields further enhances the customer experience and improves the quality of listings for better product discovery. | C16: Additional | D16: Optional but enhances listings for customers
A17: • Marketing Copy should provide a compelling, informative overview of the product, ensuring it effectively highlights key features, benefits, and use cases. | C17: Conditional | D17: Data may be required based on prior responses
A18: Incorporating comprehensive, descriptive language will enable future enhancements for capturing and improving product tagging.
A19: ◦ Provide key selling point(s)/feature(s) that differentiate your product and inform customers about your product and encourage purchase. | C19: Data Type
A20: ◦ Either Marketing Copy OR at least 3 Feature Bullets are required. Feature bullets will be displayed on Wayfair PDP in bulleted form. | C20: Text | D20: Enter a text-based response
A21: • The order in which media is input may not be reflected in order of imagery on the product page. | C21: Single-Select | D21: Select one option from a list of provided options (listed in a dropdown on the cell)
A22: • If all products in a class have the same answer to a question, a default value can be set. An answer entered in the Default Answer row will be applied to all products | C22: Multi-Select | D22: Enter one or more options from a list of provided options, separated using a semi-colon (;)
A23: in that class automatically. Additional products added to this class in the future will have the same default value applied as well. For any products that have a | C23: Number* | D23: Enter a decimal numeric response with up to 2 decimal points
A24: different answer than others in the class, enter the answer manually to the applicable row to bypass the default just for that question and product. | C24: Whole Number* | D24: Enter an integer (whole number) numeric response
C25: Yes or No | D25: Enter a Yes, No or Does Not Apply response (listed in a dropdown on the cell)
A26: Additional Tabs Instructions | D26: * Does Not Apply is a valid response when applicable
A27: Additional Cartons
A28: If a product ships in more than 5 cartons, use the Additional Cartons tab to submit data for cartons 6 and beyond. To add additional cartons, provide the Supplier Part
A29: Number followed by corresponding data for each carton.
A30: Additional Chemicals
A31: If your product contains more than 5 chemicals that need to be reported for Proposition 65, use the Additional Chemicals tab to add additional data.
A32: Additional Media
A33: If a product has more media files than there are columns for in the class sheet, use the Additional Images, Videos or Documents tabs to add additional data.
A34: Notes:
A35: • A maximum of 3 videos can be shown on a product display page in the media tray. Additional videos can be showcased within Waymore content.
A36: Valid Values
A37: The Valid Values tab shows all acceptable answers to single- and multi-select questions. Hyperlinks below each column header will bring you to the corresponding
A38: values list on this tab.
... A40: The Failed Products tab will only show if products in your template failed to upload. These products will need to be added to a new template and uploaded again.

Sheet Error Summary
A1: This Error Summary tab lists all errors and warnings in the spec sheet. Each entry includes a link to the specific cell and detailed information about the issue.
A2: Status | B2: Location | C2: Sheet Name | D2: Supplier Part Number | E2: Product Name | F2: Field | G2: Provided Answer | H2: Error Message
A3: {=_xlfn.LET(_xlpm.class6Data, GetSheetStatusData(Class6Tracker, Class6Errors), _xlpm.shippingAndFulfillment__cartonsData, GetSheetStatusData(shippingAndFulfillment__cartonsTracker, shippingAndFulfillment__cartonsErrors), _xlpm.propSixtyFive__chemicalsData, GetSheetStatusData(propSixtyFive__chemicalsTracker, propSixtyFive__chemicalsErrors), _xlpm.media__imagesData, GetSheetStatusData(media__imagesTracker, media__imagesErrors), _xlpm.media__videosData, GetSheetStatusData(media__videosTracker, media__videosErrors), _xlpm.media__documentsData, GetSheetStatusData(media__documentsTracker, media__documentsErrors), _xlpm.stackedData, _xlfn.VSTACK(_xlpm.class6Data, _xlpm.shippingAndFulfillment__cartonsData, _xlpm.propSixtyFive__chemicalsData, _xlpm.media__imagesData, _xlpm.media__videosData, _xlpm.media__documentsData), _xlfn._xlws.FILTER(_xlpm.stackedData, _xlpm.stackedData<>"", ""))} | B3: =IF(AND(C3<>"", J3<>""), HYPERLINK("#'" & C3 & "'!" & J3, J3), "") | C3: {=_xlfn.LET(_xlpm.class6Data, GetSheetNameData(Class6Tracker, Class6Errors, "6 - TV Stands & Enterta"), _xlpm.shippingAndFulfillment__cartonsData, GetSheetNameData(shippingAndFulfillment__cartonsTracker, shippingAndFulfillment__cartonsErrors, "Additional Cartons"), _xlpm.propSixtyFive__chemicalsData, GetSheetNameData(propSixtyFive__chemicalsTracker, propSixtyFive__chemicalsErrors, "Additional Chemicals"), _xlpm.media__imagesData, GetSheetNameData(media__imagesTracker, media__imagesErrors, "Additional Images"), _xlpm.media__videosData, GetSheetNameData(media__videosTracker, media__videosErrors, "Additional Videos"), _xlpm.media__documentsData, GetSheetNameData(media__documentsTracker, media__documentsErrors, "Additional Documents"), _xlpm.stackedData, _xlfn.VSTACK(_xlpm.class6Data, _xlpm.shippingAndFulfillment__cartonsData, _xlpm.propSixtyFive__chemicalsData, _xlpm.media__imagesData, _xlpm.media__videosData, _xlpm.media__documentsData), _xlfn._xlws.FILTER(_xlpm.stackedData, _xlpm.stackedData<>"", ""))} | D3: {=_xlfn.LET(_xlpm.class6PartNumbers, GetSheetSupplierPartNumbers(Class6Tracker, Class6Errors, '6 - TV Stands & Enterta'!B:B), _xlpm.shippingAndFulfillment__cartonsPartNumbers, GetSheetSupplierPartNumbers(shippingAndFulfillment__cartonsTracker, shippingAndFulfillment__cartonsErrors, 'Additional Cartons'!B:B), _xlpm.propSixtyFive__chemicalsPartNumbers, GetSheetSupplierPartNumbers(propSixtyFive__chemicalsTracker, propSixtyFive__chemicalsErrors, 'Additional Chemicals'!B:B), _xlpm.media__imagesPartNumbers, GetSheetSupplierPartNumbers(media__imagesTracker, media__imagesErrors, 'Additional Images'!B:B), _xlpm.media__videosPartNumbers, GetSheetSupplierPartNumbers(media__videosTracker, media__videosErrors, 'Additional Videos'!B:B), _xlpm.media__documentsPartNumbers, GetSheetSupplierPartNumbers(media__documentsTracker, media__documentsErrors, 'Additional Documents'!B:B), _xlpm.stackedPartNumbers, _xlfn.VSTACK(_xlpm.class6PartNumbers, _xlpm.shippingAndFulfillment__cartonsPartNumbers, _xlpm.propSixtyFive__chemicalsPartNumbers, _xlpm.media__imagesPartNumbers, _xlpm.media__videosPartNumbers, _xlpm.media__documentsPartNumbers), _xlfn._xlws.FILTER(_xlpm.stackedPartNumbers, _xlpm.stackedPartNumbers<>"", ""))} | E3: {=_xlfn.LET(_xlpm.class6ProductNames, GetSheetProductNames(Class6Tracker, Class6Errors, '6 - TV Stands & Enterta'!G:G), _xlpm.shippingAndFulfillment__cartonsProductNames, GetSheetProductNames(shippingAndFulfillment__cartonsTracker, shippingAndFulfillment__cartonsErrors, 'Additional Cartons'!Z:Z), _xlpm.propSixtyFive__chemicalsProductNames, GetSheetProductNames(propSixtyFive__chemicalsTracker, propSixtyFive__chemicalsErrors, 'Additional Chemicals'!Z:Z), _xlpm.media__imagesProductNames, GetSheetProductNames(media__imagesTracker, media__imagesErrors, 'Additional Images'!Z:Z), _xlpm.media__videosProductNames, GetSheetProductNames(media__videosTracker, media__videosErrors, 'Additional Videos'!Z:Z), _xlpm.media__documentsProductNames, GetSheetProductNames(media__documentsTracker, media__documentsErrors, 'Additional Documents'!Z:Z), _xlpm.stackedProductNames, _xlfn.VSTACK(_xlpm.class6ProductNames, _xlpm.shippingAndFulfillment__cartonsProductNames, _xlpm.propSixtyFive__chemicalsProductNames, _xlpm.media__imagesProductNames, _xlpm.media__videosProductNames, _xlpm.media__documentsProductNames), _xlfn._xlws.FILTER(_xlpm.stackedProductNames, _xlpm.stackedProductNames<>"EMPTY_ERROR", ""))} | F3: {=_xlfn.LET( _xlpm.class6QuestionDisplayNames, GetErrorQuestionDisplayNames(Class6Headers, Class6Tracker, Class6Errors) , _xlpm.shippingAndFulfillment__cartonsQuestionDisplayNames, GetErrorQuestionDisplayNames(shippingAndFulfillment__cartonsHeaders, shippingAndFulfillment__cartonsTracker, shippingAndFulfillment__cartonsErrors) , _xlpm.propSixtyFive__chemicalsQuestionDisplayNames, GetErrorQuestionDisplayNames(propSixtyFive__chemicalsHeaders, propSixtyFive__chemicalsTracker, propSixtyFive__chemicalsErrors) , _xlpm.media__imagesQuestionDisplayNames, GetErrorQuestionDisplayNames(media__imagesHeaders, media__imagesTracker, media__imagesErrors) , _xlpm.media__videosQuestionDisplayNames, GetErrorQuestionDisplayNames(media__videosHeaders, media__videosTracker, media__videosErrors) , _xlpm.media__documentsQuestionDisplayNames, GetErrorQuestionDisplayNames(media__documentsHeaders, media__documentsTracker, media__documentsErrors) , _xlpm.stackedQuestionDisplayNames, _xlfn.VSTACK(_xlpm.class6QuestionDisplayNames, _xlpm.shippingAndFulfillment__cartonsQuestionDisplayNames, _xlpm.propSixtyFive__chemicalsQuestionDisplayNames, _xlpm.media__imagesQuestionDisplayNames, _xlpm.media__videosQuestionDisplayNames, _xlpm.media__documentsQuestionDisplayNames), _xlfn._xlws.FILTER(_xlpm.stackedQuestionDisplayNames, _xlpm.stackedQuestionDisplayNames<>"", ""))} | G3: {=_xlfn.LET( _xlpm.class6ProvidedAnswers, GetFilteredProvidedAnswers(Class6Answers, Class6Errors, Class6Tracker) , _xlpm.shippingAndFulfillment__cartonsProvidedAnswers, GetFilteredProvidedAnswers(shippingAndFulfillment__cartonsAnswers, shippingAndFulfillment__cartonsErrors, shippingAndFulfillment__cartonsTracker) , _xlpm.propSixtyFive__chemicalsProvidedAnswers, GetFilteredProvidedAnswers(propSixtyFive__chemicalsAnswers, propSixtyFive__chemicalsErrors, propSixtyFive__chemicalsTracker) , _xlpm.media__imagesProvidedAnswers, GetFilteredProvidedAnswers(media__imagesAnswers, media__imagesErrors, media__imagesTracker) , _xlpm.media__videosProvidedAnswers, GetFilteredProvidedAnswers(media__videosAnswers, media__videosErrors, media__videosTracker) , _xlpm.media__documentsProvidedAnswers, GetFilteredProvidedAnswers(media__documentsAnswers, media__documentsErrors, media__documentsTracker) , _xlpm.stackedProvidedAnswers, _xlfn.VSTACK(_xlpm.class6ProvidedAnswers, _xlpm.shippingAndFulfillment__cartonsProvidedAnswers, _xlpm.propSixtyFive__chemicalsProvidedAnswers, _xlpm.media__imagesProvidedAnswers, _xlpm.media__videosProvidedAnswers, _xlpm.media__documentsProvidedAnswers), _xlfn._xlws.FILTER(_xlpm.stackedProvidedAnswers, _xlpm.stackedProvidedAnswers<>"EMPTY_ERROR", ""))} | H3: {=_xlfn.LET(_xlpm.class6ErrorMessages, _xlfn.FILTER( _xlfn.TOCOL(Class6Errors), _xlfn.TOCOL((Class6Errors <> "") * (Class6Tracker <> "Valid") * (Class6Tracker <> "Disabled")), "" ), _xlpm.shippingAndFulfillment__cartonsErrorMessages, _xlfn.FILTER( _xlfn.TOCOL(shippingAndFulfillment__cartonsErrors), _xlfn.TOCOL((shippingAndFulfillment__cartonsErrors <> "") * (shippingAndFulfillment__cartonsTracker <> "Valid") * (shippingAndFulfillment__cartonsTracker <> "Disabled")), "" ), _xlpm.propSixtyFive__chemicalsErrorMessages, _xlfn.FILTER( _xlfn.TOCOL(propSixtyFive__chemicalsErrors), _xlfn.TOCOL((propSixtyFive__chemicalsErrors <> "") * (propSixtyFive__chemicalsTracker <> "Valid") * (propSixtyFive__chemicalsTracker <> "Disabled")), "" ), _xlpm.media__imagesErrorMessages, _xlfn.FILTER( _xlfn.TOCOL(media__imagesErrors), _xlfn.TOCOL((media__imagesErrors <> "") * (media__imagesTracker <> "Valid") * (media__imagesTracker <> "Disabled")), "" ), _xlpm.media__videosErrorMessages, _xlfn.FILTER( _xlfn.TOCOL(media__videosErrors), _xlfn.TOCOL((media__videosErrors <> "") * (media__videosTracker <> "Valid") * (media__videosTracker <> "Disabled")), "" ), _xlpm.media__documentsErrorMessages, _xlfn.FILTER( _xlfn.TOCOL(media__documentsErrors), _xlfn.TOCOL((media__documentsErrors <> "") * (media__documentsTracker <> "Valid") * (media__documentsTracker <> "Disabled")), "" ), _xlpm.stackedErrorMessages, _xlfn.VSTACK(_xlpm.class6ErrorMessages, _xlpm.shippingAndFulfillment__cartonsErrorMessages, _xlpm.propSixtyFive__chemicalsErrorMessages, _xlpm.media__imagesErrorMessages, _xlpm.media__videosErrorMessages, _xlpm.media__documentsErrorMessages), _xlpm.filteredMessages, _xlfn._xlws.FILTER(_xlpm.stackedErrorMessages, _xlpm.stackedErrorMessages<>"", ""), IFERROR(_xlfn.TEXTAFTER(_xlpm.filteredMessages, ":"), _xlpm.filteredMessages))} | J3: {=_xlfn.LET(_xlpm.class6Addresses, GetSheetLocationAddresses(Class6Tracker, Class6Errors), _xlpm.shippingAndFulfillment__cartonsAddresses, GetSheetLocationAddresses(shippingAndFulfillment__cartonsTracker, shippingAndFulfillment__cartonsErrors), _xlpm.propSixtyFive__chemicalsAddresses, GetSheetLocationAddresses(propSixtyFive__chemicalsTracker, propSixtyFive__chemicalsErrors), _xlpm.media__imagesAddresses, GetSheetLocationAddresses(media__imagesTracker, media__imagesErrors), _xlpm.media__videosAddresses, GetSheetLocationAddresses(media__videosTracker, media__videosErrors), _xlpm.media__documentsAddresses, GetSheetLocationAddresses(media__documentsTracker, media__documentsErrors), _xlpm.stackedAddresses, _xlfn.VSTACK(_xlpm.class6Addresses, _xlpm.shippingAndFulfillment__cartonsAddresses, _xlpm.propSixtyFive__chemicalsAddresses, _xlpm.media__imagesAddresses, _xlpm.media__videosAddresses, _xlpm.media__documentsAddresses), _xlfn._xlws.FILTER(_xlpm.stackedAddresses, _xlpm.stackedAddresses<>"", ""))}
B4: =IF(AND(C4<>"", J4<>""), HYPERLINK("#'" & C4 & "'!" & J4, J4), "")
B5: =IF(AND(C5<>"", J5<>""), HYPERLINK("#'" & C5 & "'!" & J5, J5), "")
B6: =IF(AND(C6<>"", J6<>""), HYPERLINK("#'" & C6 & "'!" & J6, J6), "")
B7: =IF(AND(C7<>"", J7<>""), HYPERLINK("#'" & C7 & "'!" & J7, J7), "")
B8: =IF(AND(C8<>"", J8<>""), HYPERLINK("#'" & C8 & "'!" & J8, J8), "")
B9: =IF(AND(C9<>"", J9<>""), HYPERLINK("#'" & C9 & "'!" & J9, J9), "")
B10: =IF(AND(C10<>"", J10<>""), HYPERLINK("#'" & C10 & "'!" & J10, J10), "")
B11: =IF(AND(C11<>"", J11<>""), HYPERLINK("#'" & C11 & "'!" & J11, J11), "")
B12: =IF(AND(C12<>"", J12<>""), HYPERLINK("#'" & C12 & "'!" & J12, J12), "")
B13: =IF(AND(C13<>"", J13<>""), HYPERLINK("#'" & C13 & "'!" & J13, J13), "")
B14: =IF(AND(C14<>"", J14<>""), HYPERLINK("#'" & C14 & "'!" & J14, J14), "")
B15: =IF(AND(C15<>"", J15<>""), HYPERLINK("#'" & C15 & "'!" & J15, J15), "")
... B6002: =IF(AND(C6002<>"", J6002<>""), HYPERLINK("#'" & C6002 & "'!" & J6002, J6002), "")

Sheet WAYFAIR_USE_ONLY
A1: {"brand_catalog_id": 1, "previous_upload_id": null, "template_type": "DEFAULT_QUESTIONS", "supplier_id": 455634, "template_context": "STANDARD", "app_version": "v2", "product_count": 0, "default_answers_included": true, "default_answers_supported": true, "use_legacy_excel_format": false, "include_variant_grouping": false, "download_template_request_id": "9dccca51-4ea6-414d-981d-669de11ec959", "sheet_metadata": null} | C1: =_xlfn.INFO("release")
C2: =_xlfn.INFO("system")
C3: {=IF(ISERROR(_xlfn.MAP(A8:A8,_xlfn.LAMBDA(_xlpm.class,_xlpm.class<>""))), "Not Available", "Supported")}
A8: Carts & Stands | B8: Entertainment Center | C8: Yes | D8: Yes | E8: No | F8: Yes | G8: Yes | H8: Yes | I8: No | J8: Yes | K8: Yes | L8: Yes | M8: Yes | N8: No | O8: Yes | P8: No | Q8: No | R8: No | S8: Yes | T8: No | U8: No | V8: Dovetail | W8: Yes | X8: Lithium Metal | Y8: Cell | Z8: 1 | AA8: Stand alone | AB8: Cells exceeding 5 grams | AC8: Cells of between 20w/h and 60w/h | AD8: 2.5kg or less | AE8: Yes | AF8: No | AG8: Yes | AH8: Yes | AI8: Direct Vent | AJ8: Yes | AK8: Yes | AL8: Yes | AM8: Yes | AN8: Yes | AO8: Yes | AP8: Yes | AQ8: Yes | AR8: Yes | AS8: Yes | AT8: Yes | AU8: 1 | AV8: I | AW8: >0 - ≤25ml | AX8: Yes | AY8: No | AZ8: No | BA8: 1A | BB8: Yes | BC8: BIFMA Accredited | BD8: 28" | BE8: Yes | BF8: No Assembly Needed | BG8: 30 Days | BH8: Yes | BI8: Yes | BJ8: Full | BL8: US | BM8: Arabic | BN8: No | BO8: A-alpha-C (2-Amino-9H-pyrido[2,3-b]indole) | BP8: United States | BQ8: Small Parcel | BR8: 50 | BS8: 0 | BT8: 0 | BU8: No | BV8: No
A9: Multimedia Storage | B9: TV Stand | C9: No | D9: No | E9: Yes | F9: No | G9: No | H9: No | I9: Yes | J9: No | K9: No | L9: No | M9: No | N9: Yes | O9: No | P9: Yes | Q9: Yes | R9: Yes | S9: No | T9: Yes | U9: Yes | V9: Mortise and Tenon | W9: No | X9: Lithium Ion / Lithium Polymer | Y9: Battery | Z9: 2 | AA9: Contained in product | AB9: Batteries of 2 grams or less | AC9: Cells exceeding 60w/h | AD9: 2.5kg to 5kg | AE9: No | AF9: Yes | AG9: No | AH9: No | AI9: Natural Vent | AJ9: No | AK9: No | AL9: No | AM9: No | AN9: No | AO9: No | AP9: No | AQ9: No | AR9: No | AS9: No | AT9: No | AU9: 2.2 | AV9: III | AW9: >1L - ≤5L | AX9: No | AY9: Yes | AZ9: Yes | BA9: 3A or 6A | BB9: No | BC9: BIFMA Equivalent | BD9: 24" | BE9: No | BF9: Minimal Assembly Needed | BG9: 60 Days | BH9: No | BI9: No | BJ9: Limited | BL9: UK | BM9: Bulgarian | BN9: Yes | BO9: Abiraterone acetate | BP9: Canada | BQ9: LTL | BR9: 55 | BS9: 24 | BT9: 24 | BU9: Yes | BV9: Yes
A10: Speaker Stands | C10: Unavailable | F10: Does Not Apply | H10: Unavailable | I10: Unavailable | J10: Unavailable | K10: Does Not Apply | L10: Unavailable | M10: Unavailable | N10: Unavailable | O10: Unavailable | T10: Unavailable | U10: Does Not Apply | V10: Rabbet Joint | W10: Unavailable | X10: Nickel Cadmium | Y10: Button Cell | Z10: 3 | AA10: Packed with product | AB10: Batteries of between 2 and 25 grams | AC10: Cells of 20w/h or less | AD10: More than 10kg | AE10: Unavailable | AF10: Unavailable | AG10: Does Not Apply | AH10: Unavailable | AI10: Vent Free | AJ10: Unavailable | AK10: Unavailable | AL10: Unavailable | AM10: Does Not Apply | AN10: Does Not Apply | AO10: Does Not Apply | AP10: Yes, Compliance Verified Program Member | AQ10: Does Not Apply | AT10: Yes, Compliance Verified Program Member | AU10: 2.1 | AV10: No Packing Group | AW10: >0.5L - ≤1L | AY10: Yes, Compliance Verified Program Member | AZ10: Yes, Compliance Verified Program Member | BA10: Does Not Apply | BB10: Does Not Apply | BC10: Contract Grade Accredited | BD10: 40" | BF10: Full Assembly Needed | BG10: 90 Days | BH10: Does Not Apply | BJ10: Does Not Apply | BL10: EU | BM10: Czech (Czech Republic) | BO10: Acetaldehyde | BP10: Afghanistan | BR10: 60 | BS10: 48 | BT10: 48
A11: TV Stands & Entertainment Centers | V11: Basic Butt | W11: Does Not Apply | X11: Nickel Metal Hydride | Y11: Does Not Apply | Z11: 6 | AA11: Does Not Apply | AB11: Cells of 1gram or less | AC11: Batteries exceeding 300w/h | AD11: 5kg to 10kg | AF11: Does Not Apply | AI11: External | AJ11: Does Not Apply | AK11: Does Not Apply | AL11: Does Not Apply | AP11: Does Not Apply | AT11: Does Not Apply | AU11: 7 | AV11: II | AW11: >0 - ≤100g | AY11: Unavailable | AZ11: Does Not Apply | BC11: Unavailable | BD11: 32" | BF11: Does Not Apply | BG11: 6 Months | BL11: CA | BM11: Danish | BO11: Acetamide | BP11: Åland Islands | BR11: 65 | BS11: 72 | BT11: 72
A12: Audio Towers | V12: Biscuit Joint | X12: Alkaline | Z12: 7 | AB12: Cells of between 1 and 5 grams | AC12: Batteries of between 100w/h and 300 w/h | AD12: Does Not Apply | AI12: Convertible | AU12: 5.2 | AV12: Does Not Apply | AW12: >100 - ≤500g | AY12: Does Not Apply | BC12: Does Not Apply | BD12: 42" | BG12: 1 Year | BM12: German | BO12: Acetazolamide | BP12: Albania | BR12: 70 | BS12: 96 | BT12: 96
A13: Office Chairs | V13: Tongue and Groove | X13: Carbon Zinc | Z13: 5 | AB13: Batteries exceeding 25 grams | AC13: Batteries of 100w/h or less | AI13: Recirculating | AU13: 6.1 | AW13: >500g - ≤1kg | BD13: 49" | BG13: 2 Years | BM13: Greek | BO13: Acetochlor | BP13: Algeria | BR13: 77.5 | BS13: 120 | BT13: 120
A14: Beds | V14: Pocket Joint | X14: Lead Acid (Spillable) | Z14: 8 | AB14: Does Not Apply | AC14: Does Not Apply | AI14: B-Vent | AU14: 3 | AW14: >125ml - ≤500ml | BD14: 55" | BG14: 3 Years | BM14: English (United Kingdom) | BO14: Acetohydroxamic acid | BP14: American Samoa | BR14: 85 | BS14: 144
A15: Dressers & Chests | V15: Cam Bolt | X15: Lead Acid (Non-Spillable) | Z15: 10 | AI15: Does Not Apply | AU15: 4.1 | AW15: >25 - ≤125ml | BD15: 50" | BG15: 5 Years | BM15: English (United States) | BO15: 2-Acetylaminofluorene | BP15: Andorra | BR15: 92.5 | BS15: 168
A16: Nightstands | V16: Dowel Joint | X16: Silver Oxide | Z16: 4 | AU16: 4.3 | AW16: >1kg - ≤5kg | BD16: 58" | BG16: 10 Years | BM16: Spanish | BO16: Acifluorfen sodium | BP16: Angola | BR16: 100 | BS16: 192
A17: Armoires & Wardrobes | V17: Half-Lap | X17: Does Not Apply | Z17: 9 | AU17: 4.2 | AW17: >5L | BD17: 65" | BG17: 20 Years | BM17: Finnish | BO17: Acrylamide | BP17: Anguilla | BR17: 110 | BS17: 216
A18: Daybeds & Guest Beds | V18: Box | Z18: Unavailable | AU18: 5.1 | AW18: >5kg | BD18: 75" | BG18: 25 Years | BM18: French (Canada) | BO18: Acrylonitrile | BP18: Antarctica | BR18: 125 | BS18: 240
A19: Headboards | V19: Lap | Z19: Does Not Apply | AU19: 2.3 | AW19: Does Not Apply | BD19: 70" | BG19: Lifetime | BM19: Hungarian | BO19: Actinomycin D | BP19: Antigua and Barbuda | BR19: 150 | BS19: 360
A20: Bedroom Sets | V20: Double Dowelled | AU20: 6.2 | BD20: 48" | BG20: 15 Years | BM20: Indonesian | BO20: AF-2;[2-(2-furyl)-3-(5-nitro-2-furyl)]acrylamide | BP20: Argentina | BR20: 175 | BS20: 480
A21: Easels | V21: Bridle | AU21: 9 | BD21: 43" | BG21: 4 Years | BM21: Icelandic | BO21: Aflatoxins | BP21: Armenia | BR21: 200 | BS21: 600
A22: Display Cases | V22: Halved | AU22: 8 | BD22: 88" | BG22: 18 Months | BM22: Italian | BO22: Alachlor | BP22: Aruba | BR22: 250 | BS22: 720
A23: Lockers | V23: Corner Block Reinforced | AU23: Does Not Apply | BD23: 60" | BG23: 6 Years | BM23: Japanese | BO23: Alcoholic beverages, when associated with alcohol abuse | BP23: Australia | BR23: 300 | BS23: 840
A24: Lecterns & Podiums | V24: Miter | BD24: 78" | BG24: 7 Years | BM24: Korean | BO24: Aldrin | BP24: Austria | BR24: 400 | BS24: 960
A25: Desks | V25: Unavailable | BD25: 85" | BG25: 8 Years | BM25: Norwegian (Bokmål) | BO25: All-trans retinoic acid | BP25: Azerbaijan | BR25: 500
A26: Literature Racks | V26: Does Not Apply | BD26: 77" | BG26: 9 Years | BM26: Dutch | BO26: Aloe Vera, non-decolorized whole leaf extract | BP26: Bahamas
A27: Filing Cabinets | BG27: 12 Years | BM27: Polish | BO27: Alprazolam | BP27: Bahrain
A28: Bookcases | BG28: 11 Years | BM28: Portuguese | BO28: Amantadine hydrochloride | BP28: Bangladesh
A29: Classroom Chairs | BG29: 13 Years | BM29: Romanian | BO29: Amikacin sulfate | BP29: Barbados
A30: Wall & Accent Mirrors | BG30: 14 Years | BM30: Russian | BO30: 2-Aminoanthraquinone | BP30: Belarus
A31: Office Stools | BG31: No Commercial Warranty | BM31: Slovak | BO31: p-Aminoazobenzene | BP31: Belgium
A32: Office Sets | BG32: Does Not Apply | BM32: Swedish | BO32: o-Aminoazotoluene | BP32: Belize
A33: Stackable & Nesting Chairs | BM33: Ukrainian | BO33: 4-Aminobiphenyl (4-aminodiphenyl) | BP33: Benin
A34: Futon Mattresses | BM34: Vietnamese | BO34: 1-Amino-2,4-dibromoanthraquinone | BP34: Bermuda
A35: Pot Racks | BM35: Chinese (S) | BO35: 3-Amino-9-ethylcarbazole hydrochloride | BP35: Bhutan
A36: Plant Stands & Tables | BM36: Chinese (T) | BO36: 2-Aminofluorene | BP36: Bolivia
A37: Accent Chairs | BO37: Aminoglutethimide | BP37: Bosnia and Herzegovina
A38: Kitchen Islands | BO38: Aminoglycosides | BP38: Botswana
A39: Baker's Racks | BO39: 1-Amino-2-methylanthraquinone | BP39: Bouvet Island
A40: Wine Racks | BO40: 2-Amino-5-(5-nitro-2-furyl)-1,3,4-thiadiazole | BP40: Brazil
A41: Bar Stools | BO41: 4-Amino-2-nitrophenol | BP41: British Indian Ocean Territory
A42: Mantel & Tabletop Clocks | BO42: Aminopterin | BP42: Brunei Darussalam
A43: Grandfather Clocks / Floor Clocks | BO43: Amiodarone hydrochloride | BP43: Bulgaria
A44: Conference Tables | BO44: Amitraz | BP44: Burkina Faso
A45: Folding Tables | BO45: Amitrole | BP45: Burundi
A46: Coat Racks and Hooks | BO46: Amoxapine | BP46: Cambodia
A47: Cafeteria Tables | BO47: Amsacrine | BP47: Cameroon
A48: Bars & Bar Sets | BO48: Analgesic mixtures containing Phenacetin | BP48: Cape Verde
... A254: Swing Sets & Playgrounds | BO254: Dibromoacetic acid | BP254: United States - APO/FPO/DPO
A255: Swing Set Accessories | BO255: Dibromoacetonitrile
A256: Toaster Ovens | BO256: 2,3-Dibromo-1-propanol
A257: Slides | BO257: Dichloroacetic acid
A258: Coffee Makers | BO258: p-Dichlorobenzene
A259: Indoor Gardening | BO259: 3,3'-Dichlorobenzidine
A260: Wine Refrigerators | BO260: 3,3'-Dichlorobenzidine dihydrochloride
A261: Microwaves | BO261: 1,1-Dichloro-2,2-bis(p-chloropheny)ethylene (DDE)
A262: Cabinet Organization | BO262: 1,4-Dichloro-2-butene
A263: Teeter-Totters & Seesaws | BO263: 3,3'-Dichloro-4,4'-diamino-diphenyl ether
A264: Sandboxes & Sand Toys | BO264: 1,1-Dichloroethane
A265: Commercial Playground Equipment | BO265: Dichloromethane (Methylene chloride)
A266: Indoor Chaise Lounges | BO266: Dichlorophene
... A850: Cold Plunges | BO850: Nickel hydroxide
BO851: Norethisterone (Norethindrone) /Mestranol
BO852: Anabolic steroids
BO853: Altretamine
BO854: Beryllium
BO855: Beryllium Oxide
BO856: Beryllium Sulfate
BO857: Hexachlorocyclohexane (alpha isomer)
BO858: Hexachlorocyclohexane (beta isomer)
BO859: Hexachlorocyclohexane (gamma isomer)
BO860: Cyanide salts that readily dissociate in solution (expressed as cyanide)
BO861: Hydrogen cyanide
BO862: Potassium cyanide
... BO908: Vismodegib

Sheet 6 - TV Stands & Enterta
B1: core::supplierPartNumber | C1: core::amazonStandardIdentificationNumber | D1: core::manufacturerId | E1: core::manufacturerPartNumber | F1: core::universalProductCode | G1: core::productName | H1: core::collectionName | I1: core::manufacturerProductUrl | J1: price::wholesalePrice | K1: price::minimumAdvertizedPrice | L1: price::manufacturerSuggestedRetailPrice | M1: featureDescription::romanceCopy | N1: featureDescription::genericFeatures | O1: featureDescription::genericFeatures | P1: featureDescription::genericFeatures | Q1: featureDescription::genericFeatures | R1: featureDescription::genericFeatures | S1: shippingAndFulfillment::minimumOrderQuantity | T1: shippingAndFulfillment::forceQuantityMultiplier | U1: shippingAndFulfillment::displaySetQuantity | V1: shippingAndFulfillment::productWeight | W1: shippingAndFulfillment::shipType | X1: shippingAndFulfillment::freightClass | Y1: shippingAndFulfillment::leadTime | Z1: shippingAndFulfillment::replacementLeadTime | AA1: shippingAndFulfillment::nationalMotorFreightClass | AB1: shippingAndFulfillment::flatPack | AC1: shippingAndFulfillment::shipPalletized | AD1: shippingAndFulfillment::weight | AE1: shippingAndFulfillment::height | AF1: shippingAndFulfillment::width | AG1: shippingAndFulfillment::depth | AH1: propSixtyFive::warningRequired | AI1: propSixtyFive::chemicalId | AJ1: propSixtyFive::toxicity | AK1: propSixtyFive::countryOfManufacturer | AL1: media::imageValue | AM1: media::imageValue | AN1: media::imageValue | AO1: media::imageValue | AP1: media::imageValue | AQ1: media::videoValue | AR1: media::documentValue | AS1: media::documentType | AT1: media::legalDocumentType | AU1: media::regionType | AV1: media::language | AW1: media::documentValue | AX1: media::documentType | AY1: media::legalDocumentType | AZ1: media::regionType | BA1: media::language | BB1: media::documentValue | BC1: media::documentType | BD1: media::legalDocumentType | BE1: media::regionType | BF1: media::language | BG1: 5620 | BH1: 252622 | BI1: 5635 | BJ1: 5911 | BK1: 5636 | BL1: 382543 | BM1: 5634 | BN1: 5678 | BO1: 252625 | BP1: 5621 | BQ1: 5625 | BR1: 222860 | BS1: 222861 | BT1: 5624 | BU1: 220722 | BV1: 221251 | BW1: 218007 | BX1: 5648 | BY1: 5649 | BZ1: 5643 | CA1: 5645 | CB1: 189876 | CC1: 201479 | CD1: 5663 | CE1: 242478 | CF1: 227966 | CG1: 244566 | CH1: 293480 | CI1: 293547 | CJ1: 185254 | CK1: 344955 | CL1: 346869 | CM1: 351619 | CN1: 367149 | CO1: 351641 | CP1: 352351 | CQ1: 352342 | CR1: 351649 | CS1: 5949 | CT1: 5950 | CU1: 5654 | CV1: 368645 | CW1: 370848 | CX1: 5910 | CY1: 379875 | CZ1: 292794 | DA1: 220267 | DB1: 220265 | DC1: 384286 | DD1: 393970 | DE1: 400764 | DF1: 420139 | DG1: 5920 | DH1: 5916 | DI1: 5938 | DJ1: 5671 | DK1: 201426 | DL1: 224759 | DM1: 224980 | DN1: 364708 | DO1: 236083 | DP1: 249364 | DQ1: 251110 | DR1: 310560 | DS1: 339330 | DT1: 373560 | DU1: 340810 | DV1: 341070 | DW1: 369614 | DX1: 368262 | DY1: 375302 | DZ1: 376202 | EA1: 382060 | EB1: 385921 | EC1: 415242 | ED1: 421601 | EE1: 5675 | EF1: 5676 | EG1: 252485 | EH1: 252486 | EI1: 252487 | EJ1: 5681 | EK1: 217965 | EL1: 5674 | EM1: 5682 | EN1: 222775 | EO1: 222778 | EP1: 228934 | EQ1: 333812 | ER1: 254186 | ES1: 255305 | ET1: 256090
B2: Basic Information | J2: Pricing | M2: Marketing Information | S2: Fulfillment Information | AD2: Carton Details | AH2: Compliance | AL2: Media | BG2: Attributes
B3: Required | C3: Additional | D3: Required | E3: Required | F3: Recommended | G3: Required | H3: Additional | I3: Additional | J3: Required | K3: Additional | L3: Additional | M3: Conditional | N3: Conditional | O3: Conditional | P3: Conditional | Q3: Conditional | R3: Conditional | S3: Required | T3: Required | U3: Required | V3: Required | W3: Required | X3: Conditional | Y3: Required | Z3: Required | AA3: Additional | AB3: Additional | AC3: Additional | AD3: Required | AE3: Required | AF3: Required | AG3: Required | AH3: Required | AI3: Conditional | AJ3: Conditional | AK3: Required | AL3: Required | AM3: Additional | AN3: Additional | AO3: Additional | AP3: Additional | AQ3: Additional | AR3: Conditional | AS3: Conditional | AT3: Conditional | AU3: Conditional | AV3: Conditional | AW3: Conditional | AX3: Conditional | AY3: Conditional | AZ3: Conditional | BA3: Conditional | BB3: Conditional | BC3: Conditional | BD3: Conditional | BE3: Conditional | BF3: Conditional | BG3: Required | BH3: Recommended | BI3: Required | BJ3: Required | BK3: Required | BL3: Recommended | BM3: Recommended | BN3: Recommended | BO3: Recommended | BP3: Required | BQ3: Required | BR3: Recommended | BS3: Recommended | BT3: Recommended | BU3: Recommended | BV3: Recommended | BW3: Recommended | BX3: Recommended | BY3: Recommended | BZ3: Recommended | CA3: Required | CB3: Required | CC3: Required | CD3: Recommended | CE3: Recommended | CF3: Required | CG3: Additional | CH3: Recommended | CI3: Recommended | CJ3: Recommended | CK3: Required | CL3: Required | CM3: Required | CN3: Required | CO3: Additional | CP3: Additional | CQ3: Additional | CR3: Additional | CS3: Recommended | CT3: Recommended | CU3: Required | CV3: Recommended | CW3: Recommended | CX3: Recommended | CY3: Required | CZ3: Recommended | DA3: Required | DB3: Required | DC3: Recommended | DD3: Recommended | DE3: Recommended | DF3: Required | DG3: Required | DH3: Recommended | DI3: Recommended | DJ3: Required | DK3: Required | DL3: Required | DM3: Required | DN3: Required | DO3: Required | DP3: Required | DQ3: Required | DR3: Recommended | DS3: Recommended | DT3: Recommended | DU3: Recommended | DV3: Recommended | DW3: Recommended | DX3: Required | DY3: Required | DZ3: Required | EA3: Required | EB3: Recommended | EC3: Recommended | ED3: Recommended | EE3: Required | EF3: Required | EG3: Required | EH3: Required | EI3: Required | EJ3: Recommended | EK3: Required | EL3: Required | EM3: Required | EN3: Required | EO3: Recommended | EP3: Required | EQ3: Recommended | ER3: Recommended | ES3: Recommended | ET3: Recommended
A4: Errors | B4: Supplier Part Number | C4: ASIN or Amazon Seller SKU | D4: Brand | E4: Manufacturer Part Number | F4: Universal Product Code | G4: Product Name | H4: Collection Name | I4: Manufacturer Product URL | J4: Base Cost | K4: Minimum Advertised Price | L4: Manufacturer Suggested Retail Price | M4: Marketing Copy | N4: Feature Bullet 1 | O4: Feature Bullet 2 | P4: Feature Bullet 3 | Q4: Feature Bullet 4 | R4: Feature Bullet 5 | S4: Minimum Order Quantity | T4: Force Quantity Multiplier | U4: Display Set Quantity | V4: Product Weight | W4: Ship Type | X4: Freight Class | Y4: Lead Time | Z4: Replacement Lead Time | AA4: National Motor Freight Class | AB4: Flat Pack | AC4: Ship Palletized | AD4: Carton Weight 1 | AE4: Carton Height 1 | AF4: Carton Width 1 | AG4: Carton Depth 1 | AH4: Warning Required | AI4: Chemical 1 | AJ4: Toxicity 1 | AK4: Country Of Manufacturer | AL4: Image File Name or URL 1 | AM4: Image File Name or URL 2 | AN4: Image File Name or URL 3 | AO4: Image File Name or URL 4 | AP4: Image File Name or URL 5 | AQ4: Video File Name or URL 1 | AR4: Document File Name or URL 1 | AS4: Document Type 1 | AT4: Legal Document Type 1 | AU4: Document Region 1 | AV4: Document Language 1 | AW4: Document File Name or URL 2 | AX4: Document Type 2 | AY4: Legal Document Type 2 | AZ4: Document Region 2 | BA4: Document Language 2 | BB4: Document File Name or URL 3 | BC4: Document Type 3 | BD4: Legal Document Type 3 | BE4: Document Region 3 | BF4: Document Language 3 | BG4: Product Type | BH4: Pier / Bookcase Included | BI4: Drawers Included | BJ4: Number of Drawers | BK4: Cabinets Included | BL4: Shelves Included | BM4: Exterior Shelves Included | BN4: Interior Shelves Included | BO4: Bridge Included | BP4: Furniture Design | BQ4: Material | BR4: Purposeful Distressing Type | BS4: Natural Variation Type | BT4: Gloss Finish | BU4: Mirrored | BV4: Sound Bar Shelf Included | BW4: Adjustable Shelves | BX4: Media Storage Included | BY4: Cable Management | BZ4: Wheels / Casters Included | CA4: Fireplace Included | CB4: Plug-In | CC4: Tipover Restraint Device Included | CD4: Integrated TV Mount Included | CE4: Adjustable Height | CF4: Supplier Intended and Approved Use | CG4: Country of Origin - Additional Details | CH4: Main Wood Joinery Method | CI4: Kiln-Dried Wood | CJ4: Wood Species | CK4: Battery or Batteries Included | CL4: Battery Composition | CM4: Battery Type | CN4: Number of Batteries | CO4: Battery Shipment | CP4: Lithium Content | CQ4: Watt Rating of Cells / Battery | CR4: Weight of Cells / Battery | CS4: Adjustable Temperature | CT4: Adjustable Flame | CU4: Weight Capacity | CV4: Product Care | CW4: Unfinished | CX4: Shelf Material | CY4: Color / Finish | CZ4: Drawer Glide Type & Extension | DA4: Vent Type | DB4: Fuel Type | DC4: Door Design | DD4: Ribbed Detailing | DE4: Fluted Detailing | DF4: Pieces Included | DG4: Number of Cabinets | DH4: Drawer Safety Stop | DI4: Fireplace Type | DJ4: General Certificate of Conformity (GCC) | DK4: Composite Wood Product (CWP) | DL4: CARB Phase II Compliant (formaldehyde emissions) | DM4: TSCA Title VI Compliant (formaldehyde emissions) | DN4: CANFER Compliant | DO4: Uniform Packaging and Labeling Regulations (UPLR) Compliant | DP4: Canada Product Restriction | DQ4: Reason for Restriction | DR4: UL 1678 Listed | DS4: Hazardous Material / Dangerous Goods | DT4: UN or ID number | DU4: Hazard Class(es) | DV4: Packing Group | DW4: Hazardous Material Weight | DX4: Energy Efficiency Regulations Compliant | DY4: Safety Listing(s) | DZ4: Safety Listing(s) Registration Number | EA4: CPSC - 16 CFR 1263 Compliant (Reese's Law) | EB4: ISTA Certified | EC4: Sustainability & Social Responsibility Certifications (North America Only) | ED4: Commercial Certifications | EE4: TV Stand Width - Side to Side | EF4: TV Stand Depth - Front to Back | EG4: Overall Entertainment Center Height - Top to Bottom | EH4: Overall Entertainment Center Width - Side to Side | EI4: Overall Entertainment Center Depth - Front to Back | EJ4: Overall Product Weight | EK4: Maximum TV Screen Size Accommodated | EL4: TV Stand Overall Height - Top to Bottom | EM4: Assembly Required | EN4: Level of Assembly | EO4: Additional Tools Required (Not Included) | EP4: Commercial Warranty | EQ4: Commercial Warranty Length | ER4: Product Warranty | ES4: Full or Limited Warranty | ET4: Warranty Length
A5: Displays the error status and message for the first error in the row, with a link to the corresponding cell. | B5: Must be less than 64 characters and must be a unique value (products cannot be added if they have the same part number as something you already have in your catalog). This is the supplier-specific value for the product as it appears on your Inventory Feed and Purchased Orders. | C5: The Amazon Standard Identification Number (ASIN) is a 10-character alphanumeric unique identifier assigned by Amazon.com and its partners for product identification within the Amazon organization. The Amazon Seller SKU is Amazon's identifier for your product that allows you to fulfill the product through Amazon shipping even when selling the product on other sites like Wayfair. | D5: Enter your product's brand (may be the same as the product's manufacturer). New brands must be created in the brand management tool in Partner Home before they can be selected here. | E5: Must be less than 64 characters and must be a unique value (products cannot be added if they have the same part number as something you already have in your catalog). This is the part number provided by the manufacturer. | F5: Must follow the standard UPC format and must be a unique value (products cannot be added if they have the same UPC as something you already have in your catalog). | G5: Please do not use abbreviations or exceed the 255 character limit. Wayfair may adjust the provided name based on marketing standards per class. | H5: If the product belongs to a collection of associated products that are not just product variances/options, enter the collection here. This can match with collections of products you already sell on site. For example, a collection may be a bed and nightstand that both follow a modern theme, but would not be a bed that comes in two separate colors. Products in a collection do not share the same listing on site. | I5: Enter the URL for the specific manufacturer product page of your product. | J5: Your supplier profile preference for currency is used to determine the currency of the base (wholesale) cost provided. | K5: The region selected for this sheet is used to determine the currency of the MAP provided. This may differ from the currency of your base cost. | L5: The region selected for this sheet is used to determine the currency of the MSRP provided. This may differ from the currency of your base cost. | M5: Please do not use special symbols (trademark, copyright, etc.) or extra lines/spacing. This should be a short, single paragraph product description in complete sentences highlighting details about key product information. | N5: 15 words or less, describing one aspect of the product, eg., Unique aspects, benefits, use cases, technology. These provide customers with key facts at first glance and help them to decide whether they want to make the purchase. If no marketing copy is provided, then at least 3 feature bullets must be provided. | O5: 15 words or less, describing one aspect of the product, eg., Unique aspects, benefits, use cases, technology. These provide customers with key facts at first glance and help them to decide whether they want to make the purchase. If no marketing copy is provided, then at least 3 feature bullets must be provided. | P5: 15 words or less, describing one aspect of the product, eg., Unique aspects, benefits, use cases, technology. These provide customers with key facts at first glance and help them to decide whether they want to make the purchase. If no marketing copy is provided, then at least 3 feature bullets must be provided. | Q5: 15 words or less, describing one aspect of the product, eg., Unique aspects, benefits, use cases, technology. These provide customers with key facts at first glance and help them to decide whether they want to make the purchase. If no marketing copy is provided, then at least 3 feature bullets must be provided. | R5: 15 words or less, describing one aspect of the product, eg., Unique aspects, benefits, use cases, technology. These provide customers with key facts at first glance and help them to decide whether they want to make the purchase. If no marketing copy is provided, then at least 3 feature bullets must be provided. | S5: The minimum count of items a customer must choose to purchase the product. | T5: This represents how many items the customer must buy in increments of, or in addition to. For example, a multiplier of 2 would mean a custom must buy 1 quantity, 3 quantity, 5 quantity, or some other multiple of 2. | U5: Number of items represented by the part number and wholesale price. For example, if you want to sell a bundle of pillows, and the part number and wholesale cost you provided represents that full bundle of pillows, then you would answer the Display Set Quantity question with how many pillows are in the bundle. | V5: [Pounds] What is the total weight of this product once assembled? Please enter just the number (i.e. 45.5) without a unit of measurement. | W5: Enter small parcel or LTL to indicate how the product can ship based on size and weight. | X5: Each product falls into 1 of 18 classes determined by a product's 'transportability' and are crucial for calculating shipping cost. The field is required when ship type is LTL. | Y5: [Hours] This is the length of time from receipt of PO to shipment from the warehouse. | Z5: [Hours] This is length of time from receipt of a replacement PO to shipment from the warehouse | AA5: 5 to 7 digit number in length (depending on any sub classification) that will identify what is shipping in the box | AB5: Also known as 'knocked down'. Select 'Yes' if this product ships disassembled in a flat pack box. | AC5: Select 'Yes' if this product ships on a pallet. | AD5: [Pounds] Enter in the shipping weight (i.e. 45.5) of the packaging used for the product. If the product ships in more than one box, this measurement is per box. | AE5: [Inches] Enter in the shipping height (i.e. 45.5) of the packaging used for the product. If the product ships in more than one box, this measurement is per box. | AF5: [Inches] Enter in the shipping width (i.e. 45.5) of the packaging used for the product. If the product ships in more than one box, this measurement is per box. | AG5: [Inches] Enter in the shipping depth (i.e. 45.5) of the packaging used for the product. If the product ships in more than one box, this measurement is per box. | AH5: If the product requires a warning for Proposition 65 compliance in California, answer 'Yes' and indicate which chemicals and toxicities are applicable. | AI5: Select the chemical that requires the Prop65 warning. | AJ5: Select the toxicity that can result from the selected chemical. | AK5: Provide only a single country of manufacture for each product. | AL5: Your first image will be set as the lead image for this listing, however, is subject to change upon Wayfair review. For each image uploaded, provide the file name with extension (e.g. PART_1.jpeg) or a direct public URL which leads to a single image (tip: to isolate the image, right click + select Open Image in New Tab). Elements like logos, buttons, etc will interfere with our ability to download the image. Do not exceed 20 images per product. | AM5: Your first image will be set as the lead image for this listing, however, is subject to change upon Wayfair review. For each image uploaded, provide the file name with extension (e.g. PART_1.jpeg) or a direct public URL which leads to a single image (tip: to isolate the image, right click + select Open Image in New Tab). Elements like logos, buttons, etc will interfere with our ability to download the image. Do not exceed 20 images per product. | AN5: Your first image will be set as the lead image for this listing, however, is subject to change upon Wayfair review. For each image uploaded, provide the file name with extension (e.g. PART_1.jpeg) or a direct public URL which leads to a single image (tip: to isolate the image, right click + select Open Image in New Tab). Elements like logos, buttons, etc will interfere with our ability to download the image. Do not exceed 20 images per product. | AO5: Your first image will be set as the lead image for this listing, however, is subject to change upon Wayfair review. For each image uploaded, provide the file name with extension (e.g. PART_1.jpeg) or a direct public URL which leads to a single image (tip: to isolate the image, right click + select Open Image in New Tab). Elements like logos, buttons, etc will interfere with our ability to download the image. Do not exceed 20 images per product. | AP5: Your first image will be set as the lead image for this listing, however, is subject to change upon Wayfair review. For each image uploaded, provide the file name with extension (e.g. PART_1.jpeg) or a direct public URL which leads to a single image (tip: to isolate the image, right click + select Open Image in New Tab). Elements like logos, buttons, etc will interfere with our ability to download the image. Do not exceed 20 images per product. | AQ5: Provide the video’s file name with extension for separate uploads or a direct public URL. Do not exceed 10 videos per product. | AR5: Provide the document’s file name with extension for separate uploads or a direct public URL. Do not exceed 10 documents per product. | AS5: Select one or more values from the provided list that best describe the document’s purpose. This classification helps customers easily find information like “Installation & Assembly” guides, “Warranty Information,” or “Specifications. | AT5: If the document serves as a legal notice or certification (e.g., “ASTM F2057 - 19,” “ANSI A117.1 Compliant”), select the specific type(s) from the provided list. This is used for compliance and to display certifications to customers. | AU5: Select the country or region where this document is legally applicable. This is crucial for compliance-related documents that may differ across locations. | AV5: Select the language in which the document is written. | AW5: Provide the document’s file name with extension for separate uploads or a direct public URL. Do not exceed 10 documents per product. | AX5: Select one or more values from the provided list that best describe the document’s purpose. This classification helps customers easily find information like “Installation & Assembly” guides, “Warranty Information,” or “Specifications. | AY5: If the document serves as a legal notice or certification (e.g., “ASTM F2057 - 19,” “ANSI A117.1 Compliant”), select the specific type(s) from the provided list. This is used for compliance and to display certifications to customers. | AZ5: Select the country or region where this document is legally applicable. This is crucial for compliance-related documents that may differ across locations. | BA5: Select the language in which the document is written. | BB5: Provide the document’s file name with extension for separate uploads or a direct public URL. Do not exceed 10 documents per product. | BC5: Select one or more values from the provided list that best describe the document’s purpose. This classification helps customers easily find information like “Installation & Assembly” guides, “Warranty Information,” or “Specifications. | BD5: If the document serves as a legal notice or certification (e.g., “ASTM F2057 - 19,” “ANSI A117.1 Compliant”), select the specific type(s) from the provided list. This is used for compliance and to display certifications to customers. | BE5: Select the country or region where this document is legally applicable. This is crucial for compliance-related documents that may differ across locations. | BF5: Select the language in which the document is written. | BG5: What type of product is this? | BH5: Does this product have a pier / bookcase included? | BI5: Does this product have any drawers? | BJ5: How many drawers are included in this product? | BK5: Does this product include cabinets? | BL5: Does this product include shelves? | BM5: Does this product have an open space with either another shelf above it or the top surface of the product above it? We do not define the top surface of the Accent Chest/Cabinet as an exterior shelf. | BN5: Does this product have interior shelves included? | BO5: Does this product have a bridge included? | BP5: What is the design of the piece of furniture? | BQ5: What material is the product made of? | BR5: What specific type of distressing does this product have? Select all that apply. | BS5: Which of the following types of natural variation and texture does the product have? Multiple can be selected if applicable. If the product does NOT have natural variation, please select No Natural Variation. | BT5: Does this product have a shiny and sheer gloss finish over the normal painted finish? | BU5: Is the surface of the product mirrored? Please do not select “yes” if the product only features a mirror. This question refers to the surface material of the product, and if it is reflective. | BV5: Does this product have a sound bar shelf included? | BW5: Does this product have adjustable shelves? | BX5: Does this product have media storage included? | BY5: Does this product have any built-in cable or wire management, such as a hole specifically for wires (a grommet) or a tray where wires can be stored? | BZ5: Does this product have wheels or casters? | CA5: Does this product have a fireplace included? | CB5: If this product requires electricity can it be plugged into a household outlet via an integral corded plug or an AC adapter? If this product does not require electricity or if this product requires electricity but does not/cannot use household AC voltages (with or without an AC adapter) please select "No". | CC5: Does this product include a device to prevent the product from tipping over? Tipover restraint devices (TRDs) include brackets, straps, or other specialized hardware | CD5: Does this product have an integrated tv mount included? | CE5: Is the height of this product adjustable? | CF5: What type of environmental setting was this product designed and manufactured to be used in? Note: your answer indicates that Wayfair is able to market this product as being intended for use in the selected setting(s). Please select both, if both options apply. | CG5: Does this product and/or packaging have additional advertising or labeling details regarding claims about the product’s origin? Please use this field to provide a qualified or unqualified claim regarding the product origin in accordance with US Federal Trade Commission (FTC) and Canada Competition Bureau regulations. Additionally, if applicable, please use this field to communicate any appropriate qualified, comparative, or descriptive claims regarding the origin of the product. Examples include, but are not limited to, communicating relevant percentage of domestic and non-domestic content (ex: 60% U.S. Content), communicating the origin of certain components of the product (ex: "Hand carved in U.S. — Wood from Philippines"), or communicating where the product was assembled (Ex : “Assembled In Mexico”). See https://www.ftc.gov/tips-advice/business-center/guidance/complying-made-usa-standard#qualified and https://www.competitionbureau.gc.ca/eic/site/cb-bc.nsf/eng/03169.html | CH5: Which technique was used to join together the main pieces of wood to construct the overall product? | CI5: Is the wood kiln-dried? If product is not made of wood, please select "does not apply." | CJ5: What type of wood was used to construct this product? This describes the actual materials used, not the product's appearance. | CK5: Is the product a battery or does the product include batteries? | CL5: What is the composition of the batteries included with product? | CM5: What type is the battery? Button Cell, Cell, Battery? | CN5: Confirm number of batteries in this product | CO5: Do the cells/batteries ship stand alone/packed with the equipment/ contained (installed) in the equipment? | CP5: What is the aggregate lithium content of the cell/battery? Aggregate lithium content means the sum of the grams of lithium content contained by the cells comprising a battery. Please note, this is the weight weight of the lithium in the cell or battery, and not the weight of the entire cell or battery. | CQ5: What is the Watt-hour(Wh) rating of the cell/battery? The Watt-hour rating of a lithium cell or battery is calculated by multiplying the rated capacity in ampere-hours by the nominal voltage. If only the milliampere-hours (mAh) are marked on the battery then divide that number by 1000 to get ampere-hours (Ah) (i.e. 4400 mAh / 1000 = 4.4. Ah). | CR5: What is the net weight of the cells or batteries that ship with the product in grams or kilograms. | CS5: Can the amount of heat be adjusted? | CT5: Can the brightness, size, or color of the flame be adjusted? | CU5: [Pounds] What is the maximum weight capacity of the product? Please enter just the number (i.e., 45.5). | CV5: What is the appropriate way to clean and/or care for this product? Please select as many answers as applicable. | CW5: Is this product unfinished (no paint, stain, or varnish)? | CX5: What material are the shelves made of? | CY5: What is the color or finish of the product? If your color/finish name is not listed, please type in the value. | CZ5: Please select which type of glide the drawer features and/or how far it can extend. | DA5: What type of vent does this product have? | DB5: What is the source of fuel needed in order for this product to function? | DC5: Please select the design of the product. | DD5: Is there a a raised pattern of parallel lines on a surface of this product? | DE5: Is there a a concave pattern of parallel lines on a surface of this product? | DF5: What pieces are included with this product? | DG5: How many cabinets does this product have? | DH5: Do any drawers feature safety stops (intended to keep the drawers from pulling all the way out)? | DI5: What type of Fireplace is included? | DJ5: Does this product have a General Certificate of Conformity (GCC), as required by the U.S. CPSC for certain product classes? | DK5: FOR COMPLIANCE PURPOSES. Not customer facing information. Does this product include any pieces made of manufactured or composite wood products (CWP) This includes any of the following 1) HWPW-CC [Hardwood Plywood with Composite Core] 2) HWPW-VC [Hardwood Plywood with Veneer Core] 3) PB [Particleboard] 4) MDF or thin-MDF [Medium Density Fiberboard] | DL5: Is this product certified compliant for CARB ATCM Phase II formaldehyde emission standards from Composite Wood Products [California Air Resources Board (CARB)- Airborne Toxic Control Measures (ATCM) Phase II] | DM5: Is this product certified TSCA Title VI compliant regarding formaldehyde emissions from Composite Wood Products [Environmental Protection Agency (EPA)-Toxic Substance Control Act (TSCA)-Title VI] | DN5: Is this product CANFER compliant regarding formaldehyde emissions from composite wood products? [Canada Formaldehyde Emissions Regulation] NOTE: Please provide proof of certification to applicable formaldehyde emissions standards and a Declaration of Certification. More information on the Declaration of Certification and on other requirements for CANFER compliance can be found in Health Canada's Guidance Document (https://bit.ly/3FvYK2B) or by contacting any of our Product Compliance Resources (https://bit.ly/3h8EIlw). | DO5: Does your product comply with the Uniform Packaging and Labeling Regulations, which requires product packaging to be accurate and provide adequate information as to the identity and quantity of its contents, as well as the name and address of the manufacturer and/or distributor? | DP5: Is this product legally or operationally restricted from being offered for sale to Canadian customers on Wayfair.ca or delivered to Canadian addresses? Select “Yes” only if the product cannot legally be sold or shipped to Canada. For example, if it requires a license or certification you do not hold, or if you operate through a separate Canadian entity that cannot support the listing. | DQ5: Please select the reason this product can not ship to Canada? Please select from the options or write in a reason if not selectable | DR5: Is this product UL 1678 Listed? This means that the international standards testing company UL (Underwriters' Laboratories) has tested this product and found it to be in compliance with Category 1678 safety standards. | DS5: Is the product regulated as Hazardous Material / Dangerous Goods? Hazardous Materials/Dangerous Goods are substances that when transported pose a risk to health, safety, property or the environment. These materials may include explosives, compressed gases (aerosols), flammable liquids, oxidizers, toxic/poisonous, radioactive, corrosive, batteries, etc. An SDS is is a document that lists information relating to occupational safety and health for the use of various substances and products. The SDS includes information such as the properties of each chemical; the physical, health, and environmental health hazards; protective measures; and safety precautions for handling, storing, and transporting the chemical or product. | DT5: Please provide the UN or ID number. The UN or ID number is a 4 digit numeric code that identifies hazardous materials/dangerous goods, and articles in the framework of international and domestic transport. This can be found in section 14 of the Safety Data Sheet (SDS). Example - "UN3480" - Lithium Ion Batteries. If your UN number is not one of the options in the dropdown, please write this in manually. | DU5: Please provide the Hazard Class(es). This is the category of hazard assigned to a hazardous material/dangerous goods under the definitional criteria of the transportation regulations. A material may meet the defining criteria for more than one hazard class but is assigned to only one hazard class. Hazard classes vary from 1-9.This can be found in section 14 of the Safety Data Sheet (SDS). | DV5: Please provide the packing group (if applicable). Packing Groups I, II and III indicate the degree of danger presented by the material is great, medium or minor, respectively. Some hazardous materials/dangerous goods do not have a packing group assigned. This can be found in section 14 of the Safety Data Sheet (SDS). | DW5: Please provide the net weight or, for liquids, the net volume of hazardous material per unit of product. Provide the net weight of the hazardous materials/dangerous goods in your product in grams or kilograms. For example -if your product is a vacuum containing a lithium ion battery, you would enter the net weight of the battery. | DX5: Is this product compliant with U.S. Energy Efficiency requirements, including those set forth in the Energy Policy and Conservation Act of 1975 (ECPA), the National Appliance Energy Conservation Act (NAECA), the Energy Policy Act of 1992 and 2005, and the Energy Independence and Security Act of 2007, as applicable? | DY5: Which of the following certification or verification marks does your product have? If the item is not certified/verified with any safety listing, please select Does Not Apply. | DZ5: In a comma separated list, please outline the registration numbers associated to the safety listings you claimed this product has, in the following structure: Safety Listing - Registration Number. Example: UL Listed - ABC1234567, TÜV Rheinland Certified - DEFGH8910. This number may be referred to as a "Certification Number", "File Number", "Model Number", "Listing Number" or "Certification ID Number" depending on where the certification is from | EA5: Is this product compliant with 16 CFR 1263, the safety standard for button cell or coin batteries adopted per the requirements under Reese's Law? Testing to ANSI/UL 4200A-2023 demonstrates compliance. Please Note: A "No" answer to this question will result in your product being restricted from sale. | EB5: Is the packaging for this SKU ISTA Certified (1A, 3A, 6A)? | EC5: Do you have any certifications or credentials related to environmental sustainability, social responsibility, or ethical sourcing (e.g.,OEKO-TEX®, GREENGUARD, GoodWeave, Fair Trade, FSC, etc.)? To see examples of certificates currently part of our Shop Sustainably program, please visit: https://www.aboutwayfair.com/shop-sustainably. Please upload all related certificates so your products can be merchandised as part of the Shop Sustainably program. | ED5: For BIFMA Accredited products, suppliers must upload an ANSI/BIFMA durability-related testing document for the product from an ISO 17025 accredited lab. For BIFMA Equivalent products, suppliers must upload an ANSI/BIFMA durability-related testing document for the product, but the lab is not required to be ISO 17025 accredited. For Contract Grade Accredited products, suppliers must upload a testing document that aligns with Wayfair’s contract grade standards, along with a signed consent letter. Reference the Contract Grade help center article or reach out to your relationship manager for more information. | EE5: [Inches] What is the overall width of the TV Stand (side to side)? Please enter just the number (i.e. 45.5). Please DO NOT duplicate this tag - any additional information can be stored in Shelf Dimensions, Cabinet Dimensions, or as a bullet. | EF5: [Inches] What is the overall depth of the TV Stand (front to back)? Please enter just the number (i.e. 45.5). | EG5: [Inches] What is the overall height of the Entertainment Center (top to bottom)? Enter just the value (i.e., 45.5). | EH5: [Inches] What is the overall width of the Entertainment Center (side to side)? Please enter just the number (i.e. 45.5). Please DO NOT duplicate this tag - any additional information can be stored in Shelf Dimensions, Cabinet Dimensions, or as a bullet. | EI5: [Inches] What is the overall depth of the Entertainment Center (front to back)? Enter just the value (i.e., 45.5). | EJ5: [Pounds] What is the total weight of this product once assembled? If this product includes multiples of the same item, add weight of one individual unit (e.g. 1 Dining Chair in a set of 2). Please enter just the number (i.e. 45.5). | EK5: What is the largest size of TV this stand can hold, in inches? The TV size is the diagonal measurement (the distance between opposite corners) of the screen in inches. Please use the following calculation, based on a standard 16:9 HDTV aspect ratio: for TV Stands, calculate TV Stand Overall Width * 1.15, and for Entertainment Centers calculate TV Opening Width * 1.15. Both calculations should be rounded down to the closest standard TV size. | EL5: [Inches] What is the overall height of the TV stand (top to bottom)? Enter just the value (i.e., 45.5). | EM5: Does the product require any form of assembly prior to use as intended? | EN5: What is the level of assembly required? | EO5: What additional tools will the customer need to set-up this product that are NOT included with purchase? | EP5: Does the manufacturer warranty cover the use of this product in a commercial environment? | EQ5: How long does the manufacturer warranty apply for the product used in a commercial (non-residential) environment? If the correct value is not found, please select the closest available answer that is shorter than the warranty length. If warranty length varies by part, please select the answer that matches the part of the product with the shortest warranty. Please use the “Warranty Details” tag for any additional details. | ER5: Please indicate if there is a warranty on this product if it were to be used in a residential setting. | ES5: Please indicate if the warranty is Full or Limited. | ET5: Please indicate the length of the warranty offered from our list if this product were to be used in a residential setting. If the correct value is not found, please indicate both the number and unit (Days, Months, Years) that is appropriate.
A6: Read-Only | B6: Text | C6: Text | D6: Select | E6: Text | F6: Text | G6: Text | H6: Text | I6: Text | J6: Number | K6: Number | L6: Number | M6: Text | N6: Text | O6: Text | P6: Text | Q6: Text | R6: Text | S6: Whole Number | T6: Whole Number | U6: Whole Number | V6: Number | W6: Select | X6: Select | Y6: Select | Z6: Select | AA6: Text | AB6: Yes or No | AC6: Yes or No | AD6: Number | AE6: Number | AF6: Number | AG6: Number | AH6: Yes or No | AI6: Select | AJ6: Please choose one or more from the following, using a semicolon (;) to separate each value: Cancer; Developmental | AK6: Select | AL6: Text | AM6: Text | AN6: Text | AO6: Text | AP6: Text | AQ6: Text | AR6: Text | AS6: Please choose one or more from the following, using a semicolon (;) to separate each value: Specifications; Installation & Assembly; Owner Manual; Delivery Information; Warranty Information; Certifications; Disclaimers; Buying Guides; Promotions; Dimensions; Marketing Materials; Energy Guide; Other; Product Information Sheet; Digital Law Label | AT6: Please choose one or more from the following, using a semicolon (;) to separate each value: AAFA Certified; AATCC 116 Grade; AATCC 16.1-2014 Grade; AATCC 16.3-2014 Grade; AATCC 8 Grade; AC Rated; ACT Flammability Guidelines Compliant; AHAM CADR Dust rating; AHAM CADR Pollen rating; AHAM CADR Smoke rating; AHMA Certified; AHMA Compliant; AHRI Certified; ANSI A117.1 Compliant; ANSI A137.1 Compliant; ANSI IT9.2 Compliant; ANSI Z1.5A/CGA 9.1M Certified; ANSI Z124.1.2 Compliant; ANSI Z124.3 Compliant; ANSI Z124.6-97 Compliant; ANSI Z21.11.2-2016 - Gas-Fired Unvented Room Heaters and Gas-Fired Unvented Decorative Room Heaters; ANSI Z21.50-2016/CSA 2.22-2016 - Standard for Vented Decorative Gas Appliances; ANSI Z21.60-2017/CSA 2.26-2017- Standard for Decorative Gas Appliances; ANSI Z21.84-2017 - Standard for Manually Lighted/ Natural Gas/ Decorative Gas Appliances; ANSI Z21.88-2017/CSA 2.33-2017- Standard for Vented Gas Fireplace Heaters; ANSI Z358 Compliant; ANSI/BHMA A156 Certified; ANSI/BIFMA M7.1 Standard Test Method for Determining VOC Emissions; ANSI/BIFMA X5.1 Office Seating; ANSI/BIFMA X5.11 Large Occupant Office Seating; ANSI/BIFMA X5.3 Vertical Files; ANSI/BIFMA X5.4 Lounge & Public Seating; ANSI/BIFMA X5.5 Desk Products; ANSI/BIFMA X5.6 Panel Systems; ANSI/BIFMA X5.9 Storage; ANSI/BIFMA X6.1 Educational Seating; ANSI/BIFMA X7.1 Standard for Formaldehyde & TVOC Emissions; ANSI/ESD S20.20 Certified; ANSI/NISO Z39.48 Compliant; ANSI/SOHO S6.5 Small Office/Home Office; APMA Certified; ASHRAE 62.2 Standard Compliant; ASME A112.18.1 Compliant; ASME A112.18.2 Compliant; ASME A112.19.1 Compliant; ASME A112.19.2 Compliant; ASME A112.19.3 Compliant; ASP:02:01 Certification; ASSE 1001 Certified; ASSE 1006 Certified; ASSE 1016 Certified; ASTM 1821-19; ASTM E1590-07 Compliant; ASTM F1004-19 Certified; ASTM F1148-17 Compliant; ASTM F1148-18 Compliant; ASTM F1148-18 Certified; ASTM F1169 - 13 Compliant; ASTM F1487-17 Compliant; ASTM F1821 - 16 Compliant; ASTM F1912-17 Compliant; ASTM F1917 - 12 Compliant; ASTM F2057 - 14; ASTM F2057 - 17; ASTM F2057 - 19 | AU6: Select | AV6: Select | AW6: Text | AX6: Please choose one or more from the following, using a semicolon (;) to separate each value: Specifications; Installation & Assembly; Owner Manual; Delivery Information; Warranty Information; Certifications; Disclaimers; Buying Guides; Promotions; Dimensions; Marketing Materials; Energy Guide; Other; Product Information Sheet; Digital Law Label | AY6: Please choose one or more from the following, using a semicolon (;) to separate each value: AAFA Certified; AATCC 116 Grade; AATCC 16.1-2014 Grade; AATCC 16.3-2014 Grade; AATCC 8 Grade; AC Rated; ACT Flammability Guidelines Compliant; AHAM CADR Dust rating; AHAM CADR Pollen rating; AHAM CADR Smoke rating; AHMA Certified; AHMA Compliant; AHRI Certified; ANSI A117.1 Compliant; ANSI A137.1 Compliant; ANSI IT9.2 Compliant; ANSI Z1.5A/CGA 9.1M Certified; ANSI Z124.1.2 Compliant; ANSI Z124.3 Compliant; ANSI Z124.6-97 Compliant; ANSI Z21.11.2-2016 - Gas-Fired Unvented Room Heaters and Gas-Fired Unvented Decorative Room Heaters; ANSI Z21.50-2016/CSA 2.22-2016 - Standard for Vented Decorative Gas Appliances; ANSI Z21.60-2017/CSA 2.26-2017- Standard for Decorative Gas Appliances; ANSI Z21.84-2017 - Standard for Manually Lighted/ Natural Gas/ Decorative Gas Appliances; ANSI Z21.88-2017/CSA 2.33-2017- Standard for Vented Gas Fireplace Heaters; ANSI Z358 Compliant; ANSI/BHMA A156 Certified; ANSI/BIFMA M7.1 Standard Test Method for Determining VOC Emissions; ANSI/BIFMA X5.1 Office Seating; ANSI/BIFMA X5.11 Large Occupant Office Seating; ANSI/BIFMA X5.3 Vertical Files; ANSI/BIFMA X5.4 Lounge & Public Seating; ANSI/BIFMA X5.5 Desk Products; ANSI/BIFMA X5.6 Panel Systems; ANSI/BIFMA X5.9 Storage; ANSI/BIFMA X6.1 Educational Seating; ANSI/BIFMA X7.1 Standard for Formaldehyde & TVOC Emissions; ANSI/ESD S20.20 Certified; ANSI/NISO Z39.48 Compliant; ANSI/SOHO S6.5 Small Office/Home Office; APMA Certified; ASHRAE 62.2 Standard Compliant; ASME A112.18.1 Compliant; ASME A112.18.2 Compliant; ASME A112.19.1 Compliant; ASME A112.19.2 Compliant; ASME A112.19.3 Compliant; ASP:02:01 Certification; ASSE 1001 Certified; ASSE 1006 Certified; ASSE 1016 Certified; ASTM 1821-19; ASTM E1590-07 Compliant; ASTM F1004-19 Certified; ASTM F1148-17 Compliant; ASTM F1148-18 Compliant; ASTM F1148-18 Certified; ASTM F1169 - 13 Compliant; ASTM F1487-17 Compliant; ASTM F1821 - 16 Compliant; ASTM F1912-17 Compliant; ASTM F1917 - 12 Compliant; ASTM F2057 - 14; ASTM F2057 - 17; ASTM F2057 - 19 | AZ6: Select | BA6: Select | BB6: Text | BC6: Please choose one or more from the following, using a semicolon (;) to separate each value: Specifications; Installation & Assembly; Owner Manual; Delivery Information; Warranty Information; Certifications; Disclaimers; Buying Guides; Promotions; Dimensions; Marketing Materials; Energy Guide; Other; Product Information Sheet; Digital Law Label | BD6: Please choose one or more from the following, using a semicolon (;) to separate each value: AAFA Certified; AATCC 116 Grade; AATCC 16.1-2014 Grade; AATCC 16.3-2014 Grade; AATCC 8 Grade; AC Rated; ACT Flammability Guidelines Compliant; AHAM CADR Dust rating; AHAM CADR Pollen rating; AHAM CADR Smoke rating; AHMA Certified; AHMA Compliant; AHRI Certified; ANSI A117.1 Compliant; ANSI A137.1 Compliant; ANSI IT9.2 Compliant; ANSI Z1.5A/CGA 9.1M Certified; ANSI Z124.1.2 Compliant; ANSI Z124.3 Compliant; ANSI Z124.6-97 Compliant; ANSI Z21.11.2-2016 - Gas-Fired Unvented Room Heaters and Gas-Fired Unvented Decorative Room Heaters; ANSI Z21.50-2016/CSA 2.22-2016 - Standard for Vented Decorative Gas Appliances; ANSI Z21.60-2017/CSA 2.26-2017- Standard for Decorative Gas Appliances; ANSI Z21.84-2017 - Standard for Manually Lighted/ Natural Gas/ Decorative Gas Appliances; ANSI Z21.88-2017/CSA 2.33-2017- Standard for Vented Gas Fireplace Heaters; ANSI Z358 Compliant; ANSI/BHMA A156 Certified; ANSI/BIFMA M7.1 Standard Test Method for Determining VOC Emissions; ANSI/BIFMA X5.1 Office Seating; ANSI/BIFMA X5.11 Large Occupant Office Seating; ANSI/BIFMA X5.3 Vertical Files; ANSI/BIFMA X5.4 Lounge & Public Seating; ANSI/BIFMA X5.5 Desk Products; ANSI/BIFMA X5.6 Panel Systems; ANSI/BIFMA X5.9 Storage; ANSI/BIFMA X6.1 Educational Seating; ANSI/BIFMA X7.1 Standard for Formaldehyde & TVOC Emissions; ANSI/ESD S20.20 Certified; ANSI/NISO Z39.48 Compliant; ANSI/SOHO S6.5 Small Office/Home Office; APMA Certified; ASHRAE 62.2 Standard Compliant; ASME A112.18.1 Compliant; ASME A112.18.2 Compliant; ASME A112.19.1 Compliant; ASME A112.19.2 Compliant; ASME A112.19.3 Compliant; ASP:02:01 Certification; ASSE 1001 Certified; ASSE 1006 Certified; ASSE 1016 Certified; ASTM 1821-19; ASTM E1590-07 Compliant; ASTM F1004-19 Certified; ASTM F1148-17 Compliant; ASTM F1148-18 Compliant; ASTM F1148-18 Certified; ASTM F1169 - 13 Compliant; ASTM F1487-17 Compliant; ASTM F1821 - 16 Compliant; ASTM F1912-17 Compliant; ASTM F1917 - 12 Compliant; ASTM F2057 - 14; ASTM F2057 - 17; ASTM F2057 - 19 | BE6: Select | BF6: Select | BG6: Select | BH6: Yes or No | BI6: Yes or No | BJ6: Whole Number | BK6: Yes or No | BL6: Yes or No | BM6: Yes or No | BN6: Yes or No | BO6: Yes or No | BP6: Please choose one or more from the following, using a semicolon (;) to separate each value: Cabinet/Enclosed storage; TV Stand Fireplace; Open shelving; Corner unit; Hutch; Piers; Floating mount; Standard; Demilune; Nesting; Apothecary; Multi-tiered; Floor; Corner; Basket Storage; Tabletop; Hanging; Bombe; Etagere; Wall Mounted; Double Walled; Console; Pedestal; Unavailable; Does Not Apply | BQ6: Please choose one or more from the following, using a semicolon (;) to separate each value: Glass; Stainless Steel; Cane; Raffia; Mango Wood; Aluminum; Manufactured Wood; Leather; Bamboo; Ceramic; Faux Leather; Iron; Marble / Granite; Metal; Plastic / Acrylic; Teak; Solid + Manufactured Wood; Steel; Solid Wood; Wicker; Reclaimed Wood | BR6: Please choose one or more from the following, using a semicolon (;) to separate each value: Distressed Leather; Paint Distressing; Distressed Grain Accents; Coat/Paint Distressing; Wormholes; No Natural Variation; No Distressing; Distressed Metal; Worn/Fade; Wood Scoring & Rub Through; Unavailable | BS6: Please choose one or more from the following, using a semicolon (;) to separate each value: No Natural Variation; Natural Wood Grain Color Variation; Weathered Steel; Wood Knots; Natural Stone Color Variation; Unavailable | BT6: Yes or No | BU6: Yes or No | BV6: Yes or No | BW6: Yes or No | BX6: Yes or No | BY6: Yes or No | BZ6: Yes or No | CA6: Yes or No | CB6: Yes or No | CC6: Select | CD6: Yes or No | CE6: Yes or No | CF6: Please choose one or more from the following, using a semicolon (;) to separate each value: Non Residential Use; Residential Use | CG6: Please choose one or more from the following, using a semicolon (;) to separate each value: Made in USA; Made in USA of Imported Materials; Product of Canada; Made In Canada; Does Not Apply | CH6: Select | CI6: Yes or No | CJ6: Please choose one or more from the following, using a semicolon (;) to separate each value: Acacia; Alder; Ash; Bamboo; Beech; Birch; Camphor; Cedar; Cherry; Elm; Eucalyptus; Fir; Hickory; Mahogany; Mango; Maple; Oak; Pine; Poplar; Rosewood; Rubberwood; Sheesham; Spruce; Teak; Walnut; Wenge; Pecan; Shorea; Paulownia; Chestnut; Hemlock; Aspen; Mindi; Ipe; Olive; Ajo; Agarwood; Afzelia; Afrormosia; Bubinga; Brazilwood; Cumaru; Cedar, Mulanje; Cedar, Spanish; Aloewood; Lignum vitae; Mahogany, African; Mahogany, Mexican; Padauk, African; Macacauba; Ebony, Madagascar; Lignum vitae, Argentine; Gavilan; Mahogany, Honduran; Mahogany, Cuban; Stinkwood, red; Yew, Chinese; Pau rosa, Brazilian; Sandalwood, East African; Ramin; Zitan; Yew, Himalayan; Yew, Japanese; Rosewood, Siamese; Yew, Taiwan; Burlwood; Platane Wood; Sungkai; Does Not Apply | CK6: Yes or No | CL6: Select | CM6: Select | CN6: Select | CO6: Select | CP6: Select | CQ6: Select | CR6: Select | CS6: Yes or No | CT6: Yes or No | CU6: Number | CV6: Please choose one or more from the following, using a semicolon (;) to separate each value: Hand wash recommended; Dishwasher safe; Spot clean only; Hand wash only; Delicate cycle; Commercial laundry safe; Do not use a fabric softener; Cold wash; Sweep / Dust Mop; Cut loose threads using a scissor; Clean with soap and water; Clean spills immediately; Dishwasher safe component; Lay flat to dry; Dryer safe; Warm wash; Non-Abrasive, Neutral Ph Cleaner; Commercial dishwasher safe; Vacuum with no beater bar/rotating brush; Air / Line Dry; Professional / Dry Clean Recommended; Wash With Garden Hose Or Pressure Washer; Machine washable components; Professional / Dry Clean Only; Vacuum with upholstery attachment; Vacuum with beater bar/rotating brush; Clean with bleach and water; Use product specific cleaner; Oil / seal / treat regularly; Shake to remove dust; Tumble dry; Iron safe; Wipe clean with a dry cloth; Cover when not in use; Avoid use of abrasive cleaners; Tile specific cleaner; Do not wash; Dust mop; Hose down; Towel dry immediately; Household floor cleaner; Spot clean; Wipe with wet cloth; Spot clean with water; When cushions are wet, open cushion zippers and prop up to dry in order to maintain quality; Oil 1-2 times per year; No washing / drying care; Do not bleach; Treat with wood protector; Do not dry clean; Clean with diluted vinegar and water; Store indoors or cover when not in use; Use carpet cleaner; Air dry cushions covers; Do not use bleach or bleach solutions; Rinse with water only; Dishwasher safe removable parts; Clean and re-seal with natural stone sealant; To prevent oil stains wipe with a damp cloth before using; After cleaning, use sealant; Apply oil to maintain color and prolong durability; Vacuum; Avoid direct sunlight; Dry after use; Use furniture pads; Apply epoxy clear coat once per year; Clean with cloth, mild soap, and warm water; Spot clean with mild detergent; Spot clean as needed; Automatic; Hot water extraction; Spot clean with dry cloth; Clean the product at least one time per month. We suggest the use of Rejuven | CW6: Yes or No | CX6: Please choose one or more from the following, using a semicolon (;) to separate each value: Polyethylene; Steel; Wood Veneers; Polyvinyl Chloride (PVC); Polycarbonate; Stainless Steel; Marble; Solid + Manufactured Wood; Wood; Clear Glass; Stone; Glass; Melamine; Aluminum; Acrylic; Resin; Tinted Glass; Laminate; Metal; Wire; Mirrored; Plastic; Manufactured Wood; Glass / Polycarbonate; Wicker; Iron; Solid Wood; Granite; Unavailable; Does Not Apply | CY6: Please choose one or more from the following, using a semicolon (;) to separate each value: Clear; Cream; Purple; Gold; Silver; Polished Chrome; Polished Nickel; Stainless Steel; Bronze; Chrome; Oil Rubbed Bronze; Matte Black; Satin Nickel; Brushed Nickel; Antique Brass; Antique Bronze; Copper; Antique Copper; Brushed Brass; Polished Brass; Brass; Satin Brass; Brushed Gold; Nickel; Ivory; Green; Orange; Beige; Teal; Red; Satin; Yellow; Pink; White; Brown; Blue; Satin Black; Rose Gold; Navy; Black; Tan; Gray; Brown Wood; Dark Brown Wood; Medium Yellow Wood; Espresso Wood; Medium Wood; Red Wood; Beige Wood; Natural Wood; Gray Wood; Light Yellow Wood; White Wood; Oak Wood | CZ6: Please choose one or more from the following, using a semicolon (;) to separate each value: 0.6 Extension; Ball Bearing; Soft Close; Roller Glides; 0.75 Extension; Full Extension; Metal Slide; 0.5 Extension; Wood Slide; Center Slides; Kenlin; Side-Mounted Glides; Undermount Glides; Euro Glides; Unavailable; Does Not Apply | DA6: Select | DB6: Please choose one or more from the following, using a semicolon (;) to separate each value: Electric; Dual Fuel; Induction; Wood Pellets; Natural Gas; Liquid Propane; Wood Burning; Gel Fuel; Bio-Ethanol; Propane; Butane; Charcoal; Ethanol; Alcohol; Does Not Apply | DC6: Please choose one or more from the following, using a semicolon (;) to separate each value: Flush; Glass; Louvered; Paneled; Mirrored; Barn Doors; Frosted; Insulated; Contoured; Tinted; See Through; Double Pane; Does Not Apply | DD6: Yes or No | DE6: Yes or No | DF6: Please choose one or more from the following, using a semicolon (;) to separate each value: Drawers; Fireplace; Hutch; Shelves; Bridge; Exterior Shelves; Fireplace Remote; Integrated TV Mount; Interior Shelves; Media Storage; Pier / Bookcase; Sound Bar Shelf; TV Anti-Tip Kit; Wheels / Casters; Cabinets; Unavailable; Does Not Apply | DG6: Whole Number | DH6: Yes or No | DI6: Please choose one or more from the following, using a semicolon (;) to separate each value: Gel; Gas; Wood; Electric; Unavailable; Does Not Apply | DJ6: Select | DK6: Yes or No | DL6: Select | DM6: Select | DN6: Select | DO6: Select | DP6: Yes or No | DQ6: Please choose one or more from the following, using a semicolon (;) to separate each value: Dual Language; Distribution Conflict; Logistics; Does Not Apply | DR6: Select | DS6: Yes or No | DT6: Please choose one or more from the following, using a semicolon (;) to separate each value: UN3091; UN3481; UN2800; UN1950; UN3496; ID8000; UN1013; UN3082; UN3077; UN3480; UN2857; UN3358; UN3090; UN1266; UN1993; UN1944; UN1070; UN1044; UN3163; UN1268; UN1760; UN1011; UN2794; UN1759; UN3171; UN1987; UN1263; UN1170; UN3265; UN3260; UN3215; UN1006; UN3175; Does Not Apply | DU6: Select | DV6: Select | DW6: Select | DX6: Select | DY6: Please choose one or more from the following, using a semicolon (;) to separate each value: TÜV Rheinland Certified; MET Listed; AFNOR UK Ltd; BSI Assurance UK Ltd; cUL Listed; ETL Listed; DBI Certification Ltd; UL Listed; cETL Listed; CSA Certified; SGS North America Listed; Does Not Apply | DZ6: Text | EA6: Select | EB6: Select | EC6: Yes or No | ED6: Select | EE6: Number | EF6: Number | EG6: Number | EH6: Number | EI6: Number | EJ6: Number | EK6: Select | EL6: Number | EM6: Yes or No | EN6: Select | EO6: Please choose one or more from the following, using a semicolon (;) to separate each value: All Tools Included; Tool Free Assembly; Screwdriver; Allen Wrench; Adjustable Wrench; Socket Wrench; Power Drill; Hammer; Pliers; Ratchet; Utility Saw; Saw; Measuring Tape; Mallet; Level; Box Cutter; Caulk / Adhesive; Anchors / Stakes; Clamps; Drill Bit; Gloves; Hex Key; Glass Cutter; Chop Saw; Circular Saw; Phillips Head Screwdriver; Crescent Wrench; Flat Screwdriver; Adhesive Roller / Tray; Shovel; Drill; Smoother / Squeegee; Ladder; Wire Stripper; Razor Knife; Pencil; Electric Drill; Screw Gun; Scissors; Ruler; Safety Glasses; Utility Knife; Rope; Ear Protection; Stud Finder; Wrench; Tape Measure; Screws; Wire Cap; Hammer / Mallet; Chalk Line; Landscaping Fabric; No Tools Needed; Tile Cutter; Straight Edge; Silicone; Wet Saw; Torx Bit; Unavailable; Does Not Apply | EP6: Yes or No | EQ6: Select | ER6: Yes or No | ES6: Select | ET6: Please choose one or more from the following, using a semicolon (;) to separate each value: 30 Days; 60 Days; 90 Days; 6 Months; 1 Year; 2 Years; 3 Years; 5 Years; 10 Years; 20 Years; 25 Years; Lifetime; Warranty length varies by part; 15 Years; 18 Months; 12 Years; 6 Years; 4 Years; 8 Years; 7 Years; Does Not Apply
B7: Default Row: | C7: N/A | E7: N/A | F7: N/A | G7: N/A | I7: N/A | J7: N/A | AL7: N/A | AM7: N/A | AN7: N/A | AO7: N/A | AP7: N/A | AQ7: N/A
A8: =IF('6 - TV Stands & Enterta'!B8 = "", "", IF('6 - TV Stands & Enterta-WUO_ERR'!A8 = "", "Validated", HYPERLINK("#" & ADDRESS(8, '6 - TV Stands & Enterta-WUO_TRK'!A8),_xlfn.TEXTAFTER('6 - TV Stands & Enterta-WUO_ERR'!A8, ":")))) | B8: CASA-TV-018 | D8: Casa Design Furniture | E8: CASA-TV-018 | F8: 840134100181 | G8: #018 NORALIE TV STAND & FIREPLACE | J8: 899 | M8: Elevate your home with the #018 NORALIE TV STAND & FIREPLACE. A perfect blend of style and functionality for modern living spaces. | S8: 1 | T8: 1 | U8: 1 | V8: 85 | W8: N/A | Y8: N/A | Z8: N/A | AD8: N/A | AE8: N/A | AF8: N/A | AG8: N/A | AH8: No | AK8: N/A | AL8: N/A | BG8: N/A | BI8: Yes | BJ8: 2 | BK8: Yes | BP8: N/A | BQ8: Solid Wood | CA8: Yes | CB8: N/A | CC8: Yes | CF8: N/A | CK8: Yes | CL8: N/A | CM8: N/A | CN8: 1 | CU8: 150 | CY8: Natural | DA8: N/A | DB8: N/A | DF8: Yes | DG8: 2 | DJ8: N/A | DK8: N/A | DL8: N/A | DM8: N/A | DN8: N/A | DO8: N/A | DP8: N/A | DQ8: N/A | DX8: N/A | DY8: N/A | DZ8: N/A | EA8: N/A | EE8: N/A | EF8: N/A | EG8: N/A | EH8: N/A | EI8: N/A | EK8: N/A | EL8: N/A | EM8: No | EN8: Full Assembly Needed | EP8: N/A
A9: =IF('6 - TV Stands & Enterta'!B9 = "", "", IF('6 - TV Stands & Enterta-WUO_ERR'!A9 = "", "Validated", HYPERLINK("#" & ADDRESS(9, '6 - TV Stands & Enterta-WUO_TRK'!A9),_xlfn.TEXTAFTER('6 - TV Stands & Enterta-WUO_ERR'!A9, ":")))) | B9: CASA-TV-013 | D9: Casa Design Furniture | E9: CASA-TV-013 | F9: 840134100136 | G9: #013 TV STAND IN WHITE LACQUER | J9: 750 | M9: Elevate your home with the #013 TV STAND IN WHITE LACQUER. A perfect blend of style and functionality for modern living spaces. | S9: 1 | T9: 1 | U9: 1 | V9: 85 | W9: N/A | Y9: N/A | Z9: N/A | AD9: N/A | AE9: N/A | AF9: N/A | AG9: N/A | AH9: No | AK9: N/A | AL9: N/A | BG9: N/A | BI9: Yes | BJ9: 2 | BK9: Yes | BP9: N/A | BQ9: Solid Wood | CA9: Yes | CB9: N/A | CC9: Yes | CF9: N/A | CK9: Yes | CL9: N/A | CM9: N/A | CN9: 1 | CU9: 150 | CY9: Natural | DA9: N/A | DB9: N/A | DF9: Yes | DG9: 2 | DJ9: N/A | DK9: N/A | DL9: N/A | DM9: N/A | DN9: N/A | DO9: N/A | DP9: N/A | DQ9: N/A | DX9: N/A | DY9: N/A | DZ9: N/A | EA9: N/A | EE9: N/A | EF9: N/A | EG9: N/A | EH9: N/A | EI9: N/A | EK9: N/A | EL9: N/A | EM9: No | EN9: Full Assembly Needed | EP9: N/A
A10: =IF('6 - TV Stands & Enterta'!B10 = "", "", IF('6 - TV Stands & Enterta-WUO_ERR'!A10 = "", "Validated", HYPERLINK("#" & ADDRESS(10, '6 - TV Stands & Enterta-WUO_TRK'!A10),_xlfn.TEXTAFTER('6 - TV Stands & Enterta-WUO_ERR'!A10, ":")))) | B10: CASA-TV-015 | D10: Casa Design Furniture | E10: CASA-TV-015 | F10: 840134100150 | G10: #015 LED LIGHT TV STAND | J10: 680 | M10: Elevate your home with the #015 LED LIGHT TV STAND. A perfect blend of style and functionality for modern living spaces. | S10: 1 | T10: 1 | U10: 1 | V10: 85 | W10: N/A | Y10: N/A | Z10: N/A | AD10: N/A | AE10: N/A | AF10: N/A | AG10: N/A | AH10: No | AK10: N/A | AL10: N/A | BG10: N/A | BI10: Yes | BJ10: 2 | BK10: Yes | BP10: N/A | BQ10: Solid Wood | CA10: Yes | CB10: N/A | CC10: Yes | CF10: N/A | CK10: Yes | CL10: N/A | CM10: N/A | CN10: 1 | CU10: 150 | CY10: Natural | DA10: N/A | DB10: N/A | DF10: Yes | DG10: 2 | DJ10: N/A | DK10: N/A | DL10: N/A | DM10: N/A | DN10: N/A | DO10: N/A | DP10: N/A | DQ10: N/A | DX10: N/A | DY10: N/A | DZ10: N/A | EA10: N/A | EE10: N/A | EF10: N/A | EG10: N/A | EH10: N/A | EI10: N/A | EK10: N/A | EL10: N/A | EM10: No | EN10: Full Assembly Needed | EP10: N/A
A11: =IF('6 - TV Stands & Enterta'!B11 = "", "", IF('6 - TV Stands & Enterta-WUO_ERR'!A11 = "", "Validated", HYPERLINK("#" & ADDRESS(11, '6 - TV Stands & Enterta-WUO_TRK'!A11),_xlfn.TEXTAFTER('6 - TV Stands & Enterta-WUO_ERR'!A11, ":")))) | B11: CASA-TV-016 | D11: Casa Design Furniture | E11: CASA-TV-016 | F11: 840134100167 | G11: #016 TV STAND WHITE & LED LIGHT | J11: 720 | M11: Elevate your home with the #016 TV STAND WHITE & LED LIGHT. A perfect blend of style and functionality for modern living spaces. | S11: 1 | T11: 1 | U11: 1 | V11: 85 | W11: N/A | Y11: N/A | Z11: N/A | AD11: N/A | AE11: N/A | AF11: N/A | AG11: N/A | AH11: No | AK11: N/A | AL11: N/A | BG11: N/A | BI11: Yes | BJ11: 2 | BK11: Yes | BP11: N/A | BQ11: Solid Wood | CA11: Yes | CB11: N/A | CC11: Yes | CF11: N/A | CK11: Yes | CL11: N/A | CM11: N/A | CN11: 1 | CU11: 150 | CY11: Natural | DA11: N/A | DB11: N/A | DF11: Yes | DG11: 2 | DJ11: N/A | DK11: N/A | DL11: N/A | DM11: N/A | DN11: N/A | DO11: N/A | DP11: N/A | DQ11: N/A | DX11: N/A | DY11: N/A | DZ11: N/A | EA11: N/A | EE11: N/A | EF11: N/A | EG11: N/A | EH11: N/A | EI11: N/A | EK11: N/A | EL11: N/A | EM11: No | EN11: Full Assembly Needed | EP11: N/A
A12: =IF('6 - TV Stands & Enterta'!B12 = "", "", IF('6 - TV Stands & Enterta-WUO_ERR'!A12 = "", "Validated", HYPERLINK("#" & ADDRESS(12, '6 - TV Stands & Enterta-WUO_TRK'!A12),_xlfn.TEXTAFTER('6 - TV Stands & Enterta-WUO_ERR'!A12, ":")))) | B12: CASA-TV-017 | D12: Casa Design Furniture | E12: CASA-TV-017 | F12: 840134100174 | G12: #017 KL TV STAND | J12: 810 | M12: Elevate your home with the #017 KL TV STAND. A perfect blend of style and functionality for modern living spaces. | S12: 1 | T12: 1 | U12: 1 | V12: 85 | W12: N/A | Y12: N/A | Z12: N/A | AD12: N/A | AE12: N/A | AF12: N/A | AG12: N/A | AH12: No | AK12: N/A | AL12: N/A | BG12: N/A | BI12: Yes | BJ12: 2 | BK12: Yes | BP12: N/A | BQ12: Solid Wood | CA12: Yes | CB12: N/A | CC12: Yes | CF12: N/A | CK12: Yes | CL12: N/A | CM12: N/A | CN12: 1 | CU12: 150 | CY12: Natural | DA12: N/A | DB12: N/A | DF12: Yes | DG12: 2 | DJ12: N/A | DK12: N/A | DL12: N/A | DM12: N/A | DN12: N/A | DO12: N/A | DP12: N/A | DQ12: N/A | DX12: N/A | DY12: N/A | DZ12: N/A | EA12: N/A | EE12: N/A | EF12: N/A | EG12: N/A | EH12: N/A | EI12: N/A | EK12: N/A | EL12: N/A | EM12: No | EN12: Full Assembly Needed | EP12: N/A
A13: =IF('6 - TV Stands & Enterta'!B13 = "", "", IF('6 - TV Stands & Enterta-WUO_ERR'!A13 = "", "Validated", HYPERLINK("#" & ADDRESS(13, '6 - TV Stands & Enterta-WUO_TRK'!A13),_xlfn.TEXTAFTER('6 - TV Stands & Enterta-WUO_ERR'!A13, ":")))) | B13: CASA-TV-019 | D13: Casa Design Furniture | E13: CASA-TV-019 | F13: 840134100198 | G13: #019 TV STAND MIRRORED DIAMONDS | J13: 950 | M13: Elevate your home with the #019 TV STAND MIRRORED DIAMONDS. A perfect blend of style and functionality for modern living spaces. | S13: 1 | T13: 1 | U13: 1 | V13: 85 | W13: N/A | Y13: N/A | Z13: N/A | AD13: N/A | AE13: N/A | AF13: N/A | AG13: N/A | AH13: No | AK13: N/A | AL13: N/A | BG13: N/A | BI13: Yes | BJ13: 2 | BK13: Yes | BP13: N/A | BQ13: Solid Wood | CA13: Yes | CB13: N/A | CC13: Yes | CF13: N/A | CK13: Yes | CL13: N/A | CM13: N/A | CN13: 1 | CU13: 150 | CY13: Natural | DA13: N/A | DB13: N/A | DF13: Yes | DG13: 2 | DJ13: N/A | DK13: N/A | DL13: N/A | DM13: N/A | DN13: N/A | DO13: N/A | DP13: N/A | DQ13: N/A | DX13: N/A | DY13: N/A | DZ13: N/A | EA13: N/A | EE13: N/A | EF13: N/A | EG13: N/A | EH13: N/A | EI13: N/A | EK13: N/A | EL13: N/A | EM13: No | EN13: Full Assembly Needed | EP13: N/A
A14: =IF('6 - TV Stands & Enterta'!B14 = "", "", IF('6 - TV Stands & Enterta-WUO_ERR'!A14 = "", "Validated", HYPERLINK("#" & ADDRESS(14, '6 - TV Stands & Enterta-WUO_TRK'!A14),_xlfn.TEXTAFTER('6 - TV Stands & Enterta-WUO_ERR'!A14, ":")))) | B14: CASA-TV-020 | D14: Casa Design Furniture | E14: CASA-TV-020 | F14: 840134100204 | G14: #020 TV STAND ELECTRIC FIREPLACE | J14: 1100 | M14: Elevate your home with the #020 TV STAND ELECTRIC FIREPLACE. A perfect blend of style and functionality for modern living spaces. | S14: 1 | T14: 1 | U14: 1 | V14: 85 | W14: N/A | Y14: N/A | Z14: N/A | AD14: N/A | AE14: N/A | AF14: N/A | AG14: N/A | AH14: No | AK14: N/A | AL14: N/A | BG14: N/A | BI14: Yes | BJ14: 2 | BK14: Yes | BP14: N/A | BQ14: Solid Wood | CA14: Yes | CB14: N/A | CC14: Yes | CF14: N/A | CK14: Yes | CL14: N/A | CM14: N/A | CN14: 1 | CU14: 150 | CY14: Natural | DA14: N/A | DB14: N/A | DF14: Yes | DG14: 2 | DJ14: N/A | DK14: N/A | DL14: N/A | DM14: N/A | DN14: N/A | DO14: N/A | DP14: N/A | DQ14: N/A | DX14: N/A | DY14: N/A | DZ14: N/A | EA14: N/A | EE14: N/A | EF14: N/A | EG14: N/A | EH14: N/A | EI14: N/A | EK14: N/A | EL14: N/A | EM14: No | EN14: Full Assembly Needed | EP14: N/A
A15: =IF('6 - TV Stands & Enterta'!B15 = "", "", IF('6 - TV Stands & Enterta-WUO_ERR'!A15 = "", "Validated", HYPERLINK("#" & ADDRESS(15, '6 - TV Stands & Enterta-WUO_TRK'!A15),_xlfn.TEXTAFTER('6 - TV Stands & Enterta-WUO_ERR'!A15, ":")))) | B15: CASA-TV-023 | D15: Casa Design Furniture | E15: CASA-TV-023 | F15: 840134100235 | G15: #023 AMRITA TV STAND | J15: 590 | M15: Elevate your home with the #023 AMRITA TV STAND. A perfect blend of style and functionality for modern living spaces. | S15: 1 | T15: 1 | U15: 1 | V15: 85 | W15: N/A | Y15: N/A | Z15: N/A | AD15: N/A | AE15: N/A | AF15: N/A | AG15: N/A | AH15: No | AK15: N/A | AL15: N/A | BG15: N/A | BI15: Yes | BJ15: 2 | BK15: Yes | BP15: N/A | BQ15: Solid Wood | CA15: Yes | CB15: N/A | CC15: Yes | CF15: N/A | CK15: Yes | CL15: N/A | CM15: N/A | CN15: 1 | CU15: 150 | CY15: Natural | DA15: N/A | DB15: N/A | DF15: Yes | DG15: 2 | DJ15: N/A | DK15: N/A | DL15: N/A | DM15: N/A | DN15: N/A | DO15: N/A | DP15: N/A | DQ15: N/A | DX15: N/A | DY15: N/A | DZ15: N/A | EA15: N/A | EE15: N/A | EF15: N/A | EG15: N/A | EH15: N/A | EI15: N/A | EK15: N/A | EL15: N/A | EM15: No | EN15: Full Assembly Needed | EP15: N/A
A16: =IF('6 - TV Stands & Enterta'!B16 = "", "", IF('6 - TV Stands & Enterta-WUO_ERR'!A16 = "", "Validated", HYPERLINK("#" & ADDRESS(16, '6 - TV Stands & Enterta-WUO_TRK'!A16),_xlfn.TEXTAFTER('6 - TV Stands & Enterta-WUO_ERR'!A16, ":")))) | B16: CASA-TV-025 | D16: Casa Design Furniture | E16: CASA-TV-025 | F16: 840134100259 | G16: #025 AFONSO TV STAND FIREPLACE | J16: 1250 | M16: Elevate your home with the #025 AFONSO TV STAND FIREPLACE. A perfect blend of style and functionality for modern living spaces. | S16: 1 | T16: 1 | U16: 1 | V16: 85 | W16: N/A | Y16: N/A | Z16: N/A | AD16: N/A | AE16: N/A | AF16: N/A | AG16: N/A | AH16: No | AK16: N/A | AL16: N/A | BG16: N/A | BI16: Yes | BJ16: 2 | BK16: Yes | BP16: N/A | BQ16: Solid Wood | CA16: Yes | CB16: N/A | CC16: Yes | CF16: N/A | CK16: Yes | CL16: N/A | CM16: N/A | CN16: 1 | CU16: 150 | CY16: Natural | DA16: N/A | DB16: N/A | DF16: Yes | DG16: 2 | DJ16: N/A | DK16: N/A | DL16: N/A | DM16: N/A | DN16: N/A | DO16: N/A | DP16: N/A | DQ16: N/A | DX16: N/A | DY16: N/A | DZ16: N/A | EA16: N/A | EE16: N/A | EF16: N/A | EG16: N/A | EH16: N/A | EI16: N/A | EK16: N/A | EL16: N/A | EM16: No | EN16: Full Assembly Needed | EP16: N/A
A17: =IF('6 - TV Stands & Enterta'!B17 = "", "", IF('6 - TV Stands & Enterta-WUO_ERR'!A17 = "", "Validated", HYPERLINK("#" & ADDRESS(17, '6 - TV Stands & Enterta-WUO_TRK'!A17),_xlfn.TEXTAFTER('6 - TV Stands & Enterta-WUO_ERR'!A17, ":")))) | B17: CASA-TV-ELITE-101 | D17: Casa Design Furniture | E17: CASA-TV-ELITE-101 | F17: 840134100901 | G17: Elite Modern Series TV Stand Model 101 | J17: 550 | M17: Elevate your home with the Elite Modern Series TV Stand Model 101. A perfect blend of style and functionality for modern living spaces. | S17: 1 | T17: 1 | U17: 1 | V17: 85 | W17: N/A | Y17: N/A | Z17: N/A | AD17: N/A | AE17: N/A | AF17: N/A | AG17: N/A | AH17: No | AK17: N/A | AL17: N/A | BG17: N/A | BI17: Yes | BJ17: 2 | BK17: Yes | BP17: N/A | BQ17: Solid Wood | CA17: Yes | CB17: N/A | CC17: Yes | CF17: N/A | CK17: Yes | CL17: N/A | CM17: N/A | CN17: 1 | CU17: 150 | CY17: Natural | DA17: N/A | DB17: N/A | DF17: Yes | DG17: 2 | DJ17: N/A | DK17: N/A | DL17: N/A | DM17: N/A | DN17: N/A | DO17: N/A | DP17: N/A | DQ17: N/A | DX17: N/A | DY17: N/A | DZ17: N/A | EA17: N/A | EE17: N/A | EF17: N/A | EG17: N/A | EH17: N/A | EI17: N/A | EK17: N/A | EL17: N/A | EM17: No | EN17: Full Assembly Needed | EP17: N/A
A18: =IF('6 - TV Stands & Enterta'!B18 = "", "", IF('6 - TV Stands & Enterta-WUO_ERR'!A18 = "", "Validated", HYPERLINK("#" & ADDRESS(18, '6 - TV Stands & Enterta-WUO_TRK'!A18),_xlfn.TEXTAFTER('6 - TV Stands & Enterta-WUO_ERR'!A18, ":")))) | B18: CASA-TV-ELITE-102 | D18: Casa Design Furniture | E18: CASA-TV-ELITE-102 | F18: 840134100902 | G18: Elite Modern Series TV Stand Model 102 | J18: 600 | M18: Elevate your home with the Elite Modern Series TV Stand Model 102. A perfect blend of style and functionality for modern living spaces. | S18: 1 | T18: 1 | U18: 1 | V18: 85 | W18: N/A | Y18: N/A | Z18: N/A | AD18: N/A | AE18: N/A | AF18: N/A | AG18: N/A | AH18: No | AK18: N/A | AL18: N/A | BG18: N/A | BI18: Yes | BJ18: 2 | BK18: Yes | BP18: N/A | BQ18: Solid Wood | CA18: Yes | CB18: N/A | CC18: Yes | CF18: N/A | CK18: Yes | CL18: N/A | CM18: N/A | CN18: 1 | CU18: 150 | CY18: Natural | DA18: N/A | DB18: N/A | DF18: Yes | DG18: 2 | DJ18: N/A | DK18: N/A | DL18: N/A | DM18: N/A | DN18: N/A | DO18: N/A | DP18: N/A | DQ18: N/A | DX18: N/A | DY18: N/A | DZ18: N/A | EA18: N/A | EE18: N/A | EF18: N/A | EG18: N/A | EH18: N/A | EI18: N/A | EK18: N/A | EL18: N/A | EM18: No | EN18: Full Assembly Needed | EP18: N/A
A19: =IF('6 - TV Stands & Enterta'!B19 = "", "", IF('6 - TV Stands & Enterta-WUO_ERR'!A19 = "", "Validated", HYPERLINK("#" & ADDRESS(19, '6 - TV Stands & Enterta-WUO_TRK'!A19),_xlfn.TEXTAFTER('6 - TV Stands & Enterta-WUO_ERR'!A19, ":")))) | B19: CASA-TV-ELITE-103 | D19: Casa Design Furniture | E19: CASA-TV-ELITE-103 | F19: 840134100903 | G19: Elite Modern Series TV Stand Model 103 | J19: 650 | M19: Elevate your home with the Elite Modern Series TV Stand Model 103. A perfect blend of style and functionality for modern living spaces. | S19: 1 | T19: 1 | U19: 1 | V19: 85 | W19: N/A | Y19: N/A | Z19: N/A | AD19: N/A | AE19: N/A | AF19: N/A | AG19: N/A | AH19: No | AK19: N/A | AL19: N/A | BG19: N/A | BI19: Yes | BJ19: 2 | BK19: Yes | BP19: N/A | BQ19: Solid Wood | CA19: Yes | CB19: N/A | CC19: Yes | CF19: N/A | CK19: Yes | CL19: N/A | CM19: N/A | CN19: 1 | CU19: 150 | CY19: Natural | DA19: N/A | DB19: N/A | DF19: Yes | DG19: 2 | DJ19: N/A | DK19: N/A | DL19: N/A | DM19: N/A | DN19: N/A | DO19: N/A | DP19: N/A | DQ19: N/A | DX19: N/A | DY19: N/A | DZ19: N/A | EA19: N/A | EE19: N/A | EF19: N/A | EG19: N/A | EH19: N/A | EI19: N/A | EK19: N/A | EL19: N/A | EM19: No | EN19: Full Assembly Needed | EP19: N/A
A20: =IF('6 - TV Stands & Enterta'!B20 = "", "", IF('6 - TV Stands & Enterta-WUO_ERR'!A20 = "", "Validated", HYPERLINK("#" & ADDRESS(20, '6 - TV Stands & Enterta-WUO_TRK'!A20),_xlfn.TEXTAFTER('6 - TV Stands & Enterta-WUO_ERR'!A20, ":")))) | B20: CASA-TV-ELITE-104 | D20: Casa Design Furniture | E20: CASA-TV-ELITE-104 | F20: 840134100904 | G20: Elite Modern Series TV Stand Model 104 | J20: 700 | M20: Elevate your home with the Elite Modern Series TV Stand Model 104. A perfect blend of style and functionality for modern living spaces. | S20: 1 | T20: 1 | U20: 1 | V20: 85 | W20: N/A | Y20: N/A | Z20: N/A | AD20: N/A | AE20: N/A | AF20: N/A | AG20: N/A | AH20: No | AK20: N/A | AL20: N/A | BG20: N/A | BI20: Yes | BJ20: 2 | BK20: Yes | BP20: N/A | BQ20: Solid Wood | CA20: Yes | CB20: N/A | CC20: Yes | CF20: N/A | CK20: Yes | CL20: N/A | CM20: N/A | CN20: 1 | CU20: 150 | CY20: Natural | DA20: N/A | DB20: N/A | DF20: Yes | DG20: 2 | DJ20: N/A | DK20: N/A | DL20: N/A | DM20: N/A | DN20: N/A | DO20: N/A | DP20: N/A | DQ20: N/A | DX20: N/A | DY20: N/A | DZ20: N/A | EA20: N/A | EE20: N/A | EF20: N/A | EG20: N/A | EH20: N/A | EI20: N/A | EK20: N/A | EL20: N/A | EM20: No | EN20: Full Assembly Needed | EP20: N/A
A21: =IF('6 - TV Stands & Enterta'!B21 = "", "", IF('6 - TV Stands & Enterta-WUO_ERR'!A21 = "", "Validated", HYPERLINK("#" & ADDRESS(21, '6 - TV Stands & Enterta-WUO_TRK'!A21),_xlfn.TEXTAFTER('6 - TV Stands & Enterta-WUO_ERR'!A21, ":")))) | B21: CASA-TV-ELITE-105 | D21: Casa Design Furniture | E21: CASA-TV-ELITE-105 | F21: 840134100905 | G21: Elite Modern Series TV Stand Model 105 | J21: 750 | M21: Elevate your home with the Elite Modern Series TV Stand Model 105. A perfect blend of style and functionality for modern living spaces. | S21: 1 | T21: 1 | U21: 1 | V21: 85 | W21: N/A | Y21: N/A | Z21: N/A | AD21: N/A | AE21: N/A | AF21: N/A | AG21: N/A | AH21: No | AK21: N/A | AL21: N/A | BG21: N/A | BI21: Yes | BJ21: 2 | BK21: Yes | BP21: N/A | BQ21: Solid Wood | CA21: Yes | CB21: N/A | CC21: Yes | CF21: N/A | CK21: Yes | CL21: N/A | CM21: N/A | CN21: 1 | CU21: 150 | CY21: Natural | DA21: N/A | DB21: N/A | DF21: Yes | DG21: 2 | DJ21: N/A | DK21: N/A | DL21: N/A | DM21: N/A | DN21: N/A | DO21: N/A | DP21: N/A | DQ21: N/A | DX21: N/A | DY21: N/A | DZ21: N/A | EA21: N/A | EE21: N/A | EF21: N/A | EG21: N/A | EH21: N/A | EI21: N/A | EK21: N/A | EL21: N/A | EM21: No | EN21: Full Assembly Needed | EP21: N/A
A22: =IF('6 - TV Stands & Enterta'!B22 = "", "", IF('6 - TV Stands & Enterta-WUO_ERR'!A22 = "", "Validated", HYPERLINK("#" & ADDRESS(22, '6 - TV Stands & Enterta-WUO_TRK'!A22),_xlfn.TEXTAFTER('6 - TV Stands & Enterta-WUO_ERR'!A22, ":")))) | B22: CASA-TV-ELITE-106 | D22: Casa Design Furniture | E22: CASA-TV-ELITE-106 | F22: 840134100906 | G22: Elite Modern Series TV Stand Model 106 | J22: 800 | M22: Elevate your home with the Elite Modern Series TV Stand Model 106. A perfect blend of style and functionality for modern living spaces. | S22: 1 | T22: 1 | U22: 1 | V22: 85 | W22: N/A | Y22: N/A | Z22: N/A | AD22: N/A | AE22: N/A | AF22: N/A | AG22: N/A | AH22: No | AK22: N/A | AL22: N/A | BG22: N/A | BI22: Yes | BJ22: 2 | BK22: Yes | BP22: N/A | BQ22: Solid Wood | CA22: Yes | CB22: N/A | CC22: Yes | CF22: N/A | CK22: Yes | CL22: N/A | CM22: N/A | CN22: 1 | CU22: 150 | CY22: Natural | DA22: N/A | DB22: N/A | DF22: Yes | DG22: 2 | DJ22: N/A | DK22: N/A | DL22: N/A | DM22: N/A | DN22: N/A | DO22: N/A | DP22: N/A | DQ22: N/A | DX22: N/A | DY22: N/A | DZ22: N/A | EA22: N/A | EE22: N/A | EF22: N/A | EG22: N/A | EH22: N/A | EI22: N/A | EK22: N/A | EL22: N/A | EM22: No | EN22: Full Assembly Needed | EP22: N/A
A23: =IF('6 - TV Stands & Enterta'!B23 = "", "", IF('6 - TV Stands & Enterta-WUO_ERR'!A23 = "", "Validated", HYPERLINK("#" & ADDRESS(23, '6 - TV Stands & Enterta-WUO_TRK'!A23),_xlfn.TEXTAFTER('6 - TV Stands & Enterta-WUO_ERR'!A23, ":"))))
A24: =IF('6 - TV Stands & Enterta'!B24 = "", "", IF('6 - TV Stands & Enterta-WUO_ERR'!A24 = "", "Validated", HYPERLINK("#" & ADDRESS(24, '6 - TV Stands & Enterta-WUO_TRK'!A24),_xlfn.TEXTAFTER('6 - TV Stands & Enterta-WUO_ERR'!A24, ":"))))
A25: =IF('6 - TV Stands & Enterta'!B25 = "", "", IF('6 - TV Stands & Enterta-WUO_ERR'!A25 = "", "Validated", HYPERLINK("#" & ADDRESS(25, '6 - TV Stands & Enterta-WUO_TRK'!A25),_xlfn.TEXTAFTER('6 - TV Stands & Enterta-WUO_ERR'!A25, ":"))))
A26: =IF('6 - TV Stands & Enterta'!B26 = "", "", IF('6 - TV Stands & Enterta-WUO_ERR'!A26 = "", "Validated", HYPERLINK("#" & ADDRESS(26, '6 - TV Stands & Enterta-WUO_TRK'!A26),_xlfn.TEXTAFTER('6 - TV Stands & Enterta-WUO_ERR'!A26, ":"))))
A27: =IF('6 - TV Stands & Enterta'!B27 = "", "", IF('6 - TV Stands & Enterta-WUO_ERR'!A27 = "", "Validated", HYPERLINK("#" & ADDRESS(27, '6 - TV Stands & Enterta-WUO_TRK'!A27),_xlfn.TEXTAFTER('6 - TV Stands & Enterta-WUO_ERR'!A27, ":"))))
A28: =IF('6 - TV Stands & Enterta'!B28 = "", "", IF('6 - TV Stands & Enterta-WUO_ERR'!A28 = "", "Validated", HYPERLINK("#" & ADDRESS(28, '6 - TV Stands & Enterta-WUO_TRK'!A28),_xlfn.TEXTAFTER('6 - TV Stands & Enterta-WUO_ERR'!A28, ":"))))
A29: =IF('6 - TV Stands & Enterta'!B29 = "", "", IF('6 - TV Stands & Enterta-WUO_ERR'!A29 = "", "Validated", HYPERLINK("#" & ADDRESS(29, '6 - TV Stands & Enterta-WUO_TRK'!A29),_xlfn.TEXTAFTER('6 - TV Stands & Enterta-WUO_ERR'!A29, ":"))))
A30: =IF('6 - TV Stands & Enterta'!B30 = "", "", IF('6 - TV Stands & Enterta-WUO_ERR'!A30 = "", "Validated", HYPERLINK("#" & ADDRESS(30, '6 - TV Stands & Enterta-WUO_TRK'!A30),_xlfn.TEXTAFTER('6 - TV Stands & Enterta-WUO_ERR'!A30, ":"))))
A31: =IF('6 - TV Stands & Enterta'!B31 = "", "", IF('6 - TV Stands & Enterta-WUO_ERR'!A31 = "", "Validated", HYPERLINK("#" & ADDRESS(31, '6 - TV Stands & Enterta-WUO_TRK'!A31),_xlfn.TEXTAFTER('6 - TV Stands & Enterta-WUO_ERR'!A31, ":"))))
A32: =IF('6 - TV Stands & Enterta'!B32 = "", "", IF('6 - TV Stands & Enterta-WUO_ERR'!A32 = "", "Validated", HYPERLINK("#" & ADDRESS(32, '6 - TV Stands & Enterta-WUO_TRK'!A32),_xlfn.TEXTAFTER('6 - TV Stands & Enterta-WUO_ERR'!A32, ":"))))
A33: =IF('6 - TV Stands & Enterta'!B33 = "", "", IF('6 - TV Stands & Enterta-WUO_ERR'!A33 = "", "Validated", HYPERLINK("#" & ADDRESS(33, '6 - TV Stands & Enterta-WUO_TRK'!A33),_xlfn.TEXTAFTER('6 - TV Stands & Enterta-WUO_ERR'!A33, ":"))))
A34: =IF('6 - TV Stands & Enterta'!B34 = "", "", IF('6 - TV Stands & Enterta-WUO_ERR'!A34 = "", "Validated", HYPERLINK("#" & ADDRESS(34, '6 - TV Stands & Enterta-WUO_TRK'!A34),_xlfn.TEXTAFTER('6 - TV Stands & Enterta-WUO_ERR'!A34, ":"))))
A35: =IF('6 - TV Stands & Enterta'!B35 = "", "", IF('6 - TV Stands & Enterta-WUO_ERR'!A35 = "", "Validated", HYPERLINK("#" & ADDRESS(35, '6 - TV Stands & Enterta-WUO_TRK'!A35),_xlfn.TEXTAFTER('6 - TV Stands & Enterta-WUO_ERR'!A35, ":"))))
A36: =IF('6 - TV Stands & Enterta'!B36 = "", "", IF('6 - TV Stands & Enterta-WUO_ERR'!A36 = "", "Validated", HYPERLINK("#" & ADDRESS(36, '6 - TV Stands & Enterta-WUO_TRK'!A36),_xlfn.TEXTAFTER('6 - TV Stands & Enterta-WUO_ERR'!A36, ":"))))
A37: =IF('6 - TV Stands & Enterta'!B37 = "", "", IF('6 - TV Stands & Enterta-WUO_ERR'!A37 = "", "Validated", HYPERLINK("#" & ADDRESS(37, '6 - TV Stands & Enterta-WUO_TRK'!A37),_xlfn.TEXTAFTER('6 - TV Stands & Enterta-WUO_ERR'!A37, ":"))))
A38: =IF('6 - TV Stands & Enterta'!B38 = "", "", IF('6 - TV Stands & Enterta-WUO_ERR'!A38 = "", "Validated", HYPERLINK("#" & ADDRESS(38, '6 - TV Stands & Enterta-WUO_TRK'!A38),_xlfn.TEXTAFTER('6 - TV Stands & Enterta-WUO_ERR'!A38, ":"))))
A39: =IF('6 - TV Stands & Enterta'!B39 = "", "", IF('6 - TV Stands & Enterta-WUO_ERR'!A39 = "", "Validated", HYPERLINK("#" & ADDRESS(39, '6 - TV Stands & Enterta-WUO_TRK'!A39),_xlfn.TEXTAFTER('6 - TV Stands & Enterta-WUO_ERR'!A39, ":"))))
A40: =IF('6 - TV Stands & Enterta'!B40 = "", "", IF('6 - TV Stands & Enterta-WUO_ERR'!A40 = "", "Validated", HYPERLINK("#" & ADDRESS(40, '6 - TV Stands & Enterta-WUO_TRK'!A40),_xlfn.TEXTAFTER('6 - TV Stands & Enterta-WUO_ERR'!A40, ":"))))
A41: =IF('6 - TV Stands & Enterta'!B41 = "", "", IF('6 - TV Stands & Enterta-WUO_ERR'!A41 = "", "Validated", HYPERLINK("#" & ADDRESS(41, '6 - TV Stands & Enterta-WUO_TRK'!A41),_xlfn.TEXTAFTER('6 - TV Stands & Enterta-WUO_ERR'!A41, ":"))))
A42: =IF('6 - TV Stands & Enterta'!B42 = "", "", IF('6 - TV Stands & Enterta-WUO_ERR'!A42 = "", "Validated", HYPERLINK("#" & ADDRESS(42, '6 - TV Stands & Enterta-WUO_TRK'!A42),_xlfn.TEXTAFTER('6 - TV Stands & Enterta-WUO_ERR'!A42, ":"))))
A43: =IF('6 - TV Stands & Enterta'!B43 = "", "", IF('6 - TV Stands & Enterta-WUO_ERR'!A43 = "", "Validated", HYPERLINK("#" & ADDRESS(43, '6 - TV Stands & Enterta-WUO_TRK'!A43),_xlfn.TEXTAFTER('6 - TV Stands & Enterta-WUO_ERR'!A43, ":"))))
A44: =IF('6 - TV Stands & Enterta'!B44 = "", "", IF('6 - TV Stands & Enterta-WUO_ERR'!A44 = "", "Validated", HYPERLINK("#" & ADDRESS(44, '6 - TV Stands & Enterta-WUO_TRK'!A44),_xlfn.TEXTAFTER('6 - TV Stands & Enterta-WUO_ERR'!A44, ":"))))
A45: =IF('6 - TV Stands & Enterta'!B45 = "", "", IF('6 - TV Stands & Enterta-WUO_ERR'!A45 = "", "Validated", HYPERLINK("#" & ADDRESS(45, '6 - TV Stands & Enterta-WUO_TRK'!A45),_xlfn.TEXTAFTER('6 - TV Stands & Enterta-WUO_ERR'!A45, ":"))))
A46: =IF('6 - TV Stands & Enterta'!B46 = "", "", IF('6 - TV Stands & Enterta-WUO_ERR'!A46 = "", "Validated", HYPERLINK("#" & ADDRESS(46, '6 - TV Stands & Enterta-WUO_TRK'!A46),_xlfn.TEXTAFTER('6 - TV Stands & Enterta-WUO_ERR'!A46, ":"))))
A47: =IF('6 - TV Stands & Enterta'!B47 = "", "", IF('6 - TV Stands & Enterta-WUO_ERR'!A47 = "", "Validated", HYPERLINK("#" & ADDRESS(47, '6 - TV Stands & Enterta-WUO_TRK'!A47),_xlfn.TEXTAFTER('6 - TV Stands & Enterta-WUO_ERR'!A47, ":"))))
A48: =IF('6 - TV Stands & Enterta'!B48 = "", "", IF('6 - TV Stands & Enterta-WUO_ERR'!A48 = "", "Validated", HYPERLINK("#" & ADDRESS(48, '6 - TV Stands & Enterta-WUO_TRK'!A48),_xlfn.TEXTAFTER('6 - TV Stands & Enterta-WUO_ERR'!A48, ":"))))
A49: =IF('6 - TV Stands & Enterta'!B49 = "", "", IF('6 - TV Stands & Enterta-WUO_ERR'!A49 = "", "Validated", HYPERLINK("#" & ADDRESS(49, '6 - TV Stands & Enterta-WUO_TRK'!A49),_xlfn.TEXTAFTER('6 - TV Stands & Enterta-WUO_ERR'!A49, ":"))))
A50: =IF('6 - TV Stands & Enterta'!B50 = "", "", IF('6 - TV Stands & Enterta-WUO_ERR'!A50 = "", "Validated", HYPERLINK("#" & ADDRESS(50, '6 - TV Stands & Enterta-WUO_TRK'!A50),_xlfn.TEXTAFTER('6 - TV Stands & Enterta-WUO_ERR'!A50, ":"))))
A51: =IF('6 - TV Stands & Enterta'!B51 = "", "", IF('6 - TV Stands & Enterta-WUO_ERR'!A51 = "", "Validated", HYPERLINK("#" & ADDRESS(51, '6 - TV Stands & Enterta-WUO_TRK'!A51),_xlfn.TEXTAFTER('6 - TV Stands & Enterta-WUO_ERR'!A51, ":"))))
A52: =IF('6 - TV Stands & Enterta'!B52 = "", "", IF('6 - TV Stands & Enterta-WUO_ERR'!A52 = "", "Validated", HYPERLINK("#" & ADDRESS(52, '6 - TV Stands & Enterta-WUO_TRK'!A52),_xlfn.TEXTAFTER('6 - TV Stands & Enterta-WUO_ERR'!A52, ":"))))
A53: =IF('6 - TV Stands & Enterta'!B53 = "", "", IF('6 - TV Stands & Enterta-WUO_ERR'!A53 = "", "Validated", HYPERLINK("#" & ADDRESS(53, '6 - TV Stands & Enterta-WUO_TRK'!A53),_xlfn.TEXTAFTER('6 - TV Stands & Enterta-WUO_ERR'!A53, ":"))))
A54: =IF('6 - TV Stands & Enterta'!B54 = "", "", IF('6 - TV Stands & Enterta-WUO_ERR'!A54 = "", "Validated", HYPERLINK("#" & ADDRESS(54, '6 - TV Stands & Enterta-WUO_TRK'!A54),_xlfn.TEXTAFTER('6 - TV Stands & Enterta-WUO_ERR'!A54, ":"))))
A55: =IF('6 - TV Stands & Enterta'!B55 = "", "", IF('6 - TV Stands & Enterta-WUO_ERR'!A55 = "", "Validated", HYPERLINK("#" & ADDRESS(55, '6 - TV Stands & Enterta-WUO_TRK'!A55),_xlfn.TEXTAFTER('6 - TV Stands & Enterta-WUO_ERR'!A55, ":"))))
A56: =IF('6 - TV Stands & Enterta'!B56 = "", "", IF('6 - TV Stands & Enterta-WUO_ERR'!A56 = "", "Validated", HYPERLINK("#" & ADDRESS(56, '6 - TV Stands & Enterta-WUO_TRK'!A56),_xlfn.TEXTAFTER('6 - TV Stands & Enterta-WUO_ERR'!A56, ":"))))
A57: =IF('6 - TV Stands & Enterta'!B57 = "", "", IF('6 - TV Stands & Enterta-WUO_ERR'!A57 = "", "Validated", HYPERLINK("#" & ADDRESS(57, '6 - TV Stands & Enterta-WUO_TRK'!A57),_xlfn.TEXTAFTER('6 - TV Stands & Enterta-WUO_ERR'!A57, ":"))))
A58: =IF('6 - TV Stands & Enterta'!B58 = "", "", IF('6 - TV Stands & Enterta-WUO_ERR'!A58 = "", "Validated", HYPERLINK("#" & ADDRESS(58, '6 - TV Stands & Enterta-WUO_TRK'!A58),_xlfn.TEXTAFTER('6 - TV Stands & Enterta-WUO_ERR'!A58, ":"))))
A59: =IF('6 - TV Stands & Enterta'!B59 = "", "", IF('6 - TV Stands & Enterta-WUO_ERR'!A59 = "", "Validated", HYPERLINK("#" & ADDRESS(59, '6 - TV Stands & Enterta-WUO_TRK'!A59),_xlfn.TEXTAFTER('6 - TV Stands & Enterta-WUO_ERR'!A59, ":"))))
A60: =IF('6 - TV Stands & Enterta'!B60 = "", "", IF('6 - TV Stands & Enterta-WUO_ERR'!A60 = "", "Validated", HYPERLINK("#" & ADDRESS(60, '6 - TV Stands & Enterta-WUO_TRK'!A60),_xlfn.TEXTAFTER('6 - TV Stands & Enterta-WUO_ERR'!A60, ":"))))
A61: =IF('6 - TV Stands & Enterta'!B61 = "", "", IF('6 - TV Stands & Enterta-WUO_ERR'!A61 = "", "Validated", HYPERLINK("#" & ADDRESS(61, '6 - TV Stands & Enterta-WUO_TRK'!A61),_xlfn.TEXTAFTER('6 - TV Stands & Enterta-WUO_ERR'!A61, ":"))))
A62: =IF('6 - TV Stands & Enterta'!B62 = "", "", IF('6 - TV Stands & Enterta-WUO_ERR'!A62 = "", "Validated", HYPERLINK("#" & ADDRESS(62, '6 - TV Stands & Enterta-WUO_TRK'!A62),_xlfn.TEXTAFTER('6 - TV Stands & Enterta-WUO_ERR'!A62, ":"))))
A63: =IF('6 - TV Stands & Enterta'!B63 = "", "", IF('6 - TV Stands & Enterta-WUO_ERR'!A63 = "", "Validated", HYPERLINK("#" & ADDRESS(63, '6 - TV Stands & Enterta-WUO_TRK'!A63),_xlfn.TEXTAFTER('6 - TV Stands & Enterta-WUO_ERR'!A63, ":"))))
A64: =IF('6 - TV Stands & Enterta'!B64 = "", "", IF('6 - TV Stands & Enterta-WUO_ERR'!A64 = "", "Validated", HYPERLINK("#" & ADDRESS(64, '6 - TV Stands & Enterta-WUO_TRK'!A64),_xlfn.TEXTAFTER('6 - TV Stands & Enterta-WUO_ERR'!A64, ":"))))
A65: =IF('6 - TV Stands & Enterta'!B65 = "", "", IF('6 - TV Stands & Enterta-WUO_ERR'!A65 = "", "Validated", HYPERLINK("#" & ADDRESS(65, '6 - TV Stands & Enterta-WUO_TRK'!A65),_xlfn.TEXTAFTER('6 - TV Stands & Enterta-WUO_ERR'!A65, ":"))))
A66: =IF('6 - TV Stands & Enterta'!B66 = "", "", IF('6 - TV Stands & Enterta-WUO_ERR'!A66 = "", "Validated", HYPERLINK("#" & ADDRESS(66, '6 - TV Stands & Enterta-WUO_TRK'!A66),_xlfn.TEXTAFTER('6 - TV Stands & Enterta-WUO_ERR'!A66, ":"))))
A67: =IF('6 - TV Stands & Enterta'!B67 = "", "", IF('6 - TV Stands & Enterta-WUO_ERR'!A67 = "", "Validated", HYPERLINK("#" & ADDRESS(67, '6 - TV Stands & Enterta-WUO_TRK'!A67),_xlfn.TEXTAFTER('6 - TV Stands & Enterta-WUO_ERR'!A67, ":"))))
A68: =IF('6 - TV Stands & Enterta'!B68 = "", "", IF('6 - TV Stands & Enterta-WUO_ERR'!A68 = "", "Validated", HYPERLINK("#" & ADDRESS(68, '6 - TV Stands & Enterta-WUO_TRK'!A68),_xlfn.TEXTAFTER('6 - TV Stands & Enterta-WUO_ERR'!A68, ":"))))
A69: =IF('6 - TV Stands & Enterta'!B69 = "", "", IF('6 - TV Stands & Enterta-WUO_ERR'!A69 = "", "Validated", HYPERLINK("#" & ADDRESS(69, '6 - TV Stands & Enterta-WUO_TRK'!A69),_xlfn.TEXTAFTER('6 - TV Stands & Enterta-WUO_ERR'!A69, ":"))))
A70: =IF('6 - TV Stands & Enterta'!B70 = "", "", IF('6 - TV Stands & Enterta-WUO_ERR'!A70 = "", "Validated", HYPERLINK("#" & ADDRESS(70, '6 - TV Stands & Enterta-WUO_TRK'!A70),_xlfn.TEXTAFTER('6 - TV Stands & Enterta-WUO_ERR'!A70, ":"))))
A71: =IF('6 - TV Stands & Enterta'!B71 = "", "", IF('6 - TV Stands & Enterta-WUO_ERR'!A71 = "", "Validated", HYPERLINK("#" & ADDRESS(71, '6 - TV Stands & Enterta-WUO_TRK'!A71),_xlfn.TEXTAFTER('6 - TV Stands & Enterta-WUO_ERR'!A71, ":"))))
A72: =IF('6 - TV Stands & Enterta'!B72 = "", "", IF('6 - TV Stands & Enterta-WUO_ERR'!A72 = "", "Validated", HYPERLINK("#" & ADDRESS(72, '6 - TV Stands & Enterta-WUO_TRK'!A72),_xlfn.TEXTAFTER('6 - TV Stands & Enterta-WUO_ERR'!A72, ":"))))
A73: =IF('6 - TV Stands & Enterta'!B73 = "", "", IF('6 - TV Stands & Enterta-WUO_ERR'!A73 = "", "Validated", HYPERLINK("#" & ADDRESS(73, '6 - TV Stands & Enterta-WUO_TRK'!A73),_xlfn.TEXTAFTER('6 - TV Stands & Enterta-WUO_ERR'!A73, ":"))))
A74: =IF('6 - TV Stands & Enterta'!B74 = "", "", IF('6 - TV Stands & Enterta-WUO_ERR'!A74 = "", "Validated", HYPERLINK("#" & ADDRESS(74, '6 - TV Stands & Enterta-WUO_TRK'!A74),_xlfn.TEXTAFTER('6 - TV Stands & Enterta-WUO_ERR'!A74, ":"))))
A75: =IF('6 - TV Stands & Enterta'!B75 = "", "", IF('6 - TV Stands & Enterta-WUO_ERR'!A75 = "", "Validated", HYPERLINK("#" & ADDRESS(75, '6 - TV Stands & Enterta-WUO_TRK'!A75),_xlfn.TEXTAFTER('6 - TV Stands & Enterta-WUO_ERR'!A75, ":"))))
A76: =IF('6 - TV Stands & Enterta'!B76 = "", "", IF('6 - TV Stands & Enterta-WUO_ERR'!A76 = "", "Validated", HYPERLINK("#" & ADDRESS(76, '6 - TV Stands & Enterta-WUO_TRK'!A76),_xlfn.TEXTAFTER('6 - TV Stands & Enterta-WUO_ERR'!A76, ":"))))
A77: =IF('6 - TV Stands & Enterta'!B77 = "", "", IF('6 - TV Stands & Enterta-WUO_ERR'!A77 = "", "Validated", HYPERLINK("#" & ADDRESS(77, '6 - TV Stands & Enterta-WUO_TRK'!A77),_xlfn.TEXTAFTER('6 - TV Stands & Enterta-WUO_ERR'!A77, ":"))))
A78: =IF('6 - TV Stands & Enterta'!B78 = "", "", IF('6 - TV Stands & Enterta-WUO_ERR'!A78 = "", "Validated", HYPERLINK("#" & ADDRESS(78, '6 - TV Stands & Enterta-WUO_TRK'!A78),_xlfn.TEXTAFTER('6 - TV Stands & Enterta-WUO_ERR'!A78, ":"))))
A79: =IF('6 - TV Stands & Enterta'!B79 = "", "", IF('6 - TV Stands & Enterta-WUO_ERR'!A79 = "", "Validated", HYPERLINK("#" & ADDRESS(79, '6 - TV Stands & Enterta-WUO_TRK'!A79),_xlfn.TEXTAFTER('6 - TV Stands & Enterta-WUO_ERR'!A79, ":"))))
A80: =IF('6 - TV Stands & Enterta'!B80 = "", "", IF('6 - TV Stands & Enterta-WUO_ERR'!A80 = "", "Validated", HYPERLINK("#" & ADDRESS(80, '6 - TV Stands & Enterta-WUO_TRK'!A80),_xlfn.TEXTAFTER('6 - TV Stands & Enterta-WUO_ERR'!A80, ":"))))
A81: =IF('6 - TV Stands & Enterta'!B81 = "", "", IF('6 - TV Stands & Enterta-WUO_ERR'!A81 = "", "Validated", HYPERLINK("#" & ADDRESS(81, '6 - TV Stands & Enterta-WUO_TRK'!A81),_xlfn.TEXTAFTER('6 - TV Stands & Enterta-WUO_ERR'!A81, ":"))))
A82: =IF('6 - TV Stands & Enterta'!B82 = "", "", IF('6 - TV Stands & Enterta-WUO_ERR'!A82 = "", "Validated", HYPERLINK("#" & ADDRESS(82, '6 - TV Stands & Enterta-WUO_TRK'!A82),_xlfn.TEXTAFTER('6 - TV Stands & Enterta-WUO_ERR'!A82, ":"))))
A83: =IF('6 - TV Stands & Enterta'!B83 = "", "", IF('6 - TV Stands & Enterta-WUO_ERR'!A83 = "", "Validated", HYPERLINK("#" & ADDRESS(83, '6 - TV Stands & Enterta-WUO_TRK'!A83),_xlfn.TEXTAFTER('6 - TV Stands & Enterta-WUO_ERR'!A83, ":"))))
A84: =IF('6 - TV Stands & Enterta'!B84 = "", "", IF('6 - TV Stands & Enterta-WUO_ERR'!A84 = "", "Validated", HYPERLINK("#" & ADDRESS(84, '6 - TV Stands & Enterta-WUO_TRK'!A84),_xlfn.TEXTAFTER('6 - TV Stands & Enterta-WUO_ERR'!A84, ":"))))
A85: =IF('6 - TV Stands & Enterta'!B85 = "", "", IF('6 - TV Stands & Enterta-WUO_ERR'!A85 = "", "Validated", HYPERLINK("#" & ADDRESS(85, '6 - TV Stands & Enterta-WUO_TRK'!A85),_xlfn.TEXTAFTER('6 - TV Stands & Enterta-WUO_ERR'!A85, ":"))))
A86: =IF('6 - TV Stands & Enterta'!B86 = "", "", IF('6 - TV Stands & Enterta-WUO_ERR'!A86 = "", "Validated", HYPERLINK("#" & ADDRESS(86, '6 - TV Stands & Enterta-WUO_TRK'!A86),_xlfn.TEXTAFTER('6 - TV Stands & Enterta-WUO_ERR'!A86, ":"))))
A87: =IF('6 - TV Stands & Enterta'!B87 = "", "", IF('6 - TV Stands & Enterta-WUO_ERR'!A87 = "", "Validated", HYPERLINK("#" & ADDRESS(87, '6 - TV Stands & Enterta-WUO_TRK'!A87),_xlfn.TEXTAFTER('6 - TV Stands & Enterta-WUO_ERR'!A87, ":"))))
A88: =IF('6 - TV Stands & Enterta'!B88 = "", "", IF('6 - TV Stands & Enterta-WUO_ERR'!A88 = "", "Validated", HYPERLINK("#" & ADDRESS(88, '6 - TV Stands & Enterta-WUO_TRK'!A88),_xlfn.TEXTAFTER('6 - TV Stands & Enterta-WUO_ERR'!A88, ":"))))
A89: =IF('6 - TV Stands & Enterta'!B89 = "", "", IF('6 - TV Stands & Enterta-WUO_ERR'!A89 = "", "Validated", HYPERLINK("#" & ADDRESS(89, '6 - TV Stands & Enterta-WUO_TRK'!A89),_xlfn.TEXTAFTER('6 - TV Stands & Enterta-WUO_ERR'!A89, ":"))))
A90: =IF('6 - TV Stands & Enterta'!B90 = "", "", IF('6 - TV Stands & Enterta-WUO_ERR'!A90 = "", "Validated", HYPERLINK("#" & ADDRESS(90, '6 - TV Stands & Enterta-WUO_TRK'!A90),_xlfn.TEXTAFTER('6 - TV Stands & Enterta-WUO_ERR'!A90, ":"))))
A91: =IF('6 - TV Stands & Enterta'!B91 = "", "", IF('6 - TV Stands & Enterta-WUO_ERR'!A91 = "", "Validated", HYPERLINK("#" & ADDRESS(91, '6 - TV Stands & Enterta-WUO_TRK'!A91),_xlfn.TEXTAFTER('6 - TV Stands & Enterta-WUO_ERR'!A91, ":"))))
A92: =IF('6 - TV Stands & Enterta'!B92 = "", "", IF('6 - TV Stands & Enterta-WUO_ERR'!A92 = "", "Validated", HYPERLINK("#" & ADDRESS(92, '6 - TV Stands & Enterta-WUO_TRK'!A92),_xlfn.TEXTAFTER('6 - TV Stands & Enterta-WUO_ERR'!A92, ":"))))
A93: =IF('6 - TV Stands & Enterta'!B93 = "", "", IF('6 - TV Stands & Enterta-WUO_ERR'!A93 = "", "Validated", HYPERLINK("#" & ADDRESS(93, '6 - TV Stands & Enterta-WUO_TRK'!A93),_xlfn.TEXTAFTER('6 - TV Stands & Enterta-WUO_ERR'!A93, ":"))))
A94: =IF('6 - TV Stands & Enterta'!B94 = "", "", IF('6 - TV Stands & Enterta-WUO_ERR'!A94 = "", "Validated", HYPERLINK("#" & ADDRESS(94, '6 - TV Stands & Enterta-WUO_TRK'!A94),_xlfn.TEXTAFTER('6 - TV Stands & Enterta-WUO_ERR'!A94, ":"))))
A95: =IF('6 - TV Stands & Enterta'!B95 = "", "", IF('6 - TV Stands & Enterta-WUO_ERR'!A95 = "", "Validated", HYPERLINK("#" & ADDRESS(95, '6 - TV Stands & Enterta-WUO_TRK'!A95),_xlfn.TEXTAFTER('6 - TV Stands & Enterta-WUO_ERR'!A95, ":"))))
A96: =IF('6 - TV Stands & Enterta'!B96 = "", "", IF('6 - TV Stands & Enterta-WUO_ERR'!A96 = "", "Validated", HYPERLINK("#" & ADDRESS(96, '6 - TV Stands & Enterta-WUO_TRK'!A96),_xlfn.TEXTAFTER('6 - TV Stands & Enterta-WUO_ERR'!A96, ":"))))
A97: =IF('6 - TV Stands & Enterta'!B97 = "", "", IF('6 - TV Stands & Enterta-WUO_ERR'!A97 = "", "Validated", HYPERLINK("#" & ADDRESS(97, '6 - TV Stands & Enterta-WUO_TRK'!A97),_xlfn.TEXTAFTER('6 - TV Stands & Enterta-WUO_ERR'!A97, ":"))))
A98: =IF('6 - TV Stands & Enterta'!B98 = "", "", IF('6 - TV Stands & Enterta-WUO_ERR'!A98 = "", "Validated", HYPERLINK("#" & ADDRESS(98, '6 - TV Stands & Enterta-WUO_TRK'!A98),_xlfn.TEXTAFTER('6 - TV Stands & Enterta-WUO_ERR'!A98, ":"))))
A99: =IF('6 - TV Stands & Enterta'!B99 = "", "", IF('6 - TV Stands & Enterta-WUO_ERR'!A99 = "", "Validated", HYPERLINK("#" & ADDRESS(99, '6 - TV Stands & Enterta-WUO_TRK'!A99),_xlfn.TEXTAFTER('6 - TV Stands & Enterta-WUO_ERR'!A99, ":"))))
A100: =IF('6 - TV Stands & Enterta'!B100 = "", "", IF('6 - TV Stands & Enterta-WUO_ERR'!A100 = "", "Validated", HYPERLINK("#" & ADDRESS(100, '6 - TV Stands & Enterta-WUO_TRK'!A100),_xlfn.TEXTAFTER('6 - TV Stands & Enterta-WUO_ERR'!A100, ":"))))
...

Sheet 6 - TV Stands & Enterta-WUO_ERR
B1: core::supplierPartNumber | C1: core::amazonStandardIdentificationNumber | D1: core::manufacturerId | E1: core::manufacturerPartNumber | F1: core::universalProductCode | G1: core::productName | H1: core::collectionName | I1: core::manufacturerProductUrl | J1: price::wholesalePrice | K1: price::minimumAdvertizedPrice | L1: price::manufacturerSuggestedRetailPrice | M1: featureDescription::romanceCopy | N1: featureDescription::genericFeatures | O1: featureDescription::genericFeatures | P1: featureDescription::genericFeatures | Q1: featureDescription::genericFeatures | R1: featureDescription::genericFeatures | S1: shippingAndFulfillment::minimumOrderQuantity | T1: shippingAndFulfillment::forceQuantityMultiplier | U1: shippingAndFulfillment::displaySetQuantity | V1: shippingAndFulfillment::productWeight | W1: shippingAndFulfillment::shipType | X1: shippingAndFulfillment::freightClass | Y1: shippingAndFulfillment::leadTime | Z1: shippingAndFulfillment::replacementLeadTime | AA1: shippingAndFulfillment::nationalMotorFreightClass | AB1: shippingAndFulfillment::flatPack | AC1: shippingAndFulfillment::shipPalletized | AD1: shippingAndFulfillment::weight | AE1: shippingAndFulfillment::height | AF1: shippingAndFulfillment::width | AG1: shippingAndFulfillment::depth | AH1: propSixtyFive::warningRequired | AI1: propSixtyFive::chemicalId | AJ1: propSixtyFive::toxicity | AK1: propSixtyFive::countryOfManufacturer | AL1: media::imageValue | AM1: media::imageValue | AN1: media::imageValue | AO1: media::imageValue | AP1: media::imageValue | AQ1: media::videoValue | AR1: media::documentValue | AS1: media::documentType | AT1: media::legalDocumentType | AU1: media::regionType | AV1: media::language | AW1: media::documentValue | AX1: media::documentType | AY1: media::legalDocumentType | AZ1: media::regionType | BA1: media::language | BB1: media::documentValue | BC1: media::documentType | BD1: media::legalDocumentType | BE1: media::regionType | BF1: media::language | BG1: 5620 | BH1: 252622 | BI1: 5635 | BJ1: 5911 | BK1: 5636 | BL1: 382543 | BM1: 5634 | BN1: 5678 | BO1: 252625 | BP1: 5621 | BQ1: 5625 | BR1: 222860 | BS1: 222861 | BT1: 5624 | BU1: 220722 | BV1: 221251 | BW1: 218007 | BX1: 5648 | BY1: 5649 | BZ1: 5643 | CA1: 5645 | CB1: 189876 | CC1: 201479 | CD1: 5663 | CE1: 242478 | CF1: 227966 | CG1: 244566 | CH1: 293480 | CI1: 293547 | CJ1: 185254 | CK1: 344955 | CL1: 346869 | CM1: 351619 | CN1: 367149 | CO1: 351641 | CP1: 352351 | CQ1: 352342 | CR1: 351649 | CS1: 5949 | CT1: 5950 | CU1: 5654 | CV1: 368645 | CW1: 370848 | CX1: 5910 | CY1: 379875 | CZ1: 292794 | DA1: 220267 | DB1: 220265 | DC1: 384286 | DD1: 393970 | DE1: 400764 | DF1: 420139 | DG1: 5920 | DH1: 5916 | DI1: 5938 | DJ1: 5671 | DK1: 201426 | DL1: 224759 | DM1: 224980 | DN1: 364708 | DO1: 236083 | DP1: 249364 | DQ1: 251110 | DR1: 310560 | DS1: 339330 | DT1: 373560 | DU1: 340810 | DV1: 341070 | DW1: 369614 | DX1: 368262 | DY1: 375302 | DZ1: 376202 | EA1: 382060 | EB1: 385921 | EC1: 415242 | ED1: 421601 | EE1: 5675 | EF1: 5676 | EG1: 252485 | EH1: 252486 | EI1: 252487 | EJ1: 5681 | EK1: 217965 | EL1: 5674 | EM1: 5682 | EN1: 222775 | EO1: 222778 | EP1: 228934 | EQ1: 333812 | ER1: 254186 | ES1: 255305 | ET1: 256090
B2: Basic Information | J2: Pricing | M2: Marketing Information | S2: Fulfillment Information | AD2: Carton Details | AH2: Compliance | AL2: Media | BG2: Attributes
B3: Required | C3: Additional | D3: Required | E3: Required | F3: Recommended | G3: Required | H3: Additional | I3: Additional | J3: Required | K3: Additional | L3: Additional | M3: Conditional | N3: Conditional | O3: Conditional | P3: Conditional | Q3: Conditional | R3: Conditional | S3: Required | T3: Required | U3: Required | V3: Required | W3: Required | X3: Conditional | Y3: Required | Z3: Required | AA3: Additional | AB3: Additional | AC3: Additional | AD3: Required | AE3: Required | AF3: Required | AG3: Required | AH3: Required | AI3: Conditional | AJ3: Conditional | AK3: Required | AL3: Required | AM3: Additional | AN3: Additional | AO3: Additional | AP3: Additional | AQ3: Additional | AR3: Conditional | AS3: Conditional | AT3: Conditional | AU3: Conditional | AV3: Conditional | AW3: Conditional | AX3: Conditional | AY3: Conditional | AZ3: Conditional | BA3: Conditional | BB3: Conditional | BC3: Conditional | BD3: Conditional | BE3: Conditional | BF3: Conditional | BG3: Required | BH3: Recommended | BI3: Required | BJ3: Required | BK3: Required | BL3: Recommended | BM3: Recommended | BN3: Recommended | BO3: Recommended | BP3: Required | BQ3: Required | BR3: Recommended | BS3: Recommended | BT3: Recommended | BU3: Recommended | BV3: Recommended | BW3: Recommended | BX3: Recommended | BY3: Recommended | BZ3: Recommended | CA3: Required | CB3: Required | CC3: Required | CD3: Recommended | CE3: Recommended | CF3: Required | CG3: Additional | CH3: Recommended | CI3: Recommended | CJ3: Recommended | CK3: Required | CL3: Required | CM3: Required | CN3: Required | CO3: Additional | CP3: Additional | CQ3: Additional | CR3: Additional | CS3: Recommended | CT3: Recommended | CU3: Required | CV3: Recommended | CW3: Recommended | CX3: Recommended | CY3: Required | CZ3: Recommended | DA3: Required | DB3: Required | DC3: Recommended | DD3: Recommended | DE3: Recommended | DF3: Required | DG3: Required | DH3: Recommended | DI3: Recommended | DJ3: Required | DK3: Required | DL3: Required | DM3: Required | DN3: Required | DO3: Required | DP3: Required | DQ3: Required | DR3: Recommended | DS3: Recommended | DT3: Recommended | DU3: Recommended | DV3: Recommended | DW3: Recommended | DX3: Required | DY3: Required | DZ3: Required | EA3: Required | EB3: Recommended | EC3: Recommended | ED3: Recommended | EE3: Required | EF3: Required | EG3: Required | EH3: Required | EI3: Required | EJ3: Recommended | EK3: Required | EL3: Required | EM3: Required | EN3: Required | EO3: Recommended | EP3: Required | EQ3: Recommended | ER3: Recommended | ES3: Recommended | ET3: Recommended
B4: Supplier Part Number | C4: ASIN or Amazon Seller SKU | D4: Brand | E4: Manufacturer Part Number | F4: Universal Product Code | G4: Product Name | H4: Collection Name | I4: Manufacturer Product URL | J4: Base Cost | K4: Minimum Advertised Price | L4: Manufacturer Suggested Retail Price | M4: Marketing Copy | N4: Feature Bullet 1 | O4: Feature Bullet 2 | P4: Feature Bullet 3 | Q4: Feature Bullet 4 | R4: Feature Bullet 5 | S4: Minimum Order Quantity | T4: Force Quantity Multiplier | U4: Display Set Quantity | V4: Product Weight | W4: Ship Type | X4: Freight Class | Y4: Lead Time | Z4: Replacement Lead Time | AA4: National Motor Freight Class | AB4: Flat Pack | AC4: Ship Palletized | AD4: Carton Weight 1 | AE4: Carton Height 1 | AF4: Carton Width 1 | AG4: Carton Depth 1 | AH4: Warning Required | AI4: Chemical 1 | AJ4: Toxicity 1 | AK4: Country Of Manufacturer | AL4: Image File Name or URL 1 | AM4: Image File Name or URL 2 | AN4: Image File Name or URL 3 | AO4: Image File Name or URL 4 | AP4: Image File Name or URL 5 | AQ4: Video File Name or URL 1 | AR4: Document File Name or URL 1 | AS4: Document Type 1 | AT4: Legal Document Type 1 | AU4: Document Region 1 | AV4: Document Language 1 | AW4: Document File Name or URL 2 | AX4: Document Type 2 | AY4: Legal Document Type 2 | AZ4: Document Region 2 | BA4: Document Language 2 | BB4: Document File Name or URL 3 | BC4: Document Type 3 | BD4: Legal Document Type 3 | BE4: Document Region 3 | BF4: Document Language 3 | BG4: Product Type | BH4: Pier / Bookcase Included | BI4: Drawers Included | BJ4: Number of Drawers | BK4: Cabinets Included | BL4: Shelves Included | BM4: Exterior Shelves Included | BN4: Interior Shelves Included | BO4: Bridge Included | BP4: Furniture Design | BQ4: Material | BR4: Purposeful Distressing Type | BS4: Natural Variation Type | BT4: Gloss Finish | BU4: Mirrored | BV4: Sound Bar Shelf Included | BW4: Adjustable Shelves | BX4: Media Storage Included | BY4: Cable Management | BZ4: Wheels / Casters Included | CA4: Fireplace Included | CB4: Plug-In | CC4: Tipover Restraint Device Included | CD4: Integrated TV Mount Included | CE4: Adjustable Height | CF4: Supplier Intended and Approved Use | CG4: Country of Origin - Additional Details | CH4: Main Wood Joinery Method | CI4: Kiln-Dried Wood | CJ4: Wood Species | CK4: Battery or Batteries Included | CL4: Battery Composition | CM4: Battery Type | CN4: Number of Batteries | CO4: Battery Shipment | CP4: Lithium Content | CQ4: Watt Rating of Cells / Battery | CR4: Weight of Cells / Battery | CS4: Adjustable Temperature | CT4: Adjustable Flame | CU4: Weight Capacity | CV4: Product Care | CW4: Unfinished | CX4: Shelf Material | CY4: Color / Finish | CZ4: Drawer Glide Type & Extension | DA4: Vent Type | DB4: Fuel Type | DC4: Door Design | DD4: Ribbed Detailing | DE4: Fluted Detailing | DF4: Pieces Included | DG4: Number of Cabinets | DH4: Drawer Safety Stop | DI4: Fireplace Type | DJ4: General Certificate of Conformity (GCC) | DK4: Composite Wood Product (CWP) | DL4: CARB Phase II Compliant (formaldehyde emissions) | DM4: TSCA Title VI Compliant (formaldehyde emissions) | DN4: CANFER Compliant | DO4: Uniform Packaging and Labeling Regulations (UPLR) Compliant | DP4: Canada Product Restriction | DQ4: Reason for Restriction | DR4: UL 1678 Listed | DS4: Hazardous Material / Dangerous Goods | DT4: UN or ID number | DU4: Hazard Class(es) | DV4: Packing Group | DW4: Hazardous Material Weight | DX4: Energy Efficiency Regulations Compliant | DY4: Safety Listing(s) | DZ4: Safety Listing(s) Registration Number | EA4: CPSC - 16 CFR 1263 Compliant (Reese's Law) | EB4: ISTA Certified | EC4: Sustainability & Social Responsibility Certifications (North America Only) | ED4: Commercial Certifications | EE4: TV Stand Width - Side to Side | EF4: TV Stand Depth - Front to Back | EG4: Overall Entertainment Center Height - Top to Bottom | EH4: Overall Entertainment Center Width - Side to Side | EI4: Overall Entertainment Center Depth - Front to Back | EJ4: Overall Product Weight | EK4: Maximum TV Screen Size Accommodated | EL4: TV Stand Overall Height - Top to Bottom | EM4: Assembly Required | EN4: Level of Assembly | EO4: Additional Tools Required (Not Included) | EP4: Commercial Warranty | EQ4: Commercial Warranty Length | ER4: Product Warranty | ES4: Full or Limited Warranty | ET4: Warranty Length
B5: Must be less than 64 characters and must be a unique value (products cannot be added if they have the same part number as something you already have in your catalog). This is the supplier-specific value for the product as it appears on your Inventory Feed and Purchased Orders. | C5: The Amazon Standard Identification Number (ASIN) is a 10-character alphanumeric unique identifier assigned by Amazon.com and its partners for product identification within the Amazon organization. The Amazon Seller SKU is Amazon's identifier for your product that allows you to fulfill the product through Amazon shipping even when selling the product on other sites like Wayfair. | D5: Enter your product's brand (may be the same as the product's manufacturer). New brands must be created in the brand management tool in Partner Home before they can be selected here. | E5: Must be less than 64 characters and must be a unique value (products cannot be added if they have the same part number as something you already have in your catalog). This is the part number provided by the manufacturer. | F5: Must follow the standard UPC format and must be a unique value (products cannot be added if they have the same UPC as something you already have in your catalog). | G5: Please do not use abbreviations or exceed the 255 character limit. Wayfair may adjust the provided name based on marketing standards per class. | H5: If the product belongs to a collection of associated products that are not just product variances/options, enter the collection here. This can match with collections of products you already sell on site. For example, a collection may be a bed and nightstand that both follow a modern theme, but would not be a bed that comes in two separate colors. Products in a collection do not share the same listing on site. | I5: Enter the URL for the specific manufacturer product page of your product. | J5: Your supplier profile preference for currency is used to determine the currency of the base (wholesale) cost provided. | K5: The region selected for this sheet is used to determine the currency of the MAP provided. This may differ from the currency of your base cost. | L5: The region selected for this sheet is used to determine the currency of the MSRP provided. This may differ from the currency of your base cost. | M5: Please do not use special symbols (trademark, copyright, etc.) or extra lines/spacing. This should be a short, single paragraph product description in complete sentences highlighting details about key product information. | N5: 15 words or less, describing one aspect of the product, eg., Unique aspects, benefits, use cases, technology. These provide customers with key facts at first glance and help them to decide whether they want to make the purchase. If no marketing copy is provided, then at least 3 feature bullets must be provided. | O5: 15 words or less, describing one aspect of the product, eg., Unique aspects, benefits, use cases, technology. These provide customers with key facts at first glance and help them to decide whether they want to make the purchase. If no marketing copy is provided, then at least 3 feature bullets must be provided. | P5: 15 words or less, describing one aspect of the product, eg., Unique aspects, benefits, use cases, technology. These provide customers with key facts at first glance and help them to decide whether they want to make the purchase. If no marketing copy is provided, then at least 3 feature bullets must be provided. | Q5: 15 words or less, describing one aspect of the product, eg., Unique aspects, benefits, use cases, technology. These provide customers with key facts at first glance and help them to decide whether they want to make the purchase. If no marketing copy is provided, then at least 3 feature bullets must be provided. | R5: 15 words or less, describing one aspect of the product, eg., Unique aspects, benefits, use cases, technology. These provide customers with key facts at first glance and help them to decide whether they want to make the purchase. If no marketing copy is provided, then at least 3 feature bullets must be provided. | S5: The minimum count of items a customer must choose to purchase the product. | T5: This represents how many items the customer must buy in increments of, or in addition to. For example, a multiplier of 2 would mean a custom must buy 1 quantity, 3 quantity, 5 quantity, or some other multiple of 2. | U5: Number of items represented by the part number and wholesale price. For example, if you want to sell a bundle of pillows, and the part number and wholesale cost you provided represents that full bundle of pillows, then you would answer the Display Set Quantity question with how many pillows are in the bundle. | V5: [Pounds] What is the total weight of this product once assembled? Please enter just the number (i.e. 45.5) without a unit of measurement. | W5: Enter small parcel or LTL to indicate how the product can ship based on size and weight. | X5: Each product falls into 1 of 18 classes determined by a product's 'transportability' and are crucial for calculating shipping cost. The field is required when ship type is LTL. | Y5: [Hours] This is the length of time from receipt of PO to shipment from the warehouse. | Z5: [Hours] This is length of time from receipt of a replacement PO to shipment from the warehouse | AA5: 5 to 7 digit number in length (depending on any sub classification) that will identify what is shipping in the box | AB5: Also known as 'knocked down'. Select 'Yes' if this product ships disassembled in a flat pack box. | AC5: Select 'Yes' if this product ships on a pallet. | AD5: [Pounds] Enter in the shipping weight (i.e. 45.5) of the packaging used for the product. If the product ships in more than one box, this measurement is per box. | AE5: [Inches] Enter in the shipping height (i.e. 45.5) of the packaging used for the product. If the product ships in more than one box, this measurement is per box. | AF5: [Inches] Enter in the shipping width (i.e. 45.5) of the packaging used for the product. If the product ships in more than one box, this measurement is per box. | AG5: [Inches] Enter in the shipping depth (i.e. 45.5) of the packaging used for the product. If the product ships in more than one box, this measurement is per box. | AH5: If the product requires a warning for Proposition 65 compliance in California, answer 'Yes' and indicate which chemicals and toxicities are applicable. | AI5: Select the chemical that requires the Prop65 warning. | AJ5: Select the toxicity that can result from the selected chemical. | AK5: Provide only a single country of manufacture for each product. | AL5: Your first image will be set as the lead image for this listing, however, is subject to change upon Wayfair review. For each image uploaded, provide the file name with extension (e.g. PART_1.jpeg) or a direct public URL which leads to a single image (tip: to isolate the image, right click + select Open Image in New Tab). Elements like logos, buttons, etc will interfere with our ability to download the image. Do not exceed 20 images per product. | AM5: Your first image will be set as the lead image for this listing, however, is subject to change upon Wayfair review. For each image uploaded, provide the file name with extension (e.g. PART_1.jpeg) or a direct public URL which leads to a single image (tip: to isolate the image, right click + select Open Image in New Tab). Elements like logos, buttons, etc will interfere with our ability to download the image. Do not exceed 20 images per product. | AN5: Your first image will be set as the lead image for this listing, however, is subject to change upon Wayfair review. For each image uploaded, provide the file name with extension (e.g. PART_1.jpeg) or a direct public URL which leads to a single image (tip: to isolate the image, right click + select Open Image in New Tab). Elements like logos, buttons, etc will interfere with our ability to download the image. Do not exceed 20 images per product. | AO5: Your first image will be set as the lead image for this listing, however, is subject to change upon Wayfair review. For each image uploaded, provide the file name with extension (e.g. PART_1.jpeg) or a direct public URL which leads to a single image (tip: to isolate the image, right click + select Open Image in New Tab). Elements like logos, buttons, etc will interfere with our ability to download the image. Do not exceed 20 images per product. | AP5: Your first image will be set as the lead image for this listing, however, is subject to change upon Wayfair review. For each image uploaded, provide the file name with extension (e.g. PART_1.jpeg) or a direct public URL which leads to a single image (tip: to isolate the image, right click + select Open Image in New Tab). Elements like logos, buttons, etc will interfere with our ability to download the image. Do not exceed 20 images per product. | AQ5: Provide the video’s file name with extension for separate uploads or a direct public URL. Do not exceed 10 videos per product. | AR5: Provide the document’s file name with extension for separate uploads or a direct public URL. Do not exceed 10 documents per product. | AS5: Select one or more values from the provided list that best describe the document’s purpose. This classification helps customers easily find information like “Installation & Assembly” guides, “Warranty Information,” or “Specifications. | AT5: If the document serves as a legal notice or certification (e.g., “ASTM F2057 - 19,” “ANSI A117.1 Compliant”), select the specific type(s) from the provided list. This is used for compliance and to display certifications to customers. | AU5: Select the country or region where this document is legally applicable. This is crucial for compliance-related documents that may differ across locations. | AV5: Select the language in which the document is written. | AW5: Provide the document’s file name with extension for separate uploads or a direct public URL. Do not exceed 10 documents per product. | AX5: Select one or more values from the provided list that best describe the document’s purpose. This classification helps customers easily find information like “Installation & Assembly” guides, “Warranty Information,” or “Specifications. | AY5: If the document serves as a legal notice or certification (e.g., “ASTM F2057 - 19,” “ANSI A117.1 Compliant”), select the specific type(s) from the provided list. This is used for compliance and to display certifications to customers. | AZ5: Select the country or region where this document is legally applicable. This is crucial for compliance-related documents that may differ across locations. | BA5: Select the language in which the document is written. | BB5: Provide the document’s file name with extension for separate uploads or a direct public URL. Do not exceed 10 documents per product. | BC5: Select one or more values from the provided list that best describe the document’s purpose. This classification helps customers easily find information like “Installation & Assembly” guides, “Warranty Information,” or “Specifications. | BD5: If the document serves as a legal notice or certification (e.g., “ASTM F2057 - 19,” “ANSI A117.1 Compliant”), select the specific type(s) from the provided list. This is used for compliance and to display certifications to customers. | BE5: Select the country or region where this document is legally applicable. This is crucial for compliance-related documents that may differ across locations. | BF5: Select the language in which the document is written. | BG5: What type of product is this? | BH5: Does this product have a pier / bookcase included? | BI5: Does this product have any drawers? | BJ5: How many drawers are included in this product? | BK5: Does this product include cabinets? | BL5: Does this product include shelves? | BM5: Does this product have an open space with either another shelf above it or the top surface of the product above it? We do not define the top surface of the Accent Chest/Cabinet as an exterior shelf. | BN5: Does this product have interior shelves included? | BO5: Does this product have a bridge included? | BP5: What is the design of the piece of furniture? | BQ5: What material is the product made of? | BR5: What specific type of distressing does this product have? Select all that apply. | BS5: Which of the following types of natural variation and texture does the product have? Multiple can be selected if applicable. If the product does NOT have natural variation, please select No Natural Variation. | BT5: Does this product have a shiny and sheer gloss finish over the normal painted finish? | BU5: Is the surface of the product mirrored? Please do not select “yes” if the product only features a mirror. This question refers to the surface material of the product, and if it is reflective. | BV5: Does this product have a sound bar shelf included? | BW5: Does this product have adjustable shelves? | BX5: Does this product have media storage included? | BY5: Does this product have any built-in cable or wire management, such as a hole specifically for wires (a grommet) or a tray where wires can be stored? | BZ5: Does this product have wheels or casters? | CA5: Does this product have a fireplace included? | CB5: If this product requires electricity can it be plugged into a household outlet via an integral corded plug or an AC adapter? If this product does not require electricity or if this product requires electricity but does not/cannot use household AC voltages (with or without an AC adapter) please select "No". | CC5: Does this product include a device to prevent the product from tipping over? Tipover restraint devices (TRDs) include brackets, straps, or other specialized hardware | CD5: Does this product have an integrated tv mount included? | CE5: Is the height of this product adjustable? | CF5: What type of environmental setting was this product designed and manufactured to be used in? Note: your answer indicates that Wayfair is able to market this product as being intended for use in the selected setting(s). Please select both, if both options apply. | CG5: Does this product and/or packaging have additional advertising or labeling details regarding claims about the product’s origin? Please use this field to provide a qualified or unqualified claim regarding the product origin in accordance with US Federal Trade Commission (FTC) and Canada Competition Bureau regulations. Additionally, if applicable, please use this field to communicate any appropriate qualified, comparative, or descriptive claims regarding the origin of the product. Examples include, but are not limited to, communicating relevant percentage of domestic and non-domestic content (ex: 60% U.S. Content), communicating the origin of certain components of the product (ex: "Hand carved in U.S. — Wood from Philippines"), or communicating where the product was assembled (Ex : “Assembled In Mexico”). See https://www.ftc.gov/tips-advice/business-center/guidance/complying-made-usa-standard#qualified and https://www.competitionbureau.gc.ca/eic/site/cb-bc.nsf/eng/03169.html | CH5: Which technique was used to join together the main pieces of wood to construct the overall product? | CI5: Is the wood kiln-dried? If product is not made of wood, please select "does not apply." | CJ5: What type of wood was used to construct this product? This describes the actual materials used, not the product's appearance. | CK5: Is the product a battery or does the product include batteries? | CL5: What is the composition of the batteries included with product? | CM5: What type is the battery? Button Cell, Cell, Battery? | CN5: Confirm number of batteries in this product | CO5: Do the cells/batteries ship stand alone/packed with the equipment/ contained (installed) in the equipment? | CP5: What is the aggregate lithium content of the cell/battery? Aggregate lithium content means the sum of the grams of lithium content contained by the cells comprising a battery. Please note, this is the weight weight of the lithium in the cell or battery, and not the weight of the entire cell or battery. | CQ5: What is the Watt-hour(Wh) rating of the cell/battery? The Watt-hour rating of a lithium cell or battery is calculated by multiplying the rated capacity in ampere-hours by the nominal voltage. If only the milliampere-hours (mAh) are marked on the battery then divide that number by 1000 to get ampere-hours (Ah) (i.e. 4400 mAh / 1000 = 4.4. Ah). | CR5: What is the net weight of the cells or batteries that ship with the product in grams or kilograms. | CS5: Can the amount of heat be adjusted? | CT5: Can the brightness, size, or color of the flame be adjusted? | CU5: [Pounds] What is the maximum weight capacity of the product? Please enter just the number (i.e., 45.5). | CV5: What is the appropriate way to clean and/or care for this product? Please select as many answers as applicable. | CW5: Is this product unfinished (no paint, stain, or varnish)? | CX5: What material are the shelves made of? | CY5: What is the color or finish of the product? If your color/finish name is not listed, please type in the value. | CZ5: Please select which type of glide the drawer features and/or how far it can extend. | DA5: What type of vent does this product have? | DB5: What is the source of fuel needed in order for this product to function? | DC5: Please select the design of the product. | DD5: Is there a a raised pattern of parallel lines on a surface of this product? | DE5: Is there a a concave pattern of parallel lines on a surface of this product? | DF5: What pieces are included with this product? | DG5: How many cabinets does this product have? | DH5: Do any drawers feature safety stops (intended to keep the drawers from pulling all the way out)? | DI5: What type of Fireplace is included? | DJ5: Does this product have a General Certificate of Conformity (GCC), as required by the U.S. CPSC for certain product classes? | DK5: FOR COMPLIANCE PURPOSES. Not customer facing information. Does this product include any pieces made of manufactured or composite wood products (CWP) This includes any of the following 1) HWPW-CC [Hardwood Plywood with Composite Core] 2) HWPW-VC [Hardwood Plywood with Veneer Core] 3) PB [Particleboard] 4) MDF or thin-MDF [Medium Density Fiberboard] | DL5: Is this product certified compliant for CARB ATCM Phase II formaldehyde emission standards from Composite Wood Products [California Air Resources Board (CARB)- Airborne Toxic Control Measures (ATCM) Phase II] | DM5: Is this product certified TSCA Title VI compliant regarding formaldehyde emissions from Composite Wood Products [Environmental Protection Agency (EPA)-Toxic Substance Control Act (TSCA)-Title VI] | DN5: Is this product CANFER compliant regarding formaldehyde emissions from composite wood products? [Canada Formaldehyde Emissions Regulation] NOTE: Please provide proof of certification to applicable formaldehyde emissions standards and a Declaration of Certification. More information on the Declaration of Certification and on other requirements for CANFER compliance can be found in Health Canada's Guidance Document (https://bit.ly/3FvYK2B) or by contacting any of our Product Compliance Resources (https://bit.ly/3h8EIlw). | DO5: Does your product comply with the Uniform Packaging and Labeling Regulations, which requires product packaging to be accurate and provide adequate information as to the identity and quantity of its contents, as well as the name and address of the manufacturer and/or distributor? | DP5: Is this product legally or operationally restricted from being offered for sale to Canadian customers on Wayfair.ca or delivered to Canadian addresses? Select “Yes” only if the product cannot legally be sold or shipped to Canada. For example, if it requires a license or certification you do not hold, or if you operate through a separate Canadian entity that cannot support the listing. | DQ5: Please select the reason this product can not ship to Canada? Please select from the options or write in a reason if not selectable | DR5: Is this product UL 1678 Listed? This means that the international standards testing company UL (Underwriters' Laboratories) has tested this product and found it to be in compliance with Category 1678 safety standards. | DS5: Is the product regulated as Hazardous Material / Dangerous Goods? Hazardous Materials/Dangerous Goods are substances that when transported pose a risk to health, safety, property or the environment. These materials may include explosives, compressed gases (aerosols), flammable liquids, oxidizers, toxic/poisonous, radioactive, corrosive, batteries, etc. An SDS is is a document that lists information relating to occupational safety and health for the use of various substances and products. The SDS includes information such as the properties of each chemical; the physical, health, and environmental health hazards; protective measures; and safety precautions for handling, storing, and transporting the chemical or product. | DT5: Please provide the UN or ID number. The UN or ID number is a 4 digit numeric code that identifies hazardous materials/dangerous goods, and articles in the framework of international and domestic transport. This can be found in section 14 of the Safety Data Sheet (SDS). Example - "UN3480" - Lithium Ion Batteries. If your UN number is not one of the options in the dropdown, please write this in manually. | DU5: Please provide the Hazard Class(es). This is the category of hazard assigned to a hazardous material/dangerous goods under the definitional criteria of the transportation regulations. A material may meet the defining criteria for more than one hazard class but is assigned to only one hazard class. Hazard classes vary from 1-9.This can be found in section 14 of the Safety Data Sheet (SDS). | DV5: Please provide the packing group (if applicable). Packing Groups I, II and III indicate the degree of danger presented by the material is great, medium or minor, respectively. Some hazardous materials/dangerous goods do not have a packing group assigned. This can be found in section 14 of the Safety Data Sheet (SDS). | DW5: Please provide the net weight or, for liquids, the net volume of hazardous material per unit of product. Provide the net weight of the hazardous materials/dangerous goods in your product in grams or kilograms. For example -if your product is a vacuum containing a lithium ion battery, you would enter the net weight of the battery. | DX5: Is this product compliant with U.S. Energy Efficiency requirements, including those set forth in the Energy Policy and Conservation Act of 1975 (ECPA), the National Appliance Energy Conservation Act (NAECA), the Energy Policy Act of 1992 and 2005, and the Energy Independence and Security Act of 2007, as applicable? | DY5: Which of the following certification or verification marks does your product have? If the item is not certified/verified with any safety listing, please select Does Not Apply. | DZ5: In a comma separated list, please outline the registration numbers associated to the safety listings you claimed this product has, in the following structure: Safety Listing - Registration Number. Example: UL Listed - ABC1234567, TÜV Rheinland Certified - DEFGH8910. This number may be referred to as a "Certification Number", "File Number", "Model Number", "Listing Number" or "Certification ID Number" depending on where the certification is from | EA5: Is this product compliant with 16 CFR 1263, the safety standard for button cell or coin batteries adopted per the requirements under Reese's Law? Testing to ANSI/UL 4200A-2023 demonstrates compliance. Please Note: A "No" answer to this question will result in your product being restricted from sale. | EB5: Is the packaging for this SKU ISTA Certified (1A, 3A, 6A)? | EC5: Do you have any certifications or credentials related to environmental sustainability, social responsibility, or ethical sourcing (e.g.,OEKO-TEX®, GREENGUARD, GoodWeave, Fair Trade, FSC, etc.)? To see examples of certificates currently part of our Shop Sustainably program, please visit: https://www.aboutwayfair.com/shop-sustainably. Please upload all related certificates so your products can be merchandised as part of the Shop Sustainably program. | ED5: For BIFMA Accredited products, suppliers must upload an ANSI/BIFMA durability-related testing document for the product from an ISO 17025 accredited lab. For BIFMA Equivalent products, suppliers must upload an ANSI/BIFMA durability-related testing document for the product, but the lab is not required to be ISO 17025 accredited. For Contract Grade Accredited products, suppliers must upload a testing document that aligns with Wayfair’s contract grade standards, along with a signed consent letter. Reference the Contract Grade help center article or reach out to your relationship manager for more information. | EE5: [Inches] What is the overall width of the TV Stand (side to side)? Please enter just the number (i.e. 45.5). Please DO NOT duplicate this tag - any additional information can be stored in Shelf Dimensions, Cabinet Dimensions, or as a bullet. | EF5: [Inches] What is the overall depth of the TV Stand (front to back)? Please enter just the number (i.e. 45.5). | EG5: [Inches] What is the overall height of the Entertainment Center (top to bottom)? Enter just the value (i.e., 45.5). | EH5: [Inches] What is the overall width of the Entertainment Center (side to side)? Please enter just the number (i.e. 45.5). Please DO NOT duplicate this tag - any additional information can be stored in Shelf Dimensions, Cabinet Dimensions, or as a bullet. | EI5: [Inches] What is the overall depth of the Entertainment Center (front to back)? Enter just the value (i.e., 45.5). | EJ5: [Pounds] What is the total weight of this product once assembled? If this product includes multiples of the same item, add weight of one individual unit (e.g. 1 Dining Chair in a set of 2). Please enter just the number (i.e. 45.5). | EK5: What is the largest size of TV this stand can hold, in inches? The TV size is the diagonal measurement (the distance between opposite corners) of the screen in inches. Please use the following calculation, based on a standard 16:9 HDTV aspect ratio: for TV Stands, calculate TV Stand Overall Width * 1.15, and for Entertainment Centers calculate TV Opening Width * 1.15. Both calculations should be rounded down to the closest standard TV size. | EL5: [Inches] What is the overall height of the TV stand (top to bottom)? Enter just the value (i.e., 45.5). | EM5: Does the product require any form of assembly prior to use as intended? | EN5: What is the level of assembly required? | EO5: What additional tools will the customer need to set-up this product that are NOT included with purchase? | EP5: Does the manufacturer warranty cover the use of this product in a commercial environment? | EQ5: How long does the manufacturer warranty apply for the product used in a commercial (non-residential) environment? If the correct value is not found, please select the closest available answer that is shorter than the warranty length. If warranty length varies by part, please select the answer that matches the part of the product with the shortest warranty. Please use the “Warranty Details” tag for any additional details. | ER5: Please indicate if there is a warranty on this product if it were to be used in a residential setting. | ES5: Please indicate if the warranty is Full or Limited. | ET5: Please indicate the length of the warranty offered from our list if this product were to be used in a residential setting. If the correct value is not found, please indicate both the number and unit (Days, Months, Years) that is appropriate.
B6: Text | C6: Text | D6: Select | E6: Text | F6: Text | G6: Text | H6: Text | I6: Text | J6: Number | K6: Number | L6: Number | M6: Text | N6: Text | O6: Text | P6: Text | Q6: Text | R6: Text | S6: Whole Number | T6: Whole Number | U6: Whole Number | V6: Number | W6: Select | X6: Select | Y6: Select | Z6: Select | AA6: Text | AB6: Yes or No | AC6: Yes or No | AD6: Number | AE6: Number | AF6: Number | AG6: Number | AH6: Yes or No | AI6: Select | AJ6: Please choose one or more from the following, using a semicolon (;) to separate each value: Cancer; Developmental | AK6: Select | AL6: Text | AM6: Text | AN6: Text | AO6: Text | AP6: Text | AQ6: Text | AR6: Text | AS6: Please choose one or more from the following, using a semicolon (;) to separate each value: Specifications; Installation & Assembly; Owner Manual; Delivery Information; Warranty Information; Certifications; Disclaimers; Buying Guides; Promotions; Dimensions; Marketing Materials; Energy Guide; Other; Product Information Sheet; Digital Law Label | AT6: Please choose one or more from the following, using a semicolon (;) to separate each value: AAFA Certified; AATCC 116 Grade; AATCC 16.1-2014 Grade; AATCC 16.3-2014 Grade; AATCC 8 Grade; AC Rated; ACT Flammability Guidelines Compliant; AHAM CADR Dust rating; AHAM CADR Pollen rating; AHAM CADR Smoke rating; AHMA Certified; AHMA Compliant; AHRI Certified; ANSI A117.1 Compliant; ANSI A137.1 Compliant; ANSI IT9.2 Compliant; ANSI Z1.5A/CGA 9.1M Certified; ANSI Z124.1.2 Compliant; ANSI Z124.3 Compliant; ANSI Z124.6-97 Compliant; ANSI Z21.11.2-2016 - Gas-Fired Unvented Room Heaters and Gas-Fired Unvented Decorative Room Heaters; ANSI Z21.50-2016/CSA 2.22-2016 - Standard for Vented Decorative Gas Appliances; ANSI Z21.60-2017/CSA 2.26-2017- Standard for Decorative Gas Appliances; ANSI Z21.84-2017 - Standard for Manually Lighted/ Natural Gas/ Decorative Gas Appliances; ANSI Z21.88-2017/CSA 2.33-2017- Standard for Vented Gas Fireplace Heaters; ANSI Z358 Compliant; ANSI/BHMA A156 Certified; ANSI/BIFMA M7.1 Standard Test Method for Determining VOC Emissions; ANSI/BIFMA X5.1 Office Seating; ANSI/BIFMA X5.11 Large Occupant Office Seating; ANSI/BIFMA X5.3 Vertical Files; ANSI/BIFMA X5.4 Lounge & Public Seating; ANSI/BIFMA X5.5 Desk Products; ANSI/BIFMA X5.6 Panel Systems; ANSI/BIFMA X5.9 Storage; ANSI/BIFMA X6.1 Educational Seating; ANSI/BIFMA X7.1 Standard for Formaldehyde & TVOC Emissions; ANSI/ESD S20.20 Certified; ANSI/NISO Z39.48 Compliant; ANSI/SOHO S6.5 Small Office/Home Office; APMA Certified; ASHRAE 62.2 Standard Compliant; ASME A112.18.1 Compliant; ASME A112.18.2 Compliant; ASME A112.19.1 Compliant; ASME A112.19.2 Compliant; ASME A112.19.3 Compliant; ASP:02:01 Certification; ASSE 1001 Certified; ASSE 1006 Certified; ASSE 1016 Certified; ASTM 1821-19; ASTM E1590-07 Compliant; ASTM F1004-19 Certified; ASTM F1148-17 Compliant; ASTM F1148-18 Compliant; ASTM F1148-18 Certified; ASTM F1169 - 13 Compliant; ASTM F1487-17 Compliant; ASTM F1821 - 16 Compliant; ASTM F1912-17 Compliant; ASTM F1917 - 12 Compliant; ASTM F2057 - 14; ASTM F2057 - 17; ASTM F2057 - 19 | AU6: Select | AV6: Select | AW6: Text | AX6: Please choose one or more from the following, using a semicolon (;) to separate each value: Specifications; Installation & Assembly; Owner Manual; Delivery Information; Warranty Information; Certifications; Disclaimers; Buying Guides; Promotions; Dimensions; Marketing Materials; Energy Guide; Other; Product Information Sheet; Digital Law Label | AY6: Please choose one or more from the following, using a semicolon (;) to separate each value: AAFA Certified; AATCC 116 Grade; AATCC 16.1-2014 Grade; AATCC 16.3-2014 Grade; AATCC 8 Grade; AC Rated; ACT Flammability Guidelines Compliant; AHAM CADR Dust rating; AHAM CADR Pollen rating; AHAM CADR Smoke rating; AHMA Certified; AHMA Compliant; AHRI Certified; ANSI A117.1 Compliant; ANSI A137.1 Compliant; ANSI IT9.2 Compliant; ANSI Z1.5A/CGA 9.1M Certified; ANSI Z124.1.2 Compliant; ANSI Z124.3 Compliant; ANSI Z124.6-97 Compliant; ANSI Z21.11.2-2016 - Gas-Fired Unvented Room Heaters and Gas-Fired Unvented Decorative Room Heaters; ANSI Z21.50-2016/CSA 2.22-2016 - Standard for Vented Decorative Gas Appliances; ANSI Z21.60-2017/CSA 2.26-2017- Standard for Decorative Gas Appliances; ANSI Z21.84-2017 - Standard for Manually Lighted/ Natural Gas/ Decorative Gas Appliances; ANSI Z21.88-2017/CSA 2.33-2017- Standard for Vented Gas Fireplace Heaters; ANSI Z358 Compliant; ANSI/BHMA A156 Certified; ANSI/BIFMA M7.1 Standard Test Method for Determining VOC Emissions; ANSI/BIFMA X5.1 Office Seating; ANSI/BIFMA X5.11 Large Occupant Office Seating; ANSI/BIFMA X5.3 Vertical Files; ANSI/BIFMA X5.4 Lounge & Public Seating; ANSI/BIFMA X5.5 Desk Products; ANSI/BIFMA X5.6 Panel Systems; ANSI/BIFMA X5.9 Storage; ANSI/BIFMA X6.1 Educational Seating; ANSI/BIFMA X7.1 Standard for Formaldehyde & TVOC Emissions; ANSI/ESD S20.20 Certified; ANSI/NISO Z39.48 Compliant; ANSI/SOHO S6.5 Small Office/Home Office; APMA Certified; ASHRAE 62.2 Standard Compliant; ASME A112.18.1 Compliant; ASME A112.18.2 Compliant; ASME A112.19.1 Compliant; ASME A112.19.2 Compliant; ASME A112.19.3 Compliant; ASP:02:01 Certification; ASSE 1001 Certified; ASSE 1006 Certified; ASSE 1016 Certified; ASTM 1821-19; ASTM E1590-07 Compliant; ASTM F1004-19 Certified; ASTM F1148-17 Compliant; ASTM F1148-18 Compliant; ASTM F1148-18 Certified; ASTM F1169 - 13 Compliant; ASTM F1487-17 Compliant; ASTM F1821 - 16 Compliant; ASTM F1912-17 Compliant; ASTM F1917 - 12 Compliant; ASTM F2057 - 14; ASTM F2057 - 17; ASTM F2057 - 19 | AZ6: Select | BA6: Select | BB6: Text | BC6: Please choose one or more from the following, using a semicolon (;) to separate each value: Specifications; Installation & Assembly; Owner Manual; Delivery Information; Warranty Information; Certifications; Disclaimers; Buying Guides; Promotions; Dimensions; Marketing Materials; Energy Guide; Other; Product Information Sheet; Digital Law Label | BD6: Please choose one or more from the following, using a semicolon (;) to separate each value: AAFA Certified; AATCC 116 Grade; AATCC 16.1-2014 Grade; AATCC 16.3-2014 Grade; AATCC 8 Grade; AC Rated; ACT Flammability Guidelines Compliant; AHAM CADR Dust rating; AHAM CADR Pollen rating; AHAM CADR Smoke rating; AHMA Certified; AHMA Compliant; AHRI Certified; ANSI A117.1 Compliant; ANSI A137.1 Compliant; ANSI IT9.2 Compliant; ANSI Z1.5A/CGA 9.1M Certified; ANSI Z124.1.2 Compliant; ANSI Z124.3 Compliant; ANSI Z124.6-97 Compliant; ANSI Z21.11.2-2016 - Gas-Fired Unvented Room Heaters and Gas-Fired Unvented Decorative Room Heaters; ANSI Z21.50-2016/CSA 2.22-2016 - Standard for Vented Decorative Gas Appliances; ANSI Z21.60-2017/CSA 2.26-2017- Standard for Decorative Gas Appliances; ANSI Z21.84-2017 - Standard for Manually Lighted/ Natural Gas/ Decorative Gas Appliances; ANSI Z21.88-2017/CSA 2.33-2017- Standard for Vented Gas Fireplace Heaters; ANSI Z358 Compliant; ANSI/BHMA A156 Certified; ANSI/BIFMA M7.1 Standard Test Method for Determining VOC Emissions; ANSI/BIFMA X5.1 Office Seating; ANSI/BIFMA X5.11 Large Occupant Office Seating; ANSI/BIFMA X5.3 Vertical Files; ANSI/BIFMA X5.4 Lounge & Public Seating; ANSI/BIFMA X5.5 Desk Products; ANSI/BIFMA X5.6 Panel Systems; ANSI/BIFMA X5.9 Storage; ANSI/BIFMA X6.1 Educational Seating; ANSI/BIFMA X7.1 Standard for Formaldehyde & TVOC Emissions; ANSI/ESD S20.20 Certified; ANSI/NISO Z39.48 Compliant; ANSI/SOHO S6.5 Small Office/Home Office; APMA Certified; ASHRAE 62.2 Standard Compliant; ASME A112.18.1 Compliant; ASME A112.18.2 Compliant; ASME A112.19.1 Compliant; ASME A112.19.2 Compliant; ASME A112.19.3 Compliant; ASP:02:01 Certification; ASSE 1001 Certified; ASSE 1006 Certified; ASSE 1016 Certified; ASTM 1821-19; ASTM E1590-07 Compliant; ASTM F1004-19 Certified; ASTM F1148-17 Compliant; ASTM F1148-18 Compliant; ASTM F1148-18 Certified; ASTM F1169 - 13 Compliant; ASTM F1487-17 Compliant; ASTM F1821 - 16 Compliant; ASTM F1912-17 Compliant; ASTM F1917 - 12 Compliant; ASTM F2057 - 14; ASTM F2057 - 17; ASTM F2057 - 19 | BE6: Select | BF6: Select | BG6: Select | BH6: Yes or No | BI6: Yes or No | BJ6: Whole Number | BK6: Yes or No | BL6: Yes or No | BM6: Yes or No | BN6: Yes or No | BO6: Yes or No | BP6: Please choose one or more from the following, using a semicolon (;) to separate each value: Cabinet/Enclosed storage; TV Stand Fireplace; Open shelving; Corner unit; Hutch; Piers; Floating mount; Standard; Demilune; Nesting; Apothecary; Multi-tiered; Floor; Corner; Basket Storage; Tabletop; Hanging; Bombe; Etagere; Wall Mounted; Double Walled; Console; Pedestal; Unavailable; Does Not Apply | BQ6: Please choose one or more from the following, using a semicolon (;) to separate each value: Glass; Stainless Steel; Cane; Raffia; Mango Wood; Aluminum; Manufactured Wood; Leather; Bamboo; Ceramic; Faux Leather; Iron; Marble / Granite; Metal; Plastic / Acrylic; Teak; Solid + Manufactured Wood; Steel; Solid Wood; Wicker; Reclaimed Wood | BR6: Please choose one or more from the following, using a semicolon (;) to separate each value: Distressed Leather; Paint Distressing; Distressed Grain Accents; Coat/Paint Distressing; Wormholes; No Natural Variation; No Distressing; Distressed Metal; Worn/Fade; Wood Scoring & Rub Through; Unavailable | BS6: Please choose one or more from the following, using a semicolon (;) to separate each value: No Natural Variation; Natural Wood Grain Color Variation; Weathered Steel; Wood Knots; Natural Stone Color Variation; Unavailable | BT6: Yes or No | BU6: Yes or No | BV6: Yes or No | BW6: Yes or No | BX6: Yes or No | BY6: Yes or No | BZ6: Yes or No | CA6: Yes or No | CB6: Yes or No | CC6: Select | CD6: Yes or No | CE6: Yes or No | CF6: Please choose one or more from the following, using a semicolon (;) to separate each value: Non Residential Use; Residential Use | CG6: Please choose one or more from the following, using a semicolon (;) to separate each value: Made in USA; Made in USA of Imported Materials; Product of Canada; Made In Canada; Does Not Apply | CH6: Select | CI6: Yes or No | CJ6: Please choose one or more from the following, using a semicolon (;) to separate each value: Acacia; Alder; Ash; Bamboo; Beech; Birch; Camphor; Cedar; Cherry; Elm; Eucalyptus; Fir; Hickory; Mahogany; Mango; Maple; Oak; Pine; Poplar; Rosewood; Rubberwood; Sheesham; Spruce; Teak; Walnut; Wenge; Pecan; Shorea; Paulownia; Chestnut; Hemlock; Aspen; Mindi; Ipe; Olive; Ajo; Agarwood; Afzelia; Afrormosia; Bubinga; Brazilwood; Cumaru; Cedar, Mulanje; Cedar, Spanish; Aloewood; Lignum vitae; Mahogany, African; Mahogany, Mexican; Padauk, African; Macacauba; Ebony, Madagascar; Lignum vitae, Argentine; Gavilan; Mahogany, Honduran; Mahogany, Cuban; Stinkwood, red; Yew, Chinese; Pau rosa, Brazilian; Sandalwood, East African; Ramin; Zitan; Yew, Himalayan; Yew, Japanese; Rosewood, Siamese; Yew, Taiwan; Burlwood; Platane Wood; Sungkai; Does Not Apply | CK6: Yes or No | CL6: Select | CM6: Select | CN6: Select | CO6: Select | CP6: Select | CQ6: Select | CR6: Select | CS6: Yes or No | CT6: Yes or No | CU6: Number | CV6: Please choose one or more from the following, using a semicolon (;) to separate each value: Hand wash recommended; Dishwasher safe; Spot clean only; Hand wash only; Delicate cycle; Commercial laundry safe; Do not use a fabric softener; Cold wash; Sweep / Dust Mop; Cut loose threads using a scissor; Clean with soap and water; Clean spills immediately; Dishwasher safe component; Lay flat to dry; Dryer safe; Warm wash; Non-Abrasive, Neutral Ph Cleaner; Commercial dishwasher safe; Vacuum with no beater bar/rotating brush; Air / Line Dry; Professional / Dry Clean Recommended; Wash With Garden Hose Or Pressure Washer; Machine washable components; Professional / Dry Clean Only; Vacuum with upholstery attachment; Vacuum with beater bar/rotating brush; Clean with bleach and water; Use product specific cleaner; Oil / seal / treat regularly; Shake to remove dust; Tumble dry; Iron safe; Wipe clean with a dry cloth; Cover when not in use; Avoid use of abrasive cleaners; Tile specific cleaner; Do not wash; Dust mop; Hose down; Towel dry immediately; Household floor cleaner; Spot clean; Wipe with wet cloth; Spot clean with water; When cushions are wet, open cushion zippers and prop up to dry in order to maintain quality; Oil 1-2 times per year; No washing / drying care; Do not bleach; Treat with wood protector; Do not dry clean; Clean with diluted vinegar and water; Store indoors or cover when not in use; Use carpet cleaner; Air dry cushions covers; Do not use bleach or bleach solutions; Rinse with water only; Dishwasher safe removable parts; Clean and re-seal with natural stone sealant; To prevent oil stains wipe with a damp cloth before using; After cleaning, use sealant; Apply oil to maintain color and prolong durability; Vacuum; Avoid direct sunlight; Dry after use; Use furniture pads; Apply epoxy clear coat once per year; Clean with cloth, mild soap, and warm water; Spot clean with mild detergent; Spot clean as needed; Automatic; Hot water extraction; Spot clean with dry cloth; Clean the product at least one time per month. We suggest the use of Rejuven | CW6: Yes or No | CX6: Please choose one or more from the following, using a semicolon (;) to separate each value: Polyethylene; Steel; Wood Veneers; Polyvinyl Chloride (PVC); Polycarbonate; Stainless Steel; Marble; Solid + Manufactured Wood; Wood; Clear Glass; Stone; Glass; Melamine; Aluminum; Acrylic; Resin; Tinted Glass; Laminate; Metal; Wire; Mirrored; Plastic; Manufactured Wood; Glass / Polycarbonate; Wicker; Iron; Solid Wood; Granite; Unavailable; Does Not Apply | CY6: Please choose one or more from the following, using a semicolon (;) to separate each value: Clear; Cream; Purple; Gold; Silver; Polished Chrome; Polished Nickel; Stainless Steel; Bronze; Chrome; Oil Rubbed Bronze; Matte Black; Satin Nickel; Brushed Nickel; Antique Brass; Antique Bronze; Copper; Antique Copper; Brushed Brass; Polished Brass; Brass; Satin Brass; Brushed Gold; Nickel; Ivory; Green; Orange; Beige; Teal; Red; Satin; Yellow; Pink; White; Brown; Blue; Satin Black; Rose Gold; Navy; Black; Tan; Gray; Brown Wood; Dark Brown Wood; Medium Yellow Wood; Espresso Wood; Medium Wood; Red Wood; Beige Wood; Natural Wood; Gray Wood; Light Yellow Wood; White Wood; Oak Wood | CZ6: Please choose one or more from the following, using a semicolon (;) to separate each value: 0.6 Extension; Ball Bearing; Soft Close; Roller Glides; 0.75 Extension; Full Extension; Metal Slide; 0.5 Extension; Wood Slide; Center Slides; Kenlin; Side-Mounted Glides; Undermount Glides; Euro Glides; Unavailable; Does Not Apply | DA6: Select | DB6: Please choose one or more from the following, using a semicolon (;) to separate each value: Electric; Dual Fuel; Induction; Wood Pellets; Natural Gas; Liquid Propane; Wood Burning; Gel Fuel; Bio-Ethanol; Propane; Butane; Charcoal; Ethanol; Alcohol; Does Not Apply | DC6: Please choose one or more from the following, using a semicolon (;) to separate each value: Flush; Glass; Louvered; Paneled; Mirrored; Barn Doors; Frosted; Insulated; Contoured; Tinted; See Through; Double Pane; Does Not Apply | DD6: Yes or No | DE6: Yes or No | DF6: Please choose one or more from the following, using a semicolon (;) to separate each value: Drawers; Fireplace; Hutch; Shelves; Bridge; Exterior Shelves; Fireplace Remote; Integrated TV Mount; Interior Shelves; Media Storage; Pier / Bookcase; Sound Bar Shelf; TV Anti-Tip Kit; Wheels / Casters; Cabinets; Unavailable; Does Not Apply | DG6: Whole Number | DH6: Yes or No | DI6: Please choose one or more from the following, using a semicolon (;) to separate each value: Gel; Gas; Wood; Electric; Unavailable; Does Not Apply | DJ6: Select | DK6: Yes or No | DL6: Select | DM6: Select | DN6: Select | DO6: Select | DP6: Yes or No | DQ6: Please choose one or more from the following, using a semicolon (;) to separate each value: Dual Language; Distribution Conflict; Logistics; Does Not Apply | DR6: Select | DS6: Yes or No | DT6: Please choose one or more from the following, using a semicolon (;) to separate each value: UN3091; UN3481; UN2800; UN1950; UN3496; ID8000; UN1013; UN3082; UN3077; UN3480; UN2857; UN3358; UN3090; UN1266; UN1993; UN1944; UN1070; UN1044; UN3163; UN1268; UN1760; UN1011; UN2794; UN1759; UN3171; UN1987; UN1263; UN1170; UN3265; UN3260; UN3215; UN1006; UN3175; Does Not Apply | DU6: Select | DV6: Select | DW6: Select | DX6: Select | DY6: Please choose one or more from the following, using a semicolon (;) to separate each value: TÜV Rheinland Certified; MET Listed; AFNOR UK Ltd; BSI Assurance UK Ltd; cUL Listed; ETL Listed; DBI Certification Ltd; UL Listed; cETL Listed; CSA Certified; SGS North America Listed; Does Not Apply | DZ6: Text | EA6: Select | EB6: Select | EC6: Yes or No | ED6: Select | EE6: Number | EF6: Number | EG6: Number | EH6: Number | EI6: Number | EJ6: Number | EK6: Select | EL6: Number | EM6: Yes or No | EN6: Select | EO6: Please choose one or more from the following, using a semicolon (;) to separate each value: All Tools Included; Tool Free Assembly; Screwdriver; Allen Wrench; Adjustable Wrench; Socket Wrench; Power Drill; Hammer; Pliers; Ratchet; Utility Saw; Saw; Measuring Tape; Mallet; Level; Box Cutter; Caulk / Adhesive; Anchors / Stakes; Clamps; Drill Bit; Gloves; Hex Key; Glass Cutter; Chop Saw; Circular Saw; Phillips Head Screwdriver; Crescent Wrench; Flat Screwdriver; Adhesive Roller / Tray; Shovel; Drill; Smoother / Squeegee; Ladder; Wire Stripper; Razor Knife; Pencil; Electric Drill; Screw Gun; Scissors; Ruler; Safety Glasses; Utility Knife; Rope; Ear Protection; Stud Finder; Wrench; Tape Measure; Screws; Wire Cap; Hammer / Mallet; Chalk Line; Landscaping Fabric; No Tools Needed; Tile Cutter; Straight Edge; Silicone; Wet Saw; Torx Bit; Unavailable; Does Not Apply | EP6: Yes or No | EQ6: Select | ER6: Yes or No | ES6: Select | ET6: Please choose one or more from the following, using a semicolon (;) to separate each value: 30 Days; 60 Days; 90 Days; 6 Months; 1 Year; 2 Years; 3 Years; 5 Years; 10 Years; 20 Years; 25 Years; Lifetime; Warranty length varies by part; 15 Years; 18 Months; 12 Years; 6 Years; 4 Years; 8 Years; 7 Years; Does Not Apply
B7: Default Row: | C7: N/A | E7: N/A | F7: N/A | G7: N/A | I7: N/A | J7: N/A | AL7: N/A | AM7: N/A | AN7: N/A | AO7: N/A | AP7: N/A | AQ7: N/A
